Workbook
Name UPDATE: 'Data Sheet'!$E$1

Sheet Financial>

Sheet Historical FS
B2: ="Historical Financial Statement-"&'Data Sheet'!B1 -> Historical Financial Statement-JSW STEEL LTD
B3: Years | C3: ='Data Sheet'!B16 -> 42094 | D3: ='Data Sheet'!C16 -> 42460 | E3: ='Data Sheet'!D16 -> 42825 | F3: ='Data Sheet'!E16 -> 43190 | G3: ='Data Sheet'!F16 -> 43555 | H3: ='Data Sheet'!G16 -> 43921 | I3: ='Data Sheet'!H16 -> 44286 | J3: ='Data Sheet'!I16 -> 44651 | ... L3: ='Data Sheet'!K16 -> 45382 | M3: LTM
A5: # | B5: Income Statement
B6: ='Data Sheet'!A17 -> Sales | C6: ='Data Sheet'!B17 -> 52971.51 | D6: ='Data Sheet'!C17 -> 41546.17 | E6: ='Data Sheet'!D17 -> 55604 | F6: ='Data Sheet'!E17 -> 71933 | G6: ='Data Sheet'!F17 -> 84757 | H6: ='Data Sheet'!G17 -> 73326 | I6: ='Data Sheet'!H17 -> 79839 | ... L6: ='Data Sheet'!K17 -> 175006 | M6: =SUM('Data Sheet'!H42:K42) -> 170274
B7: (Sales Growth) | D7: =D6/C6-1 -> -0.2156884 | E7: =E6/D6-1 -> 0.33836645 | F7: =F6/E6-1 -> 0.29366592 | G7: =G6/F6-1 -> 0.17827701 | H7: =H6/G6-1 -> -0.13486792 | I7: =I6/H6-1 -> 0.088822519 | J7: =J6/I6-1 -> 0.83332707 | K7: =K6/J6-1 -> 0.13383116 | L7: =L6/K6-1 -> 0.05450711
B9: COGS | C9: =IFERROR(SUM('Data Sheet'!B18,'Data Sheet'!B20:B22)*1-'Data Sheet'!B19,0) -> 42072.92 | D9: =IFERROR(SUM('Data Sheet'!C18,'Data Sheet'!C20:C22)*1-'Data Sheet'!C19,0) -> 33468.38 | E9: =IFERROR(SUM('Data Sheet'!D18,'Data Sheet'!D20:D22)*1-'Data Sheet'!D19,0) -> 41733 | F9: =IFERROR(SUM('Data Sheet'!E18,'Data Sheet'!E20:E22)*1-'Data Sheet'!E19,0) -> 55278 | G9: =IFERROR(SUM('Data Sheet'!F18,'Data Sheet'!F20:F22)*1-'Data Sheet'!F19,0) -> 62906 | H9: =IFERROR(SUM('Data Sheet'!G18,'Data Sheet'!G20:G22)*1-'Data Sheet'!G19,0) -> 58084 | I9: =IFERROR(SUM('Data Sheet'!H18,'Data Sheet'!H20:H22)*1-'Data Sheet'!H19,0) -> 57246 | J9: =IFERROR(SUM('Data Sheet'!I18,'Data Sheet'!I20:I22)*1-'Data Sheet'!I19,0) -> 103778 | ... L9: =IFERROR(SUM('Data Sheet'!K18,'Data Sheet'!K20:K22)*1-'Data Sheet'!K19,0) -> 141101 | M9: =SUM('Data Sheet'!H43:K43) -> 147796
B10: (COGS% OF SALES) | C10: =C9/C6 -> 0.79425563 | D10: =D9/D6 -> 0.80557077 | E10: =E9/E6 -> 0.75053953 | F10: =F9/F6 -> 0.7684651 | G10: =G9/G6 -> 0.74219239 | H10: =H9/H6 -> 0.79213376 | I10: =I9/I6 -> 0.717018 | J10: =J9/J6 -> 0.70900657 | ... L10: =L9/L6 -> 0.80626379
B12: Gross Profit | C12: =C6-C9 -> 10898.59 | D12: =D6-D9 -> 8077.79 | E12: =E6-E9 -> 13871 | F12: =F6-F9 -> 16655 | G12: =G6-G9 -> 21851 | H12: =H6-H9 -> 15242 | I12: =I6-I9 -> 22593 | J12: =J6-J9 -> 42593 | ... M12: =M6-M9 -> 22478
B13: (Gross Margin) | C13: =C12/C6 -> 0.20574437 | D13: =D12/D6 -> 0.19442923 | E13: =E12/E6 -> 0.24946047 | F13: =F12/F6 -> 0.2315349 | G13: =G12/G6 -> 0.25780761 | H13: =H12/H6 -> 0.20786624 | I13: =I12/I6 -> 0.282982 | J13: =J12/J6 -> 0.29099343 | ... L13: =L12/L6 -> 0.19373621
B15: Selling & General Expense | C15: =IFERROR(SUM('Data Sheet'!B23:B24),0) -> 1534.73 | D15: =IFERROR(SUM('Data Sheet'!C23:C24),0) -> 1655.48 | E15: =IFERROR(SUM('Data Sheet'!D23:D24),0) -> 1563 | F15: =IFERROR(SUM('Data Sheet'!E23:E24),0) -> 1739 | G15: =IFERROR(SUM('Data Sheet'!F23:F24),0) -> 2921 | H15: =IFERROR(SUM('Data Sheet'!G23:G24),0) -> 3429 | I15: =IFERROR(SUM('Data Sheet'!H23:H24),0) -> 2415 | J15: =IFERROR(SUM('Data Sheet'!I23:I24),0) -> 3479 | ... L15: =IFERROR(SUM('Data Sheet'!K23:K24),0) -> 5748 | M15: 0
B16: S&G Exp % of Sales | C16: =C15/C6 -> 0.028972744 | D16: =D15/D6 -> 0.039846754 | E16: =E15/E6 -> 0.028109489 | F16: =F15/F6 -> 0.024175274 | G16: =G15/G6 -> 0.03446323 | H16: =H15/H6 -> 0.046763767 | I16: =I15/I6 -> 0.030248375 | J16: =J15/J6 -> 0.023768369 | ... L16: =L15/L6 -> 0.032844588
B17: Operating Profit(EBITDA) | C17: =C12-C15 -> 9363.86 | D17: =D12-D15 -> 6422.31 | E17: =E12-E15 -> 12308 | F17: =F12-F15 -> 14916 | G17: =G12-G15 -> 18930 | H17: =H12-H15 -> 11813 | I17: =I12-I15 -> 20178 | J17: =J12-J15 -> 39114 | ... M17: =M12-M15 -> 22478
B18: Ebitda Margin | C18: =C17/C6 -> 0.17677163 | D18: =D17/D6 -> 0.15458248 | E18: =E17/E6 -> 0.22135098 | F18: =F17/F6 -> 0.20735963 | G18: =G17/G6 -> 0.22334438 | H18: =H17/H6 -> 0.16110247 | I18: =I17/I6 -> 0.25273363 | J18: =J17/J6 -> 0.26722507 | ... L18: =L17/L6 -> 0.16089163
B19: Intrest | C19: ='Data Sheet'!B27 -> 3493.03 | D19: ='Data Sheet'!C27 -> 3601.18 | E19: ='Data Sheet'!D27 -> 3768 | F19: ='Data Sheet'!E27 -> 3701 | G19: ='Data Sheet'!F27 -> 3917 | H19: ='Data Sheet'!G27 -> 4265 | I19: ='Data Sheet'!H27 -> 3957 | J19: ='Data Sheet'!I27 -> 4968 | ... L19: ='Data Sheet'!K27 -> 8105 | M19: =SUM('Data Sheet'!H46:K46) -> 8380
B20: Intrest% of Sales | C20: =C19/C6 -> 0.065941673 | D20: =D19/D6 -> 0.086678989 | E20: =E19/E6 -> 0.067764909 | F20: =F19/F6 -> 0.051450655 | G20: =G19/G6 -> 0.046214472 | H20: =H19/H6 -> 0.058164907 | I20: =I19/I6 -> 0.049562244 | J20: =J19/J6 -> 0.03394115 | ... L20: =L19/L6 -> 0.046312698
B21: ='Data Sheet'!A26 -> Depreciation | C21: ='Data Sheet'!B26 -> 3434.49 | D21: ='Data Sheet'!C26 -> 3322.56 | E21: ='Data Sheet'!D26 -> 3430 | F21: ='Data Sheet'!E26 -> 3387 | G21: ='Data Sheet'!F26 -> 4041 | H21: ='Data Sheet'!G26 -> 4246 | I21: ='Data Sheet'!H26 -> 4679 | ... L21: ='Data Sheet'!K26 -> 8172 | M21: =SUM('Data Sheet'!H45:K45) -> 9006
B22: Dep % of Sales | C22: =C21/C6 -> 0.064836551 | D22: =D21/D6 -> 0.079972715 | E22: =E21/E6 -> 0.06168621 | F22: =F21/F6 -> 0.047085482 | G22: =G21/G6 -> 0.047677478 | H22: =H21/H6 -> 0.057905791 | I22: =I21/I6 -> 0.058605443 | J22: =J21/J6 -> 0.040998558 | ... L22: =L21/L6 -> 0.046695542
B23: Earning Befor Tax | C23: =C17-SUM(C19,C21) -> 2436.34 | D23: =D17-SUM(D19,D21) -> -501.43 | E23: =E17-SUM(E19,E21) -> 5110 | F23: =F17-SUM(F19,F21) -> 7828 | G23: =G17-SUM(G19,G21) -> 10972 | H23: =H17-SUM(H19,H21) -> 3302 | I23: =I17-SUM(I19,I21) -> 11542 | J23: =J17-SUM(J19,J21) -> 28145 | ... L23: =L17-SUM(L19,L21) -> 11880 | M23: =M17-SUM(M19:M21) -> 5092
B24: EBT Margin | C24: =C23/C6 -> 0.045993403 | D24: =D23/D6 -> -0.012069223 | E24: =E23/E6 -> 0.091899863 | F24: =F23/F6 -> 0.10882349 | G24: =G23/G6 -> 0.12945243 | H24: =H23/H6 -> 0.045031776 | I24: =I23/I6 -> 0.14456594 | J24: =J23/J6 -> 0.19228536 | ... L24: =L23/L6 -> 0.067883387
B25: Tax | C25: ='Data Sheet'!B29 -> 819.41 | D25: ='Data Sheet'!C29 -> -1966.21 | E25: ='Data Sheet'!D29 -> 1674 | F25: ='Data Sheet'!E29 -> 1538 | G25: ='Data Sheet'!F29 -> 3644 | H25: ='Data Sheet'!G29 -> -906 | I25: ='Data Sheet'!H29 -> 4142 | J25: ='Data Sheet'!I29 -> 8807 | ... L25: ='Data Sheet'!K29 -> 4407 | M25: =SUM('Data Sheet'!H48:K48) -> 2047
B26: Effective Tax Rate | C26: =C25/C23 -> 0.33632826 | D26: =D25/D23 -> 3.9212054 | E26: =E25/E23 -> 0.32759295 | F26: =F25/F23 -> 0.1964742 | G26: =G25/G23 -> 0.33211812 | H26: =H25/H23 -> -0.27437916 | I26: =I25/I23 -> 0.35886328 | J26: =J25/J23 -> 0.31291526 | ... L26: =L25/L23 -> 0.3709596
B27: Net Profit | C27: =C23-C25 -> 1616.93 | D27: =D23-D25 -> 1464.78 | E27: =E23-E25 -> 3436 | F27: =F23-F25 -> 6290 | G27: =G23-G25 -> 7328 | H27: =H23-H25 -> 4208 | I27: =I23-I25 -> 7400 | J27: =J23-J25 -> 19338 | ... M27: =M23-M25 -> 3045
B28: Net Profit Margin | C28: =C27/C6 -> 0.030524522 | D28: =D27/D6 -> 0.035256679 | E28: =E27/E6 -> 0.061794116 | F28: =F27/F6 -> 0.087442481 | G28: =G27/G6 -> 0.086458936 | H28: =H27/H6 -> 0.057387557 | I28: =I27/I6 -> 0.092686532 | J28: =J27/J6 -> 0.13211633 | ... L28: =L27/L6 -> 0.042701393
B29: No Of Equity Shares | C29: ='Data Sheet'!B93 -> 241.72 | D29: ='Data Sheet'!C93 -> 241.72 | E29: ='Data Sheet'!D93 -> 241.72 | F29: ='Data Sheet'!E93 -> 241.72 | G29: ='Data Sheet'!F93 -> 241.72 | H29: ='Data Sheet'!G93 -> 241.72 | I29: ='Data Sheet'!H93 -> 241.72 | J29: ='Data Sheet'!I93 -> 241.72 | ... L29: ='Data Sheet'!K93 -> 244.55 | M29: =L29 -> 244.55
B31: EPS | C31: =C27/C29 -> 6.6892686 | D31: =D27/D29 -> 6.0598213 | E31: =E27/E29 -> 14.214794 | F31: =F27/F29 -> 26.021843 | G31: =G27/G29 -> 30.316068 | H31: =H27/H29 -> 17.408572 | I31: =I27/I29 -> 30.613933 | J31: =J27/J29 -> 80.001655 | ... M31: =M27/M29 -> 12.451441
B32: Earning Per Growth | D32: =D31/C31 -> 0.90590193 | E32: =E31/D31 -> 2.3457448 | F32: =F31/E31 -> 1.830617 | G32: =G31/F31 -> 1.1650238 | H32: =H31/G31 -> 0.57423581 | I32: =I31/H31 -> 1.7585551 | J32: =J31/I31 -> 2.6132432 | K32: =K31/J31 -> 0.13331265 | ... M32: =M31/L31 -> 0.40746688
B33: Divident Per Share | C33: ='Data Sheet'!B31/'Historical FS'!C29 -> 1.3777097 | D33: ='Data Sheet'!C31/'Historical FS'!D29 -> 0.93364223 | E33: ='Data Sheet'!D31/'Historical FS'!E29 -> 2.8017955 | F33: ='Data Sheet'!E31/'Historical FS'!F29 -> 3.9980142 | G33: ='Data Sheet'!F31/'Historical FS'!G29 -> 5.105494 | H33: ='Data Sheet'!G31/'Historical FS'!H29 -> 2.4904849 | I33: ='Data Sheet'!H31/'Historical FS'!I29 -> 8.1209664 | J33: ='Data Sheet'!I31/'Historical FS'!J29 -> 21.604956 | ... L33: ='Data Sheet'!K31/'Historical FS'!L29 -> 9.1044776 | M33: 0
B34: Deivident Payout | C34: =C33/C31 -> 0.2059582 | D34: =D33/D31 -> 0.15407092 | E34: =E33/E31 -> 0.19710419 | F34: =F33/F31 -> 0.1536407 | G34: =G33/G31 -> 0.16840884 | H34: =H33/H31 -> 0.14306084 | I34: =I33/I31 -> 0.26527027 | J34: =J33/J31 -> 0.27005637 | ... M34: =M33/M31 -> 0
B35: Retained Earning | C35: =C31-C33 -> 5.3115588 | D35: =D31-D33 -> 5.1261791 | E35: =E31-E33 -> 11.412999 | F35: =F31-F33 -> 22.023829 | G35: =G31-G33 -> 25.210574 | H35: =H31-H33 -> 14.918087 | I35: =I31-I33 -> 22.492967 | J35: =J31-J33 -> 58.396699 | ... M35: =M31-M33 -> 12.451441
A37: # | B37: Balance Sheet
B39: ='Data Sheet'!A57 -> Equity Share Capital | C39: ='Data Sheet'!B57 -> 302.75 | D39: ='Data Sheet'!C57 -> 300.9 | E39: ='Data Sheet'!D57 -> 301 | F39: ='Data Sheet'!E57 -> 302 | G39: ='Data Sheet'!F57 -> 301 | H39: ='Data Sheet'!G57 -> 301 | I39: ='Data Sheet'!H57 -> 302 | ... L39: ='Data Sheet'!K57 -> 305
B40: ='Data Sheet'!A58 -> Reserves | C40: ='Data Sheet'!B58 -> 21986.89 | D40: ='Data Sheet'!C58 -> 18664.55 | E40: ='Data Sheet'!D58 -> 22346 | F40: ='Data Sheet'!E58 -> 27696 | G40: ='Data Sheet'!F58 -> 34494 | H40: ='Data Sheet'!G58 -> 36298 | I40: ='Data Sheet'!H58 -> 46462 | ... L40: ='Data Sheet'!K58 -> 77364
B41: ='Data Sheet'!A59 -> Borrowings | C41: ='Data Sheet'!B59 -> 38754.26 | D41: ='Data Sheet'!C59 -> 42204.03 | E41: ='Data Sheet'!D59 -> 43334 | F41: ='Data Sheet'!E59 -> 39393 | G41: ='Data Sheet'!F59 -> 47396 | H41: ='Data Sheet'!G59 -> 61423 | I41: ='Data Sheet'!H59 -> 62392 | ... L41: ='Data Sheet'!K59 -> 87984
B42: ='Data Sheet'!A60 -> Other Liabilities | C42: ='Data Sheet'!B60 -> 24609.98 | D42: ='Data Sheet'!C60 -> 20737.42 | E42: ='Data Sheet'!D60 -> 22024 | F42: ='Data Sheet'!E60 -> 24579 | G42: ='Data Sheet'!F60 -> 32606 | H42: ='Data Sheet'!G60 -> 33798 | I42: ='Data Sheet'!H60 -> 39161 | ... L42: ='Data Sheet'!K60 -> 62245
B43: Total Liabilites | C43: =SUM(C39:C42) -> 85653.88 | D43: =SUM(D39:D42) -> 81906.9 | E43: =SUM(E39:E42) -> 88005 | F43: =SUM(F39:F42) -> 91970 | G43: =SUM(G39:G42) -> 114797 | H43: =SUM(H39:H42) -> 131820 | I43: =SUM(I39:I42) -> 148317 | J43: =SUM(J39:J42) -> 196485 | ... L43: =SUM(L39:L42) -> 227898
B45: Fixed Asset Net Block | C45: ='Data Sheet'!B62 -> 52176.28 | D45: ='Data Sheet'!C62 -> 56139.52 | E45: ='Data Sheet'!D62 -> 58730 | F45: ='Data Sheet'!E62 -> 57848 | G45: ='Data Sheet'!F62 -> 62644 | H45: ='Data Sheet'!G62 -> 62085 | I45: ='Data Sheet'!H62 -> 64917 | J45: ='Data Sheet'!I62 -> 99880 | ... L45: ='Data Sheet'!K62 -> 112461
B46: ='Data Sheet'!A63 -> Capital Work in Progress | C46: ='Data Sheet'!B63 -> 8265.27 | D46: ='Data Sheet'!C63 -> 7270.85 | E46: ='Data Sheet'!D63 -> 4363 | F46: ='Data Sheet'!E63 -> 5950 | G46: ='Data Sheet'!F63 -> 11889 | H46: ='Data Sheet'!G63 -> 27191 | I46: ='Data Sheet'!H63 -> 32566 | ... L46: ='Data Sheet'!K63 -> 29676
B47: ='Data Sheet'!A64 -> Investments | C47: ='Data Sheet'!B64 -> 599.25 | D47: ='Data Sheet'!C64 -> 1194.61 | E47: ='Data Sheet'!D64 -> 1366 | F47: ='Data Sheet'!E64 -> 1469 | G47: ='Data Sheet'!F64 -> 1894 | H47: ='Data Sheet'!G64 -> 1259 | I47: ='Data Sheet'!H64 -> 8581 | ... L47: ='Data Sheet'!K64 -> 7246
B48: ='Data Sheet'!A65 -> Other Assets | C48: ='Data Sheet'!B74 -> 9191.04 | D48: ='Data Sheet'!C74 -> 5232.97 | E48: ='Data Sheet'!D74 -> 6517 | F48: ='Data Sheet'!E74 -> 8342 | G48: ='Data Sheet'!F74 -> 10475 | H48: ='Data Sheet'!G74 -> 11004 | I48: ='Data Sheet'!H74 -> 10705 | J48: ='Data Sheet'!I74 -> 16133 | ... L48: ='Data Sheet'!K74 -> 20804
B49: Total Non Current Asset | C49: =SUM(C45:C48) -> 70231.84 | D49: =SUM(D45:D48) -> 69837.95 | E49: =SUM(E45:E48) -> 70976 | F49: =SUM(F45:F48) -> 73609 | G49: =SUM(G45:G48) -> 86902 | H49: =SUM(H45:H48) -> 101539 | I49: =SUM(I45:I48) -> 116769 | J49: =SUM(J45:J48) -> 137858 | ... L49: =SUM(L45:L48) -> 170187
B51: ='Data Sheet'!A67 -> Receivables | C51: ='Data Sheet'!B67 -> 2499.75 | D51: ='Data Sheet'!C67 -> 2727.37 | E51: ='Data Sheet'!D67 -> 4149 | F51: ='Data Sheet'!E67 -> 4704 | G51: ='Data Sheet'!F67 -> 7160 | H51: ='Data Sheet'!G67 -> 4505 | I51: ='Data Sheet'!H67 -> 4486 | ... L51: ='Data Sheet'!K67 -> 7548
B52: ='Data Sheet'!A68 -> Inventory | C52: ='Data Sheet'!B68 -> 11009.04 | D52: ='Data Sheet'!C68 -> 8321.18 | E52: ='Data Sheet'!D68 -> 11395 | F52: ='Data Sheet'!E68 -> 12594 | G52: ='Data Sheet'!F68 -> 14548 | H52: ='Data Sheet'!G68 -> 13773 | I52: ='Data Sheet'!H68 -> 14249 | ... L52: ='Data Sheet'!K68 -> 37815
B53: ='Data Sheet'!A69 -> Cash & Bank | C53: ='Data Sheet'!B69 -> 1913.25 | D53: ='Data Sheet'!C69 -> 1020.4 | E53: ='Data Sheet'!D69 -> 1485 | F53: ='Data Sheet'!E69 -> 1063 | G53: ='Data Sheet'!F69 -> 6187 | H53: ='Data Sheet'!G69 -> 12003 | I53: ='Data Sheet'!H69 -> 12813 | ... L53: ='Data Sheet'!K69 -> 12348
B54: Total Current Asset | C54: =SUM(C51:C53) -> 15422.04 | D54: =SUM(D51:D53) -> 12068.95 | E54: =SUM(E51:E53) -> 17029 | F54: =SUM(F51:F53) -> 18361 | G54: =SUM(G51:G53) -> 27895 | H54: =SUM(H51:H53) -> 30281 | I54: =SUM(I51:I53) -> 31548 | J54: =SUM(J51:J53) -> 58627 | ... L54: =SUM(L51:L53) -> 57711
B56: Total Asset | C56: =SUM(C49,C54) -> 85653.88 | D56: =SUM(D49,D54) -> 81906.9 | E56: =SUM(E49,E54) -> 88005 | F56: =SUM(F49,F54) -> 91970 | G56: =SUM(G49,G54) -> 114797 | H56: =SUM(H49,H54) -> 131820 | I56: =SUM(I49,I54) -> 148317 | J56: =SUM(J49,J54) -> 196485 | ... L56: =SUM(L49,L54) -> 227898
B58: CHECK | C58: =C43=C56 -> TRUE | D58: =D43=D56 -> TRUE | E58: =E43=E56 -> TRUE | F58: =F43=F56 -> TRUE | G58: =G43=G56 -> TRUE | H58: =H43=H56 -> TRUE | I58: =I43=I56 -> TRUE | J58: =J43=J56 -> TRUE | ... L58: =L43=L56 -> TRUE
A60: # | B60: Cash Flow
B62: Operating Activites
B63: ='Cash Flow demo'!A3 -> Profit from operations | C63: ='Cash Flow demo'!D3 -> 8850 | D63: ='Cash Flow demo'!E3 -> 6614 | E63: ='Cash Flow demo'!F3 -> 11994 | F63: ='Cash Flow demo'!G3 -> 14920 | G63: ='Cash Flow demo'!H3 -> 18844 | H63: ='Cash Flow demo'!I3 -> 12301 | I63: ='Cash Flow demo'!J3 -> 19455 | J63: ='Cash Flow demo'!K3 -> 38913 | ... L63: ='Cash Flow demo'!M3 -> 28472
B64: ='Cash Flow demo'!A4 -> Receivables | C64: ='Cash Flow demo'!D4 -> -207 | D64: ='Cash Flow demo'!E4 -> -294 | E64: ='Cash Flow demo'!F4 -> -1352 | F64: ='Cash Flow demo'!G4 -> -640 | G64: ='Cash Flow demo'!H4 -> -2203 | H64: ='Cash Flow demo'!I4 -> 2458 | I64: ='Cash Flow demo'!J4 -> 72 | J64: ='Cash Flow demo'!K4 -> -1884 | ... L64: ='Cash Flow demo'!M4 -> -154
B65: ='Cash Flow demo'!A5 -> Inventory | C65: ='Cash Flow demo'!D5 -> -2854 | D65: ='Cash Flow demo'!E5 -> 2578 | E65: ='Cash Flow demo'!F5 -> -3065 | F65: ='Cash Flow demo'!G5 -> -1199 | G65: ='Cash Flow demo'!H5 -> -1741 | H65: ='Cash Flow demo'!I5 -> 744 | I65: ='Cash Flow demo'!J5 -> -335 | J65: ='Cash Flow demo'!K5 -> -15593 | ... L65: ='Cash Flow demo'!M5 -> -3284
B66: ='Cash Flow demo'!A6 -> Payables | C66: ='Cash Flow demo'!D6 -> 2543 | D66: ='Cash Flow demo'!E6 -> -2143 | E66: ='Cash Flow demo'!F6 -> 1561 | F66: ='Cash Flow demo'!G6 -> 2514 | G66: ='Cash Flow demo'!H6 -> 3406 | H66: ='Cash Flow demo'!I6 -> 183 | I66: ='Cash Flow demo'!J6 -> 1306 | J66: ='Cash Flow demo'!K6 -> 13013 | ... L66: ='Cash Flow demo'!M6 -> -7235
B67: ='Cash Flow demo'!A7 -> Loans Advances | C67: ='Cash Flow demo'!D7 -> 286 | D67: ='Cash Flow demo'!E7 -> 0 | E67: ='Cash Flow demo'!F7 -> 0 | F67: ='Cash Flow demo'!G7 -> 0 | G67: ='Cash Flow demo'!H7 -> 0 | H67: ='Cash Flow demo'!I7 -> 0 | I67: ='Cash Flow demo'!J7 -> 0 | J67: ='Cash Flow demo'!K7 -> 0 | ... L67: ='Cash Flow demo'!M7 -> 0
B68: ='Cash Flow demo'!A8 -> Other WC items | C68: ='Cash Flow demo'!D8 -> 31 | D68: ='Cash Flow demo'!E8 -> 351 | E68: ='Cash Flow demo'!F8 -> -1013 | F68: ='Cash Flow demo'!G8 -> -1776 | G68: ='Cash Flow demo'!H8 -> -1043 | H68: ='Cash Flow demo'!I8 -> -1746 | I68: ='Cash Flow demo'!J8 -> 221 | J68: ='Cash Flow demo'!K8 -> -2800 | ... L68: ='Cash Flow demo'!M8 -> -2942
B69: ='Cash Flow demo'!A9 -> Working capital changes | C69: ='Cash Flow demo'!D9 -> -202 | D69: ='Cash Flow demo'!E9 -> 491 | E69: ='Cash Flow demo'!F9 -> -3869 | F69: ='Cash Flow demo'!G9 -> -1101 | G69: ='Cash Flow demo'!H9 -> -1581 | H69: ='Cash Flow demo'!I9 -> 1639 | I69: ='Cash Flow demo'!J9 -> 1264 | J69: ='Cash Flow demo'!K9 -> -7264 | ... L69: ='Cash Flow demo'!M9 -> -13615
B70: ='Cash Flow demo'!A10 -> Direct taxes | C70: ='Cash Flow demo'!D10 -> -773 | D70: ='Cash Flow demo'!E10 -> -207 | E70: ='Cash Flow demo'!F10 -> -237 | F70: ='Cash Flow demo'!G10 -> -1440 | G70: ='Cash Flow demo'!H10 -> -2630 | H70: ='Cash Flow demo'!I10 -> -1155 | I70: ='Cash Flow demo'!J10 -> -1930 | J70: ='Cash Flow demo'!K10 -> -5379 | ... L70: ='Cash Flow demo'!M10 -> -2779
B71: Cash From Operating Activites | C71: =C63+C69+C70 -> 7875 | D71: =D63+D69+D70 -> 6898 | E71: =E63+E69+E70 -> 7888 | F71: =F63+F69+F70 -> 12379 | G71: =G63+G69+G70 -> 14633 | H71: =H63+H69+H70 -> 12785 | I71: =I63+I69+I70 -> 18789 | J71: =J63+J69+J70 -> 26270 | ... L71: =L63+L69+L70 -> 12078
B72: Investing Activites
B73: ='Cash Flow demo'!A12 -> Fixed assets purchased | C73: ='Cash Flow demo'!D12 -> -6721 | D73: ='Cash Flow demo'!E12 -> -5166 | E73: ='Cash Flow demo'!F12 -> -4435 | F73: ='Cash Flow demo'!G12 -> -4736 | G73: ='Cash Flow demo'!H12 -> -10206 | H73: ='Cash Flow demo'!I12 -> -12810 | I73: ='Cash Flow demo'!J12 -> -9258 | J73: ='Cash Flow demo'!K12 -> -10091 | ... L73: ='Cash Flow demo'!M12 -> -15801
B74: ='Cash Flow demo'!A13 -> Fixed assets sold | C74: ='Cash Flow demo'!D13 -> 207 | D74: ='Cash Flow demo'!E13 -> 4 | E74: ='Cash Flow demo'!F13 -> 45 | F74: ='Cash Flow demo'!G13 -> 60 | G74: ='Cash Flow demo'!H13 -> 44 | H74: ='Cash Flow demo'!I13 -> 43 | I74: ='Cash Flow demo'!J13 -> 51 | J74: ='Cash Flow demo'!K13 -> 43 | ... L74: ='Cash Flow demo'!M13 -> 254
B75: ='Cash Flow demo'!A14 -> Investments purchased | C75: ='Cash Flow demo'!D14 -> 0 | D75: ='Cash Flow demo'!E14 -> 0 | E75: ='Cash Flow demo'!F14 -> -2784 | F75: ='Cash Flow demo'!G14 -> -8111 | G75: ='Cash Flow demo'!H14 -> -8340 | H75: ='Cash Flow demo'!I14 -> -762 | I75: ='Cash Flow demo'!J14 -> -606 | J75: ='Cash Flow demo'!K14 -> -4440 | ... L75: ='Cash Flow demo'!M14 -> -3584
B76: ='Cash Flow demo'!A15 -> Investments sold | C76: ='Cash Flow demo'!D15 -> 70 | D76: ='Cash Flow demo'!E15 -> 0 | E76: ='Cash Flow demo'!F15 -> 2490 | F76: ='Cash Flow demo'!G15 -> 8120 | G76: ='Cash Flow demo'!H15 -> 8591 | H76: ='Cash Flow demo'!I15 -> 847 | I76: ='Cash Flow demo'!J15 -> 612 | J76: ='Cash Flow demo'!K15 -> 4153 | ... L76: ='Cash Flow demo'!M15 -> 3635
B77: ='Cash Flow demo'!A16 -> Interest received | C77: ='Cash Flow demo'!D16 -> 26 | D77: ='Cash Flow demo'!E16 -> 41 | E77: ='Cash Flow demo'!F16 -> 98 | F77: ='Cash Flow demo'!G16 -> 121 | G77: ='Cash Flow demo'!H16 -> 158 | H77: ='Cash Flow demo'!I16 -> 503 | I77: ='Cash Flow demo'!J16 -> 619 | J77: ='Cash Flow demo'!K16 -> 591 | ... L77: ='Cash Flow demo'!M16 -> 899
B78: ='Cash Flow demo'!A17 -> Dividends received | C78: ='Cash Flow demo'!D17 -> 21 | D78: ='Cash Flow demo'!E17 -> 20 | E78: ='Cash Flow demo'!F17 -> 20 | F78: ='Cash Flow demo'!G17 -> 5 | G78: ='Cash Flow demo'!H17 -> 0 | H78: ='Cash Flow demo'!I17 -> 10 | I78: ='Cash Flow demo'!J17 -> 11 | J78: ='Cash Flow demo'!K17 -> 25 | ... L78: ='Cash Flow demo'!M17 -> 21
B79: ='Cash Flow demo'!A18 -> Investment in group cos | C79: ='Cash Flow demo'!D18 -> -40 | D79: ='Cash Flow demo'!E18 -> -9 | E79: ='Cash Flow demo'!F18 -> -37 | F79: ='Cash Flow demo'!G18 -> -46 | G79: ='Cash Flow demo'!H18 -> -413 | H79: ='Cash Flow demo'!I18 -> 0 | I79: ='Cash Flow demo'!J18 -> -5087 | J79: ='Cash Flow demo'!K18 -> -364 | ... L79: ='Cash Flow demo'!M18 -> -396
B80: ='Cash Flow demo'!A19 -> Redemp n Canc of Shares | C80: ='Cash Flow demo'!D19 -> 0 | D80: ='Cash Flow demo'!E19 -> 0 | E80: ='Cash Flow demo'!F19 -> 0 | F80: ='Cash Flow demo'!G19 -> 0 | G80: ='Cash Flow demo'!H19 -> 0 | H80: ='Cash Flow demo'!I19 -> 164 | I80: ='Cash Flow demo'!J19 -> 0 | J80: ='Cash Flow demo'!K19 -> 0 | ... L80: ='Cash Flow demo'!M19 -> 0
B81: ='Cash Flow demo'!A20 -> Acquisition of companies | C81: ='Cash Flow demo'!D20 -> 0 | D81: ='Cash Flow demo'!E20 -> 0 | E81: ='Cash Flow demo'!F20 -> -110 | F81: ='Cash Flow demo'!G20 -> -315 | G81: ='Cash Flow demo'!H20 -> -1014 | H81: ='Cash Flow demo'!I20 -> -64 | I81: ='Cash Flow demo'!J20 -> -1575 | J81: ='Cash Flow demo'!K20 -> -20 | ... L81: ='Cash Flow demo'!M20 -> -630
B82: ='Cash Flow demo'!A21 -> Inter corporate deposits | C82: ='Cash Flow demo'!D21 -> 0 | D82: ='Cash Flow demo'!E21 -> 0 | E82: ='Cash Flow demo'!F21 -> 0 | F82: ='Cash Flow demo'!G21 -> 0 | G82: ='Cash Flow demo'!H21 -> 0 | H82: ='Cash Flow demo'!I21 -> 0 | I82: ='Cash Flow demo'!J21 -> -293 | J82: ='Cash Flow demo'!K21 -> -149 | ... L82: ='Cash Flow demo'!M21 -> 0
B83: ='Cash Flow demo'!A22 -> Other investing items | C83: ='Cash Flow demo'!D22 -> -936 | D83: ='Cash Flow demo'!E22 -> 1252 | E83: ='Cash Flow demo'!F22 -> -381 | F83: ='Cash Flow demo'!G22 -> 373 | G83: ='Cash Flow demo'!H22 -> -207 | H83: ='Cash Flow demo'!I22 -> -7520 | I83: ='Cash Flow demo'!J22 -> 7824 | J83: ='Cash Flow demo'!K22 -> -4496 | ... L83: ='Cash Flow demo'!M22 -> 1135
B84: Cash From Financing Activites | C84: =SUM(C73:C83) -> -7373 | D84: =SUM(D73:D83) -> -3858 | E84: =SUM(E73:E83) -> -5094 | F84: =SUM(F73:F83) -> -4529 | G84: =SUM(G73:G83) -> -11387 | H84: =SUM(H73:H83) -> -19589 | I84: =SUM(I73:I83) -> -7702 | J84: =SUM(J73:J83) -> -14748 | ... L84: =SUM(L73:L83) -> -14467
B85: Financing Activites
B86: ='Cash Flow demo'!A24 -> Proceeds from shares | C86: ='Cash Flow demo'!D24 -> 0 | D86: ='Cash Flow demo'!E24 -> 0 | E86: ='Cash Flow demo'!F24 -> 57 | F86: ='Cash Flow demo'!G24 -> 49 | G86: ='Cash Flow demo'!H24 -> 0 | H86: ='Cash Flow demo'!I24 -> 107 | I86: ='Cash Flow demo'!J24 -> 39 | J86: ='Cash Flow demo'!K24 -> 72 | ... L86: ='Cash Flow demo'!M24 -> 6
B87: ='Cash Flow demo'!A25 -> Redemption of debentures | C87: ='Cash Flow demo'!D25 -> 0 | D87: ='Cash Flow demo'!E25 -> 0 | E87: ='Cash Flow demo'!F25 -> 0 | F87: ='Cash Flow demo'!G25 -> 0 | G87: ='Cash Flow demo'!H25 -> 0 | H87: ='Cash Flow demo'!I25 -> -572 | I87: ='Cash Flow demo'!J25 -> 0 | J87: ='Cash Flow demo'!K25 -> 0 | ... L87: ='Cash Flow demo'!M25 -> 0
B88: ='Cash Flow demo'!A26 -> Proceeds from borrowings | C88: ='Cash Flow demo'!D26 -> 10216 | D88: ='Cash Flow demo'!E26 -> 1197 | E88: ='Cash Flow demo'!F26 -> 7101 | F88: ='Cash Flow demo'!G26 -> 6209 | G88: ='Cash Flow demo'!H26 -> 13154 | H88: ='Cash Flow demo'!I26 -> 22754 | I88: ='Cash Flow demo'!J26 -> 15897 | J88: ='Cash Flow demo'!K26 -> 17043 | ... L88: ='Cash Flow demo'!M26 -> 20858
B89: ='Cash Flow demo'!A27 -> Repayment of borrowings | C89: ='Cash Flow demo'!D27 -> -7479 | D89: ='Cash Flow demo'!E27 -> 0 | E89: ='Cash Flow demo'!F27 -> -5890 | F89: ='Cash Flow demo'!G27 -> -10001 | G89: ='Cash Flow demo'!H27 -> -6273 | H89: ='Cash Flow demo'!I27 -> -11107 | I89: ='Cash Flow demo'!J27 -> -13888 | J89: ='Cash Flow demo'!K27 -> -24091 | ... L89: ='Cash Flow demo'!M27 -> -16328
B90: ='Cash Flow demo'!A28 -> Interest paid fin | C90: ='Cash Flow demo'!D28 -> -2563 | D90: ='Cash Flow demo'!E28 -> -3125 | E90: ='Cash Flow demo'!F28 -> -3569 | F90: ='Cash Flow demo'!G28 -> -3511 | G90: ='Cash Flow demo'!H28 -> -3815 | H90: ='Cash Flow demo'!I28 -> -4520 | I90: ='Cash Flow demo'!J28 -> -4340 | J90: ='Cash Flow demo'!K28 -> -5102 | ... L90: ='Cash Flow demo'!M28 -> -8087
B91: ='Cash Flow demo'!A29 -> Dividends paid | C91: ='Cash Flow demo'!D29 -> -344 | D91: ='Cash Flow demo'!E29 -> -320 | E91: ='Cash Flow demo'!F29 -> -218 | F91: ='Cash Flow demo'!G29 -> -655 | G91: ='Cash Flow demo'!H29 -> -933 | H91: ='Cash Flow demo'!I29 -> -1195 | I91: ='Cash Flow demo'!J29 -> -483 | J91: ='Cash Flow demo'!K29 -> -1571 | ... L91: ='Cash Flow demo'!M29 -> -822
B92: ='Cash Flow demo'!A30 -> Financial liabilities | C92: ='Cash Flow demo'!D30 -> 0 | D92: ='Cash Flow demo'!E30 -> -187 | E92: ='Cash Flow demo'!F30 -> -186 | F92: ='Cash Flow demo'!G30 -> -200 | G92: ='Cash Flow demo'!H30 -> -227 | H92: ='Cash Flow demo'!I30 -> -177 | I92: ='Cash Flow demo'!J30 -> -335 | J92: ='Cash Flow demo'!K30 -> -417 | ... L92: ='Cash Flow demo'!M30 -> -632
B93: ='Cash Flow demo'!A31 -> Other financing items | C93: ='Cash Flow demo'!D31 -> 0 | D93: ='Cash Flow demo'!E31 -> -715 | E93: ='Cash Flow demo'!F31 -> -5 | F93: ='Cash Flow demo'!G31 -> -76 | G93: ='Cash Flow demo'!H31 -> -153 | H93: ='Cash Flow demo'!I31 -> -101 | I93: ='Cash Flow demo'!J31 -> 0 | J93: ='Cash Flow demo'!K31 -> -591 | ... L93: ='Cash Flow demo'!M31 -> 0
B94: Cash From Investing Activites | C94: =SUM(C86:C93) -> -170 | D94: =SUM(D86:D93) -> -3150 | E94: =SUM(E86:E93) -> -2710 | F94: =SUM(F86:F93) -> -8185 | G94: =SUM(G86:G93) -> 1753 | H94: =SUM(H86:H93) -> 5189 | I94: =SUM(I86:I93) -> -3110 | J94: =SUM(J86:J93) -> -14657 | ... L94: =SUM(L86:L93) -> -5005
B96: Net Cash Flow | C96: =SUM(C71,C84,C94) -> 332 | D96: =SUM(D71,D84,D94) -> -110 | E96: =SUM(E71,E84,E94) -> 84 | F96: =SUM(F71,F84,F94) -> -335 | G96: =SUM(G71,G84,G94) -> 4999 | H96: =SUM(H71,H84,H94) -> -1615 | I96: =SUM(I71,I84,I94) -> 7977 | J96: =SUM(J71,J84,J94) -> -3135 | K96: =SUM(K71+K84+K94) -> 6616 | L96: =SUM(L71+L84+L94) -> -7394

Sheet Ratio Analysis
B2: ="Ratio Analysis-"&'Data Sheet'!B1 -> Ratio Analysis-JSW STEEL LTD
B3: Years | C3: ='Data Sheet'!B16 -> 42094 | D3: ='Data Sheet'!C16 -> 42460 | E3: ='Data Sheet'!D16 -> 42825 | F3: ='Data Sheet'!E16 -> 43190 | G3: ='Data Sheet'!F16 -> 43555 | H3: ='Data Sheet'!G16 -> 43921 | I3: ='Data Sheet'!H16 -> 44286 | J3: ='Data Sheet'!I16 -> 44651 | ... L3: ='Data Sheet'!K16 -> 45382 | M3: Trend | N3: Mean | O3: Median
B5: Sales Growth | D5: ='Historical FS'!D7 -> -0.2156884 | E5: ='Historical FS'!E7 -> 0.33836645 | F5: ='Historical FS'!F7 -> 0.29366592 | G5: ='Historical FS'!G7 -> 0.17827701 | H5: ='Historical FS'!H7 -> -0.13486792 | I5: ='Historical FS'!I7 -> 0.088822519 | J5: ='Historical FS'!J7 -> 0.83332707 | K5: ='Historical FS'!K7 -> 0.13383116 | L5: ='Historical FS'!L7 -> 0.05450711 | N5: =AVERAGE(D5:L5) -> 0.17447121 | O5: =MEDIAN(D5:L5) -> 0.13383116
B6: EBITDA Growth | D6: ='Historical FS'!D17/'Historical FS'!C17-1 -> -0.31413861 | E6: ='Historical FS'!E17/'Historical FS'!D17-1 -> 0.91644439 | F6: ='Historical FS'!F17/'Historical FS'!E17-1 -> 0.2118947 | G6: ='Historical FS'!G17/'Historical FS'!F17-1 -> 0.269107 | H6: ='Historical FS'!H17/'Historical FS'!G17-1 -> -0.37596408 | I6: ='Historical FS'!I17/'Historical FS'!H17-1 -> 0.70811817 | J6: ='Historical FS'!J17/'Historical FS'!I17-1 -> 0.93844781 | K6: ='Historical FS'!K17/'Historical FS'!J17-1 -> -0.52779056 | L6: ='Historical FS'!L17/'Historical FS'!K17-1 -> 0.52447212 | N6: =AVERAGE(D6:L6) -> 0.26117677 | O6: =MEDIAN(D6:L6) -> 0.269107
B7: EBIT Growth | D7: ='Historical FS'!D23/'Historical FS'!C23-1 -> -1.2058128 | E7: ='Historical FS'!E23/'Historical FS'!D23-1 -> -11.190854 | F7: ='Historical FS'!F23/'Historical FS'!E23-1 -> 0.53189824 | G7: ='Historical FS'!G23/'Historical FS'!F23-1 -> 0.40163516 | H7: ='Historical FS'!H23/'Historical FS'!G23-1 -> -0.69905213 | I7: ='Historical FS'!I23/'Historical FS'!H23-1 -> 2.4954573 | J7: ='Historical FS'!J23/'Historical FS'!I23-1 -> 1.4384855 | K7: ='Historical FS'!K23/'Historical FS'!J23-1 -> -0.85453899 | L7: ='Historical FS'!L23/'Historical FS'!K23-1 -> 1.9018075 | N7: =AVERAGE(D7:L7) -> -0.79788604 | O7: =MEDIAN(D7:L7) -> 0.40163516
B8: Net Profit Growth | D8: ='Historical FS'!D27/'Historical FS'!C27-1 -> -0.094098075 | E8: ='Historical FS'!E27/'Historical FS'!D27-1 -> 1.3457448 | F8: ='Historical FS'!F27/'Historical FS'!E27-1 -> 0.830617 | G8: ='Historical FS'!G27/'Historical FS'!F27-1 -> 0.16502385 | H8: ='Historical FS'!H27/'Historical FS'!G27-1 -> -0.42576419 | I8: ='Historical FS'!I27/'Historical FS'!H27-1 -> 0.75855513 | J8: ='Historical FS'!J27/'Historical FS'!I27-1 -> 1.6132432 | K8: ='Historical FS'!K27/'Historical FS'!J27-1 -> -0.86668735 | L8: ='Historical FS'!L27/'Historical FS'!K27-1 -> 1.8987587 | N8: =AVERAGE(D8:L8) -> 0.58059923 | O8: =MEDIAN(D8:L8) -> 0.75855513
B9: Dividentv Growth | D9: ='Historical FS'!D33/'Historical FS'!C33-1 -> -0.32232298 | E9: ='Historical FS'!E33/'Historical FS'!D33-1 -> 2.0009305 | F9: ='Historical FS'!F33/'Historical FS'!E33-1 -> 0.42694721 | G9: ='Historical FS'!G33/'Historical FS'!F33-1 -> 0.27700745 | H9: ='Historical FS'!H33/'Historical FS'!G33-1 -> -0.51219512 | I9: ='Historical FS'!I33/'Historical FS'!H33-1 -> 2.2607973 | J9: ='Historical FS'!J33/'Historical FS'!I33-1 -> 1.6603923 | K9: ='Historical FS'!K33/'Historical FS'!J33-1 -> -0.80403458 | L9: ='Historical FS'!L33/'Historical FS'!K33-1 -> 1.1504146 | N9: =AVERAGE(D9:L9) -> 0.68199297 | O9: =MEDIAN(D9:L9) -> 0.42694721
B11: Gross Margin | C11: ='Historical FS'!C13 -> 0.20574437 | D11: ='Historical FS'!D13 -> 0.19442923 | E11: ='Historical FS'!E13 -> 0.24946047 | F11: ='Historical FS'!F13 -> 0.2315349 | G11: ='Historical FS'!G13 -> 0.25780761 | H11: ='Historical FS'!H13 -> 0.20786624 | I11: ='Historical FS'!I13 -> 0.282982 | J11: ='Historical FS'!J13 -> 0.29099343 | ... L11: ='Historical FS'!L13 -> 0.19373621 | N11: =AVERAGE(D11:L11) -> 0.22885108 | O11: =MEDIAN(D11:L11) -> 0.2315349
B12: EBITDA Margin | C12: ='Historical FS'!C18 -> 0.17677163 | D12: ='Historical FS'!D18 -> 0.15458248 | E12: ='Historical FS'!E18 -> 0.22135098 | F12: ='Historical FS'!F18 -> 0.20735963 | G12: ='Historical FS'!G18 -> 0.22334438 | H12: ='Historical FS'!H18 -> 0.16110247 | I12: ='Historical FS'!I18 -> 0.25273363 | J12: ='Historical FS'!J18 -> 0.26722507 | ... L12: ='Historical FS'!L18 -> 0.16089163 | N12: =AVERAGE(D12:L12) -> 0.19554246 | O12: =MEDIAN(D12:L12) -> 0.20735963
B13: EBIT Margin | C13: ='Data Sheet'!B35 -> 0.11193508 | D13: ='Data Sheet'!C35 -> 0.074609765 | E13: ='Data Sheet'!D35 -> 0.15966477 | F13: ='Data Sheet'!E35 -> 0.16027414 | G13: ='Data Sheet'!F35 -> 0.17566691 | H13: ='Data Sheet'!G35 -> 0.10319668 | I13: ='Data Sheet'!H35 -> 0.19412818 | J13: ='Data Sheet'!I35 -> 0.22622651 | ... L13: ='Data Sheet'!K35 -> 0.11419608 | N13: =AVERAGE(D13:L13) -> 0.14158 | O13: =MEDIAN(D13:L13) -> 0.15966477
B14: EBT Margin | C14: ='Historical FS'!C24 -> 0.045993403 | D14: ='Historical FS'!D24 -> -0.012069223 | E14: ='Historical FS'!E24 -> 0.091899863 | F14: ='Historical FS'!F24 -> 0.10882349 | G14: ='Historical FS'!G24 -> 0.12945243 | H14: ='Historical FS'!H24 -> 0.045031776 | I14: ='Historical FS'!I24 -> 0.14456594 | J14: ='Historical FS'!J24 -> 0.19228536 | ... L14: ='Historical FS'!L24 -> 0.067883387 | N14: =AVERAGE(D14:L14) -> 0.08806018 | O14: =MEDIAN(D14:L14) -> 0.091899863
B15: Net Profit Margin | C15: ='Historical FS'!C28 -> 0.030524522 | D15: ='Historical FS'!D28 -> 0.035256679 | E15: ='Historical FS'!E28 -> 0.061794116 | F15: ='Historical FS'!F28 -> 0.087442481 | G15: ='Historical FS'!G28 -> 0.086458936 | H15: ='Historical FS'!H28 -> 0.057387557 | I15: ='Historical FS'!I28 -> 0.092686532 | J15: ='Historical FS'!J28 -> 0.13211633 | ... L15: ='Historical FS'!L28 -> 0.042701393 | N15: =AVERAGE(D15:L15) -> 0.067930877 | O15: =MEDIAN(D15:L15) -> 0.061794116
B17: Sales Expense % of Sales | C17: ='Historical FS'!C16 -> 0.028972744 | D17: ='Historical FS'!D16 -> 0.039846754 | E17: ='Historical FS'!E16 -> 0.028109489 | F17: ='Historical FS'!F16 -> 0.024175274 | G17: ='Historical FS'!G16 -> 0.03446323 | H17: ='Historical FS'!H16 -> 0.046763767 | I17: ='Historical FS'!I16 -> 0.030248375 | J17: ='Historical FS'!J16 -> 0.023768369 | ... L17: ='Historical FS'!L16 -> 0.032844588 | N17: =AVERAGE(D17:L17) -> 0.033308619 | O17: =MEDIAN(D17:L17) -> 0.032844588
B18: Depriciaton% of Sales | C18: ='Historical FS'!C22 -> 0.064836551 | D18: ='Historical FS'!D22 -> 0.079972715 | E18: ='Historical FS'!E22 -> 0.06168621 | F18: ='Historical FS'!F22 -> 0.047085482 | G18: ='Historical FS'!G22 -> 0.047677478 | H18: ='Historical FS'!H22 -> 0.057905791 | I18: ='Historical FS'!I22 -> 0.058605443 | J18: ='Historical FS'!J22 -> 0.040998558 | ... L18: ='Historical FS'!L22 -> 0.046695542 | N18: =AVERAGE(D18:L18) -> 0.053962463 | O18: =MEDIAN(D18:L18) -> 0.047677478
B20: Return on Capital Employed% | C20: =('Historical FS'!C23+'Historical FS'!C19)/SUM('Historical FS'!C39,'Historical FS'!C40,'Historical FS'!C41) -> 0.097132883 | D20: =('Historical FS'!D23+'Historical FS'!D19)/SUM('Historical FS'!D39,'Historical FS'!D40,'Historical FS'!D41) -> 0.050674781 | E20: =('Historical FS'!E23+'Historical FS'!E19)/SUM('Historical FS'!E39,'Historical FS'!E40,'Historical FS'!E41) -> 0.13455389 | F20: =('Historical FS'!F23+'Historical FS'!F19)/SUM('Historical FS'!F39,'Historical FS'!F40,'Historical FS'!F41) -> 0.17107626 | G20: =('Historical FS'!G23+'Historical FS'!G19)/SUM('Historical FS'!G39,'Historical FS'!G40,'Historical FS'!G41) -> 0.18115122 | H20: =('Historical FS'!H23+'Historical FS'!H19)/SUM('Historical FS'!H39,'Historical FS'!H40,'Historical FS'!H41) -> 0.077196956 | I20: =('Historical FS'!I23+'Historical FS'!I19)/SUM('Historical FS'!I39,'Historical FS'!I40,'Historical FS'!I41) -> 0.14198945 | J20: =('Historical FS'!J23+'Historical FS'!J19)/SUM('Historical FS'!J39,'Historical FS'!J40,'Historical FS'!J41) -> 0.23731134 | ... L20: =('Historical FS'!L23+'Historical FS'!L19)/SUM('Historical FS'!L39,'Historical FS'!L40,'Historical FS'!L41) -> 0.12064376 | N20: =AVERAGE(D20:L20) -> 0.13218123 | O20: =MEDIAN(D20:L20) -> 0.13455389
B21: Return on Equity% | C21: ='Historical FS'!C27/SUM('Historical FS'!C39:C40) -> 0.072541773 | D21: ='Historical FS'!D27/SUM('Historical FS'!D39:D40) -> 0.077234128 | E21: ='Historical FS'!E27/SUM('Historical FS'!E39:E40) -> 0.15171987 | F21: ='Historical FS'!F27/SUM('Historical FS'!F39:F40) -> 0.2246589 | G21: ='Historical FS'!G27/SUM('Historical FS'!G39:G40) -> 0.21060497 | H21: ='Historical FS'!H27/SUM('Historical FS'!H39:H40) -> 0.11497582 | I21: ='Historical FS'!I27/SUM('Historical FS'!I39:I40) -> 0.15824138 | J21: ='Historical FS'!J27/SUM('Historical FS'!J39:J40) -> 0.28735308 | ... L21: ='Historical FS'!L27/SUM('Historical FS'!L39:L40) -> 0.096215994 | N21: =AVERAGE(D21:L21) -> 0.15113846 | O21: =MEDIAN(D21:L21) -> 0.15171987
B22: Reatined Earning% | C22: ='Historical FS'!C35 -> 5.3115588 | D22: ='Historical FS'!D35 -> 5.1261791 | E22: ='Historical FS'!E35 -> 11.412999 | F22: ='Historical FS'!F35 -> 22.023829 | G22: ='Historical FS'!G35 -> 25.210574 | H22: ='Historical FS'!H35 -> 14.918087 | I22: ='Historical FS'!I35 -> 22.492967 | J22: ='Historical FS'!J35 -> 58.396699 | ... L22: ='Historical FS'!L35 -> 21.45369 | N22: =AVERAGE(D22:L22) -> 20.829604 | O22: =MEDIAN(D22:L22) -> 21.45369
B23: Self Sustained Growth | C23: =C21*C22 -> 0.38530989 | D23: =D21*D22 -> 0.39591597 | E23: =E21*E22 -> 1.7315787 | F23: =F21*F22 -> 4.9478493 | G23: =G21*G22 -> 5.3094723 | H23: =H21*H22 -> 1.7152193 | I23: =I21*I22 -> 3.5593182 | J23: =J21*J22 -> 16.780471 | ... L23: =L21*L22 -> 2.0641881 | N23: =AVERAGE(D23:L23) -> 4.0840438 | O23: =MEDIAN(D23:L23) -> 2.0641881
B24: Intrest Coverage Ratio | C24: =SUM('Historical FS'!C23,'Historical FS'!C19)/'Historical FS'!C19 -> 1.6974861 | D24: =SUM('Historical FS'!D23,'Historical FS'!D19)/'Historical FS'!D19 -> 0.86075953 | E24: =SUM('Historical FS'!E23,'Historical FS'!E19)/'Historical FS'!E19 -> 2.3561571 | F24: =SUM('Historical FS'!F23,'Historical FS'!F19)/'Historical FS'!F19 -> 3.115104 | G24: =SUM('Historical FS'!G23,'Historical FS'!G19)/'Historical FS'!G19 -> 3.8011233 | H24: =SUM('Historical FS'!H23,'Historical FS'!H19)/'Historical FS'!H19 -> 1.7742087 | I24: =SUM('Historical FS'!I23,'Historical FS'!I19)/'Historical FS'!I19 -> 3.9168562 | J24: =SUM('Historical FS'!J23,'Historical FS'!J19)/'Historical FS'!J19 -> 6.6652576 | ... L24: =SUM('Historical FS'!L23,'Historical FS'!L19)/'Historical FS'!L19 -> 2.4657619 | N24: =AVERAGE(D24:L24) -> 2.9498211 | O24: =MEDIAN(D24:L24) -> 2.4657619
B26: Debtor Turnover Ratio | C26: ='Historical FS'!C6/'Historical FS'!C51 -> 21.190723 | D26: ='Historical FS'!D6/'Historical FS'!D51 -> 15.233052 | E26: ='Historical FS'!E6/'Historical FS'!E51 -> 13.401784 | F26: ='Historical FS'!F6/'Historical FS'!F51 -> 15.291879 | G26: ='Historical FS'!G6/'Historical FS'!G51 -> 11.83757 | H26: ='Historical FS'!H6/'Historical FS'!H51 -> 16.276582 | I26: ='Historical FS'!I6/'Historical FS'!I51 -> 17.79737 | J26: ='Historical FS'!J6/'Historical FS'!J51 -> 19.628671 | ... L26: ='Historical FS'!L6/'Historical FS'!L51 -> 23.185745 | N26: =AVERAGE(D26:L26) -> 17.323989 | O26: =MEDIAN(D26:L26) -> 16.276582
B27: Creditor Turnover Ratio | C27: ='Historical FS'!C6/'Data Sheet'!C77 -> 3.7165165 | D27: ='Historical FS'!D6/'Data Sheet'!D77 -> 3.2564799 | E27: ='Historical FS'!E6/'Data Sheet'!E77 -> 4.1657177 | F27: ='Historical FS'!F6/'Data Sheet'!F77 -> 4.5116031 | G27: ='Historical FS'!G6/'Data Sheet'!G77 -> 5.2451884 | H27: ='Historical FS'!H6/'Data Sheet'!H77 -> 4.0923094 | I27: ='Historical FS'!I6/'Data Sheet'!I77 -> 5.2377485 | J27: ='Historical FS'!J6/'Data Sheet'!J77 -> 4.7386125 | ... L27: ='Historical FS'!L6/'Data Sheet'!L77 -> 5.2451971 | N27: =AVERAGE(D27:L27) -> 4.5374464 | O27: =MEDIAN(D27:L27) -> 4.5116031
B28: Inventory Turnover Ratio | C28: ='Historical FS'!C6/'Historical FS'!C52 -> 4.8116375 | D28: ='Historical FS'!D6/'Historical FS'!D52 -> 4.9928219 | E28: ='Historical FS'!E6/'Historical FS'!E52 -> 4.8796841 | F28: ='Historical FS'!F6/'Historical FS'!F52 -> 5.7116881 | G28: ='Historical FS'!G6/'Historical FS'!G52 -> 5.8260242 | H28: ='Historical FS'!H6/'Historical FS'!H52 -> 5.3238946 | I28: ='Historical FS'!I6/'Historical FS'!I52 -> 5.60313 | J28: ='Historical FS'!J6/'Historical FS'!J52 -> 4.3321692 | ... L28: ='Historical FS'!L6/'Historical FS'!L52 -> 4.6279519 | N28: =AVERAGE(D28:L28) -> 5.1451072 | O28: =MEDIAN(D28:L28) -> 5.0086012
B29: Fixed Asset Turnover Ratio | C29: ='Historical FS'!C6/'Historical FS'!C45 -> 1.0152412 | D29: ='Historical FS'!D6/'Historical FS'!D45 -> 0.74005211 | E29: ='Historical FS'!E6/'Historical FS'!E45 -> 0.94677337 | F29: ='Historical FS'!F6/'Historical FS'!F45 -> 1.2434829 | G29: ='Historical FS'!G6/'Historical FS'!G45 -> 1.3529947 | H29: ='Historical FS'!H6/'Historical FS'!H45 -> 1.1810582 | I29: ='Historical FS'!I6/'Historical FS'!I45 -> 1.2298627 | J29: ='Historical FS'!J6/'Historical FS'!J45 -> 1.4654686 | ... L29: ='Historical FS'!L6/'Historical FS'!L45 -> 1.5561484 | N29: =AVERAGE(D29:L29) -> 1.2560783 | O29: =MEDIAN(D29:L29) -> 1.2434829
B30: Capital Turnover Ratio | C30: ='Historical FS'!C6/SUM('Historical FS'!C39:C40) -> 2.3765081 | D30: ='Historical FS'!D6/SUM('Historical FS'!D39:D40) -> 2.190624 | E30: ='Historical FS'!E6/SUM('Historical FS'!E39:E40) -> 2.4552479 | F30: ='Historical FS'!F6/SUM('Historical FS'!F39:F40) -> 2.5692192 | G30: ='Historical FS'!G6/SUM('Historical FS'!G39:G40) -> 2.435896 | H30: ='Historical FS'!H6/SUM('Historical FS'!H39:H40) -> 2.0034974 | I30: ='Historical FS'!I6/SUM('Historical FS'!I39:I40) -> 1.7072748 | J30: ='Historical FS'!J6/SUM('Historical FS'!J39:J40) -> 2.1750004 | ... L30: ='Historical FS'!L6/SUM('Historical FS'!L39:L40) -> 2.2532284 | N30: =AVERAGE(D30:L30) -> 2.2573564 | O30: =MEDIAN(D30:L30) -> 2.2532284
B32: Debtor Days | C32: =365/C26 -> 17.224518 | D32: =365/D26 -> 23.961055 | E32: =365/E26 -> 27.235181 | F32: =365/F26 -> 23.868878 | G32: =365/G26 -> 30.834031 | H32: =365/H26 -> 22.424856 | I32: =365/I26 -> 20.508649 | J32: =365/J26 -> 18.595248 | ... L32: =365/L26 -> 15.742432 | N32: =AVERAGE(D32:L32) -> 22.095591 | O32: =MEDIAN(D32:L32) -> 22.424856
B33: Inventory days | C33: =365/C27 -> 98.210245 | D33: =365/D27 -> 112.08422 | E33: =365/E27 -> 87.619955 | F33: =365/F27 -> 80.902506 | G33: =365/G27 -> 69.587586 | H33: =365/H27 -> 89.191692 | I33: =365/I27 -> 69.686431 | J33: =365/J27 -> 77.026768 | ... L33: =365/L27 -> 69.587471 | N33: =AVERAGE(D33:L33) -> 82.189716 | O33: =MEDIAN(D33:L33) -> 80.902506
B34: Payabel Days | C34: =365/C28 -> 75.857751 | D34: =365/D28 -> 73.10495 | E34: =365/E28 -> 74.799924 | F34: =365/F28 -> 63.90405 | G34: =365/G28 -> 62.649929 | H34: =365/H28 -> 68.558833 | I34: =365/I28 -> 65.142161 | J34: =365/J28 -> 84.253404 | ... L34: =365/L28 -> 78.868582 | N34: =AVERAGE(D34:L34) -> 71.572941 | O34: =MEDIAN(D34:L34) -> 72.874638
B35: Cash Conversion Cycel | C35: =365/C29 -> 359.52047 | D35: =365/D29 -> 493.20851 | E35: =365/E29 -> 385.51993 | F35: =365/F29 -> 293.53037 | G35: =365/G29 -> 269.77194 | H35: =365/H29 -> 309.04488 | I35: =365/I29 -> 296.78108 | J35: =365/J29 -> 249.0671 | ... L35: =365/L29 -> 234.55347 | N35: =AVERAGE(D35:L35) -> 306.80013 | O35: =MEDIAN(D35:L35) -> 293.53037
B37: CFO/Sales | C37: ='Historical FS'!C71/'Historical FS'!C6 -> 0.14866482 | D37: ='Historical FS'!D71/'Historical FS'!D6 -> 0.16603215 | E37: ='Historical FS'!E71/'Historical FS'!E6 -> 0.1418603 | F37: ='Historical FS'!F71/'Historical FS'!F6 -> 0.1720907 | G37: ='Historical FS'!G71/'Historical FS'!G6 -> 0.17264651 | H37: ='Historical FS'!H71/'Historical FS'!H6 -> 0.17435834 | I37: ='Historical FS'!I71/'Historical FS'!I6 -> 0.23533611 | J37: ='Historical FS'!J71/'Historical FS'!J6 -> 0.17947544 | ... L37: ='Historical FS'!L71/'Historical FS'!L6 -> 0.069014777 | N37: =AVERAGE(D37:L37) -> 0.16126091 | O37: =MEDIAN(D37:L37) -> 0.1720907
B38: CFO/Total Asset | C38: ='Historical FS'!C71/'Historical FS'!C56 -> 0.091939793 | D38: ='Historical FS'!D71/'Historical FS'!D56 -> 0.084217569 | E38: ='Historical FS'!E71/'Historical FS'!E56 -> 0.089631271 | F38: ='Historical FS'!F71/'Historical FS'!F56 -> 0.13459824 | G38: ='Historical FS'!G71/'Historical FS'!G56 -> 0.12746849 | H38: ='Historical FS'!H71/'Historical FS'!H56 -> 0.096988317 | I38: ='Historical FS'!I71/'Historical FS'!I56 -> 0.12668136 | J38: ='Historical FS'!J71/'Historical FS'!J56 -> 0.13369977 | ... L38: ='Historical FS'!L71/'Historical FS'!L56 -> 0.052997394 | N38: =AVERAGE(D38:L38) -> 0.10634 | O38: =MEDIAN(D38:L38) -> 0.11077758
B39: CFO/Total Debt | C39: ='Historical FS'!C71/'Historical FS'!C41 -> 0.20320347 | D39: ='Historical FS'!D71/'Historical FS'!D41 -> 0.16344411 | E39: ='Historical FS'!E71/'Historical FS'!E41 -> 0.18202797 | F39: ='Historical FS'!F71/'Historical FS'!F41 -> 0.31424365 | G39: ='Historical FS'!G71/'Historical FS'!G41 -> 0.30873913 | H39: ='Historical FS'!H71/'Historical FS'!H41 -> 0.20814679 | I39: ='Historical FS'!I71/'Historical FS'!I41 -> 0.30114438 | J39: ='Historical FS'!J71/'Historical FS'!J41 -> 0.36366405 | ... L39: ='Historical FS'!L71/'Historical FS'!L41 -> 0.13727496 | N39: =AVERAGE(D39:L39) -> 0.2519052 | O39: =MEDIAN(D39:L39) -> 0.28846178

Sheet Common Size Statement
B2: ="Common Size Statement "&" "& " - "&'Data Sheet'!$B$1 -> Common Size Statement - JSW STEEL LTD
B4: Particular | C4: ='Historical FS'!C3 -> 42094 | D4: ='Historical FS'!D3 -> 42460 | E4: ='Historical FS'!E3 -> 42825 | F4: ='Historical FS'!F3 -> 43190 | G4: ='Historical FS'!G3 -> 43555 | H4: ='Historical FS'!H3 -> 43921 | I4: ='Historical FS'!I3 -> 44286 | J4: ='Historical FS'!J3 -> 44651 | ... L4: ='Historical FS'!L3 -> 45382
B5: ='Data Sheet'!A17 -> Sales | C5: ='Data Sheet'!B17/'Data Sheet'!B$17 -> 1 | D5: ='Data Sheet'!C17/'Data Sheet'!C$17 -> 1 | E5: ='Data Sheet'!D17/'Data Sheet'!D$17 -> 1 | F5: ='Data Sheet'!E17/'Data Sheet'!E$17 -> 1 | G5: ='Data Sheet'!F17/'Data Sheet'!F$17 -> 1 | H5: ='Data Sheet'!G17/'Data Sheet'!G$17 -> 1 | I5: ='Data Sheet'!H17/'Data Sheet'!H$17 -> 1 | J5: ='Data Sheet'!I17/'Data Sheet'!I$17 -> 1 | ... L5: ='Data Sheet'!K17/'Data Sheet'!K$17 -> 1
B6: ='Data Sheet'!A18 -> Raw Material Cost | C6: ='Data Sheet'!B18/'Data Sheet'!B$17 -> 0.5878711 | D6: ='Data Sheet'!C18/'Data Sheet'!C$17 -> 0.50981884 | E6: ='Data Sheet'!D18/'Data Sheet'!D$17 -> 0.53501547 | F6: ='Data Sheet'!E18/'Data Sheet'!E$17 -> 0.53912669 | G6: ='Data Sheet'!F18/'Data Sheet'!F$17 -> 0.51672428 | H6: ='Data Sheet'!G18/'Data Sheet'!G$17 -> 0.53187137 | I6: ='Data Sheet'!H18/'Data Sheet'!H$17 -> 0.4115282 | J6: ='Data Sheet'!I18/'Data Sheet'!I$17 -> 0.42953181 | ... L6: ='Data Sheet'!K18/'Data Sheet'!K$17 -> 0.54143287
B7: ='Data Sheet'!A19 -> Change in Inventory | C7: ='Data Sheet'!B19/'Data Sheet'!B$17 -> 0.028094536 | D7: ='Data Sheet'!C19/'Data Sheet'!C$17 -> -0.032873307 | E7: ='Data Sheet'!D19/'Data Sheet'!D$17 -> 0.026724696 | F7: ='Data Sheet'!E19/'Data Sheet'!E$17 -> -0.0033920454 | G7: ='Data Sheet'!F19/'Data Sheet'!F$17 -> 0.006961077 | H7: ='Data Sheet'!G19/'Data Sheet'!G$17 -> 0.0036821864 | I7: ='Data Sheet'!H19/'Data Sheet'!H$17 -> 0.004358772 | J7: ='Data Sheet'!I19/'Data Sheet'!I$17 -> 0.024601868 | ... L7: ='Data Sheet'!K19/'Data Sheet'!K$17 -> 0.017639395
B8: ='Data Sheet'!A20 -> Power and Fuel | C8: ='Data Sheet'!B20/'Data Sheet'!B$17 -> 0.07783618 | D8: ='Data Sheet'!C20/'Data Sheet'!C$17 -> 0.088043735 | E8: ='Data Sheet'!D20/'Data Sheet'!D$17 -> 0.087817423 | F8: ='Data Sheet'!E20/'Data Sheet'!E$17 -> 0.079198699 | G8: ='Data Sheet'!F20/'Data Sheet'!F$17 -> 0.083214366 | H8: ='Data Sheet'!G20/'Data Sheet'!G$17 -> 0.085535826 | I8: ='Data Sheet'!H20/'Data Sheet'!H$17 -> 0.074963364 | J8: ='Data Sheet'!I20/'Data Sheet'!I$17 -> 0.077125933 | ... L8: ='Data Sheet'!K20/'Data Sheet'!K$17 -> 0.086437036
B9: ='Data Sheet'!A21 -> Other Mfr. Exp | C9: ='Data Sheet'!B21/'Data Sheet'!B$17 -> 0.12770582 | D9: ='Data Sheet'!C21/'Data Sheet'!C$17 -> 0.1382811 | E9: ='Data Sheet'!D21/'Data Sheet'!D$17 -> 0.123858 | F9: ='Data Sheet'!E21/'Data Sheet'!E$17 -> 0.1211266 | G9: ='Data Sheet'!F21/'Data Sheet'!F$17 -> 0.11984851 | H9: ='Data Sheet'!G21/'Data Sheet'!G$17 -> 0.13969124 | I9: ='Data Sheet'!H21/'Data Sheet'!H$17 -> 0.20349704 | J9: ='Data Sheet'!I21/'Data Sheet'!I$17 -> 0.20308668 | ... L9: ='Data Sheet'!K21/'Data Sheet'!K$17 -> 0.16979989
B10: ='Data Sheet'!A22 -> Employee Cost | C10: ='Data Sheet'!B22/'Data Sheet'!B$17 -> 0.028937064 | D10: ='Data Sheet'!C22/'Data Sheet'!C$17 -> 0.036553791 | E10: ='Data Sheet'!D22/'Data Sheet'!D$17 -> 0.03057334 | F10: ='Data Sheet'!E22/'Data Sheet'!E$17 -> 0.025621064 | G10: ='Data Sheet'!F22/'Data Sheet'!F$17 -> 0.029366306 | H10: ='Data Sheet'!G22/'Data Sheet'!G$17 -> 0.038717508 | I10: ='Data Sheet'!H22/'Data Sheet'!H$17 -> 0.031388169 | J10: ='Data Sheet'!I22/'Data Sheet'!I$17 -> 0.023864017 | ... L10: ='Data Sheet'!K22/'Data Sheet'!K$17 -> 0.026233386
B11: ='Data Sheet'!A23 -> Selling and admin | C11: ='Data Sheet'!B23/'Data Sheet'!B$17 -> 0.0070349137 | D11: ='Data Sheet'!C23/'Data Sheet'!C$17 -> 0.0080108467 | E11: ='Data Sheet'!D23/'Data Sheet'!D$17 -> 0.0058089346 | F11: ='Data Sheet'!E23/'Data Sheet'!E$17 -> 0.0038508056 | G11: ='Data Sheet'!F23/'Data Sheet'!F$17 -> 0.0071026582 | H11: ='Data Sheet'!G23/'Data Sheet'!G$17 -> 0.0061369773 | I11: ='Data Sheet'!H23/'Data Sheet'!H$17 -> 0.0050601836 | J11: ='Data Sheet'!I23/'Data Sheet'!I$17 -> 0.0038053986 | ... L11: ='Data Sheet'!K23/'Data Sheet'!K$17 -> 0.0051083963
B12: ='Data Sheet'!A24 -> Other Expenses | C12: ='Data Sheet'!B24/'Data Sheet'!B$17 -> 0.02193783 | D12: ='Data Sheet'!C24/'Data Sheet'!C$17 -> 0.031835907 | E12: ='Data Sheet'!D24/'Data Sheet'!D$17 -> 0.022300554 | F12: ='Data Sheet'!E24/'Data Sheet'!E$17 -> 0.020324469 | G12: ='Data Sheet'!F24/'Data Sheet'!F$17 -> 0.027360572 | H12: ='Data Sheet'!G24/'Data Sheet'!G$17 -> 0.04062679 | I12: ='Data Sheet'!H24/'Data Sheet'!H$17 -> 0.025188191 | J12: ='Data Sheet'!I24/'Data Sheet'!I$17 -> 0.019962971 | ... L12: ='Data Sheet'!K24/'Data Sheet'!K$17 -> 0.027736192
B13: ='Data Sheet'!A25 -> Other Income | C13: ='Data Sheet'!B25/'Data Sheet'!B$17 -> 0.0019400995 | D13: ='Data Sheet'!C25/'Data Sheet'!C$17 -> -0.047326384 | E13: ='Data Sheet'!D25/'Data Sheet'!D$17 -> 0.00032371772 | F13: ='Data Sheet'!E25/'Data Sheet'!E$17 -> -0.0024606231 | G13: ='Data Sheet'!F25/'Data Sheet'!F$17 -> 0.0023124934 | H13: ='Data Sheet'!G25/'Data Sheet'!G$17 -> -0.0039413032 | I13: ='Data Sheet'!H25/'Data Sheet'!H$17 -> 0.0059244229 | J13: ='Data Sheet'!I25/'Data Sheet'!I$17 -> 0.010931127 | ... L13: ='Data Sheet'!K25/'Data Sheet'!K$17 -> 0.0085711347
B14: ='Data Sheet'!A26 -> Depreciation | C14: ='Data Sheet'!B26/'Data Sheet'!B$17 -> 0.064836551 | D14: ='Data Sheet'!C26/'Data Sheet'!C$17 -> 0.079972715 | E14: ='Data Sheet'!D26/'Data Sheet'!D$17 -> 0.06168621 | F14: ='Data Sheet'!E26/'Data Sheet'!E$17 -> 0.047085482 | G14: ='Data Sheet'!F26/'Data Sheet'!F$17 -> 0.047677478 | H14: ='Data Sheet'!G26/'Data Sheet'!G$17 -> 0.057905791 | I14: ='Data Sheet'!H26/'Data Sheet'!H$17 -> 0.058605443 | J14: ='Data Sheet'!I26/'Data Sheet'!I$17 -> 0.040998558 | ... L14: ='Data Sheet'!K26/'Data Sheet'!K$17 -> 0.046695542
B15: ='Data Sheet'!A27 -> Interest | C15: ='Data Sheet'!B27/'Data Sheet'!B$17 -> 0.065941673 | D15: ='Data Sheet'!C27/'Data Sheet'!C$17 -> 0.086678989 | E15: ='Data Sheet'!D27/'Data Sheet'!D$17 -> 0.067764909 | F15: ='Data Sheet'!E27/'Data Sheet'!E$17 -> 0.051450655 | G15: ='Data Sheet'!F27/'Data Sheet'!F$17 -> 0.046214472 | H15: ='Data Sheet'!G27/'Data Sheet'!G$17 -> 0.058164907 | I15: ='Data Sheet'!H27/'Data Sheet'!H$17 -> 0.049562244 | J15: ='Data Sheet'!I27/'Data Sheet'!I$17 -> 0.03394115 | ... L15: ='Data Sheet'!K27/'Data Sheet'!K$17 -> 0.046312698
B16: ='Data Sheet'!A28 -> Profit before tax | C16: ='Data Sheet'!B28/'Data Sheet'!B$17 -> 0.047933502 | D16: ='Data Sheet'!C28/'Data Sheet'!C$17 -> -0.059395607 | E16: ='Data Sheet'!D28/'Data Sheet'!D$17 -> 0.092223581 | F16: ='Data Sheet'!E28/'Data Sheet'!E$17 -> 0.10636287 | G16: ='Data Sheet'!F28/'Data Sheet'!F$17 -> 0.13176493 | H16: ='Data Sheet'!G28/'Data Sheet'!G$17 -> 0.041090473 | I16: ='Data Sheet'!H28/'Data Sheet'!H$17 -> 0.15049036 | J16: ='Data Sheet'!I28/'Data Sheet'!I$17 -> 0.20321648 | ... L16: ='Data Sheet'!K28/'Data Sheet'!K$17 -> 0.076454522
... B18: ='Data Sheet'!A30 -> Net profit | C18: ='Data Sheet'!B30/'Data Sheet'!B$17 -> 0.033915779 | D18: ='Data Sheet'!C30/'Data Sheet'!C$17 -> -0.0080736684 | E18: ='Data Sheet'!D30/'Data Sheet'!D$17 -> 0.063358751 | F18: ='Data Sheet'!E30/'Data Sheet'!E$17 -> 0.086385942 | G18: ='Data Sheet'!F30/'Data Sheet'!F$17 -> 0.090128249 | H18: ='Data Sheet'!G30/'Data Sheet'!G$17 -> 0.054960041 | I18: ='Data Sheet'!H30/'Data Sheet'!H$17 -> 0.099086912 | J18: ='Data Sheet'!I30/'Data Sheet'!I$17 -> 0.14118234 | ... L18: ='Data Sheet'!K30/'Data Sheet'!K$17 -> 0.050352559
B19: ='Data Sheet'!A32 -> EBITDA | C19: ='Data Sheet'!B32/'Data Sheet'!B$17 -> 0.17677163 | D19: ='Data Sheet'!C32/'Data Sheet'!C$17 -> 0.15458248 | E19: ='Data Sheet'!D32/'Data Sheet'!D$17 -> 0.22135098 | F19: ='Data Sheet'!E32/'Data Sheet'!E$17 -> 0.20735963 | G19: ='Data Sheet'!F32/'Data Sheet'!F$17 -> 0.22334438 | H19: ='Data Sheet'!G32/'Data Sheet'!G$17 -> 0.16110247 | I19: ='Data Sheet'!H32/'Data Sheet'!H$17 -> 0.25273363 | J19: ='Data Sheet'!I32/'Data Sheet'!I$17 -> 0.26722507 | ... L19: ='Data Sheet'!K32/'Data Sheet'!K$17 -> 0.16089163
B21: ="Common Size Balance Sheet "&" "& " - "&'Data Sheet'!$B$1 -> Common Size Balance Sheet - JSW STEEL LTD
B23: Total Liabilites | C23: ='Data Sheet'!B61/'Data Sheet'!B$61 -> 1 | D23: ='Data Sheet'!C61/'Data Sheet'!C$61 -> 1 | E23: ='Data Sheet'!D61/'Data Sheet'!D$61 -> 1 | F23: ='Data Sheet'!E61/'Data Sheet'!E$61 -> 1 | G23: ='Data Sheet'!F61/'Data Sheet'!F$61 -> 1 | H23: ='Data Sheet'!G61/'Data Sheet'!G$61 -> 1 | I23: ='Data Sheet'!H61/'Data Sheet'!H$61 -> 1 | J23: ='Data Sheet'!I61/'Data Sheet'!I$61 -> 1 | ... L23: ='Data Sheet'!K61/'Data Sheet'!K$61 -> 1
B24: ='Data Sheet'!A57 -> Equity Share Capital | C24: ='Data Sheet'!B57/'Data Sheet'!B$61 -> 0.0035345743 | D24: ='Data Sheet'!C57/'Data Sheet'!C$61 -> 0.0036736832 | E24: ='Data Sheet'!D57/'Data Sheet'!D$61 -> 0.0034202602 | F24: ='Data Sheet'!E57/'Data Sheet'!E$61 -> 0.0032836795 | G24: ='Data Sheet'!F57/'Data Sheet'!F$61 -> 0.0026220197 | H24: ='Data Sheet'!G57/'Data Sheet'!G$61 -> 0.0022834168 | I24: ='Data Sheet'!H57/'Data Sheet'!H$61 -> 0.0020361793 | J24: ='Data Sheet'!I57/'Data Sheet'!I$61 -> 0.0015319236 | ... L24: ='Data Sheet'!K57/'Data Sheet'!K$61 -> 0.001338318
B25: ='Data Sheet'!A58 -> Reserves | C25: ='Data Sheet'!B58/'Data Sheet'!B$61 -> 0.25669462 | D25: ='Data Sheet'!C58/'Data Sheet'!C$61 -> 0.22787519 | E25: ='Data Sheet'!D58/'Data Sheet'!D$61 -> 0.25391739 | F25: ='Data Sheet'!E58/'Data Sheet'!E$61 -> 0.30114168 | G25: ='Data Sheet'!F58/'Data Sheet'!F$61 -> 0.30047824 | H25: ='Data Sheet'!G58/'Data Sheet'!G$61 -> 0.27536034 | I25: ='Data Sheet'!H58/'Data Sheet'!H$61 -> 0.31326146 | J25: ='Data Sheet'!I58/'Data Sheet'!I$61 -> 0.34097259 | ... L25: ='Data Sheet'!K58/'Data Sheet'!K$61 -> 0.33946766
B26: ='Data Sheet'!A59 -> Borrowings | C26: ='Data Sheet'!B59/'Data Sheet'!B$61 -> 0.45245189 | D26: ='Data Sheet'!C59/'Data Sheet'!C$61 -> 0.51526831 | E26: ='Data Sheet'!D59/'Data Sheet'!D$61 -> 0.49240384 | F26: ='Data Sheet'!E59/'Data Sheet'!E$61 -> 0.42832445 | G26: ='Data Sheet'!F59/'Data Sheet'!F$61 -> 0.41286793 | H26: ='Data Sheet'!G59/'Data Sheet'!G$61 -> 0.46596116 | I26: ='Data Sheet'!H59/'Data Sheet'!H$61 -> 0.42066655 | J26: ='Data Sheet'!I59/'Data Sheet'!I$61 -> 0.36764639 | ... L26: ='Data Sheet'!K59/'Data Sheet'!K$61 -> 0.38606745
B27: ='Data Sheet'!A60 -> Other Liabilities | C27: ='Data Sheet'!B60/'Data Sheet'!B$61 -> 0.28731892 | D27: ='Data Sheet'!C60/'Data Sheet'!C$61 -> 0.25318282 | E27: ='Data Sheet'!D60/'Data Sheet'!D$61 -> 0.25025851 | F27: ='Data Sheet'!E60/'Data Sheet'!E$61 -> 0.26725019 | G27: ='Data Sheet'!F60/'Data Sheet'!F$61 -> 0.28403181 | H27: ='Data Sheet'!G60/'Data Sheet'!G$61 -> 0.25639508 | I27: ='Data Sheet'!H60/'Data Sheet'!H$61 -> 0.26403582 | J27: ='Data Sheet'!I60/'Data Sheet'!I$61 -> 0.2898491 | ... L27: ='Data Sheet'!K60/'Data Sheet'!K$61 -> 0.27312657
B29: Total Asset | C29: ='Data Sheet'!B66/'Data Sheet'!B$66 -> 1 | D29: ='Data Sheet'!C66/'Data Sheet'!C$66 -> 1 | E29: ='Data Sheet'!D66/'Data Sheet'!D$66 -> 1 | F29: ='Data Sheet'!E66/'Data Sheet'!E$66 -> 1 | G29: ='Data Sheet'!F66/'Data Sheet'!F$66 -> 1 | H29: ='Data Sheet'!G66/'Data Sheet'!G$66 -> 1 | I29: ='Data Sheet'!H66/'Data Sheet'!H$66 -> 1 | J29: ='Data Sheet'!I66/'Data Sheet'!I$66 -> 1 | ... L29: ='Data Sheet'!K66/'Data Sheet'!K$66 -> 1
B30: ='Data Sheet'!A62 -> Net Block | C30: ='Data Sheet'!B62/'Data Sheet'!B$66 -> 0.60915256 | D30: ='Data Sheet'!C62/'Data Sheet'!C$66 -> 0.68540648 | E30: ='Data Sheet'!D62/'Data Sheet'!D$66 -> 0.66734845 | F30: ='Data Sheet'!E62/'Data Sheet'!E$66 -> 0.62898771 | G30: ='Data Sheet'!F62/'Data Sheet'!F$66 -> 0.5456937 | H30: ='Data Sheet'!G62/'Data Sheet'!G$66 -> 0.47098316 | I30: ='Data Sheet'!H62/'Data Sheet'!H$66 -> 0.43769089 | J30: ='Data Sheet'!I62/'Data Sheet'!I$66 -> 0.50833397 | ... L30: ='Data Sheet'!K62/'Data Sheet'!K$66 -> 0.49347076
B31: ='Data Sheet'!A63 -> Capital Work in Progress | C31: ='Data Sheet'!B63/'Data Sheet'!B$66 -> 0.096496154 | D31: ='Data Sheet'!C63/'Data Sheet'!C$66 -> 0.088769689 | E31: ='Data Sheet'!D63/'Data Sheet'!D$66 -> 0.049576729 | F31: ='Data Sheet'!E63/'Data Sheet'!E$66 -> 0.064695009 | G31: ='Data Sheet'!F63/'Data Sheet'!F$66 -> 0.10356542 | H31: ='Data Sheet'!G63/'Data Sheet'!G$66 -> 0.20627371 | I31: ='Data Sheet'!H63/'Data Sheet'!H$66 -> 0.21957024 | J31: ='Data Sheet'!I63/'Data Sheet'!I$66 -> 0.086037102 | ... L31: ='Data Sheet'!K63/'Data Sheet'!K$66 -> 0.13021615
B32: ='Data Sheet'!A64 -> Investments | C32: ='Data Sheet'!B64/'Data Sheet'!B$66 -> 0.0069961804 | D32: ='Data Sheet'!C64/'Data Sheet'!C$66 -> 0.014584974 | E32: ='Data Sheet'!D64/'Data Sheet'!D$66 -> 0.015521845 | F32: ='Data Sheet'!E64/'Data Sheet'!E$66 -> 0.0159726 | G32: ='Data Sheet'!F64/'Data Sheet'!F$66 -> 0.016498689 | H32: ='Data Sheet'!G64/'Data Sheet'!G$66 -> 0.0095509027 | I32: ='Data Sheet'!H64/'Data Sheet'!H$66 -> 0.057855809 | J32: ='Data Sheet'!I64/'Data Sheet'!I$66 -> 0.025141868 | ... L32: ='Data Sheet'!K64/'Data Sheet'!K$66 -> 0.031794926
B33: ='Data Sheet'!A65 -> Other Assets | C33: ='Data Sheet'!B74/'Data Sheet'!B$66 -> 0.10730442 | D33: ='Data Sheet'!C74/'Data Sheet'!C$66 -> 0.063889245 | E33: ='Data Sheet'!D74/'Data Sheet'!D$66 -> 0.074052611 | F33: ='Data Sheet'!E74/'Data Sheet'!E$66 -> 0.09070349 | G33: ='Data Sheet'!F74/'Data Sheet'!F$66 -> 0.091248029 | H33: ='Data Sheet'!G74/'Data Sheet'!G$66 -> 0.083477469 | I33: ='Data Sheet'!H74/'Data Sheet'!H$66 -> 0.072176487 | J33: ='Data Sheet'!I74/'Data Sheet'!I$66 -> 0.082108049 | ... L33: ='Data Sheet'!K74/'Data Sheet'!K$66 -> 0.091286453
B34: ='Data Sheet'!A67 -> Receivables | C34: ='Data Sheet'!B67/'Data Sheet'!B$66 -> 0.029184317 | D34: ='Data Sheet'!C67/'Data Sheet'!C$66 -> 0.033298416 | E34: ='Data Sheet'!D67/'Data Sheet'!D$66 -> 0.047145049 | F34: ='Data Sheet'!E67/'Data Sheet'!E$66 -> 0.051147113 | G34: ='Data Sheet'!F67/'Data Sheet'!F$66 -> 0.062370968 | H34: ='Data Sheet'!G67/'Data Sheet'!G$66 -> 0.034175391 | I34: ='Data Sheet'!H67/'Data Sheet'!H$66 -> 0.030246027 | J34: ='Data Sheet'!I67/'Data Sheet'!I$66 -> 0.037952007 | ... L34: ='Data Sheet'!K67/'Data Sheet'!K$66 -> 0.03312008
B35: ='Data Sheet'!A68 -> Inventory | C35: ='Data Sheet'!B68/'Data Sheet'!B$66 -> 0.12852938 | D35: ='Data Sheet'!C68/'Data Sheet'!C$66 -> 0.10159315 | E35: ='Data Sheet'!D68/'Data Sheet'!D$66 -> 0.12948128 | F35: ='Data Sheet'!E68/'Data Sheet'!E$66 -> 0.13693596 | G35: ='Data Sheet'!F68/'Data Sheet'!F$66 -> 0.12672805 | H35: ='Data Sheet'!G68/'Data Sheet'!G$66 -> 0.10448339 | I35: ='Data Sheet'!H68/'Data Sheet'!H$66 -> 0.096071253 | J35: ='Data Sheet'!I68/'Data Sheet'!I$66 -> 0.17195715 | ... L35: ='Data Sheet'!K68/'Data Sheet'!K$66 -> 0.16592949
B36: ='Data Sheet'!A69 -> Cash & Bank | C36: ='Data Sheet'!B69/'Data Sheet'!B$66 -> 0.022336992 | D36: ='Data Sheet'!C69/'Data Sheet'!C$66 -> 0.012458047 | E36: ='Data Sheet'!D69/'Data Sheet'!D$66 -> 0.016874041 | F36: ='Data Sheet'!E69/'Data Sheet'!E$66 -> 0.011558117 | G36: ='Data Sheet'!F69/'Data Sheet'!F$66 -> 0.053895137 | H36: ='Data Sheet'!G69/'Data Sheet'!G$66 -> 0.091055985 | I36: ='Data Sheet'!H69/'Data Sheet'!H$66 -> 0.086389288 | J36: ='Data Sheet'!I69/'Data Sheet'!I$66 -> 0.088469858 | ... L36: ='Data Sheet'!K69/'Data Sheet'!K$66 -> 0.054182134

Sheet Forcasting
B2: ='Data Sheet'!B1&"- "&'Data Sheet'!A17 -> JSW STEEL LTD- Sales | G2: ='Data Sheet'!B1&"-"&'Historical FS'!B17 -> JSW STEEL LTD-Operating Profit(EBITDA) | L2: ='Data Sheet'!B1&"-"&'Historical FS'!B31 -> JSW STEEL LTD-EPS
B3: Year Weight | C3: Year | D3: Sales | E3: Sales growth | G3: Year Weight | H3: Year | I3: EBITDA | J3: EBITDA growth | L3: Year Weight | M3: Year | N3: EPS | O3: EPS growth
B4: 1 | C4: ='Data Sheet'!B16 -> 42094 | D4: {=TRANSPOSE('Data Sheet'!B17:K17)} -> 52971.51 | G4: =B4 -> 1 | H4: =C4 -> 42094 | I4: {=TRANSPOSE('Historical FS'!C17:L17)} -> 9363.86 | L4: =G4 -> 1 | M4: =H4 -> 42094 | N4: {=TRANSPOSE('Historical FS'!C31:L31)} -> 6.6892686
B5: =B4+1 -> 2 | C5: =C4+365 -> 42459 | D5: 41546.17 | E5: =D5/D4-1 -> -0.2156884 | G5: =B5 -> 2 | H5: =C5 -> 42459 | I5: 6422.31 | J5: =I5/I4-1 -> -0.31413861 | L5: =G5 -> 2 | M5: =H5 -> 42459 | N5: 6.0598213 | O5: =N5/N4-1 -> -0.094098075
B6: =B5+1 -> 3 | C6: =C5+365 -> 42824 | D6: 55604 | E6: =D6/D5-1 -> 0.33836645 | G6: =B6 -> 3 | H6: =C6 -> 42824 | I6: 12308 | J6: =I6/I5-1 -> 0.91644439 | L6: =G6 -> 3 | M6: =H6 -> 42824 | N6: 14.214794 | O6: =N6/N5-1 -> 1.3457448
B7: =B6+1 -> 4 | C7: =C6+365 -> 43189 | D7: 71933 | E7: =D7/D6-1 -> 0.29366592 | G7: =B7 -> 4 | H7: =C7 -> 43189 | I7: 14916 | J7: =I7/I6-1 -> 0.2118947 | L7: =G7 -> 4 | M7: =H7 -> 43189 | N7: 26.021843 | O7: =N7/N6-1 -> 0.830617
B8: =B7+1 -> 5 | C8: =C7+365 -> 43554 | D8: 84757 | E8: =D8/D7-1 -> 0.17827701 | G8: =B8 -> 5 | H8: =C8 -> 43554 | I8: 18930 | J8: =I8/I7-1 -> 0.269107 | L8: =G8 -> 5 | M8: =H8 -> 43554 | N8: 30.316068 | O8: =N8/N7-1 -> 0.16502385
B9: =B8+1 -> 6 | C9: =C8+365 -> 43919 | D9: 73326 | E9: =D9/D8-1 -> -0.13486792 | G9: =B9 -> 6 | H9: =C9 -> 43919 | I9: 11813 | J9: =I9/I8-1 -> -0.37596408 | L9: =G9 -> 6 | M9: =H9 -> 43919 | N9: 17.408572 | O9: =N9/N8-1 -> -0.42576419
B10: =B9+1 -> 7 | C10: =C9+365 -> 44284 | D10: 79839 | E10: =D10/D9-1 -> 0.088822519 | G10: =B10 -> 7 | H10: =C10 -> 44284 | I10: 20178 | J10: =I10/I9-1 -> 0.70811817 | L10: =G10 -> 7 | M10: =H10 -> 44284 | N10: 30.613933 | O10: =N10/N9-1 -> 0.75855513
B11: =B10+1 -> 8 | C11: =C10+365 -> 44649 | D11: 146371 | E11: =D11/D10-1 -> 0.83332707 | G11: =B11 -> 8 | H11: =C11 -> 44649 | I11: 39114 | J11: =I11/I10-1 -> 0.93844781 | L11: =G11 -> 8 | M11: =H11 -> 44649 | N11: 80.001655 | O11: =N11/N10-1 -> 1.6132432
B12: =B11+1 -> 9 | C12: =C11+365 -> 45014 | D12: 165960 | E12: =D12/D11-1 -> 0.13383116 | G12: =B12 -> 9 | H12: =C12 -> 45014 | I12: 18470 | J12: =I12/I11-1 -> -0.52779056 | L12: =G12 -> 9 | M12: =H12 -> 45014 | N12: 10.665233 | O12: =N12/N11-1 -> -0.86668735
B13: =B12+1 -> 10 | C13: =C12+365 -> 45379 | D13: 175006 | E13: =D13/D12-1 -> 0.05450711 | G13: =B13 -> 10 | H13: =C13 -> 45379 | I13: 28157 | J13: =I13/I12-1 -> 0.52447212 | L13: =G13 -> 10 | M13: =H13 -> 45379 | N13: 30.558168 | O13: =N13/N12-1 -> 1.8652135
B14: =B13+1 -> 11 | C14: =C13+365 -> 45744 | D14: =FORECAST(B14,$D$4:$D$13,$B$4:$B$13) -> 175909.01 | E14: =D14/D13-1 -> 0.0051598726 | G14: =B14 -> 11 | H14: =C14 -> 45744 | I14: =FORECAST(G14,$I$4:$I$13,$G$4:$G$13) -> 31172.92 | J14: =I14/I13-1 -> 0.10711084 | L14: =G14 -> 11 | M14: =H14 -> 45744 | N14: =FORECAST(L14,$N$4:$N$13,$L$4:$L$13) -> 44.483637 | O14: =N14/N13-1 -> 0.45570367
B15: =B14+1 -> 12 | C15: =C14+365 -> 46109 | D15: =FORECAST(B15,$D$4:$D$13,$B$4:$B$13) -> 190668.58 | E15: =D15/D14-1 -> 0.083904577 | G15: =B15 -> 12 | H15: =C15 -> 46109 | I15: =FORECAST(G15,$I$4:$I$13,$G$4:$G$13) -> 33573.957 | J15: =I15/I14-1 -> 0.077023163 | L15: =G15 -> 12 | M15: =H15 -> 46109 | N15: =FORECAST(L15,$N$4:$N$13,$L$4:$L$13) -> 47.979765 | O15: =N15/N14-1 -> 0.078593564
B16: =B15+1 -> 13 | C16: =C15+365 -> 46474 | D16: =FORECAST(B16,$D$4:$D$13,$B$4:$B$13) -> 205428.15 | E16: =D16/D15-1 -> 0.077409561 | G16: =B16 -> 13 | H16: =C16 -> 46474 | I16: =FORECAST(G16,$I$4:$I$13,$G$4:$G$13) -> 35974.994 | J16: =I16/I15-1 -> 0.071514862 | L16: =G16 -> 13 | M16: =H16 -> 46474 | N16: =FORECAST(L16,$N$4:$N$13,$L$4:$L$13) -> 51.475893 | O16: =N16/N15-1 -> 0.072866709
B17: =B16+1 -> 14 | C17: =C16+365 -> 46839 | D17: =FORECAST(B17,$D$4:$D$13,$B$4:$B$13) -> 220187.72 | E17: =D17/D16-1 -> 0.07184785 | G17: =B17 -> 14 | H17: =C17 -> 46839 | I17: =FORECAST(G17,$I$4:$I$13,$G$4:$G$13) -> 38376.031 | J17: =I17/I16-1 -> 0.06674183 | L17: =G17 -> 14 | M17: =H17 -> 46839 | N17: =FORECAST(L17,$N$4:$N$13,$L$4:$L$13) -> 54.97202 | O17: =N17/N16-1 -> 0.067917765
B18: =B17+1 -> 15 | C18: =C17+365 -> 47204 | D18: =FORECAST(B18,$D$4:$D$13,$B$4:$B$13) -> 234947.29 | E18: =D18/D17-1 -> 0.067031762 | G18: =B18 -> 15 | H18: =C18 -> 47204 | I18: =FORECAST(G18,$I$4:$I$13,$G$4:$G$13) -> 40777.068 | J18: =I18/I17-1 -> 0.062566057 | L18: =G18 -> 15 | M18: =H18 -> 47204 | N18: =FORECAST(L18,$N$4:$N$13,$L$4:$L$13) -> 58.468148 | O18: =N18/N17-1 -> 0.06359831

Sheet DCF>
B2: Calculation OF PV Of FCFF | E2: ='Data Sheet'!K16 -> 45382 | F2: =E2+365 -> 45747 | G2: =F2+365 -> 46112 | H2: =G2+365 -> 46477 | I2: =H2+365 -> 46842 | J2: =I2+365 -> 47207
B4: EBIT | E4: ='Intrinsic Growth'!K35 -> 19985 | F4: =E4*(1+$C$14) -> 24428.616 | G4: =F4*(1+$C$14) -> 29860.26 | H4: =G4*(1+$C$14) -> 36499.616 | I4: =H4*(1+$C$14) -> 44615.218 | J4: =I4*(1+$C$14) -> 54535.303
B5: Tax Rate | E5: ='Intrinsic Growth'!K45 -> 0.25 | F5: =E5 -> 0.25 | G5: =F5 -> 0.25 | H5: =G5 -> 0.25 | I5: =H5 -> 0.25 | J5: =I5 -> 0.25
B6: EBIT(1-TaxRate) | E6: =E4*(1-E5) -> 14988.75 | F6: =F4*(1-F5) -> 18321.462 | G6: =G4*(1-G5) -> 22395.195 | H6: =H4*(1-H5) -> 27374.712 | I6: =I4*(1-I5) -> 33461.413 | J6: =J4*(1-J5) -> 40901.478
B7: Less:Reinvestment Rate | E7: =70.3% -> 0.703 | F7: =E7 -> 0.703 | G7: =F7 -> 0.703 | H7: =G7 -> 0.703 | I7: =H7 -> 0.703 | J7: =I7 -> 0.703
B8: Free Cash Flow to Firm(FCFF) | E8: =E6*(1-E7) -> 4451.6588 | F8: =F6*(1-F7) -> 5441.4743 | G8: =G6*(1-G7) -> 6651.3729 | H8: =H6*(1-H7) -> 8130.2896 | I8: =I6*(1-I7) -> 9938.0398 | J8: =J6*(1-J7) -> 12147.739
B9: Mid Year Conversion | F9: 0.5 | G9: =F9+1 -> 1.5 | H9: =G9+1 -> 2.5 | I9: =H9+1 -> 3.5 | J9: =I9+1 -> 4.5
B10: Discounting Factor | F10: =1/(1+$C$16)^F9 -> 0.9286661 | G10: =1/(1+$C$16)^G9 -> 0.8009009 | H10: =1/(1+$C$16)^H9 -> 0.69071354 | I10: =1/(1+$C$16)^I9 -> 0.59568567 | J10: =1/(1+$C$16)^J9 -> 0.51373167
B12: PV of FCFF | F12: =F8*F10 -> 5053.3127 | G12: =G8*G10 -> 5327.0905 | H12: =H8*H10 -> 5615.7011 | I12: =I8*I10 -> 5919.9479 | J12: =J8*J10 -> 6240.6782
B14: Expected Growth | C14: ='Intrinsic Growth'!K64 -> 0.22234758
B15: Terminal Growth | C15: 0.064
B16: WACC | C16: =Wacc!M40 -> 0.15952686
B18: Calculation of Terminal Value | F18: Sensitivity Analysis
F19: =C36 -> 423.596 | G19: 0.12 | H19: 0.14 | I19: 0.1595 | J19: 0.17
B20: FCFF(n+1) | C20: =J8*(1+C14) -> 14848.759 | F20: 0.04 | G20: 546.96062 | H20: 395.16386 | I20: 296.08313 | J20: 255.04377
B21: WACC | C21: =C16 -> 0.15952686 | F21: 0.05 | G21: 655.38688 | H21: 462.62909 | I21: 342.48553 | J21: 293.96602
B22: Terminal Growth | C22: =C15 -> 0.064 | F22: 0.064 | G22: 872.23939 | H22: 586.90713 | I22: 423.77477 | J22: 360.79478
G23: 293.96602 | H23: 221.68185 | I23: 168.65835 | J23: 145.14566
B24: Terminal Value | C24: =C20/(C21-C22) -> 155440.67 | F24: 0.08 | G24: 1305.9444 | H24: 799.95522 | I24: 551.7341 | J24: 462.62909
F25: 0.1 | G25: 2823.912 | H25: 1305.9444 | I25: 808.45924 | J25: 655.38688
B26: Calculation of Equity Value Per Share
B28: PV of FCFF | C28: =SUM(F12:J12) -> 28156.73
B29: Terminal Value | C29: =C24 -> 155440.67
B30: Operating Asset | C30: =SUM(C28:C29) -> 183597.4
B32: Add: Cash | C32: ='Data Sheet'!K69 -> 12348
B33: Less:Debt | C33: =SUM('Raw FS'!O7:O8) -> 92355
B34: Value OF Equity | C34: =C30+C32-C33 -> 103590.4
B35: No of Shares | C35: ='Data Sheet'!K93 -> 244.55
B36: Equity Value Per Share | C36: =C34/C35 -> 423.596
B38: Share Price | C38: =1058 -> 1058
B39: Discount/Premium | C39: =C38/C36-1 -> 1.4976629

Sheet Wacc
B2: Weighted Average Cost Of Capital
B4: All Figures are In INR as Stated Below
B6: PeerComps
J7: Debt/ | K7: Debt/ | L7: Levered | M7: Unlevered
B8: Name Of Comps | F8: Country | G8: Total Debt | H8: Total Equity | I8: Tax Rate | J8: Equity | K8: Capital | L8: Beta | M8: Beta
B9: ='Peer Comps'!C3 -> JSW Steel | F9: India | G9: ='Peer Comps'!F3 -> 95258 | H9: ='Peer Comps'!E3 -> 258459.99 | I9: 0.3 | J9: =G9/H9 -> 0.36855995 | K9: =G9/(H9+G9) -> 0.26930493 | L9: =Beta!O5 -> 1.2946664 | M9: =L9/(1+(1-I9)*J9) -> 1.0291532
B10: ='Peer Comps'!C4 -> Tata Steel | F10: India | G10: ='Peer Comps'!F4 -> 99391.76 | H10: ='Peer Comps'!E4 -> 197551.76 | I10: 0.3 | J10: =G10/H10 -> 0.50311756 | K10: =G10/(H10+G10) -> 0.33471604 | L10: 1.24 | M10: =L10/(1+(1-I10)*J10) -> 0.91703612
B11: ='Peer Comps'!C5 -> Jindal Steel | F11: India | G11: ='Peer Comps'!F5 -> 17266.45 | H11: ='Peer Comps'!E5 -> 93730.79 | I11: 0.3 | J11: =G11/H11 -> 0.18421321 | K11: =G11/(H11+G11) -> 0.15555747 | L11: 1.34 | M11: =L11/(1+(1-I11)*J11) -> 1.1869444
B12: ='Peer Comps'!C6 -> S A I L | F12: India | G12: ='Peer Comps'!F6 -> 41265.03 | H12: ='Peer Comps'!E6 -> 47480.37 | I12: 0.3 | J12: =G12/H12 -> 0.86909664 | K12: =G12/(H12+G12) -> 0.46498218 | L12: 1.65 | M12: =L12/(1+(1-I12)*J12) -> 1.0258848
H14: Average | I14: =I11 -> 0.3 | J14: =AVERAGE(J9:J12) -> 0.48124684 | K14: =AVERAGE(K9:K12) -> 0.30614016 | L14: =AVERAGE(L9:L12) -> 1.3811666 | M14: =AVERAGE(M9:M12) -> 1.0397546
H15: Median | I15: =I12 -> 0.3 | J15: =MEDIAN(J9:J12) -> 0.43583875 | K15: =MEDIAN(K9:K12) -> 0.30201049 | L15: =MEDIAN(L9:L12) -> 1.3173332 | M15: =MEDIAN(M9:M12) -> 1.027519
B18: Cost Of Debt | J18: Cost Of Equity
B20: Pre Tax Cost of Debt | F20: ='Historical FS'!M19/Wacc!G9 -> 0.087971614 | J20: Risk Free Rate | M20: =6.73% -> 0.0673
B21: Tax Rate | F21: =I14 -> 0.3 | J21: Equity Risk Premium | M21: =Rm!G6-Wacc!M20 -> 0.100548
B22: Post Tax Cost Of Debt | F22: =F20*(1-F21) -> 0.06158013 | J22: Levered Beta | M22: =M30 -> 1.3387344
J23: Cost of Equity | M23: =M20+(M21*M22) -> 0.20190707
B25: Capital Structure | J25: Levered Beta
E27: Current | F27: Target | J27: Comps Median Unlevered Beta | M27: =M15 -> 1.027519
B28: Debt | D28: =G9 -> 95258 | E28: =D28/D30 -> 0.26930493 | F28: =K15 -> 0.30201049 | J28: Target Debt/Equity | M28: =F32 -> 0.43268628
B29: Market Capatiliazation | D29: =H9 -> 258459.99 | E29: =D29/D30 -> 0.73069507 | F29: =F30-F28 -> 0.69798951 | J29: Tax Rate | M29: =I14 -> 0.3
B30: Total Capital | D30: =SUM(D28:D29) -> 353717.99 | E30: =SUM(E28:E29) -> 1 | F30: =E30 -> 1 | J30: Levered Beta | M30: =M27*(1+(1-M29)*M28) -> 1.3387344
B32: Debt /Equity | E32: =E28/E29 -> 0.36855995 | F32: =F28/F29 -> 0.43268628 | J32: Weighted Average Cost of Capital
J34: Costof Debt | M34: =F22 -> 0.06158013
B35: NOTE | J35: Weight Of Debt | M35: =F28 -> 0.30201049
A36: 1 | B36: Tax Rate is Considerd as Marginal tax rate for the country
A37: 2 | B37: Levered Beta is Based on 2 Year weekly data | J37: Cost Of Equity | M37: =M23 -> 0.20190707
A38: 3 | B38: Unlevered Beta = Levered Beta/(1+(1-TAX RATE)*DEBT/EQUITY) | J38: Weight of Equity | M38: =F29 -> 0.69798951
A39: 4 | B39: Levered Beta=Unlevered Beat*(1+(1-TAX RATE)*DEBT/EQUITY)
J40: WACC | M40: =(M34*M35)+(M37*M38) -> 0.15952686

Sheet Relative valuation
B2: Amounts in Crores
B3: Comparabel Companies Valuation
D5: Market Data | K5: Financial | O5: Valuation
B6: Companies | C6: Ticker | D6: Share price | E6: Share Outstanding | F6: Equity Value | G6: Net Debt | H6: Enterprise Value | K6: Revenue | L6: EBITDA | M6: Net Income | O6: EV/Revenue | P6: EV/EBITDA | Q6: P/E
B8: =Data2!C3 -> JSW Steel | C8: JSWSTELL | D8: =Data2!D3 -> 1058.7 | E8: =Data2!E3 -> 244.55 | F8: =D8*E8 -> 258905.09 | G8: =Data2!I3 -> 82910 | H8: =Data2!N3 -> 341815.09 | K8: =Data2!L3 -> 170274 | L8: =Data2!O3 -> 22986.892 | M8: =Data2!M3 -> 3312 | O8: =$H8/K8 -> 2.0074414 | P8: =$H8/L8 -> 14.87 | Q8: =F8/M8 -> 78.171825
B9: =Data2!C4 -> Tata Steel | C9: TATASTELL | D9: =Data2!D4 -> 157.28 | E9: =Data2!E4 -> 1248.35 | F9: =D9*E9 -> 196340.49 | G9: =Data2!I4 -> 90714.04 | H9: =Data2!N4 -> 287054.53 | K9: =Data2!L4 -> 221011.71 | L9: =Data2!O4 -> 26852.622 | M9: =Data2!M4 -> 2527.46 | O9: =$H9/K9 -> 1.2988204 | P9: =$H9/L9 -> 10.69 | Q9: =F9/M9 -> 77.682926
B10: =Data2!C5 -> Jindal Steel | C10: JINDALSTEL | D10: =Data2!D5 -> 914.3 | E10: =Data2!E5 -> 102.01 | F10: =D10*E10 -> 93267.743 | G10: =Data2!I5 -> 13242.32 | H10: =Data2!N5 -> 106510.06 | K10: =Data2!L5 -> 50068.78 | L10: =Data2!O5 -> 9753.6688 | M10: =Data2!M5 -> 4082.73 | O10: =$H10/K10 -> 2.127275 | P10: =$H10/L10 -> 10.92 | Q10: =F10/M10 -> 22.844455
B11: =Data2!C6 -> Tube Investments | C11: TIINDIA | D11: =Data2!D6 -> 2872.15 | E11: =Data2!E6 -> 19.35 | F11: =D11*E11 -> 55576.103 | G11: =Data2!I6 -> -528.48 | H11: =Data2!N6 -> 55047.623 | K11: =Data2!L6 -> 18804.8 | L11: =Data2!O6 -> 2269.0694 | M11: =Data2!M6 -> 1167.41 | O11: =$H11/K11 -> 2.9273176 | P11: =$H11/L11 -> 24.26 | Q11: =F11/M11 -> 47.606327
B12: =Data2!C7 -> Jindal Stain. | C12: JSL | D12: =Data2!D7 -> 625.7 | E12: =Data2!E7 -> 82.38 | F12: =D12*E12 -> 51545.166 | G12: =Data2!I7 -> 4484.97 | H12: =Data2!N7 -> 56030.136 | K12: =Data2!L7 -> 38567.91 | L12: =Data2!O7 -> 4889.1916 | M12: =Data2!M7 -> 2410.41 | O12: =$H12/K12 -> 1.4527657 | P12: =$H12/L12 -> 11.46 | Q12: =F12/M12 -> 21.384398
B13: =Data2!C8 -> S A I L | C13: SAIL | D13: =Data2!D8 -> 115.3 | E13: =Data2!E8 -> 413.05 | F13: =D13*E13 -> 47624.665 | G13: =Data2!I8 -> 40592.08 | H13: =Data2!N8 -> 88216.745 | K13: =Data2!L8 -> 101121.44 | L13: =Data2!O8 -> 12084.486 | M13: =Data2!M8 -> 2246.5 | O13: =$H13/K13 -> 0.87238418 | P13: =$H13/L13 -> 7.3 | Q13: =F13/M13 -> 21.199495
B14: =Data2!C9 -> APL Apollo Tubes | C14: APLAPOLLO | D14: =Data2!D9 -> 1511.55 | E14: =Data2!E9 -> 27.75 | F14: =D14*E14 -> 41945.512 | G14: =Data2!I9 -> 674.99 | H14: =Data2!N9 -> 42620.502 | K14: =Data2!L9 -> 19946.68 | L14: =Data2!O9 -> 1141.4168 | M14: =Data2!M9 -> 634.39 | O14: =$H14/K14 -> 2.1367216 | P14: =$H14/L14 -> 37.34 | Q14: =F14/M14 -> 66.119442
B16: High | O16: =MAX(O8:O14) -> 2.9273176 | P16: =MAX(P8:P14) -> 37.34 | Q16: =MAX(Q8:Q14) -> 78.171825
B17: 75th Percentile | O17: =_xlfn.QUARTILE.EXC(O8:O14,3) -> 2.1367216 | P17: =_xlfn.QUARTILE.EXC(P8:P14,3) -> 24.26 | Q17: =_xlfn.QUARTILE.EXC(Q8:Q14,3) -> 77.682926
B18: Average | O18: =AVERAGE(O8:O14) -> 1.831818 | P18: =AVERAGE(P8:P14) -> 16.691429 | Q18: =AVERAGE(Q8:Q14) -> 47.85841
B19: Median | O19: =MEDIAN(O8:O14) -> 2.0074414 | P19: =MEDIAN(P8:P14) -> 11.46 | Q19: =MEDIAN(Q8:Q14) -> 47.606327
B20: 25th Percentile | O20: =_xlfn.QUARTILE.EXC(O8:O14,1) -> 1.2988204 | P20: =_xlfn.QUARTILE.EXC(P8:P14,1) -> 10.69 | Q20: =_xlfn.QUARTILE.EXC(Q8:Q14,1) -> 21.384398
B21: Low | O21: =MIN(O8:O14) -> 0.87238418 | P21: =MIN(P8:P14) -> 7.3 | Q21: =MIN(Q8:Q14) -> 21.199495
B23: JSW Stell Comparabel Valuation | O23: EV/Revenue | P23: EV/EBITDA | Q23: P/E
B25: Implied Enterprise Value | O25: =O19*K8 -> 341815.09 | P25: =P19*L8 -> 263429.78 | Q25: =Q27+Q26 -> 240582.16
B26: Net Debt | O26: =$G$8 -> 82910 | P26: =$G$8 -> 82910 | Q26: =$G$8 -> 82910
B27: Implied Market Value | O27: =O25-O26 -> 258905.09 | P27: =P25-P26 -> 180519.78 | Q27: =Q19*M8 -> 157672.16
B28: Shares Outstanding | O28: =$E$8 -> 244.55 | P28: =$E$8 -> 244.55 | Q28: =$E$8 -> 244.55
B30: Implied value Per Share | O30: =O27/O28 -> 1058.7 | P30: =P27/P28 -> 738.17127 | Q30: =Q27/Q28 -> 644.74404
B31: Source: The Valuation School,Screener.in
O32: =IF(O30>$D$8,"Undervalued","Overvalued") -> Overvalued | P32: =IF(P30>$D$8,"Undervalued","Overvalued") -> Overvalued | Q32: =IF(Q30>$D$8,"Undervalued","Overvalued") -> Overvalued

Sheet Football Field Analysis
B2: Football Field Analysis
L5: Football Field Analysis-Data
N6: OpenLow | O6: Low | P6: OpenHigh | Q6: High
L7: Comps | N7: ='Relative valuation'!$Q$30 -> 644.74404 | O7: ='Relative valuation'!$Q$30 -> 644.74404 | P7: ='Relative valuation'!$O$30 -> 1058.7 | Q7: ='Relative valuation'!$O$30 -> 1058.7
L8: DCF Bear | N8: ='DCF>'!$J$20 -> 255.04377 | O8: ='DCF>'!$J$20 -> 255.04377 | P8: ='DCF>'!$J$25 -> 655.38688 | Q8: ='DCF>'!$J$25 -> 655.38688
L9: DCF Base | N9: ='DCF>'!$I$20 -> 296.08313 | O9: ='DCF>'!$I$20 -> 296.08313 | P9: ='DCF>'!$I$25 -> 808.45924 | Q9: ='DCF>'!$I$25 -> 808.45924
L10: DCF Bull | N10: ='DCF>'!$G$20 -> 546.96062 | O10: ='DCF>'!$G$20 -> 546.96062 | P10: ='DCF>'!$G$25 -> 2823.912 | Q10: ='DCF>'!$G$25 -> 2823.912
L11: 52 W H/L | N11: =803.1 -> 803.1 | O11: =803.1 -> 803.1 | P11: =1063 -> 1063 | Q11: =1063 -> 1063

Sheet Intrinsic Growth
B2: Calculation of ROIC | G2: ='Data Sheet'!G$16 -> 43921 | H2: ='Data Sheet'!H$16 -> 44286 | I2: ='Data Sheet'!I$16 -> 44651 | J2: ='Data Sheet'!J$16 -> 45016 | K2: ='Data Sheet'!K$16 -> 45382
B4: Current Aseet
B5: ='Raw FS'!B37 -> Inventories | G5: ='Raw FS'!K37 -> 14249 | H5: ='Raw FS'!L37 -> 33787 | I5: ='Raw FS'!M37 -> 33135 | J5: ='Raw FS'!N37 -> 37815 | K5: ='Raw FS'!O37 -> 37240
B6: ='Raw FS'!B38 -> Trade receivables | G6: ='Raw FS'!K38 -> 4486 | H6: ='Raw FS'!L38 -> 7457 | I6: ='Raw FS'!M38 -> 7134 | J6: ='Raw FS'!N38 -> 7548 | K6: ='Raw FS'!O38 -> 8002
B7: ='Raw FS'!B39 -> Cash Equivalents | G7: ='Raw FS'!K39 -> 12813 | H7: ='Raw FS'!L39 -> 17383 | I7: ='Raw FS'!M39 -> 20714 | J7: ='Raw FS'!N39 -> 12348 | K7: ='Raw FS'!O39 -> 9289
B8: ='Raw FS'!B40 -> Loans n Advances | G8: ='Raw FS'!K40 -> 1267 | H8: ='Raw FS'!L40 -> 2227 | I8: ='Raw FS'!M40 -> 3179 | J8: ='Raw FS'!N40 -> 1877 | K8: ='Raw FS'!O40 -> 7064
B9: ='Raw FS'!B41 -> Other asset items | G9: ='Raw FS'!K41 -> 9438 | H9: ='Raw FS'!L41 -> 13906 | I9: ='Raw FS'!M41 -> 14953 | J9: ='Raw FS'!N41 -> 18927 | K9: ='Raw FS'!O41 -> 16984
B10: Net Current Asset | G10: =SUM(G5:G9) -> 42253 | H10: =SUM(H5:H9) -> 74760 | I10: =SUM(I5:I9) -> 79115 | J10: =SUM(J5:J9) -> 78515 | K10: =SUM(K5:K9) -> 78579
B12: Currentr Liabilites
B13: ='Raw FS'!B13 -> Non controlling int | G13: ='Raw FS'!K13 -> -619 | H13: ='Raw FS'!L13 -> 1238 | I13: ='Raw FS'!M13 -> 1344 | J13: ='Raw FS'!N13 -> 2107 | K13: ='Raw FS'!O13 -> 2094
B14: ='Raw FS'!B14 -> Trade Payables | G14: ='Raw FS'!K14 -> 15243 | H14: ='Raw FS'!L14 -> 30889 | I14: ='Raw FS'!M14 -> 38203 | J14: ='Raw FS'!N14 -> 33365 | K14: ='Raw FS'!O14 -> 28900
B15: ='Raw FS'!B15 -> Advance from Customers | G15: ='Raw FS'!K15 -> 1984 | H15: ='Raw FS'!L15 -> 2133 | I15: ='Raw FS'!M15 -> 2338 | J15: ='Raw FS'!N15 -> 1005 | K15: ='Raw FS'!O15 -> 0
B16: ='Raw FS'!B16 -> Other liability items | G16: ='Raw FS'!K16 -> 22553 | H16: ='Raw FS'!L16 -> 22691 | I16: ='Raw FS'!M16 -> 22106 | J16: ='Raw FS'!N16 -> 25768 | K16: ='Raw FS'!O16 -> 27250
B17: Total Current Liabilites | G17: =SUM(G13:G16) -> 39161 | H17: =SUM(H13:H16) -> 56951 | I17: =SUM(I13:I16) -> 63991 | J17: =SUM(J13:J16) -> 62245 | K17: =SUM(K13:K16) -> 58244
A19: # | B19: Net Working Capital | G19: =G10-G17 -> 3092 | H19: =H10-H17 -> 17809 | I19: =I10-I17 -> 15124 | J19: =J10-J17 -> 16270 | K19: =K10-K17 -> 20335
B21: Non Current Asset
B22: ='Raw FS'!B21 -> Land | G22: ='Raw FS'!K21 -> 2946 | H22: ='Raw FS'!L21 -> 5367 | I22: ='Raw FS'!M21 -> 5501 | J22: ='Raw FS'!N21 -> 6118 | K22: ='Raw FS'!O21 -> 0
B23: ='Raw FS'!B22 -> Building | G23: ='Raw FS'!K22 -> 10575 | H23: ='Raw FS'!L22 -> 15584 | I23: ='Raw FS'!M22 -> 16612 | J23: ='Raw FS'!N22 -> 18926 | K23: ='Raw FS'!O22 -> 0
B24: ='Raw FS'!B23 -> Plant Machinery | G24: ='Raw FS'!K23 -> 69561 | H24: ='Raw FS'!L23 -> 102739 | I24: ='Raw FS'!M23 -> 113225 | J24: ='Raw FS'!N23 -> 124339 | K24: ='Raw FS'!O23 -> 0
B25: ='Raw FS'!B24 -> Equipments | G25: ='Raw FS'!K24 -> 129 | H25: ='Raw FS'!L24 -> 154 | I25: ='Raw FS'!M24 -> 203 | J25: ='Raw FS'!N24 -> 294 | K25: ='Raw FS'!O24 -> 0
B26: ='Raw FS'!B25 -> Furniture n fittings | G26: ='Raw FS'!K25 -> 155 | H26: ='Raw FS'!L25 -> 174 | I26: ='Raw FS'!M25 -> 201 | J26: ='Raw FS'!N25 -> 266 | K26: ='Raw FS'!O25 -> 0
B27: ='Raw FS'!B26 -> Vehicles | G27: ='Raw FS'!K26 -> 170 | H27: ='Raw FS'!L26 -> 207 | I27: ='Raw FS'!M26 -> 214 | J27: ='Raw FS'!N26 -> 237 | K27: ='Raw FS'!O26 -> 0
B28: ='Raw FS'!B27 -> Intangible Assets | G28: ='Raw FS'!K27 -> 2001 | H28: ='Raw FS'!L27 -> 2062 | I28: ='Raw FS'!M27 -> 644 | J28: ='Raw FS'!N27 -> 1161 | K28: ='Raw FS'!O27 -> 2951
B29: ='Raw FS'!B28 -> Other fixed assets | G29: ='Raw FS'!K28 -> 3325 | H29: ='Raw FS'!L28 -> 3689 | I29: ='Raw FS'!M28 -> 2636 | J29: ='Raw FS'!N28 -> 3354 | K29: ='Raw FS'!O28 -> 0
B30: ='Raw FS'!B29 -> Gross Block | G30: ='Raw FS'!K29 -> 88862 | H30: ='Raw FS'!L29 -> 129976 | I30: ='Raw FS'!M29 -> 139236 | J30: ='Raw FS'!N29 -> 154695 | K30: ='Raw FS'!O29 -> 0
B31: ='Raw FS'!B30 -> Accumulated Depreciation | G31: =-'Raw FS'!K30 -> -23945 | H31: =-'Raw FS'!L30 -> -30096 | I31: =-'Raw FS'!M30 -> -34784 | J31: =-'Raw FS'!N30 -> -42234 | K31: ='Raw FS'!O30 -> 0
A32: # | B32: Net Non Current Asset | G32: =G30+G31 -> 64917 | H32: =H30+H31 -> 99880 | I32: =I30+I31 -> 104452 | J32: =J30+J31 -> 112461 | K32: =K30+K31 -> 0
A34: # | B34: Invested Capital | G34: =G19+G32 -> 68009 | H34: =H19+H32 -> 117689 | I34: =I19+I32 -> 119576 | J34: =J19+J32 -> 128731 | K34: =K19+K32 -> 20335
B35: EBIT | G35: ='Historical FS'!H23+'Historical FS'!H19 -> 7567 | H35: ='Historical FS'!I23+'Historical FS'!I19 -> 15499 | I35: ='Historical FS'!J23+'Historical FS'!J19 -> 33113 | J35: ='Historical FS'!K23+'Historical FS'!K19 -> 10996 | K35: ='Historical FS'!L23+'Historical FS'!L19 -> 19985
A37: # | B37: ROIC | G37: =G35/G34 -> 0.11126469 | H37: =H35/H34 -> 0.13169455 | I37: =I35/I34 -> 0.27692012 | J37: =J35/J34 -> 0.085418431 | K37: =K35/K34 -> 0.9827883
A39: # | B39: Calculation On Invested Capital | G39: =G2 -> 43921 | H39: =H2 -> 44286 | I39: =I2 -> 44651 | J39: =J2 -> 45016 | K39: =K2 -> 45382
B41: Net Capex | G41: =-'Raw FS'!K57+'Raw FS'!K58 -> 9309 | H41: =-'Raw FS'!L57+'Raw FS'!L58 -> 10134 | I41: =-'Raw FS'!M57+'Raw FS'!M58 -> 14819 | J41: =-'Raw FS'!N57+'Raw FS'!N58 -> 16055 | K41: =-'Raw FS'!O57+'Raw FS'!O58 -> 0
B42: Change in Working Capital | H42: =H19-G19 -> 14717 | I42: =I19-H19 -> -2685 | J42: =J19-I19 -> 1146 | K42: =K19-J19 -> 4065
B44: EBIT | G44: =G35 -> 7567 | H44: =H35 -> 15499 | I44: =I35 -> 33113 | J44: =J35 -> 10996 | K44: =K35 -> 19985
B45: Marginal Tax | G45: 0.25 | H45: 0.25 | I45: 0.25 | J45: 0.25 | K45: 0.25
B46: EBIT(1-Tax) | G46: =G44*(1-G45) -> 5675.25 | H46: =H44*(1-H45) -> 11624.25 | I46: =I44*(1-I45) -> 24834.75 | J46: =J44*(1-J45) -> 8247 | K46: =K44*(1-K45) -> 14988.75
B48: Reinvestment | H48: =SUM(H41:H42) -> 24851 | I48: =SUM(I41:I42) -> 12134 | J48: =SUM(J41:J42) -> 17201 | K48: =SUM(K41:K42) -> 4065
B50: Reinvestment Rate | H50: =H48/H46 -> 2.1378584 | I50: =I48/I46 -> 0.48858958 | J50: =J48/J46 -> 2.0857281 | K50: =K48/K46 -> 0.2712034
J52: 4 Year Average | K52: =AVERAGE(H50:K50) -> 1.2458449
J53: 4 Year Median | K53: =MEDIAN(H50:K50) -> 1.2871589
B56: Calculation of Growth Rate | G56: =G2 -> 43921 | H56: =H2 -> 44286 | I56: =I2 -> 44651 | J56: =J2 -> 45016 | K56: =K2 -> 45382
B58: Reinvestment Rate | H58: =H50 -> 2.1378584 | I58: =I50 -> 0.48858958 | J58: =J50 -> 2.0857281 | K58: =K50 -> 0.2712034
B59: ROIC | H59: =H37 -> 0.13169455 | I59: =I37 -> 0.27692012 | J59: =J37 -> 0.085418431 | K59: =K37 -> 0.9827883
B61: Intrinsic Growth Rate | H61: =H58*H59 -> 0.2815443 | I61: =I58*I59 -> 0.13530028 | J61: =J58*J59 -> 0.17815962 | K61: =K58*K59 -> 0.26653553
J63: 4 Year Average | K63: =AVERAGE(H61:K61) -> 0.21538493
J64: 4 Year Median | K64: =MEDIAN(H61:K61) -> 0.22234758

Sheet Peer Comps
B2: S.No. | C2: Name | D2: CMP Rs. | E2: Mar Cap Rs.Cr. | F2: Debt Rs.Cr. | G2: Debt / Eq
B3: 1 | C3: JSW Steel | D3: 1056.9 | E3: 258459.99 | F3: 95258 | G3: 1.2
B4: 2 | C4: Tata Steel | D4: 158.25 | E4: 197551.76 | F4: 99391.76 | G4: 1.1
B5: 3 | C5: Jindal Steel | D5: 918.85 | E5: 93730.79 | F5: 17266.45 | G5: 0.36
B6: 6 | C6: S A I L | D6: 114.95 | E6: 47480.37 | F6: 41265.03 | G6: 0.72

Sheet Raw FS
B2: Particular | D2: 41334 | E2: =D2+365 -> 41699 | F2: =E2+365 -> 42064 | G2: =F2+366 -> 42430 | H2: =G2+366 -> 42796 | I2: =H2+366 -> 43162 | J2: =I2+366 -> 43528 | K2: =J2+366 -> 43894 | L2: =K2+366 -> 44260 | M2: =L2+366 -> 44626 | N2: =M2+366 -> 44992 | O2: =N2+366 -> 45358
B4: Equity Capital | C4: 284 | D4: 303 | E4: 303 | F4: 301 | G4: 301 | H4: 302 | I4: 301 | J4: 301 | K4: 302 | L4: 301 | M4: 301 | N4: 305 | O4: 305
B5: Reserves | C5: 16781 | D5: 20871 | E5: 21987 | F5: 18665 | G5: 22346 | H5: 27696 | I5: 34494 | J5: 36298 | K5: 46462 | L5: 66996 | M5: 65394 | N5: 77364 | O5: 79361
B6: Borrowings -
B7: Long term Borrowings | C7: 17393 | D7: 26703 | E7: 33677 | F7: 32793 | G7: 32416 | H7: 31723 | I7: 29656 | J7: 44673 | K7: 49731 | L7: 57929 | M7: 61966 | N7: 67354 | O7: 76547
B8: Short term Borrowings | C8: 1653 | D8: 4887 | E8: 1208 | F8: 2378 | G8: 4881 | H8: 2177 | I8: 6333 | J8: 8325 | K8: 1999 | L8: 12046 | M8: 16876 | N8: 18221 | O8: 15808
B9: Lease Liabilities | C9: 0 | D9: 0 | E9: 0 | F9: 0 | G9: 0 | H9: 0 | I9: 0 | J9: 2050 | K9: 2344 | L9: 2262 | M9: 2011 | N9: 2409 | O9: 2903
B10: Preference Capital | C10: 279 | D10: 764 | E10: 764 | F10: 0 | G10: 0 | H10: 208 | I10: 20 | J10: 24 | K10: 26 | L10: 29 | M10: 33 | N10: 36 | O10: 0
B11: Other Borrowings | C11: 2579 | D11: 3937 | E11: 3870 | F11: 7033 | G11: 6037 | H11: 5493 | I11: 11407 | J11: 6375 | K11: 8318 | L11: 0 | M11: 0 | N11: 0
B12: Other Liabilities -
B13: Non controlling int | C13: 197 | D13: 167 | E13: 98 | F13: -195 | G13: -246 | H13: -464 | I13: -450 | J13: -575 | K13: -619 | L13: 1238 | M13: 1344 | N13: 2107 | O13: 2094
B14: Trade Payables | C14: 10251 | D14: 11699 | E14: 14253 | F14: 12758 | G14: 13348 | H14: 15944 | I14: 16159 | J14: 17918 | K14: 15243 | L14: 30889 | M14: 38203 | N14: 33365 | O14: 28900
B15: Advance from Customers | C15: 200 | D15: 315 | E15: 513 | F15: 327 | G15: 377 | H15: 370 | I15: 1154 | J15: 1459 | K15: 1984 | L15: 2133 | M15: 2338 | N15: 1005
B16: Other liability items | C16: 8175 | D16: 8758 | E16: 9747 | F16: 7848 | G16: 8545 | H16: 8729 | I16: 15743 | J16: 14996 | K16: 22553 | L16: 22691 | M16: 22106 | N16: 25768 | O16: 27250
B18: Total Liabilities | C18: 57513 | D18: 77640 | E18: 85654 | F18: 81907 | G18: 88005 | H18: 91970 | I18: 114797 | J18: 131820 | K18: 148317 | L18: 196485 | M18: 210539 | N18: 227898 | O18: 233168
B20: Fixed Assets -
B21: Land | C21: 521 | D21: 1689 | E21: 2162 | F21: 2090 | G21: 2112 | H21: 2137 | I21: 2536 | J21: 2610 | K21: 2946 | L21: 5367 | M21: 5501 | N21: 6118
B22: Building | C22: 5860 | D22: 6811 | E22: 8146 | F22: 7661 | G22: 8169 | H22: 8463 | I22: 9432 | J22: 9937 | K22: 10575 | L22: 15584 | M22: 16612 | N22: 18926
B23: Plant Machinery | C23: 37037 | D23: 49885 | E23: 56800 | F23: 48633 | G23: 53948 | H23: 56071 | I23: 62976 | J23: 65282 | K23: 69561 | L23: 102739 | M23: 113225 | N23: 124339
B24: Equipments | C24: 24 | D24: 43 | E24: 62 | F24: 41 | G24: 56 | H24: 69 | I24: 85 | J24: 111 | K24: 129 | L24: 154 | M24: 203 | N24: 294
B25: Furniture n fittings | C25: 106 | D25: 121 | E25: 156 | F25: 81 | G25: 88 | H25: 119 | I25: 142 | J25: 144 | K25: 155 | L25: 174 | M25: 201 | N25: 266
B26: Vehicles | C26: 179 | D26: 193 | E26: 201 | F26: 125 | G26: 131 | H26: 144 | I26: 157 | J26: 165 | K26: 170 | L26: 207 | M26: 214 | N26: 237
B27: Intangible Assets | C27: 1340 | D27: 1600 | E27: 1634 | F27: 1706 | G27: 1670 | H27: 1678 | I27: 1872 | J27: 2054 | K27: 2001 | L27: 2062 | M27: 644 | N27: 1161 | O27: 2951
B28: Other fixed assets | C28: 801 | D28: 955 | E28: 1028 | F28: 988 | G28: 975 | H28: 1071 | I28: 1289 | J28: 1828 | K28: 3325 | L28: 3689 | M28: 2636 | N28: 3354
B29: Gross Block | C29: 45868 | D29: 61298 | E29: 70189 | F29: 61325 | G29: 67149 | H29: 69752 | I29: 78489 | J29: 82131 | K29: 88862 | L29: 129976 | M29: 139236 | N29: 154695
B30: Accumulated Depreciation | C30: 11151 | D30: 14252 | E30: 18013 | F30: 5186 | G30: 8419 | H30: 11904 | I30: 15845 | J30: 20046 | K30: 23945 | L30: 30096 | M30: 34784 | N30: 42234
B31: Net Block | C31: =C29-C30 -> 34717 | D31: =D29-D30 -> 47046 | E31: =E29-E30 -> 52176 | F31: =F29-F30 -> 56139 | G31: =G29-G30 -> 58730 | H31: =H29-H30 -> 57848 | I31: =I29-I30 -> 62644 | J31: =J29-J30 -> 62085 | ... O31: =O29-O30 -> 0
B33: CWIP | C33: 5898 | D33: 9400 | E33: 8265 | F33: 7271 | G33: 4363 | H33: 5950 | I33: 11889 | J33: 27191 | K33: 32566 | L33: 16905 | M33: 22166 | N33: 29676 | O33: 29555
B34: Investments | C34: 1750 | D34: 663 | E34: 599 | F34: 1195 | G34: 1366 | H34: 1469 | I34: 1894 | J34: 1259 | K34: 8581 | L34: 4940 | M34: 4806 | N34: 7246 | O34: 10740
B36: Other Assets -
B37: Inventories | C37: 5495 | D37: 8155 | E37: 11009 | F37: 8321 | G37: 11395 | H37: 12594 | I37: 14548 | J37: 13773 | K37: 14249 | L37: 33787 | M37: 33135 | N37: 37815 | O37: 37240
B38: Trade receivables | C38: 2106 | D38: 2292 | E38: 2500 | F38: 2727 | G38: 4149 | H38: 4704 | I38: 7160 | J38: 4505 | K38: 4486 | L38: 7457 | M38: 7134 | N38: 7548 | O38: 8002
B39: Cash Equivalents | C39: 1653 | D39: 663 | E39: 1913 | F39: 1020 | G39: 1485 | H39: 1063 | I39: 6187 | J39: 12003 | K39: 12813 | L39: 17383 | M39: 20714 | N39: 12348 | O39: 9289
B40: Loans n Advances | C40: 861 | D40: 2373 | E40: 1371 | F40: 666 | G40: 995 | H40: 1212 | I40: 1276 | J40: 1562 | K40: 1267 | L40: 2227 | M40: 3179 | N40: 1877 | O40: 7064
B41: Other asset items | C41: 5033 | D41: 7048 | E41: 7820 | F41: 4567 | G41: 5522 | H41: 7130 | I41: 9199 | J41: 9442 | K41: 9438 | L41: 13906 | M41: 14953 | N41: 18927 | O41: 16984
B43: Total Assets | C43: 57513 | D43: 77640 | E43: 85654 | F43: 81907 | G43: 88005 | H43: 91970 | I43: 114797 | J43: 131820 | K43: 148317 | L43: 196485 | M43: 210539 | N43: 227898 | O43: 233168
B45: Cash Flow
B47: Cash from Operating Activity - | C47: 5844 | D47: 2594 | E47: 7876 | F47: 6897 | G47: 7888 | H47: 12379 | I47: 14633 | J47: 12785 | K47: 18789 | L47: 26270 | M47: 23323 | N47: 12078
B48: Profit from operations | C48: 5766 | D48: 6517 | E48: 8850 | F48: 6614 | G48: 11994 | H48: 14920 | I48: 18844 | J48: 12301 | K48: 19455 | L48: 38913 | M48: 20856 | N48: 28472
B49: Receivables | C49: -644 | D49: 284 | E49: -207 | F49: -294 | G49: -1352 | H49: -640 | I49: -2203 | J49: 2458 | K49: 72 | L49: -1884 | M49: 317 | N49: -154
B50: Inventory | C50: 294 | D50: -976 | E50: -2854 | F50: 2578 | G50: -3065 | H50: -1199 | I50: -1741 | J50: 744 | K50: -335 | L50: -15593 | M50: 704 | N50: -3284
B51: Payables | C51: 0 | D51: 0 | E51: 2543 | F51: -2143 | G51: 1561 | H51: 2514 | I51: 3406 | J51: 183 | K51: 1306 | L51: 13013 | M51: 4965 | N51: -7235
B52: Loans Advances | C52: 278 | D52: 51 | E52: 286 | F52: 0 | G52: 0 | H52: 0 | I52: 0 | J52: 0 | K52: 0 | L52: 0 | M52: 0 | N52: 0
B53: Other WC items | C53: 661 | D53: -2878 | E53: 31 | F53: 351 | G53: -1013 | H53: -1776 | I53: -1043 | J53: -1746 | K53: 221 | L53: -2800 | M53: -2881 | N53: -2942
B54: Working capital changes | C54: 589 | D54: -3520 | E54: -202 | F54: 491 | G54: -3869 | H54: -1101 | I54: -1581 | J54: 1639 | K54: 1264 | L54: -7264 | M54: 3105 | N54: -13615
B55: Direct taxes | C55: -511 | D55: -404 | E55: -773 | F55: -207 | G55: -237 | H55: -1440 | I55: -2630 | J55: -1155 | K55: -1930 | L55: -5379 | M55: -638 | N55: -2779
B56: Cash from Investing Activity - | C56: -5433 | D56: -5618 | E56: -7372 | F56: -3857 | G56: -5094 | H56: -4529 | I56: -11387 | J56: -19589 | K56: -7702 | L56: -14748 | M56: -10730 | N56: -14467
B57: Fixed assets purchased | C57: -5630 | D57: -5763 | E57: -6721 | F57: -5166 | G57: -4435 | H57: -4736 | I57: -10206 | J57: -12810 | K57: -9258 | L57: -10091 | M57: -14784 | N57: -15801
B58: Fixed assets sold | C58: 12 | D58: 19 | E58: 207 | F58: 4 | G58: 45 | H58: 60 | I58: 44 | J58: 43 | K58: 51 | L58: 43 | M58: 35 | N58: 254
... B77: Net Cash Flow | C77: -380 | D77: 276 | E77: 334 | F77: -111 | G77: 84 | H77: -335 | I77: 4999 | J77: -1615 | K77: 7977 | L77: -3135 | M77: 6616 | N77: -7394

Sheet Dupont Analysis
B2: ='Data Sheet'!B1 -> JSW STEEL LTD
B3: =CONCATENATE(" ","NSE: JSWSTELL"," | ","BSE: 500228") -> NSE: JSWSTELL | BSE: 500228
B4: =CONCATENATE(" ","INR "&'Data Sheet'!B8) -> INR 1016.2
B5: 52 Week (High - INR 1074.90 & Low - 815.40)
B7: About THE Company
B8: JSW Steel Limited is an Indian multinational steel producer based in Mumbai and is a flagship company of the JSW Group. After the merger of Bhushan Power & Steel, Ispat Steel and Jindal Vijayanagar Steel Limited, JSW Steel became world's largest private sector steel company.
B13: Financial Summary
B54: Return on Equity (ROE)
C55: ='Raw FS'!I2 -> 43162 | D55: ='Raw FS'!J2 -> 43528 | E55: ='Raw FS'!K2 -> 43894 | F55: ='Raw FS'!L2 -> 44260 | G55: ='Raw FS'!M2 -> 44626 | H55: ='Raw FS'!N2 -> 44992 | I55: ='Raw FS'!O2 -> 45358
B56: Net Profit | C56: ='Data Sheet'!E30 -> 6214 | D56: ='Data Sheet'!F30 -> 7639 | E56: ='Data Sheet'!G30 -> 4030 | F56: ='Data Sheet'!H30 -> 7911 | G56: ='Data Sheet'!I30 -> 20665 | H56: ='Data Sheet'!J30 -> 4144 | I56: ='Data Sheet'!K30 -> 8812
B57: Average Shareholder Equity | C57: =(('Data Sheet'!E57+'Data Sheet'!E58)+('Data Sheet'!D57+'Data Sheet'!D58)/2) -> 39321.5 | D57: =(('Data Sheet'!F57+'Data Sheet'!F58)+('Data Sheet'!E57+'Data Sheet'!E58)/2) -> 48794 | E57: =(('Data Sheet'!G57+'Data Sheet'!G58)+('Data Sheet'!F57+'Data Sheet'!F58)/2) -> 53996.5 | F57: =(('Data Sheet'!H57+'Data Sheet'!H58)+('Data Sheet'!G57+'Data Sheet'!G58)/2) -> 65063.5 | G57: =(('Data Sheet'!I57+'Data Sheet'!I58)+('Data Sheet'!H57+'Data Sheet'!H58)/2) -> 90679 | H57: =(('Data Sheet'!J57+'Data Sheet'!J58)+('Data Sheet'!I57+'Data Sheet'!I58)/2) -> 99343.5 | I57: =(('Data Sheet'!K57+'Data Sheet'!K58)+('Data Sheet'!J57+'Data Sheet'!J58)/2) -> 110516.5
B58: Return on Equity (ROE) | C58: =C56/C57 -> 0.15803059 | D58: =D56/D57 -> 0.15655613 | E58: =E56/E57 -> 0.074634467 | F58: =F56/F57 -> 0.12158891 | G58: =G56/G57 -> 0.22789179 | H58: =H56/H57 -> 0.041713851 | I58: =I56/I57 -> 0.0797347
B60: ROE-Dupont Equation
C61: =C55 -> 43162 | D61: =D55 -> 43528 | E61: =E55 -> 43894 | F61: =F55 -> 44260 | G61: =G55 -> 44626 | H61: =H55 -> 44992 | I61: =I55 -> 45358
B62: Net Profit | C62: ='Data Sheet'!E30 -> 6214 | D62: ='Data Sheet'!F30 -> 7639 | E62: ='Data Sheet'!G30 -> 4030 | F62: ='Data Sheet'!H30 -> 7911 | G62: ='Data Sheet'!I30 -> 20665 | H62: ='Data Sheet'!J30 -> 4144 | I62: ='Data Sheet'!K30 -> 8812
B63: Revenue | C63: ='Data Sheet'!E17 -> 71933 | D63: ='Data Sheet'!F17 -> 84757 | E63: ='Data Sheet'!G17 -> 73326 | F63: ='Data Sheet'!H17 -> 79839 | G63: ='Data Sheet'!I17 -> 146371 | H63: ='Data Sheet'!J17 -> 165960 | I63: ='Data Sheet'!K17 -> 175006
B64: Net Profit Margin (A) | C64: =C62/C63 -> 0.086385942 | D64: =D62/D63 -> 0.090128249 | E64: =E62/E63 -> 0.054960041 | F64: =F62/F63 -> 0.099086912 | G64: =G62/G63 -> 0.14118234 | H64: =H62/H63 -> 0.024969872 | I64: =I62/I63 -> 0.050352559
B66: Revenue | C66: ='Data Sheet'!E17 -> 71933 | D66: ='Data Sheet'!F17 -> 84757 | E66: ='Data Sheet'!G17 -> 73326 | F66: ='Data Sheet'!H17 -> 79839 | G66: ='Data Sheet'!I17 -> 146371 | H66: ='Data Sheet'!J17 -> 165960 | I66: ='Data Sheet'!K17 -> 175006
B67: Average Total Asset | C67: =('Data Sheet'!E66+'Data Sheet'!D66)/2 -> 89987.5 | D67: =('Data Sheet'!F66+'Data Sheet'!E66)/2 -> 103383.5 | E67: =('Data Sheet'!G66+'Data Sheet'!F66)/2 -> 123308.5 | F67: =('Data Sheet'!H66+'Data Sheet'!G66)/2 -> 140068.5 | G67: =('Data Sheet'!I66+'Data Sheet'!H66)/2 -> 172401 | H67: =('Data Sheet'!J66+'Data Sheet'!I66)/2 -> 203512 | I67: =('Data Sheet'!K66+'Data Sheet'!J66)/2 -> 219218.5
B68: Asset Turnover Ratio (B) | C68: =C66/C67 -> 0.79936658 | D68: =D66/D67 -> 0.81983102 | E68: =E66/E67 -> 0.59465487 | F68: =F66/F67 -> 0.56999968 | G68: =G66/G67 -> 0.8490148 | H68: =H66/H67 -> 0.81548017 | I68: =I66/I67 -> 0.79831766
B70: =B67 -> Average Total Asset | C70: =C67 -> 89987.5 | D70: =D67 -> 103383.5 | E70: =E67 -> 123308.5 | F70: =F67 -> 140068.5 | G70: =G67 -> 172401 | H70: =H67 -> 203512 | I70: =I67 -> 219218.5
B71: =B57 -> Average Shareholder Equity | C71: =C57 -> 39321.5 | D71: =D57 -> 48794 | E71: =E57 -> 53996.5 | F71: =F57 -> 65063.5 | G71: =G57 -> 90679 | H71: =H57 -> 99343.5 | I71: =I57 -> 110516.5
B72: Financial Leverage (C) | C72: =C70/C71 -> 2.2885063 | D72: =D70/D71 -> 2.1187748 | E72: =E70/E71 -> 2.2836388 | F72: =F70/F71 -> 2.1527969 | G72: =G70/G71 -> 1.901223 | H72: =H70/H71 -> 2.0485689 | I72: =I70/I71 -> 1.9835816
B74: Return on Equity (A*B*C) | C74: =C72*C68*C64 -> 0.15803059 | D74: =D72*D68*D64 -> 0.15655613 | E74: =E72*E68*E64 -> 0.074634467 | F74: =F72*F68*F64 -> 0.12158891 | G74: =G72*G68*G64 -> 0.22789179 | H74: =H72*H68*H64 -> 0.041713851 | I74: =I72*I68*I64 -> 0.0797347
B76: Return on Asset (ROA)
C77: ='Data Sheet'!E16 -> 43190 | D77: ='Data Sheet'!F16 -> 43555 | E77: ='Data Sheet'!G16 -> 43921 | F77: ='Data Sheet'!H16 -> 44286 | G77: ='Data Sheet'!I16 -> 44651 | H77: ='Data Sheet'!J16 -> 45016 | I77: ='Data Sheet'!K16 -> 45382
B78: Net Profit | C78: =C62 -> 6214 | D78: =D62 -> 7639 | E78: =E62 -> 4030 | F78: =F62 -> 7911 | G78: =G62 -> 20665 | H78: =H62 -> 4144 | I78: =I62 -> 8812
B79: Avergae Total Asset | C79: =C67 -> 89987.5 | D79: =D67 -> 103383.5 | E79: =E67 -> 123308.5 | F79: =F67 -> 140068.5 | G79: =G67 -> 172401 | H79: =H67 -> 203512 | I79: =I67 -> 219218.5
B80: Return on Asset (ROA) | C80: =C78/C79 -> 0.069054035 | D80: =D78/D79 -> 0.073889934 | E80: =E78/E79 -> 0.032682256 | F80: =F78/F79 -> 0.056479508 | G80: =G78/G79 -> 0.11986589 | H80: =H78/H79 -> 0.020362436 | I80: =I78/I79 -> 0.040197337
B82: ROA-Dupont Equation
C83: =C77 -> 43190 | D83: =D77 -> 43555 | E83: =E77 -> 43921 | F83: =F77 -> 44286 | G83: =G77 -> 44651 | H83: =H77 -> 45016 | I83: =I77 -> 45382
B84: Net Profit | C84: =C78 -> 6214 | D84: =D78 -> 7639 | E84: =E78 -> 4030 | F84: =F78 -> 7911 | G84: =G78 -> 20665 | H84: =H78 -> 4144 | I84: =I78 -> 8812
B85: Revenue | C85: =C63 -> 71933 | D85: =D63 -> 84757 | E85: =E63 -> 73326 | F85: =F63 -> 79839 | G85: =G63 -> 146371 | H85: =H63 -> 165960 | I85: =I63 -> 175006
B86: Net Profit Margin (A) | C86: =C84/C85 -> 0.086385942 | D86: =D84/D85 -> 0.090128249 | E86: =E84/E85 -> 0.054960041 | F86: =F84/F85 -> 0.099086912 | G86: =G84/G85 -> 0.14118234 | H86: =H84/H85 -> 0.024969872 | I86: =I84/I85 -> 0.050352559
B88: Net Profit | C88: =C84 -> 6214 | D88: =D84 -> 7639 | E88: =E84 -> 4030 | F88: =F84 -> 7911 | G88: =G84 -> 20665 | H88: =H84 -> 4144 | I88: =I84 -> 8812
B89: Average Total Asset | C89: =C79 -> 89987.5 | D89: =D67 -> 103383.5 | E89: =E67 -> 123308.5 | F89: =F67 -> 140068.5 | G89: =G67 -> 172401 | H89: =H67 -> 203512 | I89: =I67 -> 219218.5
B90: Asset Turnover Ratio (B) | C90: =C88/C89 -> 0.069054035 | D90: =D88/D89 -> 0.073889934 | E90: =E88/E89 -> 0.032682256 | F90: =F88/F89 -> 0.056479508 | G90: =G88/G89 -> 0.11986589 | H90: =H88/H89 -> 0.020362436 | I90: =I88/I89 -> 0.040197337
B92: Return on Asset (A*B) | C92: =C86*C90 -> 0.0059652979 | D92: =D90*D86 -> 0.0066595704 | E92: =E90*E86 -> 0.0017962182 | F92: =F90*F86 -> 0.0055963801 | G92: =G90*G86 -> 0.016922947 | H92: =H90*H86 -> 0.00050844742 | I92: =I90*I86 -> 0.0020240388

Sheet Data Sheet
A1: COMPANY NAME | B1: JSW STEEL LTD | E1: =IF(B2<>B3, "A NEW VERSION OF THE WORKSHEET IS AVAILABLE", "")
A2: LATEST VERSION | B2: 2.1 | E2: PLEASE DO NOT MAKE ANY CHANGES TO THIS SHEET
A3: CURRENT VERSION | B3: 2.1
A5: META
A6: Number of shares | B6: =IF(B9>0, B9/B8, 0) -> 244.54544
A7: Face Value | B7: 1
A8: Current Price | B8: 1016.2
A9: Market Capitalization | B9: 248507.08
A15: PROFIT & LOSS
A16: Report Date | B16: 42094 | C16: 42460 | D16: 42825 | E16: 43190 | F16: 43555 | G16: 43921 | H16: 44286 | I16: 44651 | J16: 45016 | K16: 45382
A17: Sales | B17: 52971.51 | C17: 41546.17 | D17: 55604 | E17: 71933 | F17: 84757 | G17: 73326 | H17: 79839 | I17: 146371 | J17: 165960 | K17: 175006
A18: Raw Material Cost | B18: 31140.42 | C18: 21181.02 | D18: 29749 | E18: 38781 | F18: 43796 | G18: 39000 | H18: 32856 | I18: 62871 | J18: 95970 | K18: 94754
A19: Change in Inventory | B19: 1488.21 | C19: -1365.76 | D19: 1486 | E19: -244 | F19: 590 | G19: 270 | H19: 348 | I19: 3601 | J19: 2636 | K19: 3087
A20: Power and Fuel | B20: 4123.1 | C20: 3657.88 | D20: 4883 | E20: 5697 | F20: 7053 | G20: 6272 | H20: 5985 | I20: 11289 | J20: 17452 | K20: 15127
A21: Other Mfr. Exp | B21: 6764.77 | C21: 5745.05 | D21: 6887 | E21: 8713 | F21: 10158 | G21: 10243 | H21: 16247 | I21: 29726 | J21: 26224 | K21: 29716
A22: Employee Cost | B22: 1532.84 | C22: 1518.67 | D22: 1700 | E22: 1843 | F22: 2489 | G22: 2839 | H22: 2506 | I22: 3493 | J22: 3915 | K22: 4591
A23: Selling and admin | B23: 372.65 | C23: 332.82 | D23: 323 | E23: 277 | F23: 602 | G23: 450 | H23: 404 | I23: 557 | J23: 1018 | K23: 894
A24: Other Expenses | B24: 1162.08 | C24: 1322.66 | D24: 1240 | E24: 1462 | F24: 2319 | G24: 2979 | H24: 2011 | I24: 2922 | J24: 5547 | K24: 4854
A25: Other Income | B25: 102.77 | C25: -1966.23 | D25: 18 | E25: -177 | F25: 196 | G25: -289 | H25: 473 | I25: 1600 | J25: 1561 | K25: 1500
A26: Depreciation | B26: 3434.49 | C26: 3322.56 | D26: 3430 | E26: 3387 | F26: 4041 | G26: 4246 | H26: 4679 | I26: 6001 | J26: 7474 | K26: 8172
A27: Interest | B27: 3493.03 | C27: 3601.18 | D27: 3768 | E27: 3701 | F27: 3917 | G27: 4265 | H27: 3957 | I27: 4968 | J27: 6902 | K27: 8105
... A31: Dividend Amount | B31: 333.02 | C31: 225.68 | D31: 677.25 | E31: 966.4 | F31: 1234.1 | G31: 602 | H31: 1963 | I31: 5222.35 | J31: 1023.4 | K31: 2226.5
A32: EBITDA | B32: =B34+B26 -> 9363.86 | C32: =C34+C26 -> 6422.31 | D32: =D34+D26 -> 12308 | E32: =E34+E26 -> 14916 | F32: =F34+F26 -> 18930 | G32: =G34+G26 -> 11813 | H32: =H34+H26 -> 20178 | I32: =I34+I26 -> 39114 | ... K32: =K34+K26 -> 28157
A34: Ebit | B34: ='Historical FS'!C23+'Historical FS'!C19 -> 5929.37 | C34: ='Historical FS'!D23+'Historical FS'!D19 -> 3099.75 | D34: ='Historical FS'!E23+'Historical FS'!E19 -> 8878 | E34: ='Historical FS'!F23+'Historical FS'!F19 -> 11529 | F34: ='Historical FS'!G23+'Historical FS'!G19 -> 14889 | G34: ='Historical FS'!H23+'Historical FS'!H19 -> 7567 | H34: ='Historical FS'!I23+'Historical FS'!I19 -> 15499 | I34: ='Historical FS'!J23+'Historical FS'!J19 -> 33113 | ... K34: ='Historical FS'!L23+'Historical FS'!L19 -> 19985
A35: ebit margin | B35: =B34/B17 -> 0.11193508 | C35: =C34/C17 -> 0.074609765 | D35: =D34/D17 -> 0.15966477 | E35: =E34/E17 -> 0.16027414 | F35: =F34/F17 -> 0.17566691 | G35: =G34/G17 -> 0.10319668 | H35: =H34/H17 -> 0.19412818 | I35: =I34/I17 -> 0.22622651 | ... K35: =K34/K17 -> 0.11419608
A40: Quarters
A41: Report Date | B41: 44834 | C41: 44926 | D41: 45016 | E41: 45107 | F41: 45199 | G41: 45291 | H41: 45382 | I41: 45473 | J41: 45565 | K41: 45657
A42: Sales | B42: 41778 | C42: 39134 | D42: 46962 | E42: 42213 | F42: 44584 | G42: 41940 | H42: 46269 | I42: 42943 | J42: 39684 | K42: 41378
A43: Expenses | B43: 40082 | C43: 34643 | D43: 39031 | E43: 35201 | F43: 36722 | G43: 34776 | H43: 40243 | I43: 37445 | J43: 34309 | K43: 35799
A44: Other Income | B44: 779 | C44: 188 | D44: 465 | E44: 331 | F44: 826 | G44: 194 | H44: 242 | I44: 164 | J44: -189 | K44: 50
A45: Depreciation | B45: 1805 | C45: 1882 | D45: 2009 | E45: 1900 | F45: 2019 | G45: 2059 | H45: 2194 | I45: 2209 | J45: 2267 | K45: 2336
A46: Interest | B46: 1523 | C46: 1819 | D46: 2138 | E46: 1963 | F46: 2084 | G46: 1996 | H46: 2062 | I46: 2073 | J46: 2130 | K46: 2115
A47: Profit before tax | B47: -853 | C47: 978 | D47: 4249 | E47: 3480 | F47: 4585 | G47: 3303 | H47: 2012 | I47: 1380 | J47: 789 | K47: 1178
A48: Tax | B48: 62 | C48: 504 | D48: 508 | E48: 1052 | F48: 1812 | G48: 853 | H48: 690 | I48: 513 | J48: 385 | K48: 459
A49: Net profit | B49: -848 | C49: 490 | D49: 3664 | E49: 2338 | F49: 2760 | G49: 2415 | H49: 1299 | I49: 845 | J49: 439 | K49: 717
A50: Operating Profit | B50: 1696 | C50: 4491 | D50: 7931 | E50: 7012 | F50: 7862 | G50: 7164 | H50: 6026 | I50: 5498 | J50: 5375 | K50: 5579
A55: BALANCE SHEET
A56: Report Date | B56: 42094 | C56: 42460 | D56: 42825 | E56: 43190 | F56: 43555 | G56: 43921 | H56: 44286 | I56: 44651 | J56: 45016 | K56: 45382
A57: Equity Share Capital | B57: 302.75 | C57: 300.9 | D57: 301 | E57: 302 | F57: 301 | G57: 301 | H57: 302 | I57: 301 | J57: 301 | K57: 305
A58: Reserves | B58: 21986.89 | C58: 18664.55 | D58: 22346 | E58: 27696 | F58: 34494 | G58: 36298 | H58: 46462 | I58: 66996 | J58: 65394 | K58: 77364
A59: Borrowings | B59: 38754.26 | C59: 42204.03 | D59: 43334 | E59: 39393 | F59: 47396 | G59: 61423 | H59: 62392 | I59: 72237 | J59: 80853 | K59: 87984
A60: Other Liabilities | B60: 24609.98 | C60: 20737.42 | D60: 22024 | E60: 24579 | F60: 32606 | G60: 33798 | H60: 39161 | I60: 56951 | J60: 63991 | K60: 62245
A61: Total | B61: 85653.88 | C61: 81906.9 | D61: 88005 | E61: 91970 | F61: 114797 | G61: 131820 | H61: 148317 | I61: 196485 | J61: 210539 | K61: 227898
A62: Net Block | B62: 52176.28 | C62: 56139.52 | D62: 58730 | E62: 57848 | F62: 62644 | G62: 62085 | H62: 64917 | I62: 99880 | J62: 104452 | K62: 112461
A63: Capital Work in Progress | B63: 8265.27 | C63: 7270.85 | D63: 4363 | E63: 5950 | F63: 11889 | G63: 27191 | H63: 32566 | I63: 16905 | J63: 22166 | K63: 29676
A64: Investments | B64: 599.25 | C64: 1194.61 | D64: 1366 | E64: 1469 | F64: 1894 | G64: 1259 | H64: 8581 | I64: 4940 | J64: 4806 | K64: 7246
A65: Other Assets | B65: 24613.08 | C65: 17301.92 | D65: 23546 | E65: 26703 | F65: 38370 | G65: 41285 | H65: 42253 | I65: 74760 | J65: 79115 | K65: 78515
A66: Total | B66: 85653.88 | C66: 81906.9 | D66: 88005 | E66: 91970 | F66: 114797 | G66: 131820 | H66: 148317 | I66: 196485 | J66: 210539 | K66: 227898
A67: Receivables | B67: 2499.75 | C67: 2727.37 | D67: 4149 | E67: 4704 | F67: 7160 | G67: 4505 | H67: 4486 | I67: 7457 | J67: 7134 | K67: 7548
... A70: No. of Equity Shares | B70: 302752000 | C70: 300903227 | D70: 3012984690 | E70: 3016231580 | F70: 3011711464 | G70: 3011711464 | H70: 3015766346 | I70: 3016603583 | J70: 3020456419 | K70: 3052602319
A71: New Bonus Shares
A72: Face value | B72: 10 | C72: 10 | D72: 1 | E72: 1 | F72: 1 | G72: 1 | H72: 1 | I72: 1 | J72: 1 | K72: 1
A74: other Asset | B74: =B65-SUM(B67:B69) -> 9191.04 | C74: =C65-SUM(C67:C69) -> 5232.97 | D74: =D65-SUM(D67:D69) -> 6517 | E74: =E65-SUM(E67:E69) -> 8342 | F74: =F65-SUM(F67:F69) -> 10475 | G74: =G65-SUM(G67:G69) -> 11004 | H74: =H65-SUM(H67:H69) -> 10705 | I74: =I65-SUM(I67:I69) -> 16133 | ... K74: =K65-SUM(K67:K69) -> 20804
B76: 14253
A77: Trade Payabel | C77: 14253 | D77: 12758 | E77: 13348 | F77: 15944 | G77: 16159 | H77: 17918 | I77: 15243 | J77: 30889 | K77: 38203 | L77: 33365
A78: ebit
A79: ebitmargin
A80: CASH FLOW:
A81: Report Date | B81: 42094 | C81: 42460 | D81: 42825 | E81: 43190 | F81: 43555 | G81: 43921 | H81: 44286 | I81: 44651 | J81: 45016 | K81: 45382
A82: Cash from Operating Activity | B82: 7875.65 | C82: 6897.32 | D82: 7888 | E82: 12379 | F82: 14633 | G82: 12785 | H82: 18789 | I82: 26270 | J82: 23323 | K82: 12078
A83: Cash from Investing Activity | B83: -7372.25 | C83: -3857.37 | D83: -5094 | E83: -4529 | F83: -11387 | G83: -19589 | H83: -7702 | I83: -14748 | J83: -10730 | K83: -14467
A84: Cash from Financing Activity | B84: -169.08 | C84: -3150.66 | D84: -2710 | E84: -8185 | F84: 1753 | G84: 5189 | H84: -3110 | I84: -14657 | J84: -5977 | K84: -5005
A85: Net Cash Flow | B85: 334.32 | C85: -110.71 | D85: 84 | E85: -335 | F85: 4999 | G85: -1615 | H85: 7977 | I85: -3135 | J85: 6616 | K85: -7394
A90: PRICE: | B90: 90.66 | C90: 128.33 | D90: 188.2 | E90: 288.15 | F90: 293.05 | G90: 146.25 | H90: 468.45 | I90: 732.65 | J90: 688.1 | K90: 830.2
A92: DERIVED:
A93: Adjusted Equity Shares in Cr | B93: 241.72 | C93: 241.72 | D93: 241.72 | E93: 241.72 | F93: 241.72 | G93: 241.72 | H93: 241.72 | I93: 241.72 | J93: 241.72 | K93: 244.55
A96: EBIT Margin

Sheet Cash Flow demo
A2: Cash from Operating Activity - | B2: 5844 | C2: 2594 | D2: 7876 | E2: 6897 | F2: 7888 | G2: 12379 | H2: 14633 | I2: 12785 | J2: 18789 | K2: 26270 | L2: 23323 | M2: 12078
A3: Profit from operations | B3: 5766 | C3: 6517 | D3: 8850 | E3: 6614 | F3: 11994 | G3: 14920 | H3: 18844 | I3: 12301 | J3: 19455 | K3: 38913 | L3: 20856 | M3: 28472
A4: Receivables | B4: -644 | C4: 284 | D4: -207 | E4: -294 | F4: -1352 | G4: -640 | H4: -2203 | I4: 2458 | J4: 72 | K4: -1884 | L4: 317 | M4: -154
A5: Inventory | B5: 294 | C5: -976 | D5: -2854 | E5: 2578 | F5: -3065 | G5: -1199 | H5: -1741 | I5: 744 | J5: -335 | K5: -15593 | L5: 704 | M5: -3284
A6: Payables | B6: 0 | C6: 0 | D6: 2543 | E6: -2143 | F6: 1561 | G6: 2514 | H6: 3406 | I6: 183 | J6: 1306 | K6: 13013 | L6: 4965 | M6: -7235
A7: Loans Advances | B7: 278 | C7: 51 | D7: 286 | E7: 0 | F7: 0 | G7: 0 | H7: 0 | I7: 0 | J7: 0 | K7: 0 | L7: 0 | M7: 0
A8: Other WC items | B8: 661 | C8: -2878 | D8: 31 | E8: 351 | F8: -1013 | G8: -1776 | H8: -1043 | I8: -1746 | J8: 221 | K8: -2800 | L8: -2881 | M8: -2942
A9: Working capital changes | B9: 589 | C9: -3520 | D9: -202 | E9: 491 | F9: -3869 | G9: -1101 | H9: -1581 | I9: 1639 | J9: 1264 | K9: -7264 | L9: 3105 | M9: -13615
A10: Direct taxes | B10: -511 | C10: -404 | D10: -773 | E10: -207 | F10: -237 | G10: -1440 | H10: -2630 | I10: -1155 | J10: -1930 | K10: -5379 | L10: -638 | M10: -2779
A11: Cash from Investing Activity - | B11: -5433 | C11: -5618 | D11: -7372 | E11: -3857 | F11: -5094 | G11: -4529 | H11: -11387 | I11: -19589 | J11: -7702 | K11: -14748 | L11: -10730 | M11: -14467
A12: Fixed assets purchased | B12: -5630 | C12: -5763 | D12: -6721 | E12: -5166 | F12: -4435 | G12: -4736 | H12: -10206 | I12: -12810 | J12: -9258 | K12: -10091 | L12: -14784 | M12: -15801
A13: Fixed assets sold | B13: 12 | C13: 19 | D13: 207 | E13: 4 | F13: 45 | G13: 60 | H13: 44 | I13: 43 | J13: 51 | K13: 43 | L13: 35 | M13: 254
... A32: Net Cash Flow | B32: -380 | C32: 276 | D32: 334 | E32: -111 | F32: 84 | G32: -335 | H32: 4999 | I32: -1615 | J32: 7977 | K32: -3135 | L32: 6616 | M32: -7394

Sheet Beta
B2: ='Data Sheet'!B1 -> JSW STEEL LTD | F2: Nifty Return
N3: Beat 1 | O3: =SLOPE(D6:D108,H6:H108) -> 1.2946664
B4: Date | C4: Closing Price | D4: Return | F4: Date | G4: Closing Price | H4: Return | N4: Beta 2 | O4: =_xlfn.COVARIANCE.S(D6:D108,H6:H108)/_xlfn.VAR.S(H6:H108) -> 1.2946664
B5: =Data!A3 -> 45732 | C5: =Data!B3 -> 1050.25 | F5: =Data!I3 -> 45732 | G5: =Data!J3 -> 23190.65 | N5: Beat 3 | O5: =L29 -> 1.2946664
B6: =Data!A106 -> 45011 | C6: =Data!B106 -> 688.1 | D6: =C6/C5-1 -> -0.34482266 | F6: =Data!I106 -> 45011 | G6: =Data!J106 -> 17359.75 | H6: =G6/G5-1 -> -0.25143323
B7: =Data!A105 -> 45018 | C7: =Data!B105 -> 682.7 | D7: =C7/C6-1 -> -0.0078476966 | F7: =Data!I105 -> 45018 | G7: =Data!J105 -> 17599.15 | H7: =G7/G6-1 -> 0.013790521
B8: =Data!A104 -> 45025 | C8: =Data!B104 -> 720.65 | D8: =C8/C7-1 -> 0.055588106 | F8: =Data!I104 -> 45025 | G8: =Data!J104 -> 17828 | H8: =G8/G7-1 -> 0.013003469
B9: =Data!A103 -> 45032 | C9: =Data!B103 -> 710.65 | D9: =C9/C8-1 -> -0.013876362 | F9: =Data!I103 -> 45032 | G9: =Data!J103 -> 17624.05 | H9: =G9/G8-1 -> -0.01143987
B10: =Data!A102 -> 45039 | C10: =Data!B102 -> 725.3 | D10: =C10/C9-1 -> 0.02061493 | F10: =Data!I102 -> 45039 | G10: =Data!J102 -> 18065 | H10: =G10/G9-1 -> 0.025019788
B11: =Data!A101 -> 45046 | C11: =Data!B101 -> 733.35 | D11: =C11/C10-1 -> 0.011098856 | F11: =Data!I101 -> 45046 | G11: =Data!J101 -> 18069 | H11: =G11/G10-1 -> 0.00022142264
B12: =Data!A100 -> 45053 | C12: =Data!B100 -> 702.65 | D12: =C12/C11-1 -> -0.041862685 | F12: =Data!I100 -> 45053 | G12: =Data!J100 -> 18314.8 | H12: =G12/G11-1 -> 0.013603409 | K12: SUMMARY OUTPUT
B13: =Data!A99 -> 45060 | C13: =Data!B99 -> 693.85 | D13: =C13/C12-1 -> -0.012524016 | F13: =Data!I99 -> 45060 | G13: =Data!J99 -> 18203.4 | H13: =G13/G12-1 -> -0.0060825125
B14: =Data!A98 -> 45067 | C14: =Data!B98 -> 701.7 | D14: =C14/C13-1 -> 0.011313685 | F14: =Data!I98 -> 45067 | G14: =Data!J98 -> 18499.35 | H14: =G14/G13-1 -> 0.016257952 | K14: Regression Statistics
B15: =Data!A97 -> 45074 | C15: =Data!B97 -> 706.6 | D15: =C15/C14-1 -> 0.0069830412 | F15: =Data!I97 -> 45074 | G15: =Data!J97 -> 18534.1 | H15: =G15/G14-1 -> 0.0018784444 | K15: Multiple R | L15: 0.85283887
B16: =Data!A96 -> 45081 | C16: =Data!B96 -> 748.5 | D16: =C16/C15-1 -> 0.059298047 | F16: =Data!I96 -> 45081 | G16: =Data!J96 -> 18563.4 | H16: =G16/G15-1 -> 0.0015808699 | K16: R Square | L16: 0.72733414
B17: =Data!A95 -> 45088 | C17: =Data!B95 -> 776.1 | D17: =C17/C16-1 -> 0.036873747 | F17: =Data!I95 -> 45088 | G17: =Data!J95 -> 18826 | H17: =G17/G16-1 -> 0.014146115 | K17: Adjusted R Square | L17: 0.72463448
B18: =Data!A94 -> 45095 | C18: =Data!B94 -> 746.5 | D18: =C18/C17-1 -> -0.038139415 | F18: =Data!I94 -> 45095 | G18: =Data!J94 -> 18665.5 | H18: =G18/G17-1 -> -0.0085254435 | K18: Standard Error | L18: 0.023553699
B19: =Data!A93 -> 45102 | C19: =Data!B93 -> 784.8 | D19: =C19/C18-1 -> 0.051306095 | F19: =Data!I93 -> 45102 | G19: =Data!J93 -> 19189.05 | H19: =G19/G18-1 -> 0.028049074 | K19: Observations | L19: 103
B20: =Data!A92 -> 45109 | C20: =Data!B92 -> 788.4 | D20: =C20/C19-1 -> 0.004587156 | F20: =Data!I92 -> 45109 | G20: =Data!J92 -> 19331.8 | H20: =G20/G19-1 -> 0.0074391385
B21: =Data!A91 -> 45116 | C21: =Data!B91 -> 804.85 | D21: =C21/C20-1 -> 0.020865043 | F21: =Data!I91 -> 45116 | G21: =Data!J91 -> 19564.5 | H21: =G21/G20-1 -> 0.012037162 | K21: ANOVA
B22: =Data!A90 -> 45123 | C22: =Data!B90 -> 786.45 | D22: =C22/C21-1 -> -0.022861403 | F22: =Data!I90 -> 45123 | G22: =Data!J90 -> 19745 | H22: =G22/G21-1 -> 0.0092258938 | L22: df | M22: SS | N22: MS | O22: F | P22: Significance F
B23: =Data!A89 -> 45130 | C23: =Data!B89 -> 804.15 | D23: =C23/C22-1 -> 0.022506199 | F23: =Data!I89 -> 45130 | G23: =Data!J89 -> 19646.05 | H23: =G23/G22-1 -> -0.0050113953 | K23: Regression | L23: 1 | M23: 0.14946614 | N23: 0.14946614 | O23: 269.41675 | P23: 2.9216222e-30
B24: =Data!A88 -> 45137 | C24: =Data!B88 -> 805.95 | D24: =C24/C23-1 -> 0.0022383884 | F24: =Data!I88 -> 45137 | G24: =Data!J88 -> 19517 | H24: =G24/G23-1 -> -0.0065687505 | K24: Residual | L24: 101 | M24: 0.056032451 | N24: 0.00055477674
B25: =Data!A87 -> 45144 | C25: =Data!B87 -> 820.65 | D25: =C25/C24-1 -> 0.018239345 | F25: =Data!I87 -> 45144 | G25: =Data!J87 -> 19428.3 | H25: =G25/G24-1 -> -0.0045447559 | K25: Total | L25: 102 | M25: 0.2054986
B26: =Data!A86 -> 45151 | C26: =Data!B86 -> 787.1 | D26: =C26/C25-1 -> -0.040882228 | F26: =Data!I86 -> 45151 | G26: =Data!J86 -> 19310.15 | H26: =G26/G25-1 -> -0.006081335
B27: =Data!A85 -> 45158 | C27: =Data!B85 -> 773.15 | D27: =C27/C26-1 -> -0.017723288 | F27: =Data!I85 -> 45158 | G27: =Data!J85 -> 19265.8 | H27: =G27/G26-1 -> -0.0022967196 | L27: Coefficients | M27: Standard Error | N27: t Stat | O27: P-value | P27: Lower 95% | Q27: Upper 95% | R27: Lower 95.0% | S27: Upper 95.0%
B28: =Data!A84 -> 45165 | C28: =Data!B84 -> 806.4 | D28: =C28/C27-1 -> 0.043005885 | F28: =Data!I84 -> 45165 | G28: =Data!J84 -> 19435.3 | H28: =G28/G27-1 -> 0.0087979736 | K28: Intercept | L28: 0.00050842565 | M28: 0.0023208487 | N28: 0.21906884 | O28: 0.82703851 | P28: -0.0040955139 | Q28: 0.0051123652 | R28: -0.0040955139 | S28: 0.0051123652
B29: =Data!A83 -> 45172 | C29: =Data!B83 -> 815.75 | D29: =C29/C28-1 -> 0.011594742 | F29: =Data!I83 -> 45172 | G29: =Data!J83 -> 19819.95 | H29: =G29/G28-1 -> 0.019791308 | K29: X Variable 1 | L29: 1.2946664 | M29: 0.078876131 | N29: 16.413919 | O29: 2.9216222e-30 | P29: 1.1381974 | Q29: 1.4511355 | R29: 1.1381974 | S29: 1.4511355
B30: =Data!A82 -> 45179 | C30: =Data!B82 -> 812.85 | D30: =C30/C29-1 -> -0.0035550107 | F30: =Data!I82 -> 45179 | G30: =Data!J82 -> 20192.35 | H30: =G30/G29-1 -> 0.018789149
B31: =Data!A81 -> 45186 | C31: =Data!B81 -> 774.05 | D31: =C31/C30-1 -> -0.047733284 | F31: =Data!I81 -> 45186 | G31: =Data!J81 -> 19674.25 | H31: =G31/G30-1 -> -0.025658232
B32: =Data!A80 -> 45193 | C32: =Data!B80 -> 779.6 | D32: =C32/C31-1 -> 0.0071700795 | F32: =Data!I80 -> 45193 | G32: =Data!J80 -> 19638.3 | H32: =G32/G31-1 -> -0.0018272615
B33: =Data!A79 -> 45200 | C33: =Data!B79 -> 765.2 | D33: =C33/C32-1 -> -0.018471011 | F33: =Data!I79 -> 45200 | G33: =Data!J79 -> 19653.5 | H33: =G33/G32-1 -> 0.00077399775
B34: =Data!A78 -> 45207 | C34: =Data!B78 -> 777.25 | D34: =C34/C33-1 -> 0.015747517 | F34: =Data!I78 -> 45207 | G34: =Data!J78 -> 19751.05 | H34: =G34/G33-1 -> 0.0049634925
B35: =Data!A77 -> 45214 | C35: =Data!B77 -> 769.4 | D35: =C35/C34-1 -> -0.010099711 | F35: =Data!I77 -> 45214 | G35: =Data!J77 -> 19542.65 | H35: =G35/G34-1 -> -0.010551338
B36: =Data!A76 -> 45221 | C36: =Data!B76 -> 732 | D36: =C36/C35-1 -> -0.048609306 | F36: =Data!I76 -> 45221 | G36: =Data!J76 -> 19047.25 | H36: =G36/G35-1 -> -0.025349684
B37: =Data!A75 -> 45228 | C37: =Data!B75 -> 746.05 | D37: =C37/C36-1 -> 0.019193989 | F37: =Data!I75 -> 45228 | G37: =Data!J75 -> 19230.6 | H37: =G37/G36-1 -> 0.0096260615
B38: =Data!A74 -> 45235 | C38: =Data!B74 -> 754.75 | D38: =C38/C37-1 -> 0.011661417 | F38: =Data!I74 -> 45235 | G38: =Data!J74 -> 19425.35 | H38: =G38/G37-1 -> 0.010127089
B39: =Data!A73 -> 45242 | C39: =Data!B73 -> 768.8 | D39: =C39/C38-1 -> 0.018615436 | F39: =Data!I73 -> 45242 | G39: =Data!J73 -> 19731.8 | H39: =G39/G38-1 -> 0.015775778
B40: =Data!A72 -> 45249 | C40: =Data!B72 -> 782.05 | D40: =C40/C39-1 -> 0.017234651 | F40: =Data!I72 -> 45249 | G40: =Data!J72 -> 19794.7 | H40: =G40/G39-1 -> 0.0031877477
B41: =Data!A71 -> 45256 | C41: =Data!B71 -> 810.8 | D41: =C41/C40-1 -> 0.036762355 | F41: =Data!I71 -> 45256 | G41: =Data!J71 -> 20267.9 | H41: =G41/G40-1 -> 0.023905389
B42: =Data!A70 -> 45263 | C42: =Data!B70 -> 839.35 | D42: =C42/C41-1 -> 0.035212136 | F42: =Data!I70 -> 45263 | G42: =Data!J70 -> 20969.4 | H42: =G42/G41-1 -> 0.034611381
B43: =Data!A69 -> 45270 | C43: =Data!B69 -> 867.2 | D43: =C43/C42-1 -> 0.033180437 | F43: =Data!I69 -> 45270 | G43: =Data!J69 -> 21456.65 | H43: =G43/G42-1 -> 0.023236239
B44: =Data!A68 -> 45277 | C44: =Data!B68 -> 855.3 | D44: =C44/C43-1 -> -0.013722325 | F44: =Data!I68 -> 45277 | G44: =Data!J68 -> 21349.4 | H44: =G44/G43-1 -> -0.0049984504
B45: =Data!A67 -> 45284 | C45: =Data!B67 -> 880.25 | D45: =C45/C44-1 -> 0.029171051 | F45: =Data!I67 -> 45284 | G45: =Data!J67 -> 21731.4 | H45: =G45/G44-1 -> 0.017892775
B46: =Data!A66 -> 45291 | C46: =Data!B66 -> 829.4 | D46: =C46/C45-1 -> -0.05776768 | F46: =Data!I66 -> 45291 | G46: =Data!J66 -> 21710.8 | H46: =G46/G45-1 -> -0.00094793709
B47: =Data!A65 -> 45298 | C47: =Data!B65 -> 825.8 | D47: =C47/C46-1 -> -0.0043404871 | F47: =Data!I65 -> 45298 | G47: =Data!J65 -> 21894.55 | H47: =G47/G46-1 -> 0.0084635297
B48: =Data!A64 -> 45305 | C48: =Data!B64 -> 816.65 | D48: =C48/C47-1 -> -0.011080165 | F48: =Data!I64 -> 45305 | G48: =Data!J64 -> 21622.4 | H48: =G48/G47-1 -> -0.012430034
B49: =Data!A63 -> 45312 | C49: =Data!B63 -> 815.7 | D49: =C49/C48-1 -> -0.001163289 | F49: =Data!I63 -> 45312 | G49: =Data!J63 -> 21352.6 | H49: =G49/G48-1 -> -0.012477801
B50: =Data!A62 -> 45319 | C50: =Data!B62 -> 823.55 | D50: =C50/C49-1 -> 0.0096236361 | F50: =Data!I62 -> 45319 | G50: =Data!J62 -> 21853.8 | H50: =G50/G49-1 -> 0.023472551
B51: =Data!A61 -> 45326 | C51: =Data!B61 -> 811.75 | D51: =C51/C50-1 -> -0.014328213 | F51: =Data!I61 -> 45326 | G51: =Data!J61 -> 21782.5 | H51: =G51/G50-1 -> -0.0032625905
B52: =Data!A60 -> 45333 | C52: =Data!B60 -> 819.95 | D52: =C52/C51-1 -> 0.010101632 | F52: =Data!I60 -> 45333 | G52: =Data!J60 -> 22040.7 | H52: =G52/G51-1 -> 0.011853552
B53: =Data!A59 -> 45340 | C53: =Data!B59 -> 821 | D53: =C53/C52-1 -> 0.0012805659 | F53: =Data!I59 -> 45340 | G53: =Data!J59 -> 22212.7 | H53: =G53/G52-1 -> 0.0078037449
B54: =Data!A58 -> 45347 | C54: =Data!B58 -> 836.2 | D54: =C54/C53-1 -> 0.018514007 | F54: =Data!I58 -> 45347 | G54: =Data!J58 -> 22338.75 | H54: =G54/G53-1 -> 0.0056746816
B55: =Data!A57 -> 45354 | C55: =Data!B57 -> 830 | D55: =C55/C54-1 -> -0.0074144941 | F55: =Data!I57 -> 45354 | G55: =Data!J57 -> 22493.55 | H55: =G55/G54-1 -> 0.0069296626
B56: =Data!A56 -> 45361 | C56: =Data!B56 -> 780.65 | D56: =C56/C55-1 -> -0.059457831 | F56: =Data!I56 -> 45361 | G56: =Data!J56 -> 22023.35 | H56: =G56/G55-1 -> -0.02090377
B57: =Data!A55 -> 45368 | C57: =Data!B55 -> 824.8 | D57: =C57/C56-1 -> 0.056555435 | F57: =Data!I55 -> 45368 | G57: =Data!J55 -> 22096.75 | H57: =G57/G56-1 -> 0.0033328263
B58: =Data!A54 -> 45375 | C58: =Data!B54 -> 830.2 | D58: =C58/C57-1 -> 0.0065470417 | F58: =Data!I54 -> 45375 | G58: =Data!J54 -> 22326.9 | H58: =G58/G57-1 -> 0.010415559
B59: =Data!A53 -> 45382 | C59: =Data!B53 -> 857.1 | D59: =C59/C58-1 -> 0.032401831 | F59: =Data!I53 -> 45382 | G59: =Data!J53 -> 22513.7 | H59: =G59/G58-1 -> 0.0083665892
B60: =Data!A52 -> 45389 | C60: =Data!B52 -> 866.45 | D60: =C60/C59-1 -> 0.010908879 | F60: =Data!I52 -> 45389 | G60: =Data!J52 -> 22519.4 | H60: =G60/G59-1 -> 0.00025317918
B61: =Data!A51 -> 45396 | C61: =Data!B51 -> 864.8 | D61: =C61/C60-1 -> -0.0019043222 | F61: =Data!I51 -> 45396 | G61: =Data!J51 -> 22147 | H61: =G61/G60-1 -> -0.016536853
B62: =Data!A50 -> 45403 | C62: =Data!B50 -> 887.25 | D62: =C62/C61-1 -> 0.025959759 | F62: =Data!I50 -> 45403 | G62: =Data!J50 -> 22419.95 | H62: =G62/G61-1 -> 0.012324468
B63: =Data!A49 -> 45410 | C63: =Data!B49 -> 874.2 | D63: =C63/C62-1 -> -0.014708369 | F63: =Data!I49 -> 45410 | G63: =Data!J49 -> 22475.85 | H63: =G63/G62-1 -> 0.0024933151
B64: =Data!A48 -> 45417 | C64: =Data!B48 -> 853.6 | D64: =C64/C63-1 -> -0.023564402 | F64: =Data!I48 -> 45417 | G64: =Data!J48 -> 22055.2 | H64: =G64/G63-1 -> -0.018715644
B65: =Data!A47 -> 45424 | C65: =Data!B47 -> 907.45 | D65: =C65/C64-1 -> 0.063085754 | F65: =Data!I47 -> 45424 | G65: =Data!J47 -> 22466.1 | H65: =G65/G64-1 -> 0.018630527
B66: =Data!A46 -> 45431 | C66: =Data!B46 -> 908.65 | D66: =C66/C65-1 -> 0.0013223869 | F66: =Data!I46 -> 45431 | G66: =Data!J46 -> 22957.1 | H66: =G66/G65-1 -> 0.021855151
B67: =Data!A45 -> 45438 | C67: =Data!B45 -> 880.55 | D67: =C67/C66-1 -> -0.030924999 | F67: =Data!I45 -> 45438 | G67: =Data!J45 -> 22530.7 | H67: =G67/G66-1 -> -0.018573775
B68: =Data!A44 -> 45445 | C68: =Data!B44 -> 912.15 | D68: =C68/C67-1 -> 0.035886662 | F68: =Data!I44 -> 45445 | G68: =Data!J44 -> 23290.15 | H68: =G68/G67-1 -> 0.033707342
B69: =Data!A43 -> 45452 | C69: =Data!B43 -> 921.15 | D69: =C69/C68-1 -> 0.0098667982 | F69: =Data!I43 -> 45452 | G69: =Data!J43 -> 23465.6 | H69: =G69/G68-1 -> 0.0075332276
B70: =Data!A42 -> 45459 | C70: =Data!B42 -> 936.9 | D70: =C70/C69-1 -> 0.017098192 | F70: =Data!I42 -> 45459 | G70: =Data!J42 -> 23501.1 | H70: =G70/G69-1 -> 0.0015128529
B71: =Data!A41 -> 45466 | C71: =Data!B41 -> 931.5 | D71: =C71/C70-1 -> -0.0057636888 | F71: =Data!I41 -> 45466 | G71: =Data!J41 -> 24010.6 | H71: =G71/G70-1 -> 0.021679836
B72: =Data!A40 -> 45473 | C72: =Data!B40 -> 954.05 | D72: =C72/C71-1 -> 0.024208266 | F72: =Data!I40 -> 45473 | G72: =Data!J40 -> 24323.85 | H72: =G72/G71-1 -> 0.013046321
B73: =Data!A39 -> 45480 | C73: =Data!B39 -> 934.4 | D73: =C73/C72-1 -> -0.020596405 | F73: =Data!I39 -> 45480 | G73: =Data!J39 -> 24502.15 | H73: =G73/G72-1 -> 0.0073302541
B74: =Data!A38 -> 45487 | C74: =Data!B38 -> 889.45 | D74: =C74/C73-1 -> -0.048105736 | F74: =Data!I38 -> 45487 | G74: =Data!J38 -> 24530.9 | H74: =G74/G73-1 -> 0.0011733664
B75: =Data!A37 -> 45494 | C75: =Data!B37 -> 900.55 | D75: =C75/C74-1 -> 0.012479622 | F75: =Data!I37 -> 45494 | G75: =Data!J37 -> 24834.85 | H75: =G75/G74-1 -> 0.012390495
B76: =Data!A36 -> 45501 | C76: =Data!B36 -> 899.55 | D76: =C76/C75-1 -> -0.0011104325 | F76: =Data!I36 -> 45501 | G76: =Data!J36 -> 24717.7 | H76: =G76/G75-1 -> -0.0047171616
B77: =Data!A35 -> 45508 | C77: =Data!B35 -> 905.1 | D77: =C77/C76-1 -> 0.0061697515 | F77: =Data!I35 -> 45508 | G77: =Data!J35 -> 24367.5 | H77: =G77/G76-1 -> -0.014167985
B78: =Data!A34 -> 45515 | C78: =Data!B34 -> 908.45 | D78: =C78/C77-1 -> 0.0037012485 | F78: =Data!I34 -> 45515 | G78: =Data!J34 -> 24541.15 | H78: =G78/G77-1 -> 0.0071262953
B79: =Data!A33 -> 45522 | C79: =Data!B33 -> 941.05 | D79: =C79/C78-1 -> 0.035885299 | F79: =Data!I33 -> 45522 | G79: =Data!J33 -> 24823.15 | H79: =G79/G78-1 -> 0.011490904
B80: =Data!A32 -> 45529 | C80: =Data!B32 -> 941.1 | D80: =C80/C79-1 -> 5.313214e-05 | F80: =Data!I32 -> 45529 | G80: =Data!J32 -> 25235.9 | H80: =G80/G79-1 -> 0.016627624
B81: =Data!A31 -> 45536 | C81: =Data!B31 -> 932.8 | D81: =C81/C80-1 -> -0.0088194666 | F81: =Data!I31 -> 45536 | G81: =Data!J31 -> 24852.15 | H81: =G81/G80-1 -> -0.015206511
B82: =Data!A30 -> 45543 | C82: =Data!B30 -> 954.55 | D82: =C82/C81-1 -> 0.023316895 | F82: =Data!I30 -> 45543 | G82: =Data!J30 -> 25356.5 | H82: =G82/G81-1 -> 0.020294019
B83: =Data!A29 -> 45550 | C83: =Data!B29 -> 981.55 | D83: =C83/C82-1 -> 0.02828558 | F83: =Data!I29 -> 45550 | G83: =Data!J29 -> 25790.95 | H83: =G83/G82-1 -> 0.017133674
B84: =Data!A28 -> 45557 | C84: =Data!B28 -> 1001.55 | D84: =C84/C83-1 -> 0.020375936 | F84: =Data!I28 -> 45557 | G84: =Data!J28 -> 26178.95 | H84: =G84/G83-1 -> 0.015044037
B85: =Data!A27 -> 45564 | C85: =Data!B27 -> 1033.75 | D85: =C85/C84-1 -> 0.032150167 | F85: =Data!I27 -> 45564 | G85: =Data!J27 -> 25014.6 | H85: =G85/G84-1 -> -0.044476574
B86: =Data!A26 -> 45571 | C86: =Data!B26 -> 1012.05 | D86: =C86/C85-1 -> -0.020991536 | F86: =Data!I26 -> 45571 | G86: =Data!J26 -> 24964.25 | H86: =G86/G85-1 -> -0.0020128245
B87: =Data!A25 -> 45578 | C87: =Data!B25 -> 992.6 | D87: =C87/C86-1 -> -0.019218418 | F87: =Data!I25 -> 45578 | G87: =Data!J25 -> 24854.05 | H87: =G87/G86-1 -> -0.0044143125
B88: =Data!A24 -> 45585 | C88: =Data!B24 -> 943.85 | D88: =C88/C87-1 -> -0.049113439 | F88: =Data!I24 -> 45585 | G88: =Data!J24 -> 24180.8 | H88: =G88/G87-1 -> -0.027088141
B89: =Data!A23 -> 45592 | C89: =Data!B23 -> 968.3 | D89: =C89/C88-1 -> 0.02590454 | F89: =Data!I23 -> 45592 | G89: =Data!J23 -> 24304.35 | H89: =G89/G88-1 -> 0.0051094257
B90: =Data!A22 -> 45599 | C90: =Data!B22 -> 996.4 | D90: =C90/C89-1 -> 0.029019932 | F90: =Data!I22 -> 45599 | G90: =Data!J22 -> 24148.2 | H90: =G90/G89-1 -> -0.0064247758
B91: =Data!A21 -> 45606 | C91: =Data!B21 -> 939.05 | D91: =C91/C90-1 -> -0.057557206 | F91: =Data!I21 -> 45606 | G91: =Data!J21 -> 23532.7 | H91: =G91/G90-1 -> -0.025488442
B92: =Data!A20 -> 45613 | C92: =Data!B20 -> 977.35 | D92: =C92/C91-1 -> 0.040785901 | F92: =Data!I20 -> 45613 | G92: =Data!J20 -> 23907.25 | H92: =G92/G91-1 -> 0.015916151
B93: =Data!A19 -> 45620 | C93: =Data!B19 -> 966 | D93: =C93/C92-1 -> -0.011613035 | F93: =Data!I19 -> 45620 | G93: =Data!J19 -> 24131.1 | H93: =G93/G92-1 -> 0.0093632685
B94: =Data!A18 -> 45627 | C94: =Data!B18 -> 1003.8 | D94: =C94/C93-1 -> 0.039130435 | F94: =Data!I18 -> 45627 | G94: =Data!J18 -> 24677.8 | H94: =G94/G93-1 -> 0.022655411
B95: =Data!A17 -> 45634 | C95: =Data!B17 -> 999.85 | D95: =C95/C94-1 -> -0.0039350468 | F95: =Data!I17 -> 45634 | G95: =Data!J17 -> 24768.3 | H95: =G95/G94-1 -> 0.0036672637
B96: =Data!A16 -> 45641 | C96: =Data!B16 -> 917.35 | D96: =C96/C95-1 -> -0.082512377 | F96: =Data!I16 -> 45641 | G96: =Data!J16 -> 23587.5 | H96: =G96/G95-1 -> -0.047673841
B97: =Data!A15 -> 45648 | C97: =Data!B15 -> 913.3 | D97: =C97/C96-1 -> -0.0044148907 | F97: =Data!I15 -> 45648 | G97: =Data!J15 -> 23813.4 | H97: =G97/G96-1 -> 0.0095771065
B98: =Data!A14 -> 45655 | C98: =Data!B14 -> 915.05 | D98: =C98/C97-1 -> 0.0019161283 | F98: =Data!I14 -> 45655 | G98: =Data!J14 -> 24004.75 | H98: =G98/G97-1 -> 0.0080353918
B99: =Data!A13 -> 45662 | C99: =Data!B13 -> 900.1 | D99: =C99/C98-1 -> -0.016337905 | F99: =Data!I13 -> 45662 | G99: =Data!J13 -> 23431.5 | H99: =G99/G98-1 -> -0.02388069
B100: =Data!A12 -> 45669 | C100: =Data!B12 -> 908.6 | D100: =C100/C99-1 -> 0.0094433952 | F100: =Data!I12 -> 45669 | G100: =Data!J12 -> 23203.2 | H100: =G100/G99-1 -> -0.0097432943
B101: =Data!A11 -> 45676 | C101: =Data!B11 -> 932.45 | D101: =C101/C100-1 -> 0.026249175 | F101: =Data!I11 -> 45676 | G101: =Data!J11 -> 23092.2 | H101: =G101/G100-1 -> -0.0047838229
...

Sheet Rm
B2: Return On Market
B4: Year | C4: Return | E4: Average Return | G4: =AVERAGE(C5:C29) -> 0.153348
B5: {=Data!T5} -> 2000 | C5: =Data!U5/$E$9 -> -0.1465 | E5: Divident Yeild | G5: =1.45% -> 0.0145
B6: {=Data!T6} -> 2001 | C6: =Data!U6/$E$9 -> -0.1618 | E6: Total Market Return | G6: =SUM(G4:G5) -> 0.167848
B7: {=Data!T7} -> 2002 | C7: =Data!U7/$E$9 -> 0.0325
B8: {=Data!T8} -> 2003 | C8: =Data!U8/$E$9 -> 0.719
B9: {=Data!T9} -> 2004 | C9: =Data!U9/$E$9 -> 0.1068 | E9: =100 -> 100
B10: {=Data!T10} -> 2005 | C10: =Data!U10/$E$9 -> 0.3634
B11: {=Data!T11} -> 2006 | C11: =Data!U11/$E$9 -> 0.3983
B12: {=Data!T12} -> 2007 | C12: =Data!U12/$E$9 -> 0.5477
B13: {=Data!T13} -> 2008 | C13: =Data!U13/$E$9 -> -0.5179
B14: {=Data!T14} -> 2009 | C14: =Data!U14/$E$9 -> 0.7576
B15: {=Data!T15} -> 2010 | C15: =Data!U15/$E$9 -> 0.1795
B16: {=Data!T16} -> 2011 | C16: =Data!U16/$E$9 -> -0.2462
B17: {=Data!T17} -> 2012 | C17: =Data!U17/$E$9 -> 0.277
B18: {=Data!T18} -> 2013 | C18: =Data!U18/$E$9 -> 0.0676
B19: {=Data!T19} -> 2014 | C19: =Data!U19/$E$9 -> 0.3139
B20: {=Data!T20} -> 2015 | C20: =Data!U20/$E$9 -> -0.0406
B21: {=Data!T21} -> 2016 | C21: =Data!U21/$E$9 -> 0.0301
... B29: {=Data!T29} -> 2024 | C29: =Data!U29/$E$9 -> 0.0875

Sheet Data
A1: JSW | I1: NIFTY 50
A2: Date | B2: Price | I2: Date | J2: Price | N2: Nifty 20 years return | T2: nifty 20 Year Return
A3: 45732 | B3: 1050.25 | I3: 45732 | J3: 23190.65 | N3: Year | O3: Annual
A4: 45725 | B4: 1001.2 | I4: 45725 | J4: 22397.2 | N4: 2000 | O4: -14.65 | T4: Year | U4: Annual
A5: 45718 | B5: 1011.15 | I5: 45718 | J5: 22552.5 | N5: 2001 | O5: -16.18 | T5: 2000 | U5: -14.65
A6: 45711 | B6: 950.7 | I6: 45711 | J6: 22124.7 | N6: 2002 | O6: 3.25 | T6: 2001 | U6: -16.18
A7: 45704 | B7: 981.9 | I7: 45704 | J7: 22795.9 | N7: 2003 | O7: 71.9 | T7: 2002 | U7: 3.25
A8: 45697 | B8: 964.6 | I8: 45697 | J8: 22929.25 | N8: 2004 | O8: 10.68 | T8: 2003 | U8: 71.9
A9: 45690 | B9: 980.75 | I9: 45690 | J9: 23559.95 | N9: 2005 | O9: 36.34 | T9: 2004 | U9: 10.68
A10: 45683 | B10: 945 | I10: 45683 | J10: 23508.4 | N10: 2006 | O10: 39.83 | T10: 2005 | U10: 36.34
A11: 45676 | B11: 932.45 | I11: 45676 | J11: 23092.2 | N11: 2007 | O11: 54.77 | T11: 2006 | U11: 39.83
A12: 45669 | B12: 908.6 | I12: 45669 | J12: 23203.2 | N12: 2008 | O12: -51.79 | T12: 2007 | U12: 54.77
A13: 45662 | B13: 900.1 | I13: 45662 | J13: 23431.5 | N13: 2009 | O13: 75.76 | T13: 2008 | U13: -51.79
A14: 45655 | B14: 915.05 | I14: 45655 | J14: 24004.75 | N14: 2010 | O14: 17.95 | T14: 2009 | U14: 75.76
A15: 45648 | B15: 913.3 | I15: 45648 | J15: 23813.4 | N15: 2011 | O15: -24.62 | T15: 2010 | U15: 17.95
A16: 45641 | B16: 917.35 | I16: 45641 | J16: 23587.5 | N16: 2012 | O16: 27.7 | T16: 2011 | U16: -24.62
... A28: 45557 | B28: 1001.55 | I28: 45557 | J28: 26178.95 | N28: 2024 | O28: 8.75 | T28: 2023 | U28: 19.42
A29: 45550 | B29: 981.55 | I29: 45550 | J29: 25790.95 | N29: 2025 | T29: 2024 | U29: 8.75
A30: 45543 | B30: 954.55 | I30: 45543 | J30: 25356.5 | T30: 2025
A31: 45536 | B31: 932.8 | I31: 45536 | J31: 24852.15
A32: 45529 | B32: 941.1 | I32: 45529 | J32: 25235.9
A33: 45522 | B33: 941.05 | I33: 45522 | J33: 24823.15
A34: 45515 | B34: 908.45 | I34: 45515 | J34: 24541.15
A35: 45508 | B35: 905.1 | I35: 45508 | J35: 24367.5
A36: 45501 | B36: 899.55 | I36: 45501 | J36: 24717.7
A37: 45494 | B37: 900.55 | I37: 45494 | J37: 24834.85
A38: 45487 | B38: 889.45 | I38: 45487 | J38: 24530.9
A39: 45480 | B39: 934.4 | I39: 45480 | J39: 24502.15
A40: 45473 | B40: 954.05 | I40: 45473 | J40: 24323.85
A41: 45466 | B41: 931.5 | I41: 45466 | J41: 24010.6
A42: 45459 | B42: 936.9 | I42: 45459 | J42: 23501.1
... A106: 45011 | B106: 688.1 | I106: 45011 | J106: 17359.75

Sheet Data2
B2: S.No. | C2: Name | D2: CMP Rs. | E2: No. Eq. Shares Cr. | F2: Equity Value | G2: Debt Rs.Cr. | H2: Cash End Rs.Cr. | I2: Net Debt | J2: EV Rs.Cr. | K2: EV / EBITDA | L2: Sales Rs.Cr. | M2: NP 12M Rs.Cr. | N2: Enterprise Value | O2: EBITDA
B3: 1 | C3: JSW Steel | D3: 1058.7 | E3: 244.55 | F3: =D3*E3 -> 258905.09 | G3: 95258 | H3: 12348 | I3: =G3-H3 -> 82910 | J3: 344869.21 | K3: 14.87 | L3: 170274 | M3: 3312 | N3: =F3+G3-H3 -> 341815.09 | O3: =N3/K3 -> 22986.892
B4: 2 | C4: Tata Steel | D4: 157.28 | E4: 1248.35 | F4: =D4*E4 -> 196340.49 | G4: 99391.76 | H4: 8677.72 | I4: =G4-H4 -> 90714.04 | J4: 285798.77 | K4: 10.69 | L4: 221011.71 | M4: 2527.46 | N4: =F4+G4-H4 -> 287054.53 | O4: =N4/K4 -> 26852.622
B5: 3 | C5: Jindal Steel | D5: 914.3 | E5: 102.01 | F5: =D5*E5 -> 93267.743 | G5: 17266.45 | H5: 4024.13 | I5: =G5-H5 -> 13242.32 | J5: 107009.97 | K5: 10.92 | L5: 50068.78 | M5: 4082.73 | N5: =F5+G5-H5 -> 106510.06 | O5: =N5/K5 -> 9753.6688
B6: 4 | C6: Tube Investments | D6: 2872.15 | E6: 19.35 | F6: =D6*E6 -> 55576.103 | G6: 698.92 | H6: 1227.4 | I6: =G6-H6 -> -528.48 | J6: 54737.18 | K6: 24.26 | L6: 18804.8 | M6: 1167.41 | N6: =F6+G6-H6 -> 55047.623 | O6: =N6/K6 -> 2269.0694
B7: 5 | C7: Jindal Stain. | D7: 625.7 | E7: 82.38 | F7: =D7*E7 -> 51545.166 | G7: 6473.08 | H7: 1988.11 | I7: =G7-H7 -> 4484.97 | J7: 55898.76 | K7: 11.46 | L7: 38567.91 | M7: 2410.41 | N7: =F7+G7-H7 -> 56030.136 | O7: =N7/K7 -> 4889.1916
B8: 6 | C8: S A I L | D8: 115.3 | E8: 413.05 | F8: =D8*E8 -> 47624.665 | G8: 41265.03 | H8: 672.95 | I8: =G8-H8 -> 40592.08 | J8: 88135.57 | K8: 7.3 | L8: 101121.44 | M8: 2246.5 | N8: =F8+G8-H8 -> 88216.745 | O8: =N8/K8 -> 12084.486
B9: 7 | C9: APL Apollo Tubes | D9: 1511.55 | E9: 27.75 | F9: =D9*E9 -> 41945.512 | G9: 1022.59 | H9: 347.6 | I9: =G9-H9 -> 674.99 | J9: 42768.5 | K9: 37.34 | L9: 19946.68 | M9: 634.39 | N9: =F9+G9-H9 -> 42620.502 | O9: =N9/K9 -> 1141.4168
