Workbook
Name UPDATE: 'Data Sheet'!$E$1

Sheet Financial>

Sheet Histoirical FC
B2: ="Historical Financial Satement-"&'Data Sheet'!B1 -> Historical Financial Satement-TATA STEEL LTD
B3: Year | C3: ='Data Sheet'!B16 -> 42094 | D3: ='Data Sheet'!C16 -> 42460 | E3: ='Data Sheet'!D16 -> 42825 | F3: ='Data Sheet'!E16 -> 43190 | G3: ='Data Sheet'!F16 -> 43555 | H3: ='Data Sheet'!G16 -> 43921 | I3: ='Data Sheet'!H16 -> 44286 | J3: ='Data Sheet'!I16 -> 44651 | ... L3: ='Data Sheet'!K16 -> 45382 | M3: LTM
A5: # | B5: Income Statement
B6: Sales | C6: ='Data Sheet'!B17 -> 139503.73 | D6: ='Data Sheet'!C17 -> 101964.72 | E6: ='Data Sheet'!D17 -> 112299.42 | F6: ='Data Sheet'!E17 -> 123249.07 | G6: ='Data Sheet'!F17 -> 157668.99 | H6: ='Data Sheet'!G17 -> 139816.65 | I6: ='Data Sheet'!H17 -> 156294.18 | J6: ='Data Sheet'!I17 -> 243959.17 | ... L6: ='Data Sheet'!K17 -> 229170.78 | M6: =SUM('Data Sheet'!H42:K42) -> 221011.71
B7: Sales Growth(%) | D7: =D6/C6-1 -> -0.26908965 | E7: =E6/D6-1 -> 0.10135565 | F7: =F6/E6-1 -> 0.097504065 | G7: =G6/F6-1 -> 0.27927124 | H7: =H6/G6-1 -> -0.1132267 | I7: =I6/H6-1 -> 0.11785099 | J7: =J6/I6-1 -> 0.56089734 | K7: =K6/J6-1 -> -0.0024859898 | ... M7: =M6/L6-1 -> -0.035602576
B9: COGS | C9: =IFERROR(SUM('Data Sheet'!B18,'Data Sheet'!B20:B22)-1*'Data Sheet'!B19,0) -> 104290.94 | D9: =IFERROR(SUM('Data Sheet'!C18,'Data Sheet'!C20:C22)-1*'Data Sheet'!C19,0) -> 79237.26 | E9: =IFERROR(SUM('Data Sheet'!D18,'Data Sheet'!D20:D22)-1*'Data Sheet'!D19,0) -> 77577.09 | F9: =IFERROR(SUM('Data Sheet'!E18,'Data Sheet'!E20:E22)-1*'Data Sheet'!E19,0) -> 84710.05 | G9: =IFERROR(SUM('Data Sheet'!F18,'Data Sheet'!F20:F22)-1*'Data Sheet'!F19,0) -> 105590.05 | H9: =IFERROR(SUM('Data Sheet'!G18,'Data Sheet'!G20:G22)-1*'Data Sheet'!G19,0) -> 102560.94 | I9: =IFERROR(SUM('Data Sheet'!H18,'Data Sheet'!H20:H22)-1*'Data Sheet'!H19,0) -> 103382.36 | J9: =IFERROR(SUM('Data Sheet'!I18,'Data Sheet'!I20:I22)-1*'Data Sheet'!I19,0) -> 143605.19 | ... M9: =IFERROR(SUM('Data Sheet'!L18,'Data Sheet'!L20:L22)-1*'Data Sheet'!L19,0) -> 0
B10: (COGS %of Sale) | C10: =C9/C6 -> 0.74758532 | D10: =D9/D6 -> 0.77710467 | E10: =E9/E6 -> 0.69080579 | F10: =F9/F6 -> 0.68730782 | G10: =G9/G6 -> 0.66969447 | H10: =H9/H6 -> 0.73353882 | I10: =I9/I6 -> 0.66146007 | J10: =J9/J6 -> 0.58864436 | ... M10: =M9/M6 -> 0
B12: Gross Profit | C12: =C6-C9 -> 35212.79 | D12: =D6-D9 -> 22727.46 | E12: =E6-E9 -> 34722.33 | F12: =F6-F9 -> 38539.02 | G12: =G6-G9 -> 52078.94 | H12: =H6-H9 -> 37255.71 | I12: =I6-I9 -> 52911.82 | J12: =J6-J9 -> 100353.98 | ... M12: =M6-M9 -> 221011.71
B13: (Gross Margin) | C13: =C12/C6 -> 0.25241468 | D13: =D12/D6 -> 0.22289533 | E13: =E12/E6 -> 0.30919421 | F13: =F12/F6 -> 0.31269218 | G13: =G12/G6 -> 0.33030553 | H13: =H12/H6 -> 0.26646118 | I13: =I12/I6 -> 0.33853993 | J13: =J12/J6 -> 0.41135564 | ... M13: =M12/M6 -> 1
B15: Selling&General Expense | C15: =SUM('Data Sheet'!B23:B24) -> 31803.91 | D15: =SUM('Data Sheet'!C23:C24) -> 23352.7 | E15: =SUM('Data Sheet'!D23:D24) -> 21578.7 | F15: =SUM('Data Sheet'!E23:E24) -> 17105.83 | G15: =SUM('Data Sheet'!F23:F24) -> 22760.72 | H15: =SUM('Data Sheet'!G23:G24) -> 19792.65 | I15: =SUM('Data Sheet'!H23:H24) -> 22407.56 | J15: =SUM('Data Sheet'!I23:I24) -> 36864.03 | ... L15: =SUM('Data Sheet'!K23:K24) -> 36162.59 | M15: =SUM('Data Sheet'!H43:K43) -> 195697.33
B16: (S&G EXP %of Sale) | C16: =C15/C6 -> 0.22797892 | D16: =D15/D6 -> 0.22902726 | E16: =E15/E6 -> 0.19215326 | F16: =F15/F6 -> 0.13879074 | G16: =G15/G6 -> 0.14435762 | H16: =H15/H6 -> 0.14156147 | I16: =I15/I6 -> 0.14336785 | J16: =J15/J6 -> 0.15110738 | ... M16: =M15/M6 -> 0.88546136
B18: Operating Income(EBITDA) | C18: =C12-C15 -> 3408.88 | D18: =D12-D15 -> -625.24 | E18: =E12-E15 -> 13143.63 | F18: =F12-F15 -> 21433.19 | G18: =G12-G15 -> 29318.22 | H18: =H12-H15 -> 17463.06 | I18: =I12-I15 -> 30504.26 | J18: =J12-J15 -> 63489.95 | ... M18: =M12-M15 -> 25314.38
B19: (Operating Margin) | C19: =C18/C6 -> 0.024435762 | D19: =D18/D6 -> -0.0061319248 | E19: =E18/E6 -> 0.11704094 | F19: =F18/F6 -> 0.17390143 | G19: =G18/G6 -> 0.18594792 | H19: =H18/H6 -> 0.12489972 | I19: =I18/I6 -> 0.19517208 | J19: =J18/J6 -> 0.26024826 | ... M19: =M18/M6 -> 0.11453864
B21: ='Data Sheet'!A26 -> Depreciation | C21: ='Data Sheet'!B26 -> 5943.6 | D21: ='Data Sheet'!C26 -> 5306.35 | E21: ='Data Sheet'!D26 -> 5672.88 | F21: ='Data Sheet'!E26 -> 5741.7 | G21: ='Data Sheet'!F26 -> 7341.83 | H21: ='Data Sheet'!G26 -> 8440.73 | I21: ='Data Sheet'!H26 -> 9233.64 | ... L21: ='Data Sheet'!K26 -> 9882.16 | M21: =SUM('Data Sheet'!H45:K45) -> 10269.31
B22: (DEP % of Sale) | C22: =C21/C6 -> 0.042605312 | D22: =D21/D6 -> 0.052041039 | E22: =E21/E6 -> 0.050515666 | F22: =F21/F6 -> 0.046586153 | G22: =G21/G6 -> 0.046564832 | H22: =H21/H6 -> 0.060369992 | I22: =I21/I6 -> 0.059078591 | J22: =J21/J6 -> 0.03730489 | ... M22: =M21/M6 -> 0.046465004
B24: EBIT | C24: =C18-C21 -> -2534.72 | D24: =D18-D21 -> -5931.59 | E24: =E18-E21 -> 7470.75 | F24: =F18-F21 -> 15691.49 | G24: =G18-G21 -> 21976.39 | H24: =H18-H21 -> 9022.33 | I24: =I18-I21 -> 21270.62 | J24: =J18-J21 -> 54389.08 | ... M24: =M18-M21 -> 15045.07
B25: (EBIT Margin) | C25: =C24/C6 -> -0.01816955 | D25: =D24/D6 -> -0.058172964 | E25: =E24/E6 -> 0.066525277 | F25: =F24/F6 -> 0.12731528 | G25: =G24/G6 -> 0.13938308 | H25: =H24/H6 -> 0.064529725 | I25: =I24/I6 -> 0.13609349 | J25: =J24/J6 -> 0.22294337 | ... M25: =M24/M6 -> 0.068073633
B27: Intrest | C27: ='Data Sheet'!B27 -> 4847.75 | D27: ='Data Sheet'!C27 -> 4221.41 | E27: ='Data Sheet'!D27 -> 5072.2 | F27: ='Data Sheet'!E27 -> 5454.74 | G27: ='Data Sheet'!F27 -> 7660.1 | H27: ='Data Sheet'!G27 -> 7533.46 | I27: ='Data Sheet'!H27 -> 7606.71 | J27: ='Data Sheet'!I27 -> 5462.2 | ... L27: ='Data Sheet'!K27 -> 7507.57 | M27: =SUM('Data Sheet'!H46:K46) -> 7394.45
B28: (Intrest % of Sale) | C28: =C27/C6 -> 0.034749967 | D28: =D27/D6 -> 0.041400692 | E28: =E27/E6 -> 0.045166752 | F28: =F27/F6 -> 0.044257859 | G28: =G27/G6 -> 0.048583428 | H28: =H27/H6 -> 0.053880993 | I28: =I27/I6 -> 0.048669183 | J28: =J27/J6 -> 0.022389812 | ... M28: =M27/M6 -> 0.033457277
B30: Profit Before Tax | C30: =C24-C27 -> -7382.47 | D30: =D24-D27 -> -10153 | E30: =E24-E27 -> 2398.55 | F30: =F24-F27 -> 10236.75 | G30: =G24-G27 -> 14316.29 | H30: =H24-H27 -> 1488.87 | I30: =I24-I27 -> 13663.91 | J30: =J24-J27 -> 48926.88 | ... M30: =M24-M27 -> 7650.62
B31: (PBT % of Sale) | C31: =C30/C6 -> -0.052919517 | D31: =D30/D6 -> -0.099573656 | E31: =E30/E6 -> 0.021358525 | F31: =F30/F6 -> 0.083057422 | G31: =G30/G6 -> 0.090799656 | H31: =H30/H6 -> 0.010648732 | I31: =I30/I6 -> 0.087424305 | J31: =J30/J6 -> 0.20055356 | ... M31: =M30/M6 -> 0.034616356
B33: Tax | C33: ='Data Sheet'!B29 -> 2567.41 | D33: ='Data Sheet'!C29 -> 689.96 | E33: ='Data Sheet'!D29 -> 2778.01 | F33: ='Data Sheet'!E29 -> 3392.33 | G33: ='Data Sheet'!F29 -> 6718.43 | H33: ='Data Sheet'!G29 -> -2568.41 | I33: ='Data Sheet'!H29 -> 5653.9 | J33: ='Data Sheet'!I29 -> 8477.55 | ... L33: ='Data Sheet'!K29 -> 3762.57 | M33: =SUM('Data Sheet'!H48:K48) -> 5494.59
B34: (Effective tax Rate) | C34: =C33/C30 -> -0.34777114 | D34: =D33/D30 -> -0.067956269 | E34: =E33/E30 -> 1.1582039 | F34: =F33/F30 -> 0.3313874 | G34: =G33/G30 -> 0.46928569 | H34: =H33/H30 -> -1.7250734 | I34: =I33/I30 -> 0.41378346 | J34: =J33/J30 -> 0.17326979 | ... M34: =M33/M30 -> 0.71818885
B36: Net Profit | C36: =C30-C33 -> -9949.88 | D36: =D30-D33 -> -10842.96 | E36: =E30-E33 -> -379.46 | F36: =F30-F33 -> 6844.42 | G36: =G30-G33 -> 7597.86 | H36: =H30-H33 -> 4057.28 | I36: =I30-I33 -> 8010.01 | J36: =J30-J33 -> 40449.33 | ... M36: =M30-M33 -> 2156.03
B37: (Net Margin) | C37: =C36/C6 -> -0.071323398 | D37: =D36/D6 -> -0.10634031 | E37: =E36/E6 -> -0.0033790023 | F37: =F36/F6 -> 0.055533239 | G37: =G36/G6 -> 0.048188677 | H37: =H36/H6 -> 0.029018575 | I37: =I36/I6 -> 0.051249573 | J37: =J36/J6 -> 0.16580369 | ... M37: =M36/M6 -> 0.009755275
B39: No Of Equity Share | C39: ='Data Sheet'!B93 -> 1126.62 | D39: ='Data Sheet'!C93 -> 1126.62 | E39: ='Data Sheet'!D93 -> 1126.62 | F39: ='Data Sheet'!E93 -> 1126.48 | G39: ='Data Sheet'!F93 -> 1126.49 | H39: ='Data Sheet'!G93 -> 1126.49 | I39: ='Data Sheet'!H93 -> 1196.59 | J39: ='Data Sheet'!I93 -> 1221.3 | ... L39: ='Data Sheet'!K93 -> 1248.35 | M39: =L39 -> 1248.35
B41: EPS | C41: =C36/C39 -> -8.8316202 | D41: =D36/D39 -> -9.6243276 | E41: =E36/E39 -> -0.33681277 | F41: =F36/F39 -> 6.0759357 | G41: =G36/G39 -> 6.7447203 | H41: =H36/H39 -> 3.6017009 | I41: =I36/I39 -> 6.6940305 | J41: =J36/J39 -> 33.119897 | ... M41: =M36/M39 -> 1.7271038
B42: Earning Per Growth | D42: =D41/C41-1 -> 0.089757866 | E42: =E41/D41-1 -> -0.96500402 | F42: =F41/E41-1 -> -19.039505 | G42: =G41/F41-1 -> 0.11007106 | H42: =H41/G41-1 -> -0.465997 | I42: =I41/H41-1 -> 0.85857482 | J42: =J41/I41-1 -> 3.9476764 | K42: =K41/J41-1 -> -0.83925655 | ... M42: =M41/L41-1 -> 0.96786295
B44: Divident Per Share | C44: ='Data Sheet'!B31/'Histoirical FC'!C39 -> 0.68978893 | D44: ='Data Sheet'!C31/'Histoirical FC'!D39 -> 0.68895457 | E44: ='Data Sheet'!D31/'Histoirical FC'!E39 -> 0.86119543 | F44: ='Data Sheet'!E31/'Histoirical FC'!F39 -> 1.0163962 | G44: ='Data Sheet'!F31/'Histoirical FC'!G39 -> 1.32129 | H44: ='Data Sheet'!G31/'Histoirical FC'!H39 -> 1.0163872 | I44: ='Data Sheet'!H31/'Histoirical FC'!I39 -> 2.5021269 | J44: ='Data Sheet'!I31/'Histoirical FC'!J39 -> 5.0996234 | ... M44: ='Data Sheet'!L31/'Histoirical FC'!M39 -> 0
B45: (Divident Payout Ratio) | C45: =C44/C41 -> -0.07810446 | D45: =D44/D41 -> -0.071584696 | E45: =E44/E41 -> -2.5568966 | F45: =F44/F41 -> 0.16728225 | G45: =G44/G41 -> 0.1958999 | H45: =H44/H41 -> 0.28219645 | I45: =I44/I41 -> 0.3737848 | J45: =J44/J41 -> 0.15397461 | ... M45: =M44/M41 -> 0
B47: Retained Earning | C47: =C41-C44 -> -9.5214092 | D47: =D41-D44 -> -10.313282 | E47: =E41-E44 -> -1.1980082 | F47: =F41-F44 -> 5.0595395 | G47: =G41-G44 -> 5.4234303 | H47: =H41-H44 -> 2.5853137 | I47: =I41-I44 -> 4.1919037 | J47: =J41-J44 -> 28.020273 | ... M47: =M41-M44 -> 1.7271038
B48: Retained Earning% | C48: =C47/C41 -> 1.0781045 | D48: =D47/D41 -> 1.0715847 | E48: =E47/E41 -> 3.5568966 | F48: =F47/F41 -> 0.83271775 | G48: =G47/G41 -> 0.8041001 | H48: =H47/H41 -> 0.71780355 | I48: =I47/I41 -> 0.6262152 | J48: =J47/J41 -> 0.84602539 | ... M48: =M47/M41 -> 1
A50: # | B50: Balance Sheet
B52: ='Data Sheet'!A57 -> Equity Share Capital | C52: ='Data Sheet'!B57 -> 971.41 | D52: ='Data Sheet'!C57 -> 970.24 | E52: ='Data Sheet'!D57 -> 970.24 | F52: ='Data Sheet'!E57 -> 1144.95 | G52: ='Data Sheet'!F57 -> 1144.94 | H52: ='Data Sheet'!G57 -> 1144.95 | I52: ='Data Sheet'!H57 -> 1197.61 | ... L52: ='Data Sheet'!K57 -> 1247.44
B53: ='Data Sheet'!A58 -> Reserves | C53: ='Data Sheet'!B58 -> 30378 | D53: ='Data Sheet'!C58 -> 42762.31 | E53: ='Data Sheet'!D58 -> 36849.08 | F53: ='Data Sheet'!E58 -> 59725.67 | G53: ='Data Sheet'!F58 -> 67780.14 | H53: ='Data Sheet'!G58 -> 72431.35 | I53: ='Data Sheet'!H58 -> 73041.16 | ... L53: ='Data Sheet'!K58 -> 90788.32
B54: ='Data Sheet'!A59 -> Borrowings | C54: ='Data Sheet'!B59 -> 80701.29 | D54: ='Data Sheet'!C59 -> 81986.93 | E54: ='Data Sheet'!D59 -> 83014.49 | F54: ='Data Sheet'!E59 -> 92147.05 | G54: ='Data Sheet'!F59 -> 100816.22 | H54: ='Data Sheet'!G59 -> 116328.2 | I54: ='Data Sheet'!H59 -> 88501.41 | ... L54: ='Data Sheet'!K59 -> 87082.12
B55: ='Data Sheet'!A60 -> Other Liabilities | C55: ='Data Sheet'!B60 -> 47058.6 | D55: ='Data Sheet'!C60 -> 51164.51 | E55: ='Data Sheet'!D60 -> 51613.56 | F55: ='Data Sheet'!E60 -> 55704.47 | G55: ='Data Sheet'!F60 -> 63032.14 | H55: ='Data Sheet'!G60 -> 59244.62 | I55: ='Data Sheet'!H60 -> 81169.01 | ... L55: ='Data Sheet'!K60 -> 90194.54
B56: Total Liabilites | C56: =SUM(C52:C55) -> 159109.3 | D56: =SUM(D52:D55) -> 176883.99 | E56: =SUM(E52:E55) -> 172447.37 | F56: =SUM(F52:F55) -> 208722.14 | G56: =SUM(G52:G55) -> 232773.44 | H56: =SUM(H52:H55) -> 249149.12 | I56: =SUM(I52:I55) -> 243909.19 | J56: =SUM(J52:J55) -> 282421.67 | ... L56: =SUM(L52:L55) -> 269312.42
B58: ='Data Sheet'!A62 -> Net Block | C58: ='Data Sheet'!B62 -> 68100.33 | D58: ='Data Sheet'!C62 -> 72199.76 | E58: ='Data Sheet'!D62 -> 92006.55 | F58: ='Data Sheet'!E62 -> 96104.89 | G58: ='Data Sheet'!F62 -> 124441.91 | H58: ='Data Sheet'!G62 -> 134550.66 | I58: ='Data Sheet'!H62 -> 135775.18 | ... L58: ='Data Sheet'!K62 -> 148814.38
B59: ='Data Sheet'!A63 -> Capital Work in Progress | C59: ='Data Sheet'!B63 -> 28678.12 | D59: ='Data Sheet'!C63 -> 35996.09 | E59: ='Data Sheet'!D63 -> 15784.13 | F59: ='Data Sheet'!E63 -> 16614.41 | G59: ='Data Sheet'!F63 -> 18641.21 | H59: ='Data Sheet'!G63 -> 19496.83 | I59: ='Data Sheet'!H63 -> 19007.4 | ... L59: ='Data Sheet'!K63 -> 34355.53
B60: ='Data Sheet'!A64 -> Investments | C60: ='Data Sheet'!B64 -> 3455.05 | D60: ='Data Sheet'!C64 -> 10713.71 | E60: ='Data Sheet'!D64 -> 12457.12 | F60: ='Data Sheet'!E64 -> 17899.47 | G60: ='Data Sheet'!F64 -> 5738.17 | H60: ='Data Sheet'!G64 -> 6285.18 | I60: ='Data Sheet'!H64 -> 10681.93 | ... L60: ='Data Sheet'!K64 -> 6257.57
B61: ='Data Sheet'!A65 -> Other Assets | C61: ='Data Sheet'!B74 -> 11666.08 | D61: ='Data Sheet'!C74 -> 19708.54 | E61: ='Data Sheet'!D74 -> 10887.88 | F61: ='Data Sheet'!E74 -> 29418.96 | G61: ='Data Sheet'!F74 -> 37143.68 | H61: ='Data Sheet'!G74 -> 41808.1 | I61: ='Data Sheet'!H74 -> 29846.28 | J61: ='Data Sheet'!I74 -> 36978.69 | ... L61: ='Data Sheet'!K74 -> 15786.18
B62: Total Non Current Asset | C62: =SUM(C58:C61) -> 111899.58 | D62: =SUM(D58:D61) -> 138618.1 | E62: =SUM(E58:E61) -> 131135.68 | F62: =SUM(F58:F61) -> 160037.73 | G62: =SUM(G58:G61) -> 185964.97 | H62: =SUM(H58:H61) -> 202140.77 | I62: =SUM(I58:I61) -> 195310.79 | J62: =SUM(J58:J61) -> 205451.92 | ... L62: =SUM(L58:L61) -> 205213.66
B64: ='Data Sheet'!A67 -> Receivables | C64: ='Data Sheet'!B67 -> 13309.87 | D64: ='Data Sheet'!C67 -> 12066.22 | E64: ='Data Sheet'!D67 -> 11586.82 | F64: ='Data Sheet'!E67 -> 12415.52 | G64: ='Data Sheet'!F67 -> 11811 | H64: ='Data Sheet'!G67 -> 7884.91 | I64: ='Data Sheet'!H67 -> 9539.84 | ... L64: ='Data Sheet'!K67 -> 6263.53
B65: ='Data Sheet'!A68 -> Inventory | C65: ='Data Sheet'!B68 -> 25149.91 | D65: ='Data Sheet'!C68 -> 20013.33 | E65: ='Data Sheet'!D68 -> 24803.82 | F65: ='Data Sheet'!E68 -> 28331.04 | G65: ='Data Sheet'!F68 -> 31656.1 | H65: ='Data Sheet'!G68 -> 31068.72 | I65: ='Data Sheet'!H68 -> 33276.38 | ... L65: ='Data Sheet'!K68 -> 49157.51
B66: ='Data Sheet'!A69 -> Cash & Bank | C66: ='Data Sheet'!B69 -> 8749.94 | D66: ='Data Sheet'!C69 -> 6186.34 | E66: ='Data Sheet'!D69 -> 4921.05 | F66: ='Data Sheet'!E69 -> 7937.85 | G66: ='Data Sheet'!F69 -> 3341.37 | H66: ='Data Sheet'!G69 -> 8054.72 | I66: ='Data Sheet'!H69 -> 5782.18 | ... L66: ='Data Sheet'!K69 -> 8677.72
B67: Total Current Asset | C67: =SUM(C64:C66) -> 47209.72 | D67: =SUM(D64:D66) -> 38265.89 | E67: =SUM(E64:E66) -> 41311.69 | F67: =SUM(F64:F66) -> 48684.41 | G67: =SUM(G64:G66) -> 46808.47 | H67: =SUM(H64:H66) -> 47008.35 | I67: =SUM(I64:I66) -> 48598.4 | J67: =SUM(J64:J66) -> 76969.75 | ... L67: =SUM(L64:L66) -> 64098.76
B69: Total Asset | C69: =C62+C67 -> 159109.3 | D69: =D62+D67 -> 176883.99 | E69: =E62+E67 -> 172447.37 | F69: =F62+F67 -> 208722.14 | G69: =G62+G67 -> 232773.44 | H69: =H62+H67 -> 249149.12 | I69: =I62+I67 -> 243909.19 | J69: =J62+J67 -> 282421.67 | ... L69: =L62+L67 -> 269312.42
B71: Check | C71: =C56=C69 -> TRUE | D71: =D56=D69 -> TRUE | E71: =E56=E69 -> TRUE | F71: =F56=F69 -> TRUE | G71: =G56=G69 -> TRUE | H71: =H56=H69 -> TRUE | I71: =I56=I69 -> TRUE | J71: =J56=J69 -> TRUE | ... L71: =L56=L69 -> TRUE
A73: # | B73: Cash Flow
B75: Operating Activites
B76: ='Rough Data'!B4 -> Profit from operations | C76: ='Rough Data'!C4 -> 13955 | D76: ='Rough Data'!D4 -> 6824 | E76: ='Rough Data'!E4 -> 17581 | F76: ='Rough Data'!F4 -> 20187 | G76: ='Rough Data'!G4 -> 27840 | H76: ='Rough Data'!H4 -> 18078 | I76: ='Rough Data'!I4 -> 28540 | ... L76: ='Rough Data'!L4 -> 22237
B77: ='Rough Data'!B5 -> Receivables | C77: ='Rough Data'!C5 -> 1442 | D77: ='Rough Data'!D5 -> 0 | E77: ='Rough Data'!E5 -> 0 | F77: ='Rough Data'!F5 -> 0 | G77: ='Rough Data'!G5 -> 0 | H77: ='Rough Data'!H5 -> 0 | I77: ='Rough Data'!I5 -> 0 | ... L77: ='Rough Data'!L5 -> 0
B78: ='Rough Data'!B6 -> Inventory | C78: ='Rough Data'!C6 -> -485 | D78: ='Rough Data'!D6 -> 5618 | E78: ='Rough Data'!E6 -> -8243 | F78: ='Rough Data'!F6 -> -1595 | G78: ='Rough Data'!G6 -> -1069 | H78: ='Rough Data'!H6 -> 1562 | I78: ='Rough Data'!I6 -> 46 | ... L78: ='Rough Data'!L6 -> 5566
B79: ='Rough Data'!B7 -> Payables | C79: ='Rough Data'!C7 -> -605 | D79: ='Rough Data'!D7 -> 0 | E79: ='Rough Data'!E7 -> 0 | F79: ='Rough Data'!F7 -> 0 | G79: ='Rough Data'!G7 -> 0 | H79: ='Rough Data'!H7 -> 0 | I79: ='Rough Data'!I7 -> 0 | ... L79: ='Rough Data'!L7 -> 0
B80: ='Rough Data'!B8 -> Other WC items | C80: ='Rough Data'!C8 -> 0 | D80: ='Rough Data'!D8 -> 548 | E80: ='Rough Data'!E8 -> 3329 | F80: ='Rough Data'!F8 -> -7680 | G80: ='Rough Data'!G8 -> 3659 | H80: ='Rough Data'!H8 -> 2634 | I80: ='Rough Data'!I8 -> 16446 | ... L80: ='Rough Data'!L8 -> -2182
B81: ='Rough Data'!B9 -> Working capital changes | C81: ='Rough Data'!C9 -> 351 | D81: ='Rough Data'!D9 -> 6166 | E81: ='Rough Data'!E9 -> -4914 | F81: ='Rough Data'!F9 -> -9276 | G81: ='Rough Data'!G9 -> 2591 | H81: ='Rough Data'!H9 -> 4196 | I81: ='Rough Data'!I9 -> 16491 | ... L81: ='Rough Data'!L9 -> 3384
B82: ='Rough Data'!B10 -> Direct taxes | C82: ='Rough Data'!C10 -> -2427 | D82: ='Rough Data'!D10 -> -1534 | E82: ='Rough Data'!E10 -> -1843 | F82: ='Rough Data'!F10 -> -2888 | G82: ='Rough Data'!G10 -> -5094 | H82: ='Rough Data'!H10 -> -2106 | I82: ='Rough Data'!I10 -> -704 | ... L82: ='Rough Data'!L10 -> -5320
B83: Cash From Operating Activites | C83: =SUM(C76:C82) -> 12231 | D83: =SUM(D76:D82) -> 17622 | E83: =SUM(E76:E82) -> 5910 | F83: =SUM(F76:F82) -> -1252 | G83: =SUM(G76:G82) -> 27927 | H83: =SUM(H76:H82) -> 24364 | I83: =SUM(I76:I82) -> 60819 | J83: =SUM(J76:J82) -> 34762 | ... L83: =SUM(L76:L82) -> 23685
B84: Investing Activites
B85: ='Rough Data'!B12 -> Fixed assets purchased | C85: ='Rough Data'!C12 -> -13492 | D85: ='Rough Data'!D12 -> -10163 | E85: ='Rough Data'!E12 -> -7716 | F85: ='Rough Data'!F12 -> -7478 | G85: ='Rough Data'!G12 -> -9091 | H85: ='Rough Data'!H12 -> -10398 | I85: ='Rough Data'!I12 -> -6979 | ... L85: ='Rough Data'!L12 -> -18207
B86: ='Rough Data'!B13 -> Fixed assets sold | C86: ='Rough Data'!C13 -> 1444 | D86: ='Rough Data'!D13 -> 231 | E86: ='Rough Data'!E13 -> 289 | F86: ='Rough Data'!F13 -> 179 | G86: ='Rough Data'!G13 -> 467 | H86: ='Rough Data'!H13 -> 386 | I86: ='Rough Data'!I13 -> 445 | ... L86: ='Rough Data'!L13 -> 475
B87: ='Rough Data'!B14 -> Investments purchased | C87: ='Rough Data'!C14 -> 1531 | D87: ='Rough Data'!D14 -> -3796 | E87: ='Rough Data'!E14 -> -861 | F87: ='Rough Data'!F14 -> -8641 | G87: ='Rough Data'!G14 -> -490 | H87: ='Rough Data'!H14 -> -828 | I87: ='Rough Data'!I14 -> -3631 | ... L87: ='Rough Data'!L14 -> -4
B88: ='Rough Data'!B15 -> Investments sold | C88: ='Rough Data'!C15 -> 262 | D88: ='Rough Data'!D15 -> 4275 | E88: ='Rough Data'!E15 -> 91 | F88: ='Rough Data'!F15 -> 3899 | G88: ='Rough Data'!G15 -> 13556 | H88: ='Rough Data'!H15 -> 121 | I88: ='Rough Data'!I15 -> 0 | ... L88: ='Rough Data'!L15 -> 3171
B89: ='Rough Data'!B16 -> Interest received | C89: ='Rough Data'!C16 -> 211 | D89: ='Rough Data'!D16 -> 133 | E89: ='Rough Data'!E16 -> 140 | F89: ='Rough Data'!F16 -> 254 | G89: ='Rough Data'!G16 -> 175 | H89: ='Rough Data'!H16 -> 203 | I89: ='Rough Data'!I16 -> 266 | ... L89: ='Rough Data'!L16 -> 333
B90: ='Rough Data'!B17 -> Dividends received | C90: ='Rough Data'!C17 -> 127 | D90: ='Rough Data'!D17 -> 108 | E90: ='Rough Data'!E17 -> 85 | F90: ='Rough Data'!F17 -> 111 | G90: ='Rough Data'!G17 -> 148 | H90: ='Rough Data'!H17 -> 103 | I90: ='Rough Data'!I17 -> 135 | ... L90: ='Rough Data'!L17 -> 336
B91: ='Rough Data'!B18 -> Redemp n Canc of Shares | C91: ='Rough Data'!C18 -> 1301 | D91: ='Rough Data'!D18 -> 0 | E91: ='Rough Data'!E18 -> 0 | F91: ='Rough Data'!F18 -> 34 | G91: ='Rough Data'!G18 -> 156 | H91: ='Rough Data'!H18 -> 378 | I91: ='Rough Data'!I18 -> 90 | ... L91: ='Rough Data'!L18 -> 123
B92: ='Rough Data'!B19 -> Acquisition of companies | C92: ='Rough Data'!C19 -> -108 | D92: ='Rough Data'!D19 -> -78 | E92: ='Rough Data'!E19 -> -1081 | F92: ='Rough Data'!F19 -> -255 | G92: ='Rough Data'!G19 -> -34569 | H92: ='Rough Data'!H19 -> -4433 | I92: ='Rough Data'!I19 -> 0 | ... L92: ='Rough Data'!L19 -> 0
B93: ='Rough Data'!B20 -> Inter corporate deposits | C93: ='Rough Data'!C20 -> 277 | D93: ='Rough Data'!D20 -> 0 | E93: ='Rough Data'!E20 -> 0 | F93: ='Rough Data'!F20 -> 0 | G93: ='Rough Data'!G20 -> 0 | H93: ='Rough Data'!H20 -> 0 | I93: ='Rough Data'!I20 -> 0 | ... L93: ='Rough Data'!L20 -> 0
B94: ='Rough Data'!B21 -> Other investing items | C94: ='Rough Data'!C21 -> -573 | D94: ='Rough Data'!D21 -> 496 | E94: ='Rough Data'!E21 -> -437 | F94: ='Rough Data'!F21 -> 166 | G94: ='Rough Data'!G21 -> 471 | H94: ='Rough Data'!H21 -> 456 | I94: ='Rough Data'!I21 -> 236 | ... L94: ='Rough Data'!L21 -> -481
B95: Cash From Investing Activites | C95: =SUM(C85:C94) -> -9020 | D95: =SUM(D85:D94) -> -8794 | E95: =SUM(E85:E94) -> -9490 | F95: =SUM(F85:F94) -> -11731 | G95: =SUM(G85:G94) -> -29177 | H95: =SUM(H85:H94) -> -14012 | I95: =SUM(I85:I94) -> -9438 | J95: =SUM(J85:J94) -> -10904 | ... L95: =SUM(L85:L94) -> -14254
B96: Financial Activites
B97: ='Rough Data'!B23 -> Proceeds from shares | C97: ='Rough Data'!C23 -> 13 | D97: ='Rough Data'!D23 -> 0 | E97: ='Rough Data'!E23 -> 652 | F97: ='Rough Data'!F23 -> 9087 | G97: ='Rough Data'!G23 -> 0 | H97: ='Rough Data'!H23 -> 188 | I97: ='Rough Data'!I23 -> 3239 | ... L97: ='Rough Data'!L23 -> 0
B98: ='Rough Data'!B24 -> Proceeds from borrowings | C98: ='Rough Data'!C24 -> 0 | D98: ='Rough Data'!D24 -> 0 | E98: ='Rough Data'!E24 -> 0 | F98: ='Rough Data'!F24 -> 0 | G98: ='Rough Data'!G24 -> 33344 | H98: ='Rough Data'!H24 -> 16574 | I98: ='Rough Data'!I24 -> 9801 | ... L98: ='Rough Data'!L24 -> 14120
B99: ='Rough Data'!B25 -> Repayment of borrowings | C99: ='Rough Data'!C25 -> 0 | D99: ='Rough Data'!D25 -> 0 | E99: ='Rough Data'!E25 -> 0 | F99: ='Rough Data'!F25 -> 0 | G99: ='Rough Data'!G25 -> -25077 | H99: ='Rough Data'!H25 -> -7937 | I99: ='Rough Data'!I25 -> -39177 | ... L99: ='Rough Data'!L25 -> -11908
B100: ='Rough Data'!B26 -> Interest paid fin | C100: ='Rough Data'!C26 -> -5428 | D100: ='Rough Data'!D26 -> -5483 | E100: ='Rough Data'!E26 -> -4733 | F100: ='Rough Data'!F26 -> -5146 | G100: ='Rough Data'!G26 -> -6901 | H100: ='Rough Data'!H26 -> -7419 | I100: ='Rough Data'!I26 -> -6804 | ... L100: ='Rough Data'!L26 -> -8145
B101: ='Rough Data'!B27 -> Dividends paid | C101: ='Rough Data'!C27 -> -983 | D101: ='Rough Data'!D27 -> -788 | E101: ='Rough Data'!E27 -> -791 | F101: ='Rough Data'!F27 -> -982 | G101: ='Rough Data'!G27 -> -1186 | H101: ='Rough Data'!H27 -> -1507 | I101: ='Rough Data'!I27 -> -1151 | ... L101: ='Rough Data'!L27 -> -4429
B102: ='Rough Data'!B28 -> Financial liabilities | C102: ='Rough Data'!C28 -> 0 | D102: ='Rough Data'!D28 -> -200 | E102: ='Rough Data'!E28 -> -208 | F102: ='Rough Data'!F28 -> -211 | G102: ='Rough Data'!G28 -> -276 | H102: ='Rough Data'!H28 -> -1029 | I102: ='Rough Data'!I28 -> -1284 | ... L102: ='Rough Data'!L28 -> -1140
B103: ='Rough Data'!B29 -> Other financing items | C103: ='Rough Data'!C29 -> 3781 | D103: ='Rough Data'!D29 -> 1743 | E103: ='Rough Data'!E29 -> 2501 | F103: ='Rough Data'!F29 -> 3892 | G103: ='Rough Data'!G29 -> -576 | H103: ='Rough Data'!H29 -> -564 | I103: ='Rough Data'!I29 -> -1714 | ... L103: ='Rough Data'!L29 -> 404
B104: Cash From Financing Activites | C104: =SUM(C97:C103) -> -2617 | D104: =SUM(D97:D103) -> -4728 | E104: =SUM(E97:E103) -> -2579 | F104: =SUM(F97:F103) -> 6640 | G104: =SUM(G97:G103) -> -672 | H104: =SUM(H97:H103) -> -1694 | I104: =SUM(I97:I103) -> -37090 | J104: =SUM(J97:J103) -> -23401 | ... L104: =SUM(L97:L103) -> -11098
B106: Net Cash Flow | C106: =C83+C104+C95 -> 594 | D106: =D83+D104+D95 -> 4100 | E106: =E83+E104+E95 -> -6159 | F106: =F83+F104+F95 -> -6343 | G106: =G83+G104+G95 -> -1922 | H106: =H83+H104+H95 -> 8658 | I106: =I83+I104+I95 -> 14291 | J106: =J83+J104+J95 -> 457 | ... L106: =L83+L104+L95 -> -1667

Sheet Ratio Analysis
B2: ="Ratio Analysis-"&'Data Sheet'!B1 -> Ratio Analysis-TATA STEEL LTD
B3: Year | C3: ='Data Sheet'!B16 -> 42094 | D3: ='Data Sheet'!C16 -> 42460 | E3: ='Data Sheet'!D16 -> 42825 | F3: ='Data Sheet'!E16 -> 43190 | G3: ='Data Sheet'!F16 -> 43555 | H3: ='Data Sheet'!G16 -> 43921 | I3: ='Data Sheet'!H16 -> 44286 | J3: ='Data Sheet'!I16 -> 44651 | ... L3: ='Data Sheet'!K16 -> 45382 | M3: Trend | N3: Mean | O3: Median
B5: Sales Growth | D5: ='Histoirical FC'!D6/'Histoirical FC'!C6-1 -> -0.26908965 | E5: ='Histoirical FC'!E6/'Histoirical FC'!D6-1 -> 0.10135565 | F5: ='Histoirical FC'!F6/'Histoirical FC'!E6-1 -> 0.097504065 | G5: ='Histoirical FC'!G6/'Histoirical FC'!F6-1 -> 0.27927124 | H5: ='Histoirical FC'!H6/'Histoirical FC'!G6-1 -> -0.1132267 | I5: ='Histoirical FC'!I6/'Histoirical FC'!H6-1 -> 0.11785099 | J5: ='Histoirical FC'!J6/'Histoirical FC'!I6-1 -> 0.56089734 | K5: ='Histoirical FC'!K6/'Histoirical FC'!J6-1 -> -0.0024859898 | L5: ='Histoirical FC'!L6/'Histoirical FC'!K6-1 -> -0.058277186 | N5: =AVERAGE(D5:L5) -> 0.079311082 | O5: =MEDIAN(D5:L5) -> 0.097504065
B6: EBITDA Growth | D6: ='Histoirical FC'!D18/'Histoirical FC'!C18-1 -> -1.1834151 | E6: ='Histoirical FC'!E18/'Histoirical FC'!D18-1 -> -22.021736 | F6: ='Histoirical FC'!F18/'Histoirical FC'!E18-1 -> 0.6306903 | G6: ='Histoirical FC'!G18/'Histoirical FC'!F18-1 -> 0.36788877 | H6: ='Histoirical FC'!H18/'Histoirical FC'!G18-1 -> -0.40436152 | I6: ='Histoirical FC'!I18/'Histoirical FC'!H18-1 -> 0.74678779 | J6: ='Histoirical FC'!J18/'Histoirical FC'!I18-1 -> 1.081347 | K6: ='Histoirical FC'!K18/'Histoirical FC'!J18-1 -> -0.49125555 | L6: ='Histoirical FC'!L18/'Histoirical FC'!K18-1 -> -0.31121332 | N6: =AVERAGE(D6:L6) -> -2.398363 | O6: =MEDIAN(D6:L6) -> -0.31121332
B7: EBIT Growth | D7: ='Histoirical FC'!D24/'Histoirical FC'!C24-1 -> 1.3401362 | E7: ='Histoirical FC'!E24/'Histoirical FC'!D24-1 -> -2.2594852 | F7: ='Histoirical FC'!F24/'Histoirical FC'!E24-1 -> 1.1003902 | G7: ='Histoirical FC'!G24/'Histoirical FC'!F24-1 -> 0.4005292 | H7: ='Histoirical FC'!H24/'Histoirical FC'!G24-1 -> -0.5894535 | I7: ='Histoirical FC'!I24/'Histoirical FC'!H24-1 -> 1.3575529 | J7: ='Histoirical FC'!J24/'Histoirical FC'!I24-1 -> 1.5570049 | K7: ='Histoirical FC'!K24/'Histoirical FC'!J24-1 -> -0.57776524 | L7: ='Histoirical FC'!L24/'Histoirical FC'!K24-1 -> -0.46153793 | N7: =AVERAGE(D7:L7) -> 0.20748572 | O7: =MEDIAN(D7:L7) -> 0.4005292
B8: Net Profit Growth | D8: ='Histoirical FC'!D36/'Histoirical FC'!C36-1 -> 0.089757866 | E8: ='Histoirical FC'!E36/'Histoirical FC'!D36-1 -> -0.96500402 | F8: ='Histoirical FC'!F36/'Histoirical FC'!E36-1 -> -19.037263 | G8: ='Histoirical FC'!G36/'Histoirical FC'!F36-1 -> 0.11008091 | H8: ='Histoirical FC'!H36/'Histoirical FC'!G36-1 -> -0.465997 | I8: ='Histoirical FC'!I36/'Histoirical FC'!H36-1 -> 0.9742315 | J8: ='Histoirical FC'!J36/'Histoirical FC'!I36-1 -> 4.0498476 | K8: ='Histoirical FC'!K36/'Histoirical FC'!J36-1 -> -0.83914468 | L8: ='Histoirical FC'!L36/'Histoirical FC'!K36-1 -> -0.83161121 | N8: =AVERAGE(D8:L8) -> -1.8794558 | O8: =MEDIAN(D8:L8) -> -0.465997
B9: Divident Growth | D9: ='Histoirical FC'!D44/'Histoirical FC'!C44-1 -> -0.0012095788 | E9: ='Histoirical FC'!E44/'Histoirical FC'!D44-1 -> 0.25000322 | F9: ='Histoirical FC'!F44/'Histoirical FC'!E44-1 -> 0.18021551 | G9: ='Histoirical FC'!G44/'Histoirical FC'!F44-1 -> 0.29997536 | H9: ='Histoirical FC'!H44/'Histoirical FC'!G44-1 -> -0.23076148 | I9: ='Histoirical FC'!I44/'Histoirical FC'!H44-1 -> 1.4617851 | J9: ='Histoirical FC'!J44/'Histoirical FC'!I44-1 -> 1.0381154 | K9: ='Histoirical FC'!K44/'Histoirical FC'!J44-1 -> -0.29459179 | L9: ='Histoirical FC'!L44/'Histoirical FC'!K44-1 -> 1.5657977e-05 | N9: =AVERAGE(D9:L9) -> 0.30039416 | O9: =MEDIAN(D9:L9) -> 0.18021551
B11: Gross Margin | C11: ='Histoirical FC'!C12/'Histoirical FC'!C6 -> 0.25241468 | D11: ='Histoirical FC'!D12/'Histoirical FC'!D6 -> 0.22289533 | E11: ='Histoirical FC'!E12/'Histoirical FC'!E6 -> 0.30919421 | F11: ='Histoirical FC'!F12/'Histoirical FC'!F6 -> 0.31269218 | G11: ='Histoirical FC'!G12/'Histoirical FC'!G6 -> 0.33030553 | H11: ='Histoirical FC'!H12/'Histoirical FC'!H6 -> 0.26646118 | I11: ='Histoirical FC'!I12/'Histoirical FC'!I6 -> 0.33853993 | J11: ='Histoirical FC'!J12/'Histoirical FC'!J6 -> 0.41135564 | ... L11: ='Histoirical FC'!L12/'Histoirical FC'!L6 -> 0.25487765 | N11: =AVERAGE(D11:L11) -> 0.30150217 | O11: =MEDIAN(D11:L11) -> 0.30919421
B12: EBITDA Margin | C12: ='Histoirical FC'!C18/'Histoirical FC'!C6 -> 0.024435762 | D12: ='Histoirical FC'!D18/'Histoirical FC'!D6 -> -0.0061319248 | E12: ='Histoirical FC'!E18/'Histoirical FC'!E6 -> 0.11704094 | F12: ='Histoirical FC'!F18/'Histoirical FC'!F6 -> 0.17390143 | G12: ='Histoirical FC'!G18/'Histoirical FC'!G6 -> 0.18594792 | H12: ='Histoirical FC'!H18/'Histoirical FC'!H6 -> 0.12489972 | I12: ='Histoirical FC'!I18/'Histoirical FC'!I6 -> 0.19517208 | J12: ='Histoirical FC'!J18/'Histoirical FC'!J6 -> 0.26024826 | ... L12: ='Histoirical FC'!L18/'Histoirical FC'!L6 -> 0.09708009 | N12: =AVERAGE(D12:L12) -> 0.14232093 | O12: =MEDIAN(D12:L12) -> 0.13272983
B13: EBIT Margin | C13: ='Histoirical FC'!C24/'Histoirical FC'!C6 -> -0.01816955 | D13: ='Histoirical FC'!D24/'Histoirical FC'!D6 -> -0.058172964 | E13: ='Histoirical FC'!E24/'Histoirical FC'!E6 -> 0.066525277 | F13: ='Histoirical FC'!F24/'Histoirical FC'!F6 -> 0.12731528 | G13: ='Histoirical FC'!G24/'Histoirical FC'!G6 -> 0.13938308 | H13: ='Histoirical FC'!H24/'Histoirical FC'!H6 -> 0.064529725 | I13: ='Histoirical FC'!I24/'Histoirical FC'!I6 -> 0.13609349 | J13: ='Histoirical FC'!J24/'Histoirical FC'!J6 -> 0.22294337 | ... L13: ='Histoirical FC'!L24/'Histoirical FC'!L6 -> 0.053958711 | N13: =AVERAGE(D13:L13) -> 0.094105002 | O13: =MEDIAN(D13:L13) -> 0.094369041
B14: EBT Margin | C14: ='Histoirical FC'!C30/'Histoirical FC'!C6 -> -0.052919517 | D14: ='Histoirical FC'!D30/'Histoirical FC'!D6 -> -0.099573656 | E14: ='Histoirical FC'!E30/'Histoirical FC'!E6 -> 0.021358525 | F14: ='Histoirical FC'!F30/'Histoirical FC'!F6 -> 0.083057422 | G14: ='Histoirical FC'!G30/'Histoirical FC'!G6 -> 0.090799656 | H14: ='Histoirical FC'!H30/'Histoirical FC'!H6 -> 0.010648732 | I14: ='Histoirical FC'!I30/'Histoirical FC'!I6 -> 0.087424305 | J14: ='Histoirical FC'!J30/'Histoirical FC'!J6 -> 0.20055356 | ... L14: ='Histoirical FC'!L30/'Histoirical FC'!L6 -> 0.021198994 | N14: =AVERAGE(D14:L14) -> 0.053772619 | O14: =MEDIAN(D14:L14) -> 0.068486032
B15: Net Profit Margin | C15: ='Histoirical FC'!C36/'Histoirical FC'!C6 -> -0.071323398 | D15: ='Histoirical FC'!D36/'Histoirical FC'!D6 -> -0.10634031 | E15: ='Histoirical FC'!E36/'Histoirical FC'!E6 -> -0.0033790023 | F15: ='Histoirical FC'!F36/'Histoirical FC'!F6 -> 0.055533239 | G15: ='Histoirical FC'!G36/'Histoirical FC'!G6 -> 0.048188677 | H15: ='Histoirical FC'!H36/'Histoirical FC'!H6 -> 0.029018575 | I15: ='Histoirical FC'!I36/'Histoirical FC'!I6 -> 0.051249573 | J15: ='Histoirical FC'!J36/'Histoirical FC'!J6 -> 0.16580369 | ... L15: ='Histoirical FC'!L36/'Histoirical FC'!L6 -> 0.0047808015 | N15: =AVERAGE(D15:L15) -> 0.030176901 | O15: =MEDIAN(D15:L15) -> 0.029018575
B17: Sales Expense % of Sale | C17: ='Histoirical FC'!C16 -> 0.22797892 | D17: ='Histoirical FC'!D16 -> 0.22902726 | E17: ='Histoirical FC'!E16 -> 0.19215326 | F17: ='Histoirical FC'!F16 -> 0.13879074 | G17: ='Histoirical FC'!G16 -> 0.14435762 | H17: ='Histoirical FC'!H16 -> 0.14156147 | I17: ='Histoirical FC'!I16 -> 0.14336785 | J17: ='Histoirical FC'!J16 -> 0.15110738 | ... L17: ='Histoirical FC'!L16 -> 0.15779756 | N17: =AVERAGE(D17:L17) -> 0.15918125 | O17: =MEDIAN(D17:L17) -> 0.14435762
B18: Depriciation % of Sale | C18: ='Histoirical FC'!C22 -> 0.042605312 | D18: ='Histoirical FC'!D22 -> 0.052041039 | E18: ='Histoirical FC'!E22 -> 0.050515666 | F18: ='Histoirical FC'!F22 -> 0.046586153 | G18: ='Histoirical FC'!G22 -> 0.046564832 | H18: ='Histoirical FC'!H22 -> 0.060369992 | I18: ='Histoirical FC'!I22 -> 0.059078591 | J18: ='Histoirical FC'!J22 -> 0.03730489 | ... L18: ='Histoirical FC'!L22 -> 0.043121379 | N18: =AVERAGE(D18:L18) -> 0.048215925 | O18: =MEDIAN(D18:L18) -> 0.046586153
B20: Debt to Equity Ratio
B21: Debt/Equity | C21: =SUM('Rough Data'!P6:P7)/SUM('Rough Data'!P3:P4) -> 2.4011611 | D21: =SUM('Rough Data'!Q6:Q7)/SUM('Rough Data'!Q3:Q4) -> 1.8429297 | E21: =SUM('Rough Data'!R6:R7)/SUM('Rough Data'!R3:R4) -> 2.1774769 | F21: =SUM('Rough Data'!S6:S7)/SUM('Rough Data'!S3:S4) -> 1.4567528 | G21: =SUM('Rough Data'!T6:T7)/SUM('Rough Data'!T3:T4) -> 1.3223794 | H21: =SUM('Rough Data'!U6:U7)/SUM('Rough Data'!U3:U4) -> 1.5397548 | I21: =SUM('Rough Data'!V6:V7)/SUM('Rough Data'!V3:V4) -> 1.1032072 | J21: =SUM('Rough Data'!W6:W7)/SUM('Rough Data'!W3:W4) -> 0.60142604 | ... L21: =SUM('Rough Data'!Y6:Y7)/SUM('Rough Data'!Y3:Y4) -> 0.88633672 | N21: =AVERAGE(D21:L21) -> 1.2985675 | O21: =MEDIAN(D21:L21) -> 1.3223794
B22: Intrest Coverage Ratio | C22: ='Histoirical FC'!C24/'Data Sheet'!B27 -> -0.52286525 | D22: ='Histoirical FC'!D24/'Data Sheet'!C27 -> -1.4051206 | E22: ='Histoirical FC'!E24/'Data Sheet'!D27 -> 1.4728816 | F22: ='Histoirical FC'!F24/'Data Sheet'!E27 -> 2.8766706 | G22: ='Histoirical FC'!G24/'Data Sheet'!F27 -> 2.868943 | H22: ='Histoirical FC'!H24/'Data Sheet'!G27 -> 1.1976343 | I22: ='Histoirical FC'!I24/'Data Sheet'!H27 -> 2.796297 | J22: ='Histoirical FC'!J24/'Data Sheet'!I27 -> 9.9573578 | ... L22: ='Histoirical FC'!L24/'Data Sheet'!K27 -> 1.6471055 | N22: =AVERAGE(D22:L22) -> 2.7841948 | O22: =MEDIAN(D22:L22) -> 2.796297
B24: Return Ratio
B25: Return on Equity | C25: ='Histoirical FC'!C36/SUM('Data Sheet'!B57:B58) -> -0.31738652 | D25: ='Histoirical FC'!D36/SUM('Data Sheet'!C57:C58) -> -0.24793798 | E25: ='Histoirical FC'!E36/SUM('Data Sheet'!D57:D58) -> -0.010033496 | F25: ='Histoirical FC'!F36/SUM('Data Sheet'!E57:E58) -> 0.11244209 | G25: ='Histoirical FC'!G36/SUM('Data Sheet'!F57:F58) -> 0.1102336 | H25: ='Histoirical FC'!H36/SUM('Data Sheet'!G57:G58) -> 0.055143844 | I25: ='Histoirical FC'!I36/SUM('Data Sheet'!H57:H58) -> 0.10789524 | J25: ='Histoirical FC'!J36/SUM('Data Sheet'!I57:I58) -> 0.35344508 | ... L25: ='Histoirical FC'!L36/SUM('Data Sheet'!K57:K58) -> 0.011904286 | N25: =AVERAGE(D25:L25) -> 0.061801353 | O25: =MEDIAN(D25:L25) -> 0.063119494
B26: Return On Captial Employed | C26: ='Histoirical FC'!C24/SUM('Histoirical FC'!C52:C54) -> -0.022621188 | D26: ='Histoirical FC'!D24/SUM('Histoirical FC'!D52:D54) -> -0.047181153 | E26: ='Histoirical FC'!E24/SUM('Histoirical FC'!E52:E54) -> 0.061826653 | F26: ='Histoirical FC'!F24/SUM('Histoirical FC'!F52:F54) -> 0.10254692 | G26: ='Histoirical FC'!G24/SUM('Histoirical FC'!G52:G54) -> 0.12946991 | H26: ='Histoirical FC'!H24/SUM('Histoirical FC'!H52:H54) -> 0.047509827 | I26: ='Histoirical FC'!I24/SUM('Histoirical FC'!I52:I54) -> 0.13070294 | J26: ='Histoirical FC'!J24/SUM('Histoirical FC'!J52:J54) -> 0.2862517 | ... L26: ='Histoirical FC'!L24/SUM('Histoirical FC'!L52:L54) -> 0.069036994 | N26: =AVERAGE(D26:L26) -> 0.10025933 | O26: =MEDIAN(D26:L26) -> 0.10254692
B27: Retained Earning% | C27: ='Histoirical FC'!C48 -> 1.0781045 | D27: ='Histoirical FC'!D48 -> 1.0715847 | E27: ='Histoirical FC'!E48 -> 3.5568966 | F27: ='Histoirical FC'!F48 -> 0.83271775 | G27: ='Histoirical FC'!G48 -> 0.8041001 | H27: ='Histoirical FC'!H48 -> 0.71780355 | I27: ='Histoirical FC'!I48 -> 0.6262152 | J27: ='Histoirical FC'!J48 -> 0.84602539 | ... L27: ='Histoirical FC'!L48 -> -3.0988481 | N27: =AVERAGE(D27:L27) -> 0.63119904 | O27: =MEDIAN(D27:L27) -> 0.8041001
B28: Selfsustained Growth | C28: =C27*C25 -> -0.34217582 | D28: =D27*D25 -> -0.26568654 | E28: =E27*E25 -> -0.035688109 | F28: =F27*F25 -> 0.093632527 | G28: =G27*G25 -> 0.088638853 | H28: =H27*H25 -> 0.039582447 | I28: =I27*I25 -> 0.06756564 | J28: =J27*J25 -> 0.29902351 | ... L28: =L27*L25 -> -0.036889574 | N28: =AVERAGE(D28:L28) -> 0.030072019 | O28: =MEDIAN(D28:L28) -> 0.039582447
B30: Turnover Ratio
B31: Receivabel Turnover Ratio | C31: ='Histoirical FC'!C6/'Histoirical FC'!C64 -> 10.481224 | D31: ='Histoirical FC'!D6/'Histoirical FC'!D64 -> 8.4504277 | E31: ='Histoirical FC'!E6/'Histoirical FC'!E64 -> 9.6919966 | F31: ='Histoirical FC'!F6/'Histoirical FC'!F64 -> 9.9270163 | G31: ='Histoirical FC'!G6/'Histoirical FC'!G64 -> 13.349335 | H31: ='Histoirical FC'!H6/'Histoirical FC'!H64 -> 17.732181 | I31: ='Histoirical FC'!I6/'Histoirical FC'!I64 -> 16.383313 | J31: ='Histoirical FC'!J6/'Histoirical FC'!J64 -> 19.92084 | ... L31: ='Histoirical FC'!L6/'Histoirical FC'!L64 -> 36.588119 | N31: =AVERAGE(D31:L31) -> 17.946073 | O31: =MEDIAN(D31:L31) -> 16.383313
B32: Payabel Turnover Ratio | C32: ='Histoirical FC'!C6/'Rough Data'!P13 -> 7.2696055 | D32: ='Histoirical FC'!D6/'Rough Data'!Q13 -> 5.4946769 | E32: ='Histoirical FC'!E6/'Rough Data'!R13 -> 6.0460547 | F32: ='Histoirical FC'!F6/'Rough Data'!S13 -> 6.0374777 | G32: ='Histoirical FC'!G6/'Rough Data'!T13 -> 7.2601644 | H32: ='Histoirical FC'!H6/'Rough Data'!U13 -> 6.5392942 | I32: ='Histoirical FC'!I6/'Rough Data'!V13 -> 6.0189541 | J32: ='Histoirical FC'!J6/'Rough Data'!W13 -> 6.6356363 | ... L32: ='Histoirical FC'!L6/'Rough Data'!Y13 -> 6.4673566 | N32: =AVERAGE(D32:L32) -> 6.3257668 | O32: =MEDIAN(D32:L32) -> 6.4322864
B33: Inventory Turnover Ratio | C33: ='Histoirical FC'!C6/'Histoirical FC'!C65 -> 5.5468878 | D33: ='Histoirical FC'!D6/'Histoirical FC'!D65 -> 5.0948403 | E33: ='Histoirical FC'!E6/'Histoirical FC'!E65 -> 4.527505 | F33: ='Histoirical FC'!F6/'Histoirical FC'!F65 -> 4.3503193 | G33: ='Histoirical FC'!G6/'Histoirical FC'!G65 -> 4.9806827 | H33: ='Histoirical FC'!H6/'Histoirical FC'!H65 -> 4.5002385 | I33: ='Histoirical FC'!I6/'Histoirical FC'!I65 -> 4.6968504 | J33: ='Histoirical FC'!J6/'Histoirical FC'!J65 -> 4.996666 | ... L33: ='Histoirical FC'!L6/'Histoirical FC'!L65 -> 4.6619688 | N33: =AVERAGE(D33:L33) -> 4.6979118 | O33: =MEDIAN(D33:L33) -> 4.6619688
B34: Fixed Asset Turnover Ratio | C34: ='Histoirical FC'!C6/'Histoirical FC'!C62 -> 1.2466868 | D34: ='Histoirical FC'!D6/'Histoirical FC'!D62 -> 0.73558013 | E34: ='Histoirical FC'!E6/'Histoirical FC'!E62 -> 0.85636053 | F34: ='Histoirical FC'!F6/'Histoirical FC'!F62 -> 0.77012508 | G34: ='Histoirical FC'!G6/'Histoirical FC'!G62 -> 0.84784242 | H34: ='Histoirical FC'!H6/'Histoirical FC'!H62 -> 0.69167962 | I34: ='Histoirical FC'!I6/'Histoirical FC'!I62 -> 0.80023321 | J34: ='Histoirical FC'!J6/'Histoirical FC'!J62 -> 1.1874271 | ... L34: ='Histoirical FC'!L6/'Histoirical FC'!L62 -> 1.1167423 | N34: =AVERAGE(D34:L34) -> 0.90759135 | O34: =MEDIAN(D34:L34) -> 0.84784242
B35: Capital Turnover Ratio | C35: ='Histoirical FC'!C6/SUM('Histoirical FC'!C52:C53) -> 4.4499635 | D35: ='Histoirical FC'!D6/SUM('Histoirical FC'!D52:D53) -> 2.3315521 | E35: ='Histoirical FC'!E6/SUM('Histoirical FC'!E52:E53) -> 2.9693665 | F35: ='Histoirical FC'!F6/SUM('Histoirical FC'!F52:F53) -> 2.0247711 | G35: ='Histoirical FC'!G6/SUM('Histoirical FC'!G52:G53) -> 2.2875416 | H35: ='Histoirical FC'!H6/SUM('Histoirical FC'!H52:H53) -> 1.9002947 | I35: ='Histoirical FC'!I6/SUM('Histoirical FC'!I52:I53) -> 2.1052905 | J35: ='Histoirical FC'!J6/SUM('Histoirical FC'!J52:J53) -> 2.1317082 | ... L35: ='Histoirical FC'!L6/SUM('Histoirical FC'!L52:L53) -> 2.4900189 | N35: =AVERAGE(D35:L35) -> 2.2890344 | O35: =MEDIAN(D35:L35) -> 2.2875416
B37: WC(Cash Conversion Cycel)
B38: Debtor Day | C38: =365/C31 -> 34.824177 | D38: =365/D31 -> 43.19308 | E38: =365/E31 -> 37.659939 | F38: =365/F31 -> 36.768349 | G38: =365/G31 -> 27.342187 | H38: =365/H31 -> 20.584045 | I38: =365/I31 -> 22.278767 | J38: =365/J31 -> 18.322521 | ... L38: =365/L31 -> 9.975916 | N38: =AVERAGE(D38:L38) -> 25.389964 | O38: =MEDIAN(D38:L38) -> 22.278767
B39: Payabel Day | C39: =365/C32 -> 50.209052 | D39: =365/D32 -> 66.427927 | E39: =365/E32 -> 60.369947 | F39: =365/F32 -> 60.45571 | G39: =365/G32 -> 50.274344 | H39: =365/H32 -> 55.816421 | I39: =365/I32 -> 60.641765 | J39: =365/J32 -> 55.006028 | ... L39: =365/L32 -> 56.437278 | N39: =AVERAGE(D39:L39) -> 58.019378 | O39: =MEDIAN(D39:L39) -> 56.744986
B40: Inventory Day | C40: =365/C33 -> 65.802665 | D40: =365/D33 -> 71.641107 | E40: =365/E33 -> 80.618353 | F40: =365/F33 -> 83.901887 | G40: =365/G33 -> 73.283126 | H40: =365/H33 -> 81.106812 | I40: =365/I33 -> 77.711651 | J40: =365/J33 -> 73.048709 | ... L40: =365/L33 -> 78.293102 | N40: =AVERAGE(D40:L40) -> 77.913472 | O40: =MEDIAN(D40:L40) -> 78.293102
B41: Cash Conversion Cycel | C41: =C38+C40-C39 -> 50.41779 | D41: =D38+D40-D39 -> 48.40626 | E41: =E38+E40-E39 -> 57.908345 | F41: =F38+F40-F39 -> 60.214527 | G41: =G38+G40-G39 -> 50.350969 | H41: =H38+H40-H39 -> 45.874436 | I41: =I38+I40-I39 -> 39.348652 | J41: =J38+J40-J39 -> 36.365201 | ... L41: =L38+L40-L39 -> 31.83174 | N41: =AVERAGE(D41:L41) -> 45.284058 | O41: =MEDIAN(D41:L41) -> 45.874436
B43: CFO/Sales | C43: ='Histoirical FC'!C83/'Histoirical FC'!C6 -> 0.087675075 | D43: ='Histoirical FC'!D83/'Histoirical FC'!D6 -> 0.17282448 | E43: ='Histoirical FC'!E83/'Histoirical FC'!E6 -> 0.052627164 | F43: ='Histoirical FC'!F83/'Histoirical FC'!F6 -> -0.010158292 | G43: ='Histoirical FC'!G83/'Histoirical FC'!G6 -> 0.17712424 | H43: ='Histoirical FC'!H83/'Histoirical FC'!H6 -> 0.17425679 | I43: ='Histoirical FC'!I83/'Histoirical FC'!I6 -> 0.38913157 | J43: ='Histoirical FC'!J83/'Histoirical FC'!J6 -> 0.14249106 | ... L43: ='Histoirical FC'!L83/'Histoirical FC'!L6 -> 0.10335087 | N43: =AVERAGE(D43:L43) -> 0.14172445 | O43: =MEDIAN(D43:L43) -> 0.14249106
B44: CFO/Total Asset | C44: ='Histoirical FC'!C83/'Histoirical FC'!C69 -> 0.076871685 | D44: ='Histoirical FC'!D83/'Histoirical FC'!D69 -> 0.099624618 | E44: ='Histoirical FC'!E83/'Histoirical FC'!E69 -> 0.034271326 | F44: ='Histoirical FC'!F83/'Histoirical FC'!F69 -> -0.0059984053 | G44: ='Histoirical FC'!G83/'Histoirical FC'!G69 -> 0.11997503 | H44: ='Histoirical FC'!H83/'Histoirical FC'!H69 -> 0.097788826 | I44: ='Histoirical FC'!I83/'Histoirical FC'!I69 -> 0.249351 | J44: ='Histoirical FC'!J83/'Histoirical FC'!J69 -> 0.12308546 | ... L44: ='Histoirical FC'!L83/'Histoirical FC'!L69 -> 0.087946185 | N44: =AVERAGE(D44:L44) -> 0.096559306 | O44: =MEDIAN(D44:L44) -> 0.097788826
B45: CFO/ Total Debt | C45: ='Histoirical FC'!C83/'Histoirical FC'!C54 -> 0.15155892 | D45: ='Histoirical FC'!D83/'Histoirical FC'!D54 -> 0.2149367 | E45: ='Histoirical FC'!E83/'Histoirical FC'!E54 -> 0.071192391 | F45: ='Histoirical FC'!F83/'Histoirical FC'!F54 -> -0.013586979 | G45: ='Histoirical FC'!G83/'Histoirical FC'!G54 -> 0.277009 | H45: ='Histoirical FC'!H83/'Histoirical FC'!H54 -> 0.20944191 | I45: ='Histoirical FC'!I83/'Histoirical FC'!I54 -> 0.68720939 | J45: ='Histoirical FC'!J83/'Histoirical FC'!J54 -> 0.46005001 | ... L45: ='Histoirical FC'!L83/'Histoirical FC'!L54 -> 0.27198465 | N45: =AVERAGE(D45:L45) -> 0.26555529 | O45: =MEDIAN(D45:L45) -> 0.2149367 | P45: (Long Term Only)

Sheet Common Size Statement
B2: ="Common Size Statement-"&'Data Sheet'!B1 -> Common Size Statement-TATA STEEL LTD
B4: Particular | C4: ='Data Sheet'!B16 -> 42094 | D4: ='Data Sheet'!C16 -> 42460 | E4: ='Data Sheet'!D16 -> 42825 | F4: ='Data Sheet'!E16 -> 43190 | G4: ='Data Sheet'!F16 -> 43555 | H4: ='Data Sheet'!G16 -> 43921 | I4: ='Data Sheet'!H16 -> 44286 | J4: ='Data Sheet'!I16 -> 44651 | ... L4: ='Data Sheet'!K16 -> 45382
B5: ='Data Sheet'!A17 -> Sales | C5: ='Data Sheet'!B17/'Data Sheet'!B$17 -> 1 | D5: ='Data Sheet'!C17/'Data Sheet'!C$17 -> 1 | E5: ='Data Sheet'!D17/'Data Sheet'!D$17 -> 1 | F5: ='Data Sheet'!E17/'Data Sheet'!E$17 -> 1 | G5: ='Data Sheet'!F17/'Data Sheet'!F$17 -> 1 | H5: ='Data Sheet'!G17/'Data Sheet'!G$17 -> 1 | I5: ='Data Sheet'!H17/'Data Sheet'!H$17 -> 1 | J5: ='Data Sheet'!I17/'Data Sheet'!I$17 -> 1 | ... L5: ='Data Sheet'!K17/'Data Sheet'!K$17 -> 1
B6: ='Data Sheet'!A18 -> Raw Material Cost | C6: ='Data Sheet'!B18/'Data Sheet'!B$17 -> 0.39099499 | D6: ='Data Sheet'!C18/'Data Sheet'!C$17 -> 0.37950646 | E6: ='Data Sheet'!D18/'Data Sheet'!D$17 -> 0.3904119 | F6: ='Data Sheet'!E18/'Data Sheet'!E$17 -> 0.37433962 | G6: ='Data Sheet'!F18/'Data Sheet'!F$17 -> 0.38610668 | H6: ='Data Sheet'!G18/'Data Sheet'!G$17 -> 0.41511501 | I6: ='Data Sheet'!H18/'Data Sheet'!H$17 -> 0.35460937 | J6: ='Data Sheet'!I18/'Data Sheet'!I$17 -> 0.37332727 | ... L6: ='Data Sheet'!K18/'Data Sheet'!K$17 -> 0.42547479
B7: ='Data Sheet'!A19 -> Change in Inventory | C7: ='Data Sheet'!B19/'Data Sheet'!B$17 -> -0.008044086 | D7: ='Data Sheet'!C19/'Data Sheet'!C$17 -> -0.018880942 | E7: ='Data Sheet'!D19/'Data Sheet'!D$17 -> 0.040410983 | F7: ='Data Sheet'!E19/'Data Sheet'!E$17 -> -0.00080576673 | G7: ='Data Sheet'!F19/'Data Sheet'!F$17 -> 0.00061337363 | H7: ='Data Sheet'!G19/'Data Sheet'!G$17 -> 0.0040427231 | I7: ='Data Sheet'!H19/'Data Sheet'!H$17 -> -0.009704584 | J7: ='Data Sheet'!I19/'Data Sheet'!I$17 -> 0.031144023 | ... L7: ='Data Sheet'!K19/'Data Sheet'!K$17 -> -0.019240455
B8: ='Data Sheet'!A20 -> Power and Fuel | C8: ='Data Sheet'!B20/'Data Sheet'!B$17 -> 0.049069512 | D8: ='Data Sheet'!C20/'Data Sheet'!C$17 -> 0.048976646 | E8: ='Data Sheet'!D20/'Data Sheet'!D$17 -> 0.046490267 | F8: ='Data Sheet'!E20/'Data Sheet'!E$17 -> 0.036028101 | G8: ='Data Sheet'!F20/'Data Sheet'!F$17 -> 0.033719757 | H8: ='Data Sheet'!G20/'Data Sheet'!G$17 -> 0.03804926 | I8: ='Data Sheet'!H20/'Data Sheet'!H$17 -> 0.0370358 | J8: ='Data Sheet'!I20/'Data Sheet'!I$17 -> 0.032908335 | ... L8: ='Data Sheet'!K20/'Data Sheet'!K$17 -> 0.043949102
B9: ='Data Sheet'!A21 -> Other Mfr. Exp | C9: ='Data Sheet'!B21/'Data Sheet'!B$17 -> 0.14602104 | D9: ='Data Sheet'!C21/'Data Sheet'!C$17 -> 0.15725321 | E9: ='Data Sheet'!D21/'Data Sheet'!D$17 -> 0.14068764 | F9: ='Data Sheet'!E21/'Data Sheet'!E$17 -> 0.13757337 | G9: ='Data Sheet'!F21/'Data Sheet'!F$17 -> 0.13150512 | H9: ='Data Sheet'!G21/'Data Sheet'!G$17 -> 0.15186096 | I9: ='Data Sheet'!H21/'Data Sheet'!H$17 -> 0.13272996 | J9: ='Data Sheet'!I21/'Data Sheet'!I$17 -> 0.11819215 | ... L9: ='Data Sheet'!K21/'Data Sheet'!K$17 -> 0.14950903
B10: ='Data Sheet'!A22 -> Employee Cost | C10: ='Data Sheet'!B22/'Data Sheet'!B$17 -> 0.15345568 | D10: ='Data Sheet'!C22/'Data Sheet'!C$17 -> 0.17248741 | E10: ='Data Sheet'!D22/'Data Sheet'!D$17 -> 0.15362697 | F10: ='Data Sheet'!E22/'Data Sheet'!E$17 -> 0.13856096 | G10: ='Data Sheet'!F22/'Data Sheet'!F$17 -> 0.11897628 | H10: ='Data Sheet'!G22/'Data Sheet'!G$17 -> 0.13255632 | I10: ='Data Sheet'!H22/'Data Sheet'!H$17 -> 0.12738037 | J10: ='Data Sheet'!I22/'Data Sheet'!I$17 -> 0.095360629 | ... L10: ='Data Sheet'!K22/'Data Sheet'!K$17 -> 0.10694897
B11: ='Data Sheet'!A23 -> Selling and admin | C11: ='Data Sheet'!B23/'Data Sheet'!B$17 -> 0.11374871 | D11: ='Data Sheet'!C23/'Data Sheet'!C$17 -> 0.12659692 | E11: ='Data Sheet'!D23/'Data Sheet'!D$17 -> 0.12263928 | F11: ='Data Sheet'!E23/'Data Sheet'!E$17 -> 0.11703025 | G11: ='Data Sheet'!F23/'Data Sheet'!F$17 -> 0.10729529 | H11: ='Data Sheet'!G23/'Data Sheet'!G$17 -> 0.11156804 | I11: ='Data Sheet'!H23/'Data Sheet'!H$17 -> 0.10828253 | J11: ='Data Sheet'!I23/'Data Sheet'!I$17 -> 0.11250108 | ... L11: ='Data Sheet'!K23/'Data Sheet'!K$17 -> 0.11849368
B12: ='Data Sheet'!A24 -> Other Expenses | C12: ='Data Sheet'!B24/'Data Sheet'!B$17 -> 0.11423021 | D12: ='Data Sheet'!C24/'Data Sheet'!C$17 -> 0.10243033 | E12: ='Data Sheet'!D24/'Data Sheet'!D$17 -> 0.069513983 | F12: ='Data Sheet'!E24/'Data Sheet'!E$17 -> 0.021760489 | G12: ='Data Sheet'!F24/'Data Sheet'!F$17 -> 0.037062329 | H12: ='Data Sheet'!G24/'Data Sheet'!G$17 -> 0.029993424 | I12: ='Data Sheet'!H24/'Data Sheet'!H$17 -> 0.035085312 | J12: ='Data Sheet'!I24/'Data Sheet'!I$17 -> 0.038606296 | ... L12: ='Data Sheet'!K24/'Data Sheet'!K$17 -> 0.039303876
B13: ='Data Sheet'!A25 -> Other Income | C13: ='Data Sheet'!B25/'Data Sheet'!B$17 -> 0.042969317 | D13: ='Data Sheet'!C25/'Data Sheet'!C$17 -> 0.10146519 | E13: ='Data Sheet'!D25/'Data Sheet'!D$17 -> -0.033741136 | F13: ='Data Sheet'!E25/'Data Sheet'!E$17 -> 0.0884259 | G13: ='Data Sheet'!F25/'Data Sheet'!F$17 -> 0.0096677857 | H13: ='Data Sheet'!G25/'Data Sheet'!G$17 -> -0.020624368 | I13: ='Data Sheet'!H25/'Data Sheet'!H$17 -> 0.0011502668 | J13: ='Data Sheet'!I25/'Data Sheet'!I$17 -> 0.0053287196 | ... L13: ='Data Sheet'!K25/'Data Sheet'!K$17 -> -0.02620417
B14: ='Data Sheet'!A26 -> Depreciation | C14: ='Data Sheet'!B26/'Data Sheet'!B$17 -> 0.042605312 | D14: ='Data Sheet'!C26/'Data Sheet'!C$17 -> 0.052041039 | E14: ='Data Sheet'!D26/'Data Sheet'!D$17 -> 0.050515666 | F14: ='Data Sheet'!E26/'Data Sheet'!E$17 -> 0.046586153 | G14: ='Data Sheet'!F26/'Data Sheet'!F$17 -> 0.046564832 | H14: ='Data Sheet'!G26/'Data Sheet'!G$17 -> 0.060369992 | I14: ='Data Sheet'!H26/'Data Sheet'!H$17 -> 0.059078591 | J14: ='Data Sheet'!I26/'Data Sheet'!I$17 -> 0.03730489 | ... L14: ='Data Sheet'!K26/'Data Sheet'!K$17 -> 0.043121379
B15: ='Data Sheet'!A27 -> Interest | C15: ='Data Sheet'!B27/'Data Sheet'!B$17 -> 0.034749967 | D15: ='Data Sheet'!C27/'Data Sheet'!C$17 -> 0.041400692 | E15: ='Data Sheet'!D27/'Data Sheet'!D$17 -> 0.045166752 | F15: ='Data Sheet'!E27/'Data Sheet'!E$17 -> 0.044257859 | G15: ='Data Sheet'!F27/'Data Sheet'!F$17 -> 0.048583428 | H15: ='Data Sheet'!G27/'Data Sheet'!G$17 -> 0.053880993 | I15: ='Data Sheet'!H27/'Data Sheet'!H$17 -> 0.048669183 | J15: ='Data Sheet'!I27/'Data Sheet'!I$17 -> 0.022389812 | ... L15: ='Data Sheet'!K27/'Data Sheet'!K$17 -> 0.032759717
B16: ='Data Sheet'!A28 -> Profit before tax | C16: ='Data Sheet'!B28/'Data Sheet'!B$17 -> -0.0099501999 | D16: ='Data Sheet'!C28/'Data Sheet'!C$17 -> 0.0018915366 | E16: ='Data Sheet'!D28/'Data Sheet'!D$17 -> -0.012382611 | F16: ='Data Sheet'!E28/'Data Sheet'!E$17 -> 0.17148332 | G16: ='Data Sheet'!F28/'Data Sheet'!F$17 -> 0.10046744 | H16: ='Data Sheet'!G28/'Data Sheet'!G$17 -> -0.0099756359 | I16: ='Data Sheet'!H28/'Data Sheet'!H$17 -> 0.088574571 | J16: ='Data Sheet'!I28/'Data Sheet'!I$17 -> 0.20588228 | ... L16: ='Data Sheet'!K28/'Data Sheet'!K$17 -> -0.0050051756
... B18: ='Data Sheet'!A30 -> Net profit | C18: ='Data Sheet'!B30/'Data Sheet'!B$17 -> -0.028139176 | D18: ='Data Sheet'!C30/'Data Sheet'!C$17 -> -0.0037540436 | E18: ='Data Sheet'!D30/'Data Sheet'!D$17 -> -0.037763329 | F18: ='Data Sheet'!E30/'Data Sheet'!E$17 -> 0.10900147 | G18: ='Data Sheet'!F30/'Data Sheet'!F$17 -> 0.064808749 | H18: ='Data Sheet'!G30/'Data Sheet'!G$17 -> 0.011132723 | I18: ='Data Sheet'!H30/'Data Sheet'!H$17 -> 0.047923857 | J18: ='Data Sheet'!I30/'Data Sheet'!I$17 -> 0.16459283 | ... L18: ='Data Sheet'!K30/'Data Sheet'!K$17 -> -0.019363027
B20: ="Common Size Balance Sheet-"&'Data Sheet'!B1 -> Common Size Balance Sheet-TATA STEEL LTD
B22: Total Liabilites
B23: ='Data Sheet'!A57 -> Equity Share Capital | C23: ='Data Sheet'!B57/'Data Sheet'!B$61 -> 0.0061052999 | D23: ='Data Sheet'!C57/'Data Sheet'!C$61 -> 0.005485177 | E23: ='Data Sheet'!D57/'Data Sheet'!D$61 -> 0.0056262963 | F23: ='Data Sheet'!E57/'Data Sheet'!E$61 -> 0.0054855225 | G23: ='Data Sheet'!F57/'Data Sheet'!F$61 -> 0.0049186883 | H23: ='Data Sheet'!G57/'Data Sheet'!G$61 -> 0.0045954407 | I23: ='Data Sheet'!H57/'Data Sheet'!H$61 -> 0.0049100651 | J23: ='Data Sheet'!I57/'Data Sheet'!I$61 -> 0.0043240662 | ... L23: ='Data Sheet'!K57/'Data Sheet'!K$61 -> 0.0046319438
B24: ='Data Sheet'!A58 -> Reserves | C24: ='Data Sheet'!B58/'Data Sheet'!B$61 -> 0.19092536 | D24: ='Data Sheet'!C58/'Data Sheet'!C$61 -> 0.24175342 | E24: ='Data Sheet'!D58/'Data Sheet'!D$61 -> 0.21368305 | F24: ='Data Sheet'!E58/'Data Sheet'!E$61 -> 0.28614918 | G24: ='Data Sheet'!F58/'Data Sheet'!F$61 -> 0.29118503 | H24: ='Data Sheet'!G58/'Data Sheet'!G$61 -> 0.29071485 | I24: ='Data Sheet'!H58/'Data Sheet'!H$61 -> 0.29946047 | J24: ='Data Sheet'!I58/'Data Sheet'!I$61 -> 0.4008964 | ... L24: ='Data Sheet'!K58/'Data Sheet'!K$61 -> 0.33711152
B25: ='Data Sheet'!A59 -> Borrowings | C25: ='Data Sheet'!B59/'Data Sheet'!B$61 -> 0.50720662 | D25: ='Data Sheet'!C59/'Data Sheet'!C$61 -> 0.46350679 | E25: ='Data Sheet'!D59/'Data Sheet'!D$61 -> 0.48139029 | F25: ='Data Sheet'!E59/'Data Sheet'!E$61 -> 0.44148191 | G25: ='Data Sheet'!F59/'Data Sheet'!F$61 -> 0.43310878 | H25: ='Data Sheet'!G59/'Data Sheet'!G$61 -> 0.46690191 | I25: ='Data Sheet'!H59/'Data Sheet'!H$61 -> 0.36284574 | J25: ='Data Sheet'!I59/'Data Sheet'!I$61 -> 0.26754799 | ... L25: ='Data Sheet'!K59/'Data Sheet'!K$61 -> 0.32334981
B26: ='Data Sheet'!A60 -> Other Liabilities | C26: ='Data Sheet'!B60/'Data Sheet'!B$61 -> 0.29576272 | D26: ='Data Sheet'!C60/'Data Sheet'!C$61 -> 0.28925461 | E26: ='Data Sheet'!D60/'Data Sheet'!D$61 -> 0.29930036 | F26: ='Data Sheet'!E60/'Data Sheet'!E$61 -> 0.26688338 | G26: ='Data Sheet'!F60/'Data Sheet'!F$61 -> 0.27078751 | H26: ='Data Sheet'!G60/'Data Sheet'!G$61 -> 0.2377878 | I26: ='Data Sheet'!H60/'Data Sheet'!H$61 -> 0.33278373 | J26: ='Data Sheet'!I60/'Data Sheet'!I$61 -> 0.32723155 | ... L26: ='Data Sheet'!K60/'Data Sheet'!K$61 -> 0.33490672
B28: Total Asset
B29: ='Data Sheet'!A62 -> Net Block | C29: ='Data Sheet'!B62/'Data Sheet'!B$66 -> 0.42800974 | D29: ='Data Sheet'!C62/'Data Sheet'!C$66 -> 0.40817578 | E29: ='Data Sheet'!D62/'Data Sheet'!D$66 -> 0.53353409 | F29: ='Data Sheet'!E62/'Data Sheet'!E$66 -> 0.46044416 | G29: ='Data Sheet'!F62/'Data Sheet'!F$66 -> 0.53460528 | H29: ='Data Sheet'!G62/'Data Sheet'!G$66 -> 0.54004068 | I29: ='Data Sheet'!H62/'Data Sheet'!H$66 -> 0.55666283 | J29: ='Data Sheet'!I62/'Data Sheet'!I$66 -> 0.47194619 | ... L29: ='Data Sheet'!K62/'Data Sheet'!K$66 -> 0.55257154
B30: ='Data Sheet'!A63 -> Capital Work in Progress | C30: ='Data Sheet'!B63/'Data Sheet'!B$66 -> 0.18024163 | D30: ='Data Sheet'!C63/'Data Sheet'!C$66 -> 0.20350112 | E30: ='Data Sheet'!D63/'Data Sheet'!D$66 -> 0.091530129 | F30: ='Data Sheet'!E63/'Data Sheet'!E$66 -> 0.079600612 | G30: ='Data Sheet'!F63/'Data Sheet'!F$66 -> 0.080083063 | H30: ='Data Sheet'!G63/'Data Sheet'!G$66 -> 0.078253658 | I30: ='Data Sheet'!H63/'Data Sheet'!H$66 -> 0.077928183 | J30: ='Data Sheet'!I63/'Data Sheet'!I$66 -> 0.078058989 | ... L30: ='Data Sheet'!K63/'Data Sheet'!K$66 -> 0.12756757
B31: ='Data Sheet'!A64 -> Investments | C31: ='Data Sheet'!B64/'Data Sheet'!B$66 -> 0.021714947 | D31: ='Data Sheet'!C64/'Data Sheet'!C$66 -> 0.060569133 | E31: ='Data Sheet'!D64/'Data Sheet'!D$66 -> 0.072237228 | F31: ='Data Sheet'!E64/'Data Sheet'!E$66 -> 0.085757409 | G31: ='Data Sheet'!F64/'Data Sheet'!F$66 -> 0.024651309 | H31: ='Data Sheet'!G64/'Data Sheet'!G$66 -> 0.025226579 | I31: ='Data Sheet'!H64/'Data Sheet'!H$66 -> 0.043794701 | J31: ='Data Sheet'!I64/'Data Sheet'!I$66 -> 0.046525644 | ... L31: ='Data Sheet'!K64/'Data Sheet'!K$66 -> 0.023235356
B32: ='Data Sheet'!A65 -> Other Assets | C32: ='Data Sheet'!B74/'Data Sheet'!B66 -> 0.07332117 | D32: ='Data Sheet'!C74/'Data Sheet'!C66 -> 0.11142071 | E32: ='Data Sheet'!D74/'Data Sheet'!D66 -> 0.063137408 | F32: ='Data Sheet'!E74/'Data Sheet'!E66 -> 0.14094796 | G32: ='Data Sheet'!F74/'Data Sheet'!F66 -> 0.1595701 | H32: ='Data Sheet'!G74/'Data Sheet'!G66 -> 0.16780352 | I32: ='Data Sheet'!H74/'Data Sheet'!H66 -> 0.12236636 | J32: ='Data Sheet'!I74/'Data Sheet'!I66 -> 0.13093432 | ... L32: ='Data Sheet'!K74/'Data Sheet'!K66 -> 0.058616606
B33: ='Data Sheet'!A67 -> Receivables | C33: ='Data Sheet'!B67/'Data Sheet'!B$66 -> 0.08365237 | D33: ='Data Sheet'!C67/'Data Sheet'!C$66 -> 0.068215444 | E33: ='Data Sheet'!D67/'Data Sheet'!D$66 -> 0.067190471 | F33: ='Data Sheet'!E67/'Data Sheet'!E$66 -> 0.059483484 | G33: ='Data Sheet'!F67/'Data Sheet'!F$66 -> 0.050740325 | H33: ='Data Sheet'!G67/'Data Sheet'!G$66 -> 0.031647352 | I33: ='Data Sheet'!H67/'Data Sheet'!H$66 -> 0.039112261 | J33: ='Data Sheet'!I67/'Data Sheet'!I$66 -> 0.043362218 | ... L33: ='Data Sheet'!K67/'Data Sheet'!K$66 -> 0.023257487
B34: ='Data Sheet'!A68 -> Inventory | C34: ='Data Sheet'!B68/'Data Sheet'!B$61 -> 0.15806688 | D34: ='Data Sheet'!C68/'Data Sheet'!C$61 -> 0.11314382 | E34: ='Data Sheet'!D68/'Data Sheet'!D$61 -> 0.14383414 | F34: ='Data Sheet'!E68/'Data Sheet'!E$61 -> 0.13573567 | G34: ='Data Sheet'!F68/'Data Sheet'!F$61 -> 0.13599533 | H34: ='Data Sheet'!G68/'Data Sheet'!G$61 -> 0.1246993 | I34: ='Data Sheet'!H68/'Data Sheet'!H$61 -> 0.13642938 | J34: ='Data Sheet'!I68/'Data Sheet'!I$61 -> 0.17287763 | ... L34: ='Data Sheet'!K68/'Data Sheet'!K$61 -> 0.18252968
B35: ='Data Sheet'!A69 -> Cash & Bank | C35: ='Data Sheet'!B69/'Data Sheet'!B$61 -> 0.054993266 | D35: ='Data Sheet'!C69/'Data Sheet'!C$61 -> 0.034973996 | E35: ='Data Sheet'!D69/'Data Sheet'!D$61 -> 0.028536533 | F35: ='Data Sheet'!E69/'Data Sheet'!E$61 -> 0.038030704 | G35: ='Data Sheet'!F69/'Data Sheet'!F$61 -> 0.014354602 | H35: ='Data Sheet'!G69/'Data Sheet'!G$61 -> 0.032328912 | I35: ='Data Sheet'!H69/'Data Sheet'!H$61 -> 0.023706282 | J35: ='Data Sheet'!I69/'Data Sheet'!I$61 -> 0.056295007 | ... L35: ='Data Sheet'!K69/'Data Sheet'!K$61 -> 0.032221759

Sheet Forcasting
B2: ='Data Sheet'!B1& "-" &'Data Sheet'!A17 -> TATA STEEL LTD-Sales | G2: ='Data Sheet'!B1&"-"&'Histoirical FC'!B18 -> TATA STEEL LTD-Operating Income(EBITDA) | L2: ='Data Sheet'!B1&"-"&'Histoirical FC'!B41 -> TATA STEEL LTD-EPS
B3: Weight | C3: Year | D3: Sales | E3: Sales Growth | G3: Weight | H3: Year | I3: Ebitda | J3: Ebitda Growth | L3: Weight | M3: Year | N3: EPS | O3: EPS Growth
B4: 1 | C4: 2015 | D4: {=TRANSPOSE('Data Sheet'!B17:K17)} -> 139503.73 | G4: 1 | H4: 2015 | I4: {=TRANSPOSE('Histoirical FC'!C18:L18)} -> 3408.88 | L4: 1 | M4: 2015 | N4: {=TRANSPOSE('Histoirical FC'!C41:M41)} -> -8.8316202
B5: =B4+1 -> 2 | C5: =C4+1 -> 2016 | D5: 101964.72 | E5: =D5/D4-1 -> -0.26908965 | G5: =G4+1 -> 2 | H5: =H4+1 -> 2016 | I5: -625.24 | J5: =I5/I4-1 -> -1.1834151 | L5: =L4+1 -> 2 | M5: =M4+1 -> 2016 | N5: -9.6243276 | O5: =N5/N4-1 -> 0.089757866
B6: =B5+1 -> 3 | C6: =C5+1 -> 2017 | D6: 112299.42 | E6: =D6/D5-1 -> 0.10135565 | G6: =G5+1 -> 3 | H6: =H5+1 -> 2017 | I6: 13143.63 | J6: =I6/I5-1 -> -22.021736 | L6: =L5+1 -> 3 | M6: =M5+1 -> 2017 | N6: -0.33681277 | O6: =N6/N5-1 -> -0.96500402
B7: =B6+1 -> 4 | C7: =C6+1 -> 2018 | D7: 123249.07 | E7: =D7/D6-1 -> 0.097504065 | G7: =G6+1 -> 4 | H7: =H6+1 -> 2018 | I7: 21433.19 | J7: =I7/I6-1 -> 0.6306903 | L7: =L6+1 -> 4 | M7: =M6+1 -> 2018 | N7: 6.0759357 | O7: =N7/N6-1 -> -19.039505
B8: =B7+1 -> 5 | C8: =C7+1 -> 2019 | D8: 157668.99 | E8: =D8/D7-1 -> 0.27927124 | G8: =G7+1 -> 5 | H8: =H7+1 -> 2019 | I8: 29318.22 | J8: =I8/I7-1 -> 0.36788877 | L8: =L7+1 -> 5 | M8: =M7+1 -> 2019 | N8: 6.7447203 | O8: =N8/N7-1 -> 0.11007106
B9: =B8+1 -> 6 | C9: =C8+1 -> 2020 | D9: 139816.65 | E9: =D9/D8-1 -> -0.1132267 | G9: =G8+1 -> 6 | H9: =H8+1 -> 2020 | I9: 17463.06 | J9: =I9/I8-1 -> -0.40436152 | L9: =L8+1 -> 6 | M9: =M8+1 -> 2020 | N9: 3.6017009 | O9: =N9/N8-1 -> -0.465997
B10: =B9+1 -> 7 | C10: =C9+1 -> 2021 | D10: 156294.18 | E10: =D10/D9-1 -> 0.11785099 | G10: =G9+1 -> 7 | H10: =H9+1 -> 2021 | I10: 30504.26 | J10: =I10/I9-1 -> 0.74678779 | L10: =L9+1 -> 7 | M10: =M9+1 -> 2021 | N10: 6.6940305 | O10: =N10/N9-1 -> 0.85857482
B11: =B10+1 -> 8 | C11: =C10+1 -> 2022 | D11: 243959.17 | E11: =D11/D10-1 -> 0.56089734 | G11: =G10+1 -> 8 | H11: =H10+1 -> 2022 | I11: 63489.95 | J11: =I11/I10-1 -> 1.081347 | L11: =L10+1 -> 8 | M11: =M10+1 -> 2022 | N11: 33.119897 | O11: =N11/N10-1 -> 3.9476764
B12: =B11+1 -> 9 | C12: =C11+1 -> 2023 | D12: 243352.69 | E12: =D12/D11-1 -> -0.0024859898 | G12: =G11+1 -> 9 | H12: =H11+1 -> 2023 | I12: 32300.16 | J12: =I12/I11-1 -> -0.49125555 | L12: =L11+1 -> 9 | M12: =M11+1 -> 2023 | N12: 5.3238064 | O12: =N12/N11-1 -> -0.83925655
B13: =B12+1 -> 10 | C13: =C12+1 -> 2024 | D13: 229170.78 | E13: =D13/D12-1 -> -0.058277186 | G13: =G12+1 -> 10 | H13: =H12+1 -> 2024 | I13: 22247.92 | J13: =I13/I12-1 -> -0.31121332 | L13: =L12+1 -> 10 | M13: =M12+1 -> 2024 | N13: 0.8776545 | O13: =N13/N12-1 -> -0.8351453
B14: =B13+1 -> 11 | C14: =C13+1 -> 2025 | D14: =FORECAST(B14,$D$4:$D$13,$B$4:$B$13) -> 249271.31 | E14: =D14/D13-1 -> 0.087709812 | G14: =G13+1 -> 11 | H14: =H13+1 -> 2025 | I14: =FORECAST(G14,$I$4:$I$13,$G$4:$G$13) -> 45505.697 | J14: =I14/I13-1 -> 1.0453911 | L14: =L13+1 -> 11 | M14: =M13+1 -> 2025 | N14: =FORECAST(L14,$N$4:$N$13,$L$4:$L$13) -> 16.298339 | O14: =N14/N13-1 -> 17.570336
B15: =B14+1 -> 12 | C15: =C14+1 -> 2026 | D15: =FORECAST(B15,$D$4:$D$13,$B$4:$B$13) -> 264642.83 | E15: =D15/D14-1 -> 0.061665826 | G15: =G14+1 -> 12 | H15: =H14+1 -> 2026 | I15: =FORECAST(G15,$I$4:$I$13,$G$4:$G$13) -> 49548.841 | J15: =I15/I14-1 -> 0.08884919 | L15: =L14+1 -> 12 | M15: =M14+1 -> 2026 | N15: =FORECAST(L15,$N$4:$N$13,$L$4:$L$13) -> 18.468128 | O15: =N15/N14-1 -> 0.13312947
B16: =B15+1 -> 13 | C16: =C15+1 -> 2027 | D16: =FORECAST(B16,$D$4:$D$13,$B$4:$B$13) -> 280014.35 | E16: =D16/D15-1 -> 0.058084027 | G16: =G15+1 -> 13 | H16: =H15+1 -> 2027 | I16: =FORECAST(G16,$I$4:$I$13,$G$4:$G$13) -> 53591.985 | J16: =I16/I15-1 -> 0.08159917 | L16: =L15+1 -> 13 | M16: =M15+1 -> 2027 | N16: =FORECAST(L16,$N$4:$N$13,$L$4:$L$13) -> 20.637918 | O16: =N16/N15-1 -> 0.11748831
B17: =B16+1 -> 14 | C17: =C16+1 -> 2028 | D17: =FORECAST(B17,$D$4:$D$13,$B$4:$B$13) -> 295385.87 | E17: =D17/D16-1 -> 0.054895477 | G17: =G16+1 -> 14 | H17: =H16+1 -> 2028 | I17: =FORECAST(G17,$I$4:$I$13,$G$4:$G$13) -> 57635.13 | J17: =I17/I16-1 -> 0.075443078 | L17: =L16+1 -> 14 | M17: =M16+1 -> 2028 | N17: =FORECAST(L17,$N$4:$N$13,$L$4:$L$13) -> 22.807707 | O17: =N17/N16-1 -> 0.10513605
B18: =B17+1 -> 15 | C18: =C17+1 -> 2029 | D18: =FORECAST(B18,$D$4:$D$13,$B$4:$B$13) -> 310757.39 | E18: =D18/D17-1 -> 0.052038783 | G18: =G17+1 -> 15 | H18: =H17+1 -> 2029 | I18: =FORECAST(G18,$I$4:$I$13,$G$4:$G$13) -> 61678.274 | J18: =I18/I17-1 -> 0.070150693 | L18: =L17+1 -> 15 | M18: =M17+1 -> 2029 | N18: =FORECAST(L18,$N$4:$N$13,$L$4:$L$13) -> 24.977496 | O18: =N18/N17-1 -> 0.095134037

Sheet DCF>
B2: The Valuation School
B6: Calculation of PV of FCFF | E6: ='Intrinsic Growth'!K2 -> 45382 | F6: =E6+365 -> 45747 | G6: =F6+365 -> 46112 | H6: =G6+365 -> 46477 | I6: =H6+365 -> 46842 | J6: =I6+365 -> 47207
B8: EBIT | E8: ='Histoirical FC'!L24 -> 12365.76 | F8: =E8*(1+$E$18) -> 13659.218 | G8: =F8*(1+$E$18) -> 15087.973 | H8: =G8*(1+$E$18) -> 16666.175 | I8: =H8*(1+$E$18) -> 18409.457 | J8: =I8*(1+$E$18) -> 20335.086
B9: Tax Rate | E9: 0.25 | F9: =E9 -> 0.25 | G9: =F9 -> 0.25 | H9: =G9 -> 0.25 | I9: =H9 -> 0.25 | J9: =I9 -> 0.25
B10: EBIT(1-Tax) | E10: =E8*(1-E9) -> 9274.32 | F10: =F8*(1-F9) -> 10244.414 | G10: =G8*(1-G9) -> 11315.98 | H10: =H8*(1-H9) -> 12499.631 | I10: =I8*(1-I9) -> 13807.092 | J10: =J8*(1-J9) -> 15251.314
B11: Less:Reinvestment Rate | E11: 0.703 | F11: =E11 -> 0.703 | G11: =F11 -> 0.703 | H11: =G11 -> 0.703 | I11: =H11 -> 0.703 | J11: =I11 -> 0.703
B12: Free Cashflow to the Firm | E12: =E10*(1-E11) -> 2754.473 | F12: =F10*(1-F11) -> 3042.5909 | G12: =G10*(1-G11) -> 3360.8459 | H12: =H10*(1-H11) -> 3712.3904 | I12: =I10*(1-I11) -> 4100.7065 | J12: =J10*(1-J11) -> 4529.6403
B13: Mid Year Conversion | F13: 0.5 | G13: =F13+1 -> 1.5 | H13: =G13+1 -> 2.5 | I13: =H13+1 -> 3.5 | J13: =I13+1 -> 4.5
B14: Discounting Factor | F14: =1/(1+$E$20)^F13 -> 0.94660588 | G14: =1/(1+$E$20)^G13 -> 0.8482182 | H14: =1/(1+$E$20)^H13 -> 0.76005668 | I14: =1/(1+$E$20)^I13 -> 0.68105843 | J14: =1/(1+$E$20)^J13 -> 0.61027104
B16: PV of FCFF | F16: =F12*F14 -> 2880.1344 | G16: =G12*G14 -> 2850.7307 | H16: =H12*H14 -> 2821.6271 | I16: =I12*I14 -> 2792.8207 | J16: =J12*J14 -> 2764.3083
B18: Expected Growth rate | E18: 0.1046
B19: Terminal Growth | E19: 0.067
B20: Wacc | E20: =WACC!J42 -> 0.11599335
B22: Calculation of Terminal Value
B24: FCFF(n+1) | D24: =J12*(1+E18) -> 5003.4407
B25: WACC | D25: =E20 -> 0.11599335
B26: Terminal Growth Rate | D26: =E19 -> 0.067
B28: Terminal Value | D28: =D24/(D25-D26) -> 102124.89 | F28: Sensitivity Analysis
F29: =D42 -> 2.8334964 | G29: 0.1 | H29: =D25 -> 0.11599335 | I29: 0.13 | J29: 0.14
B30: Calculation of Equity Value | F30: 0.04 | G30: -6.3249269 | H30: -6.3249269 | I30: -19.913742 | J30: -22.631505
F31: 0.05 | G31: 1.828362 | H31: 1.828362 | I31: -16.516538 | J31: -19.913742
B32: PV of FCFF | D32: =SUM(F16:J16) -> 14109.621 | F32: =D26 -> 0.067 | G32: 1.828362 | H32: 1.828362 | I32: -16.516538 | J32: -19.913742
B33: Terminal Value | D33: =D28*J14 -> 62323.863 | F33: 0.08 | G33: 75.207962 | H33: 75.207962 | I33: 1.828362 | J33: -6.3249269
B34: Operating Asset | D34: =SUM(D32:D33) -> 76433.484 | F34: 0.09 | G34: 197.5073 | H34: 197.5073 | I34: 14.058295 | J34: 1.828362
B36: Add Cash | D36: ='Data Sheet'!K69 -> 8677.72
B37: Less Debt | D37: ='Raw FC'!N7+'Raw FC'!N8 -> 81574
B39: Value of Equity | D39: =D34+D36-D37 -> 3537.204 | E39: (FCFE)
B40: No of Share | D40: ='Data Sheet'!B6 -> 1248.3531
B42: Equity Value Per Share | D42: =D39/D40 -> 2.8334964
B44: Share price | D44: 131
B45: Discount/Premium | D45: =D44/D42 -> 46.232633

Sheet WACC
B2: Weighted Average Cost of Capital
B4: All Fig Are in INR as Stated Below
B6: PeerComs
G7: Debt / | H7: Debt / | I7: Levered | J7: Unlevered
B8: Name of Comps | C8: Country | D8: Total Debt | E8: Toatal Equity | F8: TaxRate 1 | G8: Equity | H8: Capital | I8: Beta 2 | J8: Beta 3
B10: ='Peer Comps'!C4 -> JSW Steel | C10: India | D10: ='Peer Comps'!D4 -> 95258 | E10: ='Peer Comps'!E4 -> 245951.53 | F10: 0.3 | G10: =D10/E10 -> 0.38730395 | H10: =D10/(E10+D10) -> 0.27917743 | I10: 1.09 | J10: =I10/(1+(1-F10*G10)) -> 0.57861498
B11: ='Peer Comps'!C5 -> Tata Steel | C11: India | D11: ='Peer Comps'!D5 -> 99391.76 | E11: ='Peer Comps'!E5 -> 175256.24 | F11: 0.3 | G11: =D11/E11 -> 0.56712252 | H11: =D11/(E11+D11) -> 0.3618878 | I11: =Beta!P6 -> 2.6354669 | J11: =I11/(1+(1-F11*G11)) -> 1.4402535
B12: ='Peer Comps'!C6 -> Jindal Steel | C12: India | D12: ='Peer Comps'!D6 -> 17266.45 | E12: ='Peer Comps'!E6 -> 86717.69 | F12: 0.3 | G12: =D12/E12 -> 0.19911105 | H12: =D12/(E12+D12) -> 0.16604888 | I12: 1.03 | J12: =I12/(1+(1-F12*G12)) -> 0.53085486
B13: ='Peer Comps'!C7 -> Tube Investments | C13: India | D13: ='Peer Comps'!D7 -> 698.92 | E13: ='Peer Comps'!E7 -> 51029.18 | F13: 0.3 | G13: =D13/E13 -> 0.013696477 | H13: =D13/(E13+D13) -> 0.013511418 | I13: 0.61 | J13: =I13/(1+(1-F13*G13)) -> 0.3056279
B14: ='Peer Comps'!C8 -> S A I L | C14: India | D14: ='Peer Comps'!D8 -> 41265.03 | E14: ='Peer Comps'!E8 -> 46509.71 | F14: 0.3 | G14: =D14/E14 -> 0.88723473 | H14: =D14/(E14+D14) -> 0.47012421 | I14: 1.17 | J14: =I14/(1+(1-F14*G14)) -> 0.67480681
E16: Average | F16: =AVERAGE(F10:F14) -> 0.3 | G16: =AVERAGE(G10:G14) -> 0.41089374 | H16: =AVERAGE(H10:H14) -> 0.25814995 | I16: =MEDIAN(I9:I13) -> 1.06 | J16: =MEDIAN(J9:J13) -> 0.55473492
E17: Median | F17: =MEDIAN(F10:F14) -> 0.3 | G17: =MEDIAN(G10:G14) -> 0.38730395 | H17: =MEDIAN(H10:H14) -> 0.27917743 | I17: =MEDIAN(I10:I14) -> 1.09 | J17: =MEDIAN(J10:J14) -> 0.57861498
B20: Cost of Debt | G20: Cost of Equity
B22: Pre Cost of Debt | C22: int/debt) | E22: ='Data Sheet'!K27/WACC!D11 -> 0.075535135 | G22: RisK Free Rate | J22: 0.0646 | K22: 10 YEARS GOVERNMENT BOND
B23: Tax Rate | E23: 0.3 | G23: Equity Risk Premium | J23: =RM!G8-WACC!J22 -> 0.101948 | K23: prime investors sae yearly return for nifty
B24: Post Cost of Debt | E24: =E22*(1-E23) -> 0.052874594 | G24: Levered Beta 4 | J24: =J33 -> 0.71955802
G25: Cost Of Equity | J25: =J22+J23*J24 -> 0.1379575
B28: Capital Structure | G28: Levered Beta
D29: Current | E29: Target
B30: Debt | C30: =D11 -> 99391.76 | D30: =C30/$C$32 -> 0.3618878 | E30: =H16 -> 0.25814995 | G30: Comps Median Unleverd Beta | J30: =J17 -> 0.57861498
B31: Market Capitalization | C31: =E11 -> 175256.24 | D31: =C31/$C$32 -> 0.6381122 | E31: =E32-E30 -> 0.74185005 | G31: Target Debt / Equity | J31: =E34 -> 0.3479813 | K31: BETA ALWAYS BE TAKEN OF THESE MOSTOF THE TIME COMPARABEL COMPS KA BETA BOLTA HAI NIKAL NAE
B32: Total Capital | C32: =SUM(C30:C31) -> 274648 | D32: =C32/$C$32 -> 1 | E32: =D32 -> 1 | G32: Tax Rate | J32: =F14 -> 0.3
G33: Levered Beta | J33: =J30*(1+(1-J32)*J31) -> 0.71955802
B34: Debt/Equity | D34: =D30/D31 -> 0.56712252 | E34: =E30/E31 -> 0.3479813
G35: Weighted Average Cost of Capital
B36: Notes
A37: 1 | B37: Tax Rate Is Considerd as Marginal Tax Rate of Country . | G37: Cost of Equity | J37: =J25 -> 0.1379575
A38: 2 | B38: Levered Beta is based in on 5 year monthly Data. | G38: Weight of Equity | J38: =E31 -> 0.74185005
A39: 3 | B39: Unlevered Beta= Levered Beta/(1+(1-Tax Rate)*Debt/ Equity)
A40: 4 | B40: Levered Beta= Unlevered Beta*(1+(1-Tax Rate)*Debt/ Equity) | G40: Cost of Debt | J40: =E24 -> 0.052874594
G41: Weight of Debt | J41: =E30 -> 0.25814995
G42: WACC | J42: =(J37*J38)+(J40*J41) -> 0.11599335

Sheet Relative Valuation
B2: Amount are In Crores
B3: Comparabel Companies Valuation
D5: Market Data | J5: Financial | N5: Valuation
B6: Companies | C6: Ticker | D6: Share Price | E6: Outstanding Share | F6: Equity Value | G6: Net Debt | H6: Enterprise Value | J6: Revenue | K6: EBITDA | L6: Income | N6: Ev/Revenue | O6: EV/Ebitda | P6: P/E
B8: ='Rough Data Relative valuation'!C4 -> Tata Steel | D8: ='Rough Data Relative valuation'!D4 -> 130.2 | E8: ='Rough Data Relative valuation'!M3 -> 244.55 | F8: =D8*E8 -> 31840.41 | G8: ='Rough Data Relative valuation'!L4 -> 90714.04 | H8: =F8+G8 -> 122554.45 | J8: ='Rough Data Relative valuation'!G4 -> 221011.71 | K8: ='Rough Data Relative valuation'!J4 -> 26734.912 | L8: ='Rough Data Relative valuation'!N4 -> 2831.41 | N8: =H8/J8 -> 0.55451564 | O8: =H8/K8 -> 4.5840604 | P8: =F8/L8 -> 11.245425
B9: ='Rough Data Relative valuation'!C3 -> JSW Steel | D9: ='Rough Data Relative valuation'!D3 -> 956.2 | E9: ='Rough Data Relative valuation'!M3 -> 244.55 | F9: =D9*E9 -> 233838.71 | G9: ='Rough Data Relative valuation'!L3 -> 82910 | H9: =F9+G9 -> 316748.71 | J9: ='Rough Data Relative valuation'!G3 -> 170274 | K9: ='Rough Data Relative valuation'!J3 -> 23188.736 | L9: ='Rough Data Relative valuation'!N3 -> 3498.48 | N9: =H9/J9 -> 1.8602295 | O9: =H9/K9 -> 13.659593 | P9: =F9/L9 -> 66.840088
B10: ='Rough Data Relative valuation'!C5 -> Jindal Steel | D10: ='Rough Data Relative valuation'!D5 -> 801.35 | E10: ='Rough Data Relative valuation'!M5 -> 102.01 | F10: =D10*E10 -> 81745.714 | G10: ='Rough Data Relative valuation'!L5 -> 13242.32 | H10: =F10+G10 -> 94988.034 | J10: ='Rough Data Relative valuation'!G5 -> 50068.78 | K10: ='Rough Data Relative valuation'!J5 -> 9799.463 | L10: ='Rough Data Relative valuation'!N5 -> 4082.33 | N10: =H10/J10 -> 1.8971509 | O10: =H10/K10 -> 9.6931876 | P10: =F10/L10 -> 20.024279
B11: ='Rough Data Relative valuation'!C6 -> Tube Investments | D11: ='Rough Data Relative valuation'!D6 -> 2570 | E11: ='Rough Data Relative valuation'!M6 -> 19.35 | F11: =D11*E11 -> 49729.5 | G11: ='Rough Data Relative valuation'!L6 -> -528.48 | H11: =F11+G11 -> 49201.02 | J11: ='Rough Data Relative valuation'!G6 -> 18804.8 | K11: ='Rough Data Relative valuation'!J6 -> 2256.1681 | L11: ='Rough Data Relative valuation'!N6 -> 819.65 | N11: =H11/J11 -> 2.6164075 | O11: =H11/K11 -> 21.807338 | P11: =F11/L11 -> 60.671628
B12: ='Rough Data Relative valuation'!C7 -> S A I L | D12: ='Rough Data Relative valuation'!D7 -> 104.8 | E12: ='Rough Data Relative valuation'!M7 -> 413.05 | F12: =D12*E12 -> 43287.64 | G12: ='Rough Data Relative valuation'!L7 -> 40592.08 | H12: =F12+G12 -> 83879.72 | J12: ='Rough Data Relative valuation'!G7 -> 101121.44 | K12: ='Rough Data Relative valuation'!J7 -> 12076.503 | L12: ='Rough Data Relative valuation'!N7 -> 2921.77 | N12: =H12/J12 -> 0.82949491 | O12: =H12/K12 -> 6.9456962 | P12: =F12/L12 -> 14.815554
B13: ='Rough Data Relative valuation'!C8 -> Jindal Stain. | D13: ='Rough Data Relative valuation'!D8 -> 524.1 | E13: ='Rough Data Relative valuation'!M8 -> 82.38 | F13: =D13*E13 -> 43175.358 | G13: ='Rough Data Relative valuation'!L8 -> 4484.97 | H13: =F13+G13 -> 47660.328 | J13: ='Rough Data Relative valuation'!G8 -> 38567.91 | K13: ='Rough Data Relative valuation'!J8 -> 4875.2256 | L13: ='Rough Data Relative valuation'!N8 -> 2411.59 | N13: =H13/J13 -> 1.2357509 | O13: =H13/K13 -> 9.7760251 | P13: =F13/L13 -> 17.903275
B14: ='Rough Data Relative valuation'!C9 -> APL Apollo Tubes | D14: ='Rough Data Relative valuation'!D9 -> 1467.55 | E14: ='Rough Data Relative valuation'!M9 -> 27.75 | F14: =D14*E14 -> 40724.512 | G14: ='Rough Data Relative valuation'!L9 -> 674.99 | H14: =F14+G14 -> 41399.502 | J14: ='Rough Data Relative valuation'!G9 -> 19946.68 | K14: ='Rough Data Relative valuation'!J9 -> 1145.4212 | L14: ='Rough Data Relative valuation'!N9 -> 634.39 | N14: =H14/J14 -> 2.0755084 | O14: =H14/K14 -> 36.143476 | P14: =F14/L14 -> 64.194758
G15: debt-cash
B17: High | N17: =MAX(N8:N14) -> 2.6164075 | O17: =MAX(O8:O14) -> 36.143476 | P17: =MAX(P8:P14) -> 66.840088
B18: 75th Percentile | N18: =QUARTILE(N8:N14,3) -> 1.9863297 | O18: =QUARTILE(O8:O14,3) -> 17.733466 | P18: =QUARTILE(P8:P14,3) -> 62.433193
B19: Average | N19: =AVERAGE(N8:N14) -> 1.581294 | O19: =AVERAGE(O8:O14) -> 14.658482 | P19: =AVERAGE(P8:P14) -> 36.527858
B20: Median | N20: =MEDIAN(N8:N14) -> 1.8602295 | O20: =MEDIAN(O8:O14) -> 9.7760251 | P20: =MEDIAN(P8:P14) -> 20.024279
B21: 25th Percentile | N21: =QUARTILE(N8:N14,1) -> 1.0326229 | O21: =QUARTILE(O8:O14,1) -> 8.3194419 | P21: =QUARTILE(P8:P14,1) -> 16.359414
B22: Low | N22: =MIN(N8:N14) -> 0.55451564 | O22: =MIN(O8:O14) -> 4.5840604 | P22: =MIN(P8:P14) -> 11.245425
B24: Tata Stell Comparabel valuation | N24: =N6 -> Ev/Revenue | O24: =O6 -> EV/Ebitda | P24: =P6 -> P/E
B26: Implied Enterprise Value | N26: =J8*N20 -> 411132.49 | O26: =K8*O20 -> 261361.17 | P26: =P27+P28 -> 147410.98
B27: Net Debt | N27: =$G$8 -> 90714.04 | O27: =$G$8 -> 90714.04 | P27: =$G$8 -> 90714.04
B28: Implied Market Value | N28: =N26-N27 -> 320418.45 | O28: =O26-O27 -> 170647.13 | P28: =P20*L8 -> 56696.943
B29: Shares Outstanding | N29: =$E$8 -> 244.55 | O29: =$E$8 -> 244.55 | P29: =$E$8 -> 244.55
B31: Implied Value Per Share | N31: =N28/N29 -> 1310.237 | O31: =O28/O29 -> 697.80057 | P31: =P28/P29 -> 231.84193
B32: Source:The Valuation School.Screener.in
N33: =IF(N31>$D$8,"Undervalued","Overvalued") -> Undervalued | O33: =IF(O31>$D$8,"Undervalued","Overvalued") -> Undervalued | P33: =IF(P31>$D$8,"Undervalued","Overvalued") -> Undervalued

Sheet Football Field Analysis
B2: Football Field Analysis
K5: Football Field Analysis - Data
L6: OpenLow | M6: Low | N6: OpenHigh | O6: High
K7: Comps | L7: =M7 -> 231.84193 | M7: ='Relative Valuation'!P31 -> 231.84193 | N7: =O7 -> 1310.237 | O7: ='Relative Valuation'!N31 -> 1310.237
K8: DCF Bear | L8: =M8 -> -22.631505 | M8: ='DCF>'!J30 -> -22.631505 | N8: =O8 -> 1.828362 | O8: ='DCF>'!J34 -> 1.828362
K9: DCF Base | L9: =M9 -> -6.3249269 | M9: ='DCF>'!H30 -> -6.3249269 | N9: =O9 -> 197.5073 | O9: ='DCF>'!H34 -> 197.5073
K10: DCF Bull | L10: =M10 -> -6.3249269 | M10: ='DCF>'!G30 -> -6.3249269 | N10: =O10 -> 197.5073 | O10: ='DCF>'!G34 -> 197.5073
K11: 52W H/L | L11: =M11 -> 122.6 | M11: 122.6 | N11: =O11 -> 184.6 | O11: 184.6

Sheet Intrinsic Growth
B2: Calculation of ROIC | G2: ='Data Sheet'!$G$16 -> 43921 | H2: ='Data Sheet'!$H$16 -> 44286 | I2: ='Data Sheet'!$I$16 -> 44651 | J2: ='Data Sheet'!$J$16 -> 45016 | K2: ='Data Sheet'!$K$16 -> 45382
B4: Current Asset
B5: ='Raw FC'!B38 -> Inventories | G5: ='Raw FC'!J38 -> 31069 | H5: ='Raw FC'!K38 -> 33276 | I5: ='Raw FC'!L38 -> 48824 | J5: ='Raw FC'!M38 -> 54415 | K5: ='Raw FC'!N38 -> 49158
B6: ='Raw FC'!B39 -> Trade receivables - | G6: ='Raw FC'!J39 -> 7885 | H6: ='Raw FC'!K39 -> 9540 | I6: ='Raw FC'!L39 -> 12246 | J6: ='Raw FC'!M39 -> 8257 | K6: ='Raw FC'!N39 -> 6264
B7: ='Raw FC'!B41 -> Loans n Advances | G7: ='Raw FC'!J41 -> 195 | H7: ='Raw FC'!K41 -> 914 | I7: ='Raw FC'!L41 -> -158 | J7: ='Raw FC'!M41 -> -90 | K7: ='Raw FC'!N41 -> -56
B8: ='Raw FC'!B42 -> Other asset items | G8: ='Raw FC'!J42 -> 41613 | H8: ='Raw FC'!K42 -> 28932 | I8: ='Raw FC'!L42 -> 37137 | J8: ='Raw FC'!M42 -> 23211 | K8: ='Raw FC'!N42 -> 15842
B9: Total Current Asset | G9: =SUM(G5:G8) -> 80762 | H9: =SUM(H5:H8) -> 72662 | I9: =SUM(I5:I8) -> 98049 | J9: =SUM(J5:J8) -> 85793 | K9: =SUM(K5:K8) -> 71208
B11: Currrent Liabilites
B12: ='Raw FC'!B13 -> Non controlling int | G12: ='Raw FC'!J13 -> 2587 | H12: ='Raw FC'!K13 -> 3270 | I12: ='Raw FC'!L13 -> 2655 | J12: ='Raw FC'!M13 -> 2093 | K12: ='Raw FC'!N13 -> 397
B13: ='Raw FC'!B14 -> Trade Payables | G13: ='Raw FC'!J14 -> 21381 | H13: ='Raw FC'!K14 -> 25967 | I13: ='Raw FC'!L14 -> 36765 | J13: ='Raw FC'!M14 -> 37833 | K13: ='Raw FC'!N14 -> 35435
B14: ='Raw FC'!B15 -> Advance from Customers | G14: ='Raw FC'!J15 -> 869 | H14: ='Raw FC'!K15 -> 2399 | I14: ='Raw FC'!L15 -> 3253 | J14: ='Raw FC'!M15 -> 3394 | K14: ='Raw FC'!N15 -> 2773
B15: ='Raw FC'!B16 -> Other liability items | G15: ='Raw FC'!J16 -> 34408 | H15: ='Raw FC'!K16 -> 49533 | I15: ='Raw FC'!L16 -> 49744 | J15: ='Raw FC'!M16 -> 54101 | K15: ='Raw FC'!N16 -> 51590
B16: Total Current Liabilites | G16: =SUM(G12:G15) -> 59245 | H16: =SUM(H12:H15) -> 81169 | I16: =SUM(I12:I15) -> 92417 | J16: =SUM(J12:J15) -> 97421 | K16: =SUM(K12:K15) -> 90195
A18: # | B18: Net Working Capital | G18: =G9-G16 -> 21517 | H18: =H9-H16 -> -8507 | I18: =I9-I16 -> 5632 | J18: =J9-J16 -> -11628 | K18: =K9-K16 -> -18987
B20: Non Current Asset
B21: ='Raw FC'!B21 -> Land | G21: ='Raw FC'!J21 -> 19853 | H21: ='Raw FC'!K21 -> 20656 | I21: ='Raw FC'!L21 -> 20770 | J21: ='Raw FC'!M21 -> 21701 | K21: ='Raw FC'!N21 -> 22067
B22: ='Raw FC'!B22 -> Building | G22: ='Raw FC'!J22 -> 25883 | H22: ='Raw FC'!K22 -> 26828 | I22: ='Raw FC'!L22 -> 27588 | J22: ='Raw FC'!M22 -> 28904 | K22: ='Raw FC'!N22 -> 30173
B23: ='Raw FC'!B23 -> Plant Machinery | G23: ='Raw FC'!J23 -> 141914 | H23: ='Raw FC'!K23 -> 155596 | I23: ='Raw FC'!L23 -> 152754 | J23: ='Raw FC'!M23 -> 163134 | K23: ='Raw FC'!N23 -> 175111
B24: ='Raw FC'!B24 -> Equipments | G24: ='Raw FC'!J24 -> 796 | H24: ='Raw FC'!K24 -> 1033 | I24: ='Raw FC'!L24 -> 0 | J24: ='Raw FC'!M24 -> 0 | K24: ='Raw FC'!N24 -> 0
B25: ='Raw FC'!B25 -> Furniture n fittings | G25: ='Raw FC'!J25 -> 19 | H25: ='Raw FC'!K25 -> 14 | I25: ='Raw FC'!L25 -> 991 | J25: ='Raw FC'!M25 -> 1111 | K25: ='Raw FC'!N25 -> 1238
B26: ='Raw FC'!B26 -> Railway sidings | G26: ='Raw FC'!J26 -> 1676 | H26: ='Raw FC'!K26 -> 1671 | I26: ='Raw FC'!L26 -> 1780 | J26: ='Raw FC'!M26 -> 1841 | K26: ='Raw FC'!N26 -> 1872
B27: ='Raw FC'!B27 -> Vehicles | G27: ='Raw FC'!J27 -> 615 | H27: ='Raw FC'!K27 -> 681 | I27: ='Raw FC'!L27 -> 686 | J27: ='Raw FC'!M27 -> 749 | K27: ='Raw FC'!N27 -> 794
B28: ='Raw FC'!B28 -> Intangible Assets | G28: ='Raw FC'!J28 -> 5868 | H28: ='Raw FC'!K28 -> 6289 | I28: ='Raw FC'!L28 -> 6229 | J28: ='Raw FC'!M28 -> 7572 | K28: ='Raw FC'!N28 -> 7772
B29: ='Raw FC'!B29 -> Other fixed assets | G29: ='Raw FC'!J29 -> 4424 | H29: ='Raw FC'!K29 -> 5171 | I29: ='Raw FC'!L29 -> 10953 | J29: ='Raw FC'!M29 -> 20384 | K29: ='Raw FC'!N29 -> 20546
B31: ='Raw FC'!B30 -> Gross Block | G31: =SUM(G21:G29) -> 201048 | H31: =SUM(H21:H29) -> 217939 | I31: =SUM(I21:I29) -> 221751 | J31: =SUM(J21:J29) -> 245396 | K31: =SUM(K21:K29) -> 259573
B32: ='Raw FC'!B31 -> Accumulated Depreciation | G32: ='Raw FC'!J31 -> 61396 | H32: ='Raw FC'!K31 -> 71472 | I32: ='Raw FC'!L31 -> 77783 | J32: ='Raw FC'!M31 -> 88205 | K32: ='Raw FC'!N31 -> 97940
A33: # | B33: Net Non Current Asset | G33: =G31-G32 -> 139652 | H33: =H31-H32 -> 146467 | I33: =I31-I32 -> 143968 | J33: =J31-J32 -> 157191 | K33: =K31-K32 -> 161633
A35: # | B35: Invested Capital | G35: =G33+G18 -> 161169 | H35: =H33+H18 -> 137960 | I35: =I33+I18 -> 149600 | J35: =J33+J18 -> 145563 | K35: =K33+K18 -> 142646
B36: EBIT | G36: ='Histoirical FC'!H24 -> 9022.33 | H36: ='Histoirical FC'!I24 -> 21270.62 | I36: ='Histoirical FC'!J24 -> 54389.08 | J36: ='Histoirical FC'!K24 -> 22964.96 | K36: ='Histoirical FC'!L24 -> 12365.76
A38: # | B38: ROIC | G38: =G36/G35 -> 0.055980555 | H38: =H36/H35 -> 0.15417962 | I38: =I36/I35 -> 0.36356337 | J38: =J36/J35 -> 0.15776647 | K38: =K36/K35 -> 0.086688446
B40: Calculation of Reinvestment Rate | G40: =G2 -> 43921 | H40: =H2 -> 44286 | I40: =I2 -> 44651 | J40: =J2 -> 45016 | K40: =K2 -> 45382
B42: Net Capex | G42: =-SUM('Raw FC'!J60:J61) -> 707 | H42: =-SUM('Raw FC'!K60:K61) -> 3631 | I42: =-SUM('Raw FC'!L60:L61) -> 1090 | J42: =-SUM('Raw FC'!M60:M61) -> -4865 | K42: =-SUM('Raw FC'!N60:N61) -> -3167
B43: Change In Working Capital | H43: =H18-G18 -> -30024 | I43: =I18-H18 -> 14139 | J43: =J18-I18 -> -17260 | K43: =K18-J18 -> -7359
B45: EBIT | G45: ='Histoirical FC'!H24 -> 9022.33 | H45: ='Histoirical FC'!I24 -> 21270.62 | I45: ='Histoirical FC'!J24 -> 54389.08 | J45: ='Histoirical FC'!K24 -> 22964.96 | K45: ='Histoirical FC'!L24 -> 12365.76
B46: Marginal Tax Rate | G46: 0.25 | H46: 0.25 | I46: 0.25 | J46: 0.25 | K46: 0.25
B47: EBIT(1-Tax) | G47: =G45*(1-G46) -> 6766.7475 | H47: =H45*(1-H46) -> 15952.965 | I47: =I45*(1-I46) -> 40791.81 | J47: =J45*(1-J46) -> 17223.72 | K47: =K45*(1-K46) -> 9274.32
B49: Reinvestment | H49: =SUM(H42:H43) -> -26393 | I49: =SUM(I42:I43) -> 15229 | J49: =SUM(J42:J43) -> -22125 | K49: =SUM(K42:K43) -> -10526
B51: Reinvestment Rate | H51: =H49/H47 -> -1.654426 | I51: =I49/I47 -> 0.37333475 | J51: =J49/J47 -> -1.2845657 | K51: =K49/K47 -> -1.1349619
J53: 4 Year Average | K53: =AVERAGE(H51:K51) -> -0.92515472
J54: 4 Year Median | K54: =MEDIAN(H51:K51) -> -1.2097638
B56: Calculation Of Growth rate | G56: =G40 -> 43921 | H56: =H40 -> 44286 | I56: =I40 -> 44651 | J56: =J40 -> 45016 | K56: =K40 -> 45382
B58: Reinvestment Rate | H58: =H51 -> -1.654426 | I58: =I51 -> 0.37333475 | J58: =J51 -> -1.2845657 | K58: =K51 -> -1.1349619
B59: ROIC | H59: =H38 -> 0.15417962 | I59: =I38 -> 0.36356337 | J59: =J38 -> 0.15776647 | K59: =K38 -> 0.086688446
B61: Intrinsic Growth Rate | H61: =H58*H59 -> -0.25507877 | I61: =I58*I59 -> 0.13573084 | J61: =J58*J59 -> -0.20266139 | K61: =K58*K59 -> -0.098388084
J63: 4 Year Average | K63: =AVERAGE(H61:K61) -> -0.10509935
J64: 4 Year Median | K64: =MEDIAN(H61:K61) -> -0.15052474

Sheet Raw FC
B2: Particular | C2: 41334 | D2: =C2+365 -> 41699 | E2: =D2+365 -> 42064 | F2: =E2+365 -> 42429 | G2: =F2+365 -> 42794 | H2: =G2+365 -> 43159 | I2: =H2+365 -> 43524 | J2: =I2+365 -> 43889 | K2: =J2+365 -> 44254 | ... N2: =M2+365 -> 45349 | O2: LTM
B4: ='Rough Data'!AC4 -> Equity Capital | C4: ='Rough Data'!AD4 -> 971 | D4: ='Rough Data'!AE4 -> 971 | E4: ='Rough Data'!AF4 -> 971 | F4: ='Rough Data'!AG4 -> 970 | G4: ='Rough Data'!AH4 -> 970 | H4: ='Rough Data'!AI4 -> 1145 | I4: ='Rough Data'!AJ4 -> 1145 | ... O4: ='Rough Data'!AP4 -> 1247
B5: ='Rough Data'!AC5 -> Reserves | C5: ='Rough Data'!AD5 -> 33201 | D5: ='Rough Data'!AE5 -> 39561 | E5: ='Rough Data'!AF5 -> 30378 | F5: ='Rough Data'!AG5 -> 42762 | G5: ='Rough Data'!AH5 -> 36849 | H5: ='Rough Data'!AI5 -> 59726 | I5: ='Rough Data'!AJ5 -> 67780 | ... O5: ='Rough Data'!AP5 -> 88900
B6: ='Rough Data'!AC6 -> Borrowings -
B7: ='Rough Data'!AC7 -> Long term Borrowings | C7: ='Rough Data'!AD7 -> 46858 | D7: ='Rough Data'!AE7 -> 52366 | E7: ='Rough Data'!AF7 -> 65675 | F7: ='Rough Data'!AG7 -> 64873 | G7: ='Rough Data'!AH7 -> 64022 | H7: ='Rough Data'!AI7 -> 72789 | I7: ='Rough Data'!AJ7 -> 80343 | ... O7: ='Rough Data'!AP7 -> 67148
B8: ='Rough Data'!AC8 -> Short term Borrowings | C8: ='Rough Data'!AD8 -> 10548 | D8: ='Rough Data'!AE8 -> 16026 | E8: ='Rough Data'!AF8 -> 9599 | F8: ='Rough Data'!AG8 -> 15722 | G8: ='Rough Data'!AH8 -> 18328 | H8: ='Rough Data'!AI8 -> 15885 | I8: ='Rough Data'!AJ8 -> 10802 | ... O8: ='Rough Data'!AP8 -> 26960
B9: ='Rough Data'!AC9 -> Lease Liabilities | C9: ='Rough Data'!AD9 -> 0 | D9: ='Rough Data'!AE9 -> 0 | E9: ='Rough Data'!AF9 -> 0 | F9: ='Rough Data'!AG9 -> 0 | G9: ='Rough Data'!AH9 -> 0 | H9: ='Rough Data'!AI9 -> 0 | I9: ='Rough Data'!AJ9 -> 0 | ... O9: ='Rough Data'!AP9 -> 5284
B10: ='Rough Data'!AC10 -> Preference Capital | C10: ='Rough Data'!AD10 -> 21 | D10: ='Rough Data'!AE10 -> 20 | E10: ='Rough Data'!AF10 -> 0 | F10: ='Rough Data'!AG10 -> 0 | G10: ='Rough Data'!AH10 -> 0 | H10: ='Rough Data'!AI10 -> 20 | I10: ='Rough Data'!AJ10 -> 13 | ... O10: ='Rough Data'!AP10 -> 0
B11: ='Rough Data'!AC11 -> Other Borrowings | C11: ='Rough Data'!AD11 -> 11123 | D11: ='Rough Data'!AE11 -> 13236 | E11: ='Rough Data'!AF11 -> 5428 | F11: ='Rough Data'!AG11 -> 1392 | G11: ='Rough Data'!AH11 -> 664 | H11: ='Rough Data'!AI11 -> 3473 | I11: ='Rough Data'!AJ11 -> 9671 | ... O11: ='Rough Data'!AP11 -> 0
B12: ='Rough Data'!AC12 -> Other Liabilities -
B13: ='Rough Data'!AC13 -> Non controlling int | C13: ='Rough Data'!AD13 -> 1669 | D13: ='Rough Data'!AE13 -> 1738 | E13: ='Rough Data'!AF13 -> 1704 | F13: ='Rough Data'!AG13 -> 781 | G13: ='Rough Data'!AH13 -> 1602 | H13: ='Rough Data'!AI13 -> 937 | I13: ='Rough Data'!AJ13 -> 2364 | ... O13: ='Rough Data'!AP13 -> 362
B14: ='Rough Data'!AC14 -> Trade Payables | C14: ='Rough Data'!AD14 -> 19340 | D14: ='Rough Data'!AE14 -> 22904 | E14: ='Rough Data'!AF14 -> 19190 | F14: ='Rough Data'!AG14 -> 18557 | G14: ='Rough Data'!AH14 -> 18574 | H14: ='Rough Data'!AI14 -> 20414 | I14: ='Rough Data'!AJ14 -> 21717 | ... O14: ='Rough Data'!AP14 -> 32502
B15: ='Rough Data'!AC15 -> Advance from Customers | C15: ='Rough Data'!AD15 -> 556 | D15: ='Rough Data'!AE15 -> 310 | E15: ='Rough Data'!AF15 -> 367 | F15: ='Rough Data'!AG15 -> 456 | G15: ='Rough Data'!AH15 -> 566 | H15: ='Rough Data'!AI15 -> 616 | I15: ='Rough Data'!AJ15 -> 819 | ... O15: ='Rough Data'!AP15 -> 0
B16: ='Rough Data'!AC16 -> Other liability items | C16: ='Rough Data'!AD16 -> 22610 | D16: ='Rough Data'!AE16 -> 24491 | E16: ='Rough Data'!AF16 -> 25798 | F16: ='Rough Data'!AG16 -> 31371 | G16: ='Rough Data'!AH16 -> 30871 | H16: ='Rough Data'!AI16 -> 33738 | I16: ='Rough Data'!AJ16 -> 38131 | ... O16: ='Rough Data'!AP16 -> 58437
B18: Total Liabilites | C18: =SUM(C4:C16) -> 146897 | D18: =SUM(D4:D16) -> 171623 | E18: =SUM(E4:E16) -> 159110 | F18: =SUM(F4:F16) -> 176884 | G18: =SUM(G4:G16) -> 172446 | H18: =SUM(H4:H16) -> 208743 | I18: =SUM(I4:I16) -> 232785 | J18: =SUM(J4:J16) -> 249149 | ... O18: =SUM(O4:O16) -> 280840
B20: ='Rough Data'!AC18 -> Fixed Assets -
B21: ='Rough Data'!AC19 -> Land | C21: ='Rough Data'!AD19 -> 2513 | D21: ='Rough Data'!AE19 -> 2758 | E21: ='Rough Data'!AF19 -> 2433 | F21: ='Rough Data'!AG19 -> 16499 | G21: ='Rough Data'!AH19 -> 16545 | H21: ='Rough Data'!AI19 -> 16955 | I21: ='Rough Data'!AJ19 -> 17126 | ... O21: ='Rough Data'!AP19 -> 0
B22: ='Rough Data'!AC20 -> Building | C22: ='Rough Data'!AD20 -> 13060 | D22: ='Rough Data'!AE20 -> 15141 | E22: ='Rough Data'!AF20 -> 14186 | F22: ='Rough Data'!AG20 -> 11058 | G22: ='Rough Data'!AH20 -> 11141 | H22: ='Rough Data'!AI20 -> 12148 | I22: ='Rough Data'!AJ20 -> 21753 | ... O22: ='Rough Data'!AP20 -> 0
B23: ='Rough Data'!AC21 -> Plant Machinery | C23: ='Rough Data'!AD21 -> 111394 | D23: ='Rough Data'!AE21 -> 128424 | E23: ='Rough Data'!AF21 -> 124249 | F23: ='Rough Data'!AG21 -> 73865 | G23: ='Rough Data'!AH21 -> 93462 | H23: ='Rough Data'!AI21 -> 104889 | I23: ='Rough Data'!AJ21 -> 127435 | ... O23: ='Rough Data'!AP21 -> 0
B24: ='Rough Data'!AC22 -> Equipments | C24: ='Rough Data'!AD22 -> 335 | D24: ='Rough Data'!AE22 -> 385 | E24: ='Rough Data'!AF22 -> 403 | F24: ='Rough Data'!AG22 -> 414 | G24: ='Rough Data'!AH22 -> 543 | H24: ='Rough Data'!AI22 -> 668 | I24: ='Rough Data'!AJ22 -> 739 | ... O24: ='Rough Data'!AP22 -> 0
B25: ='Rough Data'!AC23 -> Furniture n fittings | C25: ='Rough Data'!AD23 -> 897 | D25: ='Rough Data'!AE23 -> 1064 | E25: ='Rough Data'!AF23 -> 916 | F25: ='Rough Data'!AG23 -> 0 | G25: ='Rough Data'!AH23 -> 0 | H25: ='Rough Data'!AI23 -> 0 | I25: ='Rough Data'!AJ23 -> 0 | ... O25: ='Rough Data'!AP23 -> 0
B26: ='Rough Data'!AC24 -> Railway sidings | C26: ='Rough Data'!AD24 -> 1234 | D26: ='Rough Data'!AE24 -> 1416 | E26: ='Rough Data'!AF24 -> 1239 | F26: ='Rough Data'!AG24 -> 757 | G26: ='Rough Data'!AH24 -> 1350 | H26: ='Rough Data'!AI24 -> 1397 | I26: ='Rough Data'!AJ24 -> 1549 | ... O26: ='Rough Data'!AP24 -> 0
B27: ='Rough Data'!AC25 -> Vehicles | C27: ='Rough Data'!AD25 -> 318 | D27: ='Rough Data'!AE25 -> 350 | E27: ='Rough Data'!AF25 -> 376 | F27: ='Rough Data'!AG25 -> 335 | G27: ='Rough Data'!AH25 -> 352 | H27: ='Rough Data'!AI25 -> 343 | I27: ='Rough Data'!AJ25 -> 398 | ... O27: ='Rough Data'!AP25 -> 0
B28: ='Rough Data'!AC26 -> Intangible Assets | C28: ='Rough Data'!AD26 -> 13154 | D28: ='Rough Data'!AE26 -> 15858 | E28: ='Rough Data'!AF26 -> 13500 | F28: ='Rough Data'!AG26 -> 6026 | G28: ='Rough Data'!AH26 -> 4990 | H28: ='Rough Data'!AI26 -> 5810 | I28: ='Rough Data'!AJ26 -> 4293 | ... O28: ='Rough Data'!AP26 -> 18829
B29: ='Rough Data'!AC27 -> Other fixed assets | C29: ='Rough Data'!AD27 -> 4935 | D29: ='Rough Data'!AE27 -> 6495 | E29: ='Rough Data'!AF27 -> 7315 | F29: ='Rough Data'!AG27 -> 5154 | G29: ='Rough Data'!AH27 -> 2919 | H29: ='Rough Data'!AI27 -> 3233 | I29: ='Rough Data'!AJ27 -> 3742 | ... O29: ='Rough Data'!AP27 -> 0
B30: ='Rough Data'!AC28 -> Gross Block | C30: ='Rough Data'!AD28 -> 147839 | D30: ='Rough Data'!AE28 -> 171891 | E30: ='Rough Data'!AF28 -> 164618 | F30: ='Rough Data'!AG28 -> 114109 | G30: ='Rough Data'!AH28 -> 131302 | H30: ='Rough Data'!AI28 -> 145444 | I30: ='Rough Data'!AJ28 -> 177037 | ... O30: ='Rough Data'!AP28 -> 0
B31: ='Rough Data'!AC29 -> Accumulated Depreciation | C31: ='Rough Data'!AD29 -> 72716 | D31: ='Rough Data'!AE29 -> 88452 | E31: ='Rough Data'!AF29 -> 84913 | F31: ='Rough Data'!AG29 -> 36022 | G31: ='Rough Data'!AH29 -> 35373 | H31: ='Rough Data'!AI29 -> 46251 | I31: ='Rough Data'!AJ29 -> 49609 | ... O31: ='Rough Data'!AP29 -> 0
B32: Net Block | C32: =C30-C31 -> 75123 | D32: =D30-D31 -> 83439 | E32: =E30-E31 -> 79705 | F32: =F30-F31 -> 78087 | G32: =G30-G31 -> 95929 | H32: =H30-H31 -> 99193 | I32: =I30-I31 -> 127428 | J32: =J30-J31 -> 139651 | ... O32: =O30-O31 -> 0
B34: ='Rough Data'!AC30 -> CWIP | C34: ='Rough Data'!AD30 -> 14277 | D34: ='Rough Data'!AE30 -> 26822 | E34: ='Rough Data'!AF30 -> 28678 | F34: ='Rough Data'!AG30 -> 35996 | G34: ='Rough Data'!AH30 -> 15784 | H34: ='Rough Data'!AI30 -> 16614 | I34: ='Rough Data'!AJ30 -> 18641 | ... O34: ='Rough Data'!AP30 -> 39051
B35: ='Rough Data'!AC31 -> Investments | C35: ='Rough Data'!AD31 -> 3258 | D35: ='Rough Data'!AE31 -> 5093 | E35: ='Rough Data'!AF31 -> 3455 | F35: ='Rough Data'!AG31 -> 10714 | G35: ='Rough Data'!AH31 -> 12457 | H35: ='Rough Data'!AI31 -> 17899 | I35: ='Rough Data'!AJ31 -> 5738 | ... O35: ='Rough Data'!AP31 -> 6471
B37: ='Rough Data'!AC32 -> Other Assets -
B38: ='Rough Data'!AC33 -> Inventories | C38: ='Rough Data'!AD33 -> 24091 | D38: ='Rough Data'!AE33 -> 26880 | E38: ='Rough Data'!AF33 -> 25150 | F38: ='Rough Data'!AG33 -> 20013 | G38: ='Rough Data'!AH33 -> 24804 | H38: ='Rough Data'!AI33 -> 28331 | I38: ='Rough Data'!AJ33 -> 31656 | ... O38: ='Rough Data'!AP33 -> 51172
B39: ='Rough Data'!AC34 -> Trade receivables - | C39: ='Rough Data'!AD34 -> 13994 | D39: ='Rough Data'!AE34 -> 16006 | E39: ='Rough Data'!AF34 -> 13310 | F39: ='Rough Data'!AG34 -> 12066 | G39: ='Rough Data'!AH34 -> 11587 | H39: ='Rough Data'!AI34 -> 12416 | I39: ='Rough Data'!AJ34 -> 11811 | ... O39: ='Rough Data'!AP34 -> 6041
B40: ='Rough Data'!AC38 -> Cash Equivalents | C40: ='Rough Data'!AD38 -> 9834 | D40: ='Rough Data'!AE38 -> 8604 | E40: ='Rough Data'!AF38 -> 8750 | F40: ='Rough Data'!AG38 -> 6186 | G40: ='Rough Data'!AH38 -> 4921 | H40: ='Rough Data'!AI38 -> 7938 | I40: ='Rough Data'!AJ38 -> 3341 | ... O40: ='Rough Data'!AP38 -> 9934
B41: ='Rough Data'!AC39 -> Loans n Advances | C41: ='Rough Data'!AD39 -> 487 | D41: ='Rough Data'!AE39 -> 171 | E41: ='Rough Data'!AF39 -> -182 | F41: ='Rough Data'!AG39 -> 107 | G41: ='Rough Data'!AH39 -> 98 | H41: ='Rough Data'!AI39 -> 219 | I41: ='Rough Data'!AJ39 -> -56 | ... O41: ='Rough Data'!AP39 -> 1779
B42: ='Rough Data'!AC40 -> Other asset items | C42: ='Rough Data'!AD40 -> 12934 | D42: ='Rough Data'!AE40 -> 13119 | E42: ='Rough Data'!AF40 -> 11848 | F42: ='Rough Data'!AG40 -> 19602 | G42: ='Rough Data'!AH40 -> 10790 | H42: ='Rough Data'!AI40 -> 29200 | I42: ='Rough Data'!AJ40 -> 37200 | ... O42: ='Rough Data'!AP40 -> 16843
B44: ='Rough Data'!AC41 -> Total Assets
B47: Cash Flow
B49: ='Rough Data'!B3 -> Cash from Operating Activity - | C49: ='Rough Data'!AU4 -> 14035 | D49: ='Rough Data'!AV4 -> 13146 | E49: ='Rough Data'!AW4 -> 11880 | F49: ='Rough Data'!AX4 -> 11455 | G49: ='Rough Data'!AY4 -> 10824 | H49: ='Rough Data'!AZ4 -> 8023 | I49: ='Rough Data'!BA4 -> 25336 | J49: ='Rough Data'!BB4 -> 20169 | ... N49: ='Rough Data'!BF4 -> 20301
B50: ='Rough Data'!B4 -> Profit from operations | C50: ='Rough Data'!AU5 -> 12764 | D50: ='Rough Data'!AV5 -> 17507 | E50: ='Rough Data'!AW5 -> 13955 | F50: ='Rough Data'!AX5 -> 6824 | G50: ='Rough Data'!AY5 -> 17581 | H50: ='Rough Data'!AZ5 -> 20187 | I50: ='Rough Data'!BA5 -> 27840 | J50: ='Rough Data'!BB5 -> 18078 | ... N50: ='Rough Data'!BF5 -> 22237
B51: ='Rough Data'!B5 -> Receivables | C51: ='Rough Data'!AU6 -> 1342 | D51: ='Rough Data'!AV6 -> -1483 | E51: ='Rough Data'!AW6 -> 1442 | F51: ='Rough Data'!AX6 -> 0 | G51: ='Rough Data'!AY6 -> 0 | H51: ='Rough Data'!AZ6 -> 0 | I51: ='Rough Data'!BA6 -> 0 | J51: ='Rough Data'!BB6 -> 0 | ... N51: ='Rough Data'!BF6 -> 0
B52: ='Rough Data'!B6 -> Inventory | C52: ='Rough Data'!AU7 -> 1915 | D52: ='Rough Data'!AV7 -> 389 | E52: ='Rough Data'!AW7 -> -485 | F52: ='Rough Data'!AX7 -> 5618 | G52: ='Rough Data'!AY7 -> -8243 | H52: ='Rough Data'!AZ7 -> -1595 | I52: ='Rough Data'!BA7 -> -1069 | J52: ='Rough Data'!BB7 -> 1562 | ... N52: ='Rough Data'!BF7 -> 5566
B53: ='Rough Data'!B7 -> Payables | C53: ='Rough Data'!AU8 -> 583 | D53: ='Rough Data'!AV8 -> -255 | E53: ='Rough Data'!AW8 -> -605 | F53: ='Rough Data'!AX8 -> 0 | G53: ='Rough Data'!AY8 -> 0 | H53: ='Rough Data'!AZ8 -> 0 | I53: ='Rough Data'!BA8 -> 0 | J53: ='Rough Data'!BB8 -> 0 | ... N53: ='Rough Data'!BF8 -> 0
B54: ='Rough Data'!B8 -> Other WC items | C54: ='Rough Data'!AU9 -> 0 | D54: ='Rough Data'!AV9 -> 0 | E54: ='Rough Data'!AW9 -> 0 | F54: ='Rough Data'!AX9 -> 548 | G54: ='Rough Data'!AY9 -> 3329 | H54: ='Rough Data'!AZ9 -> -7680 | I54: ='Rough Data'!BA9 -> 3659 | J54: ='Rough Data'!BB9 -> 2634 | ... N54: ='Rough Data'!BF9 -> -2182
B55: ='Rough Data'!B9 -> Working capital changes | C55: ='Rough Data'!AU10 -> 3841 | D55: ='Rough Data'!AV10 -> -1349 | E55: ='Rough Data'!AW10 -> 351 | F55: ='Rough Data'!AX10 -> 6166 | G55: ='Rough Data'!AY10 -> -4914 | H55: ='Rough Data'!AZ10 -> -9276 | I55: ='Rough Data'!BA10 -> 2591 | J55: ='Rough Data'!BB10 -> 4196 | ... N55: ='Rough Data'!BF10 -> 3384
B56: ='Rough Data'!B10 -> Direct taxes | C56: ='Rough Data'!AU11 -> -2569 | D56: ='Rough Data'!AV11 -> -3013 | E56: ='Rough Data'!AW11 -> -2427 | F56: ='Rough Data'!AX11 -> -1534 | G56: ='Rough Data'!AY11 -> -1843 | H56: ='Rough Data'!AZ11 -> -2888 | I56: ='Rough Data'!BA11 -> -5094 | J56: ='Rough Data'!BB11 -> -2106 | ... N56: ='Rough Data'!BF11 -> -5320
B57: ='Rough Data'!B11 -> Cash from Investing Activity - | C57: ='Rough Data'!AU12 -> -13099 | D57: ='Rough Data'!AV12 -> -15378 | E57: ='Rough Data'!AW12 -> -9021 | F57: ='Rough Data'!AX12 -> -8794 | G57: ='Rough Data'!AY12 -> -9490 | H57: ='Rough Data'!AZ12 -> -11730 | I57: ='Rough Data'!BA12 -> -29176 | J57: ='Rough Data'!BB12 -> -14012 | ... N57: ='Rough Data'!BF12 -> -14253
B58: ='Rough Data'!B12 -> Fixed assets purchased | C58: ='Rough Data'!AU13 -> -15472 | D58: ='Rough Data'!AV13 -> -16420 | E58: ='Rough Data'!AW13 -> -13492 | F58: ='Rough Data'!AX13 -> -10163 | G58: ='Rough Data'!AY13 -> -7716 | H58: ='Rough Data'!AZ13 -> -7478 | I58: ='Rough Data'!BA13 -> -9091 | J58: ='Rough Data'!BB13 -> -10398 | ... N58: ='Rough Data'!BF13 -> -18207
B59: ='Rough Data'!B13 -> Fixed assets sold | C59: ='Rough Data'!AU14 -> 249 | D59: ='Rough Data'!AV14 -> 295 | E59: ='Rough Data'!AW14 -> 1444 | F59: ='Rough Data'!AX14 -> 231 | G59: ='Rough Data'!AY14 -> 289 | H59: ='Rough Data'!AZ14 -> 179 | I59: ='Rough Data'!BA14 -> 467 | J59: ='Rough Data'!BB14 -> 386 | ... N59: ='Rough Data'!BF14 -> 475
B60: ='Rough Data'!B14 -> Investments purchased | C60: ='Rough Data'!AU15 -> 0 | D60: ='Rough Data'!AV15 -> -612 | E60: ='Rough Data'!AW15 -> 1531 | F60: ='Rough Data'!AX15 -> -3796 | G60: ='Rough Data'!AY15 -> -861 | H60: ='Rough Data'!AZ15 -> -8641 | I60: ='Rough Data'!BA15 -> -490 | J60: ='Rough Data'!BB15 -> -828 | ... N60: ='Rough Data'!BF15 -> -4
... B75: ='Rough Data'!B29 -> Other financing items | C75: ='Rough Data'!AU30 -> 2589 | D75: ='Rough Data'!AV30 -> 5466 | E75: ='Rough Data'!AW30 -> 3781 | F75: ='Rough Data'!AX30 -> 1743 | G75: ='Rough Data'!AY30 -> 2501 | H75: ='Rough Data'!AZ30 -> 3892 | I75: ='Rough Data'!BA30 -> -576 | J75: ='Rough Data'!BB30 -> -564 | ... N75: ='Rough Data'!BF30 -> 404
B77: ='Rough Data'!B30 -> Net Cash Flow | C77: ='Rough Data'!AU31 -> -844 | D77: ='Rough Data'!AV31 -> -1218 | E77: ='Rough Data'!AW31 -> 241 | F77: ='Rough Data'!AX31 -> -2068 | G77: ='Rough Data'!AY31 -> -1245 | H77: ='Rough Data'!AZ31 -> 2933 | I77: ='Rough Data'!BA31 -> -4513 | J77: ='Rough Data'!BB31 -> 4462 | ... N77: ='Rough Data'!BF31 -> -5049

Sheet Dupont Analysis
B2: ='Data Sheet'!B1 -> TATA STEEL LTD
B3: =CONCATENATE( " ","NSE:TATASTELLEQ","|","BSE: 500470") -> NSE:TATASTELLEQ|BSE: 500470
B4: =CONCATENATE(" "," INR "&'Data Sheet'!B8) -> INR 145.35
B5: 52 Week (High- INR 184.60 & Low -INR 122.60)
B8: About the Company
B9: Tata Steel Limited is an Indian multinational steel-making company, headquartered in Mumbai, Maharashtra, with its primary operations based in Jamshedpur, Jharkhand. It is a subsidiary of the Tata Group.Formerly known as Tata Iron and Steel Company Limited (TISCO), Tata Steel is one of the largest steel producers globally, with an annual crude steel capacity of 35 million tons and one of the world's most geographically diversified steel producers, with operations and commercial presence spanning multiple regions worldwide.
B18: Financial Summary
A45: Recent Updates
B73: Dupont Analysis - Return on Equity & Return On Asset.
B75: Return On Equity(ROE)
E76: ='Data Sheet'!E16 -> 43190 | F76: ='Data Sheet'!F16 -> 43555 | G76: ='Data Sheet'!G16 -> 43921 | H76: ='Data Sheet'!H16 -> 44286 | I76: ='Data Sheet'!I16 -> 44651 | J76: ='Data Sheet'!J16 -> 45016 | K76: ='Data Sheet'!K16 -> 45382
B77: Net Profit | E77: ='Data Sheet'!E30 -> 13434.33 | F77: ='Data Sheet'!F30 -> 10218.33 | G77: ='Data Sheet'!G30 -> 1556.54 | H77: ='Data Sheet'!H30 -> 7490.22 | I77: ='Data Sheet'!I30 -> 40153.93 | J77: ='Data Sheet'!J30 -> 8760.4 | K77: ='Data Sheet'!K30 -> -4437.44
B78: Avergae Shareholder Equity | E78: =('Data Sheet'!E57+'Data Sheet'!D57)+('Data Sheet'!E58+'Data Sheet'!D58)/2 -> 50402.565 | F78: =('Data Sheet'!F57+'Data Sheet'!E57)+('Data Sheet'!F58+'Data Sheet'!E58)/2 -> 66042.795 | G78: =('Data Sheet'!G57+'Data Sheet'!F57)+('Data Sheet'!G58+'Data Sheet'!F58)/2 -> 72395.635 | H78: =('Data Sheet'!H57+'Data Sheet'!G57)+('Data Sheet'!H58+'Data Sheet'!G58)/2 -> 75078.815 | I78: =('Data Sheet'!I57+'Data Sheet'!H57)+('Data Sheet'!I58+'Data Sheet'!H58)/2 -> 95550.315 | J78: =('Data Sheet'!J57+'Data Sheet'!I57)+('Data Sheet'!J58+'Data Sheet'!I58)/2 -> 109983.79 | K78: =('Data Sheet'!K57+'Data Sheet'!J57)+('Data Sheet'!K58+'Data Sheet'!J58)/2 -> 98793.27
B79: Return on Equity | E79: =E77/E78 -> 0.2665406 | F79: =F77/F78 -> 0.15472286 | G79: =G77/G78 -> 0.021500468 | H79: =H77/H78 -> 0.099764761 | I79: =I77/I78 -> 0.42023859 | J79: =J77/J78 -> 0.079651734 | K79: =K77/K78 -> -0.04491642
B81: Return On Equity - Dupont Equation
E82: =E76 -> 43190 | F82: =F76 -> 43555 | G82: =G76 -> 43921 | H82: =H76 -> 44286 | I82: =I76 -> 44651 | J82: =J76 -> 45016 | K82: =K76 -> 45382
B83: Net Profit | E83: =E77 -> 13434.33 | F83: =F77 -> 10218.33 | G83: =G77 -> 1556.54 | H83: =H77 -> 7490.22 | I83: =I77 -> 40153.93 | J83: =J77 -> 8760.4 | K83: =K77 -> -4437.44
B84: Revenue | E84: ='Data Sheet'!E17 -> 123249.07 | F84: ='Data Sheet'!F17 -> 157668.99 | G84: ='Data Sheet'!G17 -> 139816.65 | H84: ='Data Sheet'!H17 -> 156294.18 | I84: ='Data Sheet'!I17 -> 243959.17 | J84: ='Data Sheet'!J17 -> 243352.69 | K84: ='Data Sheet'!K17 -> 229170.78
B85: Net Profit Margin(A) | E85: =E83/E84 -> 0.10900147 | F85: =F83/F84 -> 0.064808749 | G85: =G83/G84 -> 0.011132723 | H85: =H83/H84 -> 0.047923857 | I85: =I83/I84 -> 0.16459283 | J85: =J83/J84 -> 0.03599878 | K85: =K83/K84 -> -0.019363027
B87: =B84 -> Revenue | E87: =E84 -> 123249.07 | F87: =F84 -> 157668.99 | G87: =G84 -> 139816.65 | H87: =H84 -> 156294.18 | I87: =I84 -> 243959.17 | J87: =J84 -> 243352.69 | K87: =K84 -> 229170.78
B88: Average Total Asset | E88: =('Data Sheet'!E66+'Data Sheet'!D66)/2 -> 190584.76 | F88: =('Data Sheet'!F66+'Data Sheet'!E66)/2 -> 220747.79 | G88: =('Data Sheet'!G66+'Data Sheet'!F66)/2 -> 240961.28 | H88: =('Data Sheet'!H66+'Data Sheet'!G66)/2 -> 246529.15 | I88: =('Data Sheet'!I66+'Data Sheet'!H66)/2 -> 263165.43 | J88: =('Data Sheet'!J66+'Data Sheet'!I66)/2 -> 283908.72 | K88: =('Data Sheet'!K66+'Data Sheet'!J66)/2 -> 277354.1
B89: Asset Turnover Ratio(B) | E89: =E87/E88 -> 0.64668903 | F89: =F87/F88 -> 0.71424946 | G89: =G87/G88 -> 0.5802453 | H89: =H87/H88 -> 0.63397848 | I89: =I87/I88 -> 0.9270183 | J89: =J87/J88 -> 0.85715115 | K89: =K87/K88 -> 0.82627508
B91: =B88 -> Average Total Asset | E91: =E88 -> 190584.76 | F91: =F88 -> 220747.79 | G91: =G88 -> 240961.28 | H91: =H88 -> 246529.15 | I91: =I88 -> 263165.43 | J91: =J88 -> 283908.72 | K91: =K88 -> 277354.1
B92: =B78 -> Avergae Shareholder Equity | E92: =E78 -> 50402.565 | F92: =F78 -> 66042.795 | G92: =G78 -> 72395.635 | H92: =H78 -> 75078.815 | I92: =I78 -> 95550.315 | J92: =J78 -> 109983.79 | K92: =K78 -> 98793.27
B93: Financial Leverage (C) | E93: =E91/E92 -> 3.7812511 | F93: =F91/F92 -> 3.3424962 | G93: =G91/G92 -> 3.3283951 | H93: =H91/H92 -> 3.2836048 | I93: =I91/I92 -> 2.7542079 | J93: =J91/J92 -> 2.5813687 | K93: =K91/K92 -> 2.807419
B95: Return On Equity(A*B*C) | E95: =E85*E89*E93 -> 0.2665406 | F95: =F85*F89*F93 -> 0.15472286 | G95: =G85*G89*G93 -> 0.021500468 | H95: =H85*H89*H93 -> 0.099764761 | I95: =I85*I89*I93 -> 0.42023859 | J95: =J85*J89*J93 -> 0.079651734 | K95: =K85*K89*K93 -> -0.04491642
B97: Return On Asset(ROA)
E98: =E82 -> 43190 | F98: =F82 -> 43555 | G98: =G82 -> 43921 | H98: =H82 -> 44286 | I98: =I82 -> 44651 | J98: =J82 -> 45016 | K98: =K82 -> 45382
B99: Net Profit | E99: =E83 -> 13434.33 | F99: =F83 -> 10218.33 | G99: =G83 -> 1556.54 | H99: =H83 -> 7490.22 | I99: =I83 -> 40153.93 | J99: =J83 -> 8760.4 | K99: =K83 -> -4437.44
B100: =B91 -> Average Total Asset | E100: =E91 -> 190584.76 | F100: =F91 -> 220747.79 | G100: =G91 -> 240961.28 | H100: =H91 -> 246529.15 | I100: =I91 -> 263165.43 | J100: =J91 -> 283908.72 | K100: =K91 -> 277354.1
B101: Return on Equity | E101: =E99/E100 -> 0.070490056 | F101: =F99/F100 -> 0.046289614 | G101: =G99/G100 -> 0.00645971 | H101: =H99/H100 -> 0.030382694 | I101: =I99/I100 -> 0.15258057 | J101: =J99/J100 -> 0.030856396 | K101: =K99/K100 -> -0.015999187
B103: Return On Asset - Dupont Equation
E104: =E98 -> 43190 | F104: =F98 -> 43555 | G104: =G98 -> 43921 | H104: =H98 -> 44286 | I104: =I98 -> 44651 | J104: =J98 -> 45016 | K104: =K98 -> 45382
B105: Net Profit | E105: =E99 -> 13434.33 | F105: =F99 -> 10218.33 | G105: =G99 -> 1556.54 | H105: =H99 -> 7490.22 | I105: =I99 -> 40153.93 | J105: =J99 -> 8760.4 | K105: =K99 -> -4437.44
B106: Revenue | E106: =E87 -> 123249.07 | F106: =F87 -> 157668.99 | G106: =G87 -> 139816.65 | H106: =H87 -> 156294.18 | I106: =I87 -> 243959.17 | J106: =J87 -> 243352.69 | K106: =K87 -> 229170.78
B107: Net Profit Margin(A) | E107: =E105/E106 -> 0.10900147 | F107: =F105/F106 -> 0.064808749 | G107: =G105/G106 -> 0.011132723 | H107: =H105/H106 -> 0.047923857 | I107: =I105/I106 -> 0.16459283 | J107: =J105/J106 -> 0.03599878 | K107: =K105/K106 -> -0.019363027
B109: =B106 -> Revenue | E109: =E106 -> 123249.07 | F109: =F106 -> 157668.99 | G109: =G106 -> 139816.65 | H109: =H106 -> 156294.18 | I109: =I106 -> 243959.17 | J109: =J106 -> 243352.69 | K109: =K106 -> 229170.78
B110: Average Total Asset | E110: =E100 -> 190584.76 | F110: =F100 -> 220747.79 | G110: =G100 -> 240961.28 | H110: =H100 -> 246529.15 | I110: =I100 -> 263165.43 | J110: =J100 -> 283908.72 | K110: =K100 -> 277354.1
B111: Asset Turnover Ratio(B) | E111: =E109/E110 -> 0.64668903 | F111: =F109/F110 -> 0.71424946 | G111: =G109/G110 -> 0.5802453 | H111: =H109/H110 -> 0.63397848 | I111: =I109/I110 -> 0.9270183 | J111: =J109/J110 -> 0.85715115 | K111: =K109/K110 -> 0.82627508
B113: Return On Asset (A*B) | E113: =E107*E111 -> 0.070490056 | F113: =F107*F111 -> 0.046289614 | G113: =G107*G111 -> 0.00645971 | H113: =H107*H111 -> 0.030382694 | I113: =I107*I111 -> 0.15258057 | J113: =J107*J111 -> 0.030856396 | K113: =K107*K111 -> -0.015999187
B116: Dupont Summary

Sheet Alt Man Z Score

Sheet VAR
B2: Date | C2: Closing Price | D2: Return | E2: Sorted Return | G2: Calculation of Value at Risk- Tata Stell (Historical)
B3: Mar 29, 1999 | C3: 12.84 | D3: =(C3-C4)/C4 -> -0.30669546 | E3: 9.5245902
B4: Nov 23, 1999 | C4: 18.52 | D4: =(C4-C5)/C5 -> -0.12847059 | E4: 9.5227273 | G4: Mean | K4: =AVERAGE(E3:E7354) -> 0.016596515
B5: Apr 14, 1997 | C5: 21.25 | D5: =(C5-C6)/C6 -> 0.41383899 | E5: 9.519802 | G5: Standerd Deviation | K5: =_xlfn.STDEV.S(E3:E7354) -> 0.39587383
B6: Mar 2, 1999 | C6: 15.03 | D6: =(C6-C7)/C7 -> -0.20936349 | E6: 9.5104895 | G6: Mim | K6: =MIN(E3:E7354) -> -0.91024555
B7: Nov 8, 1999 | C7: 19.01 | D7: =(C7-C8)/C8 -> 0.31193927 | E7: 9.5027624 | G7: Max | K7: =MAX(E3:E7354) -> 9.5245902
B8: Dec 25, 1998 | C8: 14.49 | D8: =(C8-C9)/C9 -> -0.45648912 | E8: 9.5 | G8: CMP | K8: 127.3
B9: Mar 7, 1997 | C9: 26.66 | D9: =(C9-C10)/C10 -> 1.4915888 | E9: 9.496063
B10: Nov 4, 1998 | C10: 10.7 | D10: =(C10-C11)/C11 -> -0.50163018 | E10: 9.4901961 | G10: Percentile | H10: Confidence | I10: VAR% | J10: Stock Price | K10: VAR(INR)
B11: Nov 12, 1996 | C11: 21.47 | D11: =(C11-C12)/C12 -> 1.2065776 | E11: 9.4731707 | G11: 0.05 | H11: =100%-G11 -> 0.95 | I11: =_xlfn.PERCENTILE.INC($E$3:$E$7354,G11) -> -0.041580189 | J11: =$K$8*(1-I11) -> 132.59316 | K11: =$K$8-J11 -> -5.293158
B12: Apr 27, 1999 | C12: 9.73 | D12: =(C12-C13)/C13 -> -0.17612193 | E12: 9.4623656 | G12: 0.01 | H12: =100%-G12 -> 0.99 | I12: =_xlfn.PERCENTILE.INC($E$3:$E$7354,G12) -> -0.077309692 | J12: =$K$8*(1-I12) -> 137.14152 | K12: =$K$8-J12 -> -9.8415238
B13: Nov 25, 1998 | C13: 11.81 | D13: =(C13-C14)/C14 -> -0.67758668 | E13: 9.4513274 | G13: 0.005 | H13: =100%-G13 -> 0.995 | I13: =_xlfn.PERCENTILE.INC($E$3:$E$7354,G13) -> -0.097967738 | J13: =$K$8*(1-I13) -> 139.77129 | K13: =$K$8-J13 -> -12.471293
B14: Nov 26, 2003 | C14: 36.63 | D14: =(C14-C15)/C15 -> -0.14395887 | E14: 6.0038241 | G14: 0.08 | H14: =100%-G14 -> 0.92 | I14: =_xlfn.PERCENTILE.INC($E$3:$E$7354,G14) -> -0.033242379 | J14: =$K$8*(1-I14) -> 131.53175 | K14: =$K$8-J14 -> -4.2317548
B15: Dec 25, 2003 | C15: 42.79 | D15: =(C15-C16)/C16 -> 0.0030473511 | E15: 6.0032733
B16: Apr 26, 2004 | C16: 42.66 | D16: =(C16-C17)/C17 -> 2.1460177 | E16: 5.9934426
B17: Apr 14, 2003 | C17: 13.56 | D17: =(C17-C18)/C18 -> -0.84158879 | E17: 5.9896907
B18: Jun 16, 2022 | C18: 85.6 | D18: =(C18-C19)/C19 -> 8.1550802 | E18: 1.0060933
B19: May 18, 2009 | C19: 9.35 | D19: =(C19-C20)/C20 -> -0.63787761 | E19: 0.17021277
B20: Oct 29, 2007 | C20: 25.82 | D20: =(C20-C21)/C21 -> 0.2037296 | E20: 0.16938406
B21: Oct 10, 2007 | C21: 21.45 | D21: =(C21-C22)/C22 -> 7.4448819 | E21: 0.14828694
B22: Feb 8, 1996 | C22: 2.54 | D22: =(C22-C23)/C23 -> -0.80669711 | E22: 0.14414414
B23: Mar 13, 2020 | C23: 13.14 | D23: =(C23-C24)/C24 -> 1.3890909 | E23: 0.1366782
B24: Dec 4, 2008 | C24: 5.5 | D24: =(C24-C25)/C25 -> -0.36781609 | E24: 0.13636364
B25: Feb 15, 2016 | C25: 8.7 | D25: =(C25-C26)/C26 -> 0.38095238 | E25: 0.13428944
B26: Nov 10, 2008 | C26: 6.3 | D26: =(C26-C27)/C27 -> -0.42307692 | E26: 0.13105925
... B7354: Nov 26, 1998 | C7354: 1.06 | D7354: =(C7354-C7355)/C7355 -> -0.56557377 | E7354: -0.91024555
B7355: Jan 1, 1996 | C7355: 2.44

Sheet Monte Carlo Simulation
B3: The Valuation School
B8: Date | C8: Closing Price | D8: Return | E8: Sorted Return | F8: Replication | G8: Simulated Return | H8: Calculation of Value at Risk- Tata Stell (Simulation)
B9: Mar 29, 1999 | C9: 12.84 | D9: =(C9-C10)/C10 -> -0.30669546 | E9: 9.5245902 | F9: 1 | G9: =_xlfn.NORM.INV(RAND(),L$11,L$12) -> -0.20237664
B10: Nov 23, 1999 | C10: 18.52 | D10: =(C10-C11)/C11 -> -0.12847059 | E10: 9.5227273 | F10: 2 | G10: =_xlfn.NORM.INV(RAND(),L$11,L$12) -> -0.34206172 | H10: Historical Approach
B11: Apr 14, 1997 | C11: 21.25 | D11: =(C11-C12)/C12 -> 0.41383899 | E11: 9.519802 | F11: 3 | G11: =_xlfn.NORM.INV(RAND(),L$11,L$12) -> -0.22093794 | H11: Mean | L11: =AVERAGE(E9:E7360) -> 0.016596515
B12: Mar 2, 1999 | C12: 15.03 | D12: =(C12-C13)/C13 -> -0.20936349 | E12: 9.5104895 | F12: 4 | G12: =_xlfn.NORM.INV(RAND(),L$11,L$12) -> -0.092283872 | H12: Standerd Deviation | L12: =_xlfn.STDEV.S(E9:E7360) -> 0.39587383
B13: Nov 8, 1999 | C13: 19.01 | D13: =(C13-C14)/C14 -> 0.31193927 | E13: 9.5027624 | F13: 5 | G13: =_xlfn.NORM.INV(RAND(),L$11,L$12) -> 0.3759342 | H13: Mim | L13: =MIN(E9:E7360) -> -0.91024555
B14: Dec 25, 1998 | C14: 14.49 | D14: =(C14-C15)/C15 -> -0.45648912 | E14: 9.5 | F14: 6 | G14: =_xlfn.NORM.INV(RAND(),L$11,L$12) -> -0.00049874898 | H14: Max | L14: =MAX(E9:E7360) -> 9.5245902
B15: Mar 7, 1997 | C15: 26.66 | D15: =(C15-C16)/C16 -> 1.4915888 | E15: 9.496063 | F15: 7 | G15: =_xlfn.NORM.INV(RAND(),L$11,L$12) -> 0.022765405 | H15: CMP | L15: 127.3
B16: Nov 4, 1998 | C16: 10.7 | D16: =(C16-C17)/C17 -> -0.50163018 | E16: 9.4901961 | F16: 8 | G16: =_xlfn.NORM.INV(RAND(),L$11,L$12) -> 0.18392864
B17: Nov 12, 1996 | C17: 21.47 | D17: =(C17-C18)/C18 -> 1.2065776 | E17: 9.4731707 | F17: 9 | G17: =_xlfn.NORM.INV(RAND(),L$11,L$12) -> 0.11138755 | H17: Monte Carlo Simulation
B18: Apr 27, 1999 | C18: 9.73 | D18: =(C18-C19)/C19 -> -0.17612193 | E18: 9.4623656 | F18: 10 | G18: =_xlfn.NORM.INV(RAND(),L$11,L$12) -> 0.035873407 | H18: Mean | L18: =AVERAGE(G9:G7361) -> 0.015304105
B19: Nov 25, 1998 | C19: 11.81 | D19: =(C19-C20)/C20 -> -0.67758668 | E19: 9.4513274 | F19: 11 | G19: =_xlfn.NORM.INV(RAND(),L$11,L$12) -> -0.2708711 | H19: Standerd Deviation | L19: =_xlfn.STDEV.S(G9:G7361) -> 0.39808392
B20: Nov 26, 2003 | C20: 36.63 | D20: =(C20-C21)/C21 -> -0.14395887 | E20: 6.0038241 | F20: 12 | G20: =_xlfn.NORM.INV(RAND(),L$11,L$12) -> -0.15557423 | H20: Mim | L20: =MIN(G9:G7361) -> -1.6184454
B21: Dec 25, 2003 | C21: 42.79 | D21: =(C21-C22)/C22 -> 0.0030473511 | E21: 6.0032733 | F21: 13 | G21: =_xlfn.NORM.INV(RAND(),L$11,L$12) -> 0.50560685 | H21: Max | L21: =MAX(G9:G7361) -> 1.6855927
B22: Apr 26, 2004 | C22: 42.66 | D22: =(C22-C23)/C23 -> 2.1460177 | E22: 5.9934426 | F22: 14 | G22: =_xlfn.NORM.INV(RAND(),L$11,L$12) -> -0.053071808 | H22: CMP | L22: 127.3
B23: Apr 14, 2003 | C23: 13.56 | D23: =(C23-C24)/C24 -> -0.84158879 | E23: 5.9896907 | F23: 15 | G23: =_xlfn.NORM.INV(RAND(),L$11,L$12) -> -0.2944372
B24: Jun 16, 2022 | C24: 85.6 | D24: =(C24-C25)/C25 -> 8.1550802 | E24: 1.0060933 | F24: 16 | G24: =_xlfn.NORM.INV(RAND(),L$11,L$12) -> -0.78956074 | H24: Percentile | I24: Confidence | J24: VAR% | K24: Stock Price | L24: VAR(INR)
B25: May 18, 2009 | C25: 9.35 | D25: =(C25-C26)/C26 -> -0.63787761 | E25: 0.17021277 | F25: 17 | G25: =_xlfn.NORM.INV(RAND(),L$11,L$12) -> -0.56407218 | H25: 0.05 | I25: =100%-H25 -> 0.95 | J25: =_xlfn.PERCENTILE.INC($G$9:$G$7361,H25) -> -0.63983915 | K25: =$L$15*(1-J25) -> 208.75152 | L25: =$L$15-K25 -> -81.451523
B26: Oct 29, 2007 | C26: 25.82 | D26: =(C26-C27)/C27 -> 0.2037296 | E26: 0.16938406 | F26: 18 | G26: =_xlfn.NORM.INV(RAND(),L$11,L$12) -> 0.17176787 | H26: 0.01 | I26: =100%-H26 -> 0.99 | J26: =_xlfn.PERCENTILE.INC($G$9:$G$7361,H26) -> -0.90031726 | K26: =$L$15*(1-J26) -> 241.91039 | L26: =$L$15-K26 -> -114.61039
B27: Oct 10, 2007 | C27: 21.45 | D27: =(C27-C28)/C28 -> 7.4448819 | E27: 0.14828694 | F27: 19 | G27: =_xlfn.NORM.INV(RAND(),L$11,L$12) -> -0.25163478 | H27: 0.005 | I27: =100%-H27 -> 0.995 | J27: =_xlfn.PERCENTILE.INC($G$9:$G$7361,H27) -> -0.98251622 | K27: =$L$15*(1-J27) -> 252.37431 | L27: =$L$15-K27 -> -125.07431
B28: Feb 8, 1996 | C28: 2.54 | D28: =(C28-C29)/C29 -> -0.80669711 | E28: 0.14414414 | F28: 20 | G28: =_xlfn.NORM.INV(RAND(),L$11,L$12) -> -0.4056405 | H28: 0.08 | I28: =100%-H28 -> 0.92 | J28: =_xlfn.PERCENTILE.INC($G$9:$G$7361,H28) -> -0.54884053 | K28: =$L$15*(1-J28) -> 197.1674 | L28: =$L$15-K28 -> -69.8674
B29: Mar 13, 2020 | C29: 13.14 | D29: =(C29-C30)/C30 -> 1.3890909 | E29: 0.1366782 | F29: 21 | G29: =_xlfn.NORM.INV(RAND(),L$11,L$12) -> 0.10022235
B30: Dec 4, 2008 | C30: 5.5 | D30: =(C30-C31)/C31 -> -0.36781609 | E30: 0.13636364 | F30: 22 | G30: =_xlfn.NORM.INV(RAND(),L$11,L$12) -> -0.15400838
B31: Feb 15, 2016 | C31: 8.7 | D31: =(C31-C32)/C32 -> 0.38095238 | E31: 0.13428944 | F31: 23 | G31: =_xlfn.NORM.INV(RAND(),L$11,L$12) -> 0.30948538
B32: Nov 10, 2008 | C32: 6.3 | D32: =(C32-C33)/C33 -> -0.42307692 | E32: 0.13105925 | F32: 24 | G32: =_xlfn.NORM.INV(RAND(),L$11,L$12) -> 0.34481933
B33: May 20, 2009 | C33: 10.92 | D33: =(C33-C34)/C34 -> 5.6585366 | E33: 0.12809917 | F33: 25 | G33: =_xlfn.NORM.INV(RAND(),L$11,L$12) -> 0.34579229
B34: Mar 14, 2001 | C34: 1.64 | D34: =(C34-C35)/C35 -> -0.73376623 | E34: 0.12328767 | F34: 26 | G34: =_xlfn.NORM.INV(RAND(),L$11,L$12) -> -0.43264237
B35: Oct 31, 2008 | C35: 6.16 | D35: =(C35-C36)/C36 -> 2.5 | E35: 0.12204007 | F35: 27 | G35: =_xlfn.NORM.INV(RAND(),L$11,L$12) -> 0.29321077
B36: Jun 2, 2000 | C36: 1.76 | D36: =(C36-C37)/C37 -> -0.597254 | E36: 0.12101911 | F36: 28 | G36: =_xlfn.NORM.INV(RAND(),L$11,L$12) -> 0.071943723
B37: May 18, 2004 | C37: 4.37 | D37: =(C37-C38)/C38 -> -0.61361627 | E37: 0.11764706 | F37: 29 | G37: =_xlfn.NORM.INV(RAND(),L$11,L$12) -> 0.30185605
B38: Jun 16, 2006 | C38: 11.31 | D38: =(C38-C39)/C39 -> 0.7671875 | E38: 0.1120944 | F38: 30 | G38: =_xlfn.NORM.INV(RAND(),L$11,L$12) -> 0.027412398
B39: Dec 10, 2008 | C39: 6.4 | D39: =(C39-C40)/C40 -> 0.16575592 | E39: 0.11111111 | F39: 31 | G39: =_xlfn.NORM.INV(RAND(),L$11,L$12) -> 0.22170167
B40: Oct 29, 2008 | C40: 5.49 | D40: =(C40-C41)/C41 -> 0.13429752 | E40: 0.10909091 | F40: 32 | G40: =_xlfn.NORM.INV(RAND(),L$11,L$12) -> -0.10267756
... B7360: Nov 26, 1998 | C7360: 1.06 | D7360: =(C7360-C7361)/C7361 -> -0.56557377 | E7360: -0.91024555 | F7360: 7352 | G7360: =_xlfn.NORM.INV(RAND(),L$11,L$12) -> -0.26933197
B7361: Jan 1, 1996 | C7361: 2.44 | F7361: 7353 | G7361: =_xlfn.NORM.INV(RAND(),L$11,L$12) -> 1.2266451

Sheet Peer Comps
C2: Peer Comps
D3: Debt | E3: Equity
B4: 1 | C4: JSW Steel | D4: 95258 | E4: 245951.53
B5: 2 | C5: Tata Steel | D5: 99391.76 | E5: 175256.24
B6: 3 | C6: Jindal Steel | D6: 17266.45 | E6: 86717.69
B7: 4 | C7: Tube Investments | D7: 698.92 | E7: 51029.18
B8: 5 | C8: S A I L | D8: 41265.03 | E8: 46509.71

Sheet Data Sheet
A1: COMPANY NAME | B1: TATA STEEL LTD | E1: =IF(B2<>B3, "A NEW VERSION OF THE WORKSHEET IS AVAILABLE", "")
A2: LATEST VERSION | B2: 2.1 | E2: PLEASE DO NOT MAKE ANY CHANGES TO THIS SHEET
A3: CURRENT VERSION | B3: 2.1
A5: META
A6: Number of shares | B6: =IF(B9>0, B9/B8, 0) -> 1248.3531
A7: Face Value | B7: 1
A8: Current Price | B8: 145.35
A9: Market Capitalization | B9: 181448.12
A15: PROFIT & LOSS
A16: Report Date | B16: 42094 | C16: 42460 | D16: 42825 | E16: 43190 | F16: 43555 | G16: 43921 | H16: 44286 | I16: 44651 | J16: 45016 | K16: 45382
A17: Sales | B17: 139503.73 | C17: 101964.72 | D17: 112299.42 | E17: 123249.07 | F17: 157668.99 | G17: 139816.65 | H17: 156294.18 | I17: 243959.17 | J17: 243352.69 | K17: 229170.78
A18: Raw Material Cost | B18: 54545.26 | C18: 38696.27 | D18: 43843.03 | E18: 46137.01 | F18: 60877.05 | G18: 58039.99 | H18: 55423.38 | I18: 91076.61 | J18: 116597.19 | K18: 97506.39
A19: Change in Inventory | B19: -1122.18 | C19: -1925.19 | D19: 4538.13 | E19: -99.31 | F19: 96.71 | G19: 565.24 | H19: -1516.77 | I19: 7597.87 | J19: 3358.89 | K19: -4409.35
A20: Power and Fuel | B20: 6845.38 | C20: 4993.89 | D20: 5220.83 | E20: 4440.43 | F20: 5316.56 | G20: 5319.92 | H20: 5788.48 | I20: 8028.29 | J20: 9526.91 | K20: 10071.85
A21: Other Mfr. Exp | B21: 20370.48 | C21: 16034.28 | D21: 15799.14 | E21: 16955.79 | F21: 20734.28 | G21: 21232.69 | H21: 20744.92 | I21: 28834.06 | J21: 33144.83 | K21: 34263.1
A22: Employee Cost | B22: 21407.64 | C22: 17587.63 | D22: 17252.22 | E22: 17077.51 | F22: 18758.87 | G22: 18533.58 | H22: 19908.81 | I22: 23264.1 | J22: 22419.32 | K22: 24509.58
A23: Selling and admin | B23: 15868.37 | C23: 12908.42 | D23: 13772.32 | E23: 14423.87 | F23: 16917.14 | G23: 15599.07 | H23: 16923.93 | I23: 27445.67 | J23: 25519.92 | K23: 27155.29
A24: Other Expenses | B24: 15935.54 | C24: 10444.28 | D24: 7806.38 | E24: 2681.96 | F24: 5843.58 | G24: 4193.58 | H24: 5483.63 | I24: 9418.36 | J24: 7203.25 | K24: 9007.3
A25: Other Income | B25: 5994.38 | C25: 10345.87 | D25: -3789.11 | E25: 10898.41 | F25: 1524.31 | G25: -2883.63 | H25: 179.78 | I25: 1299.99 | J25: 1568.86 | K25: -6005.23
A26: Depreciation | B26: 5943.6 | C26: 5306.35 | D26: 5672.88 | E26: 5741.7 | F26: 7341.83 | G26: 8440.73 | H26: 9233.64 | I26: 9100.87 | J26: 9335.2 | K26: 9882.16
A27: Interest | B27: 4847.75 | C27: 4221.41 | D27: 5072.2 | E27: 5454.74 | F27: 7660.1 | G27: 7533.46 | H27: 7606.71 | I27: 5462.2 | J27: 6298.7 | K27: 7507.57
... A31: Dividend Amount | B31: 777.13 | C31: 776.19 | D31: 970.24 | E31: 1144.95 | F31: 1488.42 | G31: 1144.95 | H31: 2994.02 | I31: 6228.17 | J31: 4396.46 | K31: 4490.78
A33: EBITDA | B33: =B17-SUM(B18:B24) -> 5653.24
A34: EBIT
A40: Quarters
A41: Report Date | B41: 44834 | C41: 44926 | D41: 45016 | E41: 45107 | F41: 45199 | G41: 45291 | H41: 45382 | I41: 45473 | J41: 45565 | K41: 45657
A42: Sales | B42: 59877.52 | C42: 57083.56 | D42: 62961.54 | E42: 59489.66 | F42: 55681.93 | G42: 55311.88 | H42: 58687.31 | I42: 54771.39 | J42: 53904.71 | K42: 53648.3
A43: Expenses | B43: 53817.2 | C43: 53035.72 | D43: 55742.34 | E43: 54587.06 | F43: 51414.11 | G43: 49048.31 | H43: 52086.68 | I43: 48076.92 | J43: 47788.92 | K43: 47744.81
A44: Other Income | B44: 411.69 | C44: 491.43 | D44: 277.38 | E44: 1190.24 | F44: -6567.77 | G44: -32.84 | H44: -381.56 | I44: -5.51 | J44: 616.68 | K44: 141.82
A45: Depreciation | B45: 2347.82 | C45: 2368.38 | D45: 2382.21 | E45: 2412.32 | F45: 2479.85 | G45: 2422.04 | H45: 2567.95 | I45: 2535.43 | J45: 2596.74 | K45: 2569.19
A46: Interest | B46: 1519.07 | C46: 1767.92 | D46: 1793.6 | E46: 1825.15 | F46: 1959.39 | G46: 1880.78 | H46: 1842.25 | I46: 1776.71 | J46: 1971.4 | K46: 1804.09
A47: Profit before tax | B47: 2605.12 | C47: 402.97 | D47: 3320.77 | E47: 1855.37 | F47: -6739.19 | G47: 1927.91 | H47: 1808.87 | I47: 2376.82 | J47: 2164.33 | K47: 1672.03
A48: Tax | B48: 1308.06 | C48: 2904.92 | D48: 1754.53 | E48: 1330.52 | F48: -228.03 | G48: 1405.77 | H48: 1254.31 | I48: 1458.25 | J48: 1405.49 | K48: 1376.54
A49: Net profit | B49: 1514.42 | C49: -2223.84 | D49: 1704.86 | E49: 633.95 | F49: -6196.24 | G49: 513.37 | H49: 611.48 | I49: 959.61 | J49: 833.45 | K49: 326.64
A50: Operating Profit | B50: 6060.32 | C50: 4047.84 | D50: 7219.2 | E50: 4902.6 | F50: 4267.82 | G50: 6263.57 | H50: 6600.63 | I50: 6694.47 | J50: 6115.79 | K50: 5903.49
A55: BALANCE SHEET
A56: Report Date | B56: 42094 | C56: 42460 | D56: 42825 | E56: 43190 | F56: 43555 | G56: 43921 | H56: 44286 | I56: 44651 | J56: 45016 | K56: 45382
A57: Equity Share Capital | B57: 971.41 | C57: 970.24 | D57: 970.24 | E57: 1144.95 | F57: 1144.94 | G57: 1144.95 | H57: 1197.61 | I57: 1221.21 | J57: 1221.24 | K57: 1247.44
A58: Reserves | B58: 30378 | C58: 42762.31 | D58: 36849.08 | E58: 59725.67 | F58: 67780.14 | G58: 72431.35 | H58: 73041.16 | I58: 113221.83 | J58: 101860.86 | K58: 90788.32
A59: Borrowings | B59: 80701.29 | C59: 81986.93 | D59: 83014.49 | E59: 92147.05 | F59: 100816.22 | G59: 116328.2 | H59: 88501.41 | I59: 75561.35 | J59: 84893.05 | K59: 87082.12
A60: Other Liabilities | B60: 47058.6 | C60: 51164.51 | D60: 51613.56 | E60: 55704.47 | F60: 63032.14 | G60: 59244.62 | H60: 81169.01 | I60: 92417.28 | J60: 97420.63 | K60: 90194.54
A61: Total | B61: 159109.3 | C61: 176883.99 | D61: 172447.37 | E61: 208722.14 | F61: 232773.44 | G61: 249149.12 | H61: 243909.19 | I61: 282421.67 | J61: 285395.78 | K61: 269312.42
A62: Net Block | B62: 68100.33 | C62: 72199.76 | D62: 92006.55 | E62: 96104.89 | F62: 124441.91 | G62: 134550.66 | H62: 135775.18 | I62: 133287.83 | J62: 146621.46 | K62: 148814.38
A63: Capital Work in Progress | B63: 28678.12 | C63: 35996.09 | D63: 15784.13 | E63: 16614.41 | F63: 18641.21 | G63: 19496.83 | H63: 19007.4 | I63: 22045.55 | J63: 31213.02 | K63: 34355.53
A64: Investments | B64: 3455.05 | C64: 10713.71 | D64: 12457.12 | E64: 17899.47 | F64: 5738.17 | G64: 6285.18 | H64: 10681.93 | I64: 13139.85 | J64: 8410.31 | K64: 6257.57
A65: Other Assets | B65: 58875.8 | C65: 57974.43 | D65: 52199.57 | E65: 78103.37 | F65: 83952.15 | G65: 88816.45 | H65: 78444.68 | I65: 113948.44 | J65: 99150.99 | K65: 79884.94
A66: Total | B66: 159109.3 | C66: 176883.99 | D66: 172447.37 | E66: 208722.14 | F66: 232773.44 | G66: 249149.12 | H66: 243909.19 | I66: 282421.67 | J66: 285395.78 | K66: 269312.42
A67: Receivables | B67: 13309.87 | C67: 12066.22 | D67: 11586.82 | E67: 12415.52 | F67: 11811 | G67: 7884.91 | H67: 9539.84 | I67: 12246.43 | J67: 8257.24 | K67: 6263.53
... A70: No. of Equity Shares | B70: 971604916 | C70: 970436562 | D70: 970436562 | E70: 1203340563 | F70: 1203331928 | G70: 1203332459 | H70: 1203334622 | I70: 1221566453 | J70: 12212353070 | K70: 12474347611
A71: New Bonus Shares
A72: Face value | B72: 10 | C72: 10 | D72: 10 | E72: 10 | F72: 10 | G72: 10 | H72: 10 | I72: 10 | J72: 1 | K72: 1
A74: Other Asset | B74: =B65-SUM(B67:B69) -> 11666.08 | C74: =C65-SUM(C67:C69) -> 19708.54 | D74: =D65-SUM(D67:D69) -> 10887.88 | E74: =E65-SUM(E67:E69) -> 29418.96 | F74: =F65-SUM(F67:F69) -> 37143.68 | G74: =G65-SUM(G67:G69) -> 41808.1 | H74: =H65-SUM(H67:H69) -> 29846.28 | I74: =I65-SUM(I67:I69) -> 36978.69 | ... K74: =K65-SUM(K67:K69) -> 15786.18
A80: CASH FLOW:
A81: Report Date | B81: 42094 | C81: 42460 | D81: 42825 | E81: 43190 | F81: 43555 | G81: 43921 | H81: 44286 | I81: 44651 | J81: 45016 | K81: 45382
A82: Cash from Operating Activity | B82: 11879.77 | C82: 11455.35 | D82: 10824.36 | E82: 8023.39 | F82: 25335.95 | G82: 20168.72 | H82: 44326.68 | I82: 44380.99 | J82: 21683.08 | K82: 20300.67
A83: Cash from Investing Activity | B83: -9021.13 | C83: -8794.31 | D83: -9489.65 | E83: -11730.31 | F83: -29176.45 | G83: -14012.06 | H83: -9437.27 | I83: -10905.02 | J83: -18179.45 | K83: -14252.74
A84: Cash from Financing Activity | B84: -2617.19 | C84: -4729.12 | D84: -2579.36 | E84: 6639.94 | F84: -672.7 | G84: -1694.62 | H84: -37089.67 | I84: -23401.09 | J84: -6980.69 | K84: -11096.99
A85: Net Cash Flow | B85: 241.45 | C85: -2068.08 | D85: -1244.65 | E85: 2933.02 | F85: -4513.2 | G85: 4462.04 | H85: -2200.26 | I85: 10074.88 | J85: -3477.06 | K85: -5049.06
A90: PRICE: | B90: 30.18 | C90: 30.46 | D90: 45.99 | E90: 57.11 | F90: 52.1 | G90: 26.96 | H90: 81.19 | I90: 130.72 | J90: 104.5 | K90: 155.85
A92: DERIVED:
A93: Adjusted Equity Shares in Cr | B93: 1126.62 | C93: 1126.62 | D93: 1126.62 | E93: 1126.48 | F93: 1126.49 | G93: 1126.49 | H93: 1196.59 | I93: 1221.3 | J93: 1222.15 | K93: 1248.35

Sheet Rough Data
O1: Balance Sheet
C2: 42064 | D2: 42430 | E2: 42795 | F2: 43160 | G2: 43525 | H2: 43891 | I2: 44256 | J2: 44621 | K2: 44986 | L2: 45352 | P2: 42064 | Q2: 42430 | R2: 42795 | S2: 43160 | T2: 43525 | U2: 43891 | V2: 44256 | W2: 44621 | X2: 44986 | Y2: 45352 | Z2: 45536 | AB2: Balance Sheet | AT2: Profit &Loss
B3: Cash from Operating Activity - | C3: 11880 | D3: 11455 | E3: 10824 | F3: 8023 | G3: 25336 | H3: 20169 | I3: 44327 | J3: 44381 | K3: 21683 | L3: 20301 | O3: Equity Capital | P3: 971 | Q3: 970 | R3: 970 | S3: 1145 | T3: 1145 | U3: 1145 | V3: 1198 | W3: 1221 | X3: 1221 | Y3: 1247 | Z3: 1247 | AD3: 41334 | AE3: 41699 | AF3: 42064 | AG3: 42430 | AH3: 42795 | AI3: 43160 | AJ3: 43525 | AK3: 43891 | AL3: 44256 | AM3: 44621 | AN3: 44986 | AO3: 45352 | AP3: 45536 | AU3: 41334 | AV3: 41699 | AW3: 42064 | AX3: 42430 | AY3: 42795 | AZ3: 43160 | BA3: 43525 | BB3: 43891 | BC3: 44256 | BD3: 44621 | BE3: 44986 | BF3: 45352
B4: Profit from operations | C4: 13955 | D4: 6824 | E4: 17581 | F4: 20187 | G4: 27840 | H4: 18078 | I4: 28540 | J4: 65900 | K4: 30908 | L4: 22237 | O4: Reserves | P4: 30378 | Q4: 42762 | R4: 36849 | S4: 59726 | T4: 67780 | U4: 72431 | V4: 73041 | W4: 113222 | X4: 101861 | Y4: 90788 | Z4: 88900 | AC4: Equity Capital | AD4: 971 | AE4: 971 | AF4: 971 | AG4: 970 | AH4: 970 | AI4: 1145 | AJ4: 1145 | AK4: 1145 | AL4: 1198 | AM4: 1221 | AN4: 1221 | AO4: 1247 | AP4: 1247 | AT4: Cash from Operating Activity - | AU4: 14035 | AV4: 13146 | AW4: 11880 | AX4: 11455 | AY4: 10824 | AZ4: 8023 | BA4: 25336 | BB4: 20169 | BC4: 44327 | BD4: 44381 | BE4: 21683 | BF4: 20301
B5: Receivables | C5: 1442 | D5: 0 | E5: 0 | F5: 0 | G5: 0 | H5: 0 | I5: 0 | J5: 0 | K5: 0 | L5: 0 | O5: Borrowings - | P5: 80701 | Q5: 81987 | R5: 83014 | S5: 92147 | T5: 100816 | U5: 116328 | V5: 88501 | W5: 75561 | X5: 84893 | Y5: 87082 | Z5: 99392 | AC5: Reserves | AD5: 33201 | AE5: 39561 | AF5: 30378 | AG5: 42762 | AH5: 36849 | AI5: 59726 | AJ5: 67780 | AK5: 72431 | AL5: 73041 | AM5: 113222 | AN5: 101861 | AO5: 90788 | AP5: 88900 | AT5: Profit from operations | AU5: 12764 | AV5: 17507 | AW5: 13955 | AX5: 6824 | AY5: 17581 | AZ5: 20187 | BA5: 27840 | BB5: 18078 | BC5: 28540 | BD5: 65900 | BE5: 30908 | BF5: 22237
B6: Inventory | C6: -485 | D6: 5618 | E6: -8243 | F6: -1595 | G6: -1069 | H6: 1562 | I6: 46 | J6: -16917 | K6: -4031 | L6: 5566 | O6: Long term Borrowings | P6: 65675 | Q6: 64873 | R6: 64022 | S6: 72789 | T6: 80343 | U6: 94105 | V6: 72409 | W6: 44764 | X6: 51446 | Y6: 51577 | Z6: 67148 | AC6: Borrowings - | AD6: 68529 | AE6: 81629 | AF6: 80701 | AG6: 81987 | AH6: 83014 | AI6: 92147 | AJ6: 100816 | AK6: 116328 | AL6: 88501 | AM6: 75561 | AN6: 84893 | AO6: 87082 | AP6: 99392 | AT6: Receivables | AU6: 1342 | AV6: -1483 | AW6: 1442 | AX6: 0 | AY6: 0 | AZ6: 0 | BA6: 0 | BB6: 0 | BC6: 0 | BD6: 0 | BE6: 0 | BF6: 0
B7: Payables | C7: -605 | D7: 0 | E7: 0 | F7: 0 | G7: 0 | H7: 0 | I7: 0 | J7: 0 | K7: 0 | L7: 0 | O7: Short term Borrowings | P7: 9599 | Q7: 15722 | R7: 18328 | S7: 15885 | T7: 10802 | U7: 19184 | V7: 9492 | W7: 24065 | X7: 26571 | Y7: 29997 | Z7: 26960 | AC7: Long term Borrowings | AD7: 46858 | AE7: 52366 | AF7: 65675 | AG7: 64873 | AH7: 64022 | AI7: 72789 | AJ7: 80343 | AK7: 94105 | AL7: 72409 | AM7: 44764 | AN7: 51446 | AO7: 51577 | AP7: 67148 | AT7: Inventory | AU7: 1915 | AV7: 389 | AW7: -485 | AX7: 5618 | AY7: -8243 | AZ7: -1595 | BA7: -1069 | BB7: 1562 | BC7: 46 | BD7: -16917 | BE7: -4031 | BF7: 5566
B8: Other WC items | C8: 0 | D8: 548 | E8: 3329 | F8: -7680 | G8: 3659 | H8: 2634 | I8: 16446 | J8: 7299 | K8: 325 | L8: -2182 | O8: Lease Liabilities | P8: 0 | Q8: 0 | R8: 0 | S8: 0 | T8: 0 | U8: 0 | V8: 0 | W8: 6733 | X8: 6875 | Y8: 5508 | Z8: 5284 | AC8: Short term Borrowings | AD8: 10548 | AE8: 16026 | AF8: 9599 | AG8: 15722 | AH8: 18328 | AI8: 15885 | AJ8: 10802 | AK8: 19184 | AL8: 9492 | AM8: 24065 | AN8: 26571 | AO8: 29997 | AP8: 26960 | AT8: Payables | AU8: 583 | AV8: -255 | AW8: -605 | AX8: 0 | AY8: 0 | AZ8: 0 | BA8: 0 | BB8: 0 | BC8: 0 | BD8: 0 | BE8: 0 | BF8: 0
B9: Working capital changes | C9: 351 | D9: 6166 | E9: -4914 | F9: -9276 | G9: 2591 | H9: 4196 | I9: 16491 | J9: -9618 | K9: -3706 | L9: 3384 | O9: Preference Capital | P9: 0 | Q9: 0 | R9: 0 | S9: 20 | T9: 13 | U9: 0 | V9: 0 | W9: 0 | X9: 0 | Y9: 0 | Z9: 0 | AC9: Lease Liabilities | AD9: 0 | AE9: 0 | AF9: 0 | AG9: 0 | AH9: 0 | AI9: 0 | AJ9: 0 | AK9: 0 | AL9: 0 | AM9: 6733 | AN9: 6875 | AO9: 5508 | AP9: 5284 | AT9: Other WC items | AU9: 0 | AV9: 0 | AW9: 0 | AX9: 548 | AY9: 3329 | AZ9: -7680 | BA9: 3659 | BB9: 2634 | BC9: 16446 | BD9: 7299 | BE9: 325 | BF9: -2182
B10: Direct taxes | C10: -2427 | D10: -1534 | E10: -1843 | F10: -2888 | G10: -5094 | H10: -2106 | I10: -704 | J10: -11902 | K10: -5519 | L10: -5320 | O10: Other Borrowings | P10: 5428 | Q10: 1392 | R10: 664 | S10: 3473 | T10: 9671 | U10: 3039 | V10: 6601 | W10: 0 | X10: 0 | Y10: 0 | AC10: Preference Capital | AD10: 21 | AE10: 20 | AF10: 0 | AG10: 0 | AH10: 0 | AI10: 20 | AJ10: 13 | AK10: 0 | AL10: 0 | AM10: 0 | AN10: 0 | AO10: 0 | AP10: 0 | AT10: Working capital changes | AU10: 3841 | AV10: -1349 | AW10: 351 | AX10: 6166 | AY10: -4914 | AZ10: -9276 | BA10: 2591 | BB10: 4196 | BC10: 16491 | BD10: -9618 | BE10: -3706 | BF10: 3384
B11: Cash from Investing Activity - | C11: -9021 | D11: -8794 | E11: -9490 | F11: -11730 | G11: -29176 | H11: -14012 | I11: -9437 | J11: -10905 | K11: -18179 | L11: -14253 | O11: Other Liabilities - | P11: 47059 | Q11: 51165 | R11: 51614 | S11: 55704 | T11: 63032 | U11: 59245 | V11: 81169 | W11: 92417 | X11: 97421 | Y11: 90195 | Z11: 91302 | AC11: Other Borrowings | AD11: 11123 | AE11: 13236 | AF11: 5428 | AG11: 1392 | AH11: 664 | AI11: 3473 | AJ11: 9671 | AK11: 3039 | AL11: 6601 | AM11: 0 | AN11: 0 | AO11: 0 | AT11: Direct taxes | AU11: -2569 | AV11: -3013 | AW11: -2427 | AX11: -1534 | AY11: -1843 | AZ11: -2888 | BA11: -5094 | BB11: -2106 | BC11: -704 | BD11: -11902 | BE11: -5519 | BF11: -5320
B12: Fixed assets purchased | C12: -13492 | D12: -10163 | E12: -7716 | F12: -7478 | G12: -9091 | H12: -10398 | I12: -6979 | J12: -10522 | K12: -14142 | L12: -18207 | O12: Non controlling int | P12: 1704 | Q12: 781 | R12: 1602 | S12: 937 | T12: 2364 | U12: 2587 | V12: 3270 | W12: 2655 | X12: 2093 | Y12: 397 | Z12: 362 | AC12: Other Liabilities - | AD12: 44176 | AE12: 49443 | AF12: 47059 | AG12: 51165 | AH12: 51614 | AI12: 55704 | AJ12: 63032 | AK12: 59245 | AL12: 81169 | AM12: 92417 | AN12: 97421 | AO12: 90195 | AP12: 91302 | AT12: Cash from Investing Activity - | AU12: -13099 | AV12: -15378 | AW12: -9021 | AX12: -8794 | AY12: -9490 | AZ12: -11730 | BA12: -29176 | BB12: -14012 | BC12: -9437 | BD12: -10905 | BE12: -18179 | BF12: -14253
B13: Fixed assets sold | C13: 1444 | D13: 231 | E13: 289 | F13: 179 | G13: 467 | H13: 386 | I13: 445 | J13: 569 | K13: 328 | L13: 475 | O13: Trade Payables | P13: 19190 | Q13: 18557 | R13: 18574 | S13: 20414 | T13: 21717 | U13: 21381 | V13: 25967 | W13: 36765 | X13: 37833 | Y13: 35435 | Z13: 32502 | AC13: Non controlling int | AD13: 1669 | AE13: 1738 | AF13: 1704 | AG13: 781 | AH13: 1602 | AI13: 937 | AJ13: 2364 | AK13: 2587 | AL13: 3270 | AM13: 2655 | AN13: 2093 | AO13: 397 | AP13: 362 | AT13: Fixed assets purchased | AU13: -15472 | AV13: -16420 | AW13: -13492 | AX13: -10163 | AY13: -7716 | AZ13: -7478 | BA13: -9091 | BB13: -10398 | BC13: -6979 | BD13: -10522 | BE13: -14142 | BF13: -18207
B14: Investments purchased | C14: 1531 | D14: -3796 | E14: -861 | F14: -8641 | G14: -490 | H14: -828 | I14: -3631 | J14: -1153 | K14: -326 | L14: -4 | O14: Advance from Customers | P14: 367 | Q14: 456 | R14: 566 | S14: 616 | T14: 819 | U14: 869 | V14: 2399 | W14: 3253 | X14: 3394 | Y14: 2773 | AC14: Trade Payables | AD14: 19340 | AE14: 22904 | AF14: 19190 | AG14: 18557 | AH14: 18574 | AI14: 20414 | AJ14: 21717 | AK14: 21381 | AL14: 25967 | AM14: 36765 | AN14: 37833 | AO14: 35435 | AP14: 32502 | AT14: Fixed assets sold | AU14: 249 | AV14: 295 | AW14: 1444 | AX14: 231 | AY14: 289 | AZ14: 179 | BA14: 467 | BB14: 386 | BC14: 445 | BD14: 569 | BE14: 328 | BF14: 475
B15: Investments sold | C15: 262 | D15: 4275 | E15: 91 | F15: 3899 | G15: 13556 | H15: 121 | I15: 0 | J15: 63 | K15: 5191 | L15: 3171 | O15: Other liability items | P15: 25798 | Q15: 31371 | R15: 30871 | S15: 33738 | T15: 38131 | U15: 34408 | V15: 49533 | W15: 49744 | X15: 54101 | Y15: 51590 | Z15: 58437 | AC15: Advance from Customers | AD15: 556 | AE15: 310 | AF15: 367 | AG15: 456 | AH15: 566 | AI15: 616 | AJ15: 819 | AK15: 869 | AL15: 2399 | AM15: 3253 | AN15: 3394 | AO15: 2773 | AT15: Investments purchased | AU15: 0 | AV15: -612 | AW15: 1531 | AX15: -3796 | AY15: -861 | AZ15: -8641 | BA15: -490 | BB15: -828 | BC15: -3631 | BD15: -1153 | BE15: -326 | BF15: -4
B16: Interest received | C16: 211 | D16: 133 | E16: 140 | F16: 254 | G16: 175 | H16: 203 | I16: 266 | J16: 137 | K16: 248 | L16: 333 | O16: Total Liabilities | P16: 159109 | Q16: 176884 | R16: 172447 | S16: 208722 | T16: 232773 | U16: 249149 | V16: 243909 | W16: 282422 | X16: 285396 | Y16: 269312 | Z16: 280841 | AC16: Other liability items | AD16: 22610 | AE16: 24491 | AF16: 25798 | AG16: 31371 | AH16: 30871 | AI16: 33738 | AJ16: 38131 | AK16: 34408 | AL16: 49533 | AM16: 49744 | AN16: 54101 | AO16: 51590 | AP16: 58437 | AT16: Investments sold | AU16: 917 | AV16: 0 | AW16: 262 | AX16: 4275 | AY16: 91 | AZ16: 3899 | BA16: 13556 | BB16: 121 | BC16: 0 | BD16: 63 | BE16: 5191 | BF16: 3171
B17: Dividends received | C17: 127 | D17: 108 | E17: 85 | F17: 111 | G17: 148 | H17: 103 | I17: 135 | J17: 162 | K17: 317 | L17: 336 | O17: Fixed Assets - | P17: 68100 | Q17: 72200 | R17: 92007 | S17: 96105 | T17: 124442 | U17: 134551 | V17: 135775 | W17: 133288 | X17: 146621 | Y17: 148814 | Z17: 149550 | AC17: Total Liabilities | AD17: 146876 | AE17: 171604 | AF17: 159109 | AG17: 176884 | AH17: 172447 | AI17: 208722 | AJ17: 232773 | AK17: 249149 | AL17: 243909 | AM17: 282422 | AN17: 285396 | AO17: 269312 | AP17: 280841 | AT17: Interest received | AU17: 211 | AV17: 265 | AW17: 211 | AX17: 133 | AY17: 140 | AZ17: 254 | BA17: 175 | BB17: 203 | BC17: 266 | BD17: 137 | BE17: 248 | BF17: 333
B18: Redemp n Canc of Shares | C18: 1301 | D18: 0 | E18: 0 | F18: 34 | G18: 156 | H18: 378 | I18: 90 | J18: 1208 | K18: 166 | L18: 123 | O18: Land | P18: 2433 | Q18: 16499 | R18: 16545 | S18: 16955 | T18: 17126 | U18: 19853 | V18: 20656 | W18: 20770 | X18: 21701 | Y18: 22067 | AC18: Fixed Assets - | AD18: 68002 | AE18: 74907 | AF18: 68100 | AG18: 72200 | AH18: 92007 | AI18: 96105 | AJ18: 124442 | AK18: 134551 | AL18: 135775 | AM18: 133288 | AN18: 146621 | AO18: 148814 | AP18: 149550 | AT18: Dividends received | AU18: 146 | AV18: 87 | AW18: 127 | AX18: 108 | AY18: 85 | AZ18: 111 | BA18: 148 | BB18: 103 | BC18: 135 | BD18: 162 | BE18: 317 | BF18: 336
B19: Acquisition of companies | C19: -108 | D19: -78 | E19: -1081 | F19: -255 | G19: -34569 | H19: -4433 | I19: 0 | J19: -53 | K19: -10569 | L19: 0 | O19: Building | P19: 14186 | Q19: 11058 | R19: 11141 | S19: 12148 | T19: 21753 | U19: 25883 | V19: 26828 | W19: 27588 | X19: 28904 | Y19: 30173 | AC19: Land | AD19: 2513 | AE19: 2758 | AF19: 2433 | AG19: 16499 | AH19: 16545 | AI19: 16955 | AJ19: 17126 | AK19: 19853 | AL19: 20656 | AM19: 20770 | AN19: 21701 | AO19: 22067 | AT19: Redemp n Canc of Shares | AU19: 902 | AV19: 59 | AW19: 1301 | AX19: 0 | AY19: 0 | AZ19: 34 | BA19: 156 | BB19: 378 | BC19: 90 | BD19: 1208 | BE19: 166 | BF19: 123
B20: Inter corporate deposits | C20: 277 | D20: 0 | E20: 0 | F20: 0 | G20: 0 | H20: 0 | I20: 0 | J20: 0 | K20: 0 | L20: 0 | O20: Plant Machinery | P20: 124249 | Q20: 73865 | R20: 93462 | S20: 104889 | T20: 127435 | U20: 141914 | V20: 155596 | W20: 152754 | X20: 163134 | Y20: 175111 | AC20: Building | AD20: 13060 | AE20: 15141 | AF20: 14186 | AG20: 11058 | AH20: 11141 | AI20: 12148 | AJ20: 21753 | AK20: 25883 | AL20: 26828 | AM20: 27588 | AN20: 28904 | AO20: 30173 | AT20: Acquisition of companies | AU20: -156 | AV20: 0 | AW20: -108 | AX20: -78 | AY20: -1081 | AZ20: -255 | BA20: -34569 | BB20: -4433 | BC20: 0 | BD20: -53 | BE20: -10569 | BF20: 0
B21: Other investing items | C21: -573 | D21: 496 | E21: -437 | F21: 166 | G21: 471 | H21: 456 | I21: 236 | J21: -1315 | K21: 609 | L21: -481 | O21: Equipments | P21: 403 | Q21: 414 | R21: 543 | S21: 668 | T21: 739 | U21: 796 | V21: 1033 | W21: 0 | X21: 0 | Y21: 0 | AC21: Plant Machinery | AD21: 111394 | AE21: 128424 | AF21: 124249 | AG21: 73865 | AH21: 93462 | AI21: 104889 | AJ21: 127435 | AK21: 141914 | AL21: 155596 | AM21: 152754 | AN21: 163134 | AO21: 175111 | AT21: Inter corporate deposits | AU21: -95 | AV21: -96 | AW21: 277 | AX21: 0 | AY21: 0 | AZ21: 0 | BA21: 0 | BB21: 0 | BC21: 0 | BD21: 0 | BE21: 0 | BF21: 0
B22: Cash from Financing Activity - | C22: -2617 | D22: -4729 | E22: -2579 | F22: 6640 | G22: -673 | H22: -1695 | I22: -37090 | J22: -23401 | K22: -6981 | L22: -11097 | O22: Furniture n fittings | P22: 916 | Q22: 0 | R22: 0 | S22: 0 | T22: 0 | U22: 19 | V22: 14 | W22: 991 | X22: 1111 | Y22: 1238 | AC22: Equipments | AD22: 335 | AE22: 385 | AF22: 403 | AG22: 414 | AH22: 543 | AI22: 668 | AJ22: 739 | AK22: 796 | AL22: 1033 | AM22: 0 | AN22: 0 | AO22: 0 | AT22: Other investing items | AU22: 198 | AV22: 1044 | AW22: -573 | AX22: 496 | AY22: -437 | AZ22: 166 | BA22: 471 | BB22: 456 | BC22: 236 | BD22: -1315 | BE22: 609 | BF22: -481
B23: Proceeds from shares | C23: 13 | D23: 0 | E23: 652 | F23: 9087 | G23: 0 | H23: 188 | I23: 3239 | J23: 326 | K23: 1 | L23: 0 | O23: Railway sidings | P23: 1239 | Q23: 757 | R23: 1350 | S23: 1397 | T23: 1549 | U23: 1676 | V23: 1671 | W23: 1780 | X23: 1841 | Y23: 1872 | AC23: Furniture n fittings | AD23: 897 | AE23: 1064 | AF23: 916 | AG23: 0 | AH23: 0 | AI23: 0 | AJ23: 0 | AK23: 19 | AL23: 14 | AM23: 991 | AN23: 1111 | AO23: 1238 | AT23: Cash from Financing Activity - | AU23: -1780 | AV23: 1015 | AW23: -2617 | AX23: -4729 | AY23: -2579 | AZ23: 6640 | BA23: -673 | BB23: -1695 | BC23: -37090 | BD23: -23401 | BE23: -6981 | BF23: -11097
B24: Proceeds from borrowings | C24: 0 | D24: 0 | E24: 0 | F24: 0 | G24: 33344 | H24: 16574 | I24: 9801 | J24: 12439 | K24: 16769 | L24: 14120 | O24: Vehicles | P24: 376 | Q24: 335 | R24: 352 | S24: 343 | T24: 398 | U24: 615 | V24: 681 | W24: 686 | X24: 749 | Y24: 794 | AC24: Railway sidings | AD24: 1234 | AE24: 1416 | AF24: 1239 | AG24: 757 | AH24: 1350 | AI24: 1397 | AJ24: 1549 | AK24: 1676 | AL24: 1671 | AM24: 1780 | AN24: 1841 | AO24: 1872 | AT24: Proceeds from shares | AU24: 0 | AV24: 11 | AW24: 13 | AX24: 0 | AY24: 652 | AZ24: 9087 | BA24: 0 | BB24: 188 | BC24: 3239 | BD24: 326 | BE24: 1 | BF24: 0
B25: Repayment of borrowings | C25: 0 | D25: 0 | E25: 0 | F25: 0 | G25: -25077 | H25: -7937 | I25: -39177 | J25: -26360 | K25: -10226 | L25: -11908 | O25: Intangible Assets | P25: 13500 | Q25: 6026 | R25: 4990 | S25: 5810 | T25: 4293 | U25: 5868 | V25: 6289 | W25: 6229 | X25: 7572 | Y25: 7772 | Z25: 18829 | AC25: Vehicles | AD25: 318 | AE25: 350 | AF25: 376 | AG25: 335 | AH25: 352 | AI25: 343 | AJ25: 398 | AK25: 615 | AL25: 681 | AM25: 686 | AN25: 749 | AO25: 794 | AT25: Proceeds from borrowings | AU25: 0 | AV25: 0 | AW25: 0 | AX25: 0 | AY25: 0 | AZ25: 0 | BA25: 33344 | BB25: 16574 | BC25: 9801 | BD25: 12439 | BE25: 16769 | BF25: 14120
B26: Interest paid fin | C26: -5428 | D26: -5483 | E26: -4733 | F26: -5146 | G26: -6901 | H26: -7419 | I26: -6804 | J26: -4687 | K26: -6120 | L26: -8145 | O26: Other fixed assets | P26: 7315 | Q26: 5154 | R26: 2919 | S26: 3233 | T26: 3742 | U26: 4424 | V26: 5171 | W26: 10953 | X26: 20384 | Y26: 20546 | AC26: Intangible Assets | AD26: 13154 | AE26: 15858 | AF26: 13500 | AG26: 6026 | AH26: 4990 | AI26: 5810 | AJ26: 4293 | AK26: 5868 | AL26: 6289 | AM26: 6229 | AN26: 7572 | AO26: 7772 | AP26: 18829 | AT26: Repayment of borrowings | AU26: 0 | AV26: 0 | AW26: 0 | AX26: 0 | AY26: 0 | AZ26: 0 | BA26: -25077 | BB26: -7937 | BC26: -39177 | BD26: -26360 | BE26: -10226 | BF26: -11908
B27: Dividends paid | C27: -983 | D27: -788 | E27: -791 | F27: -982 | G27: -1186 | H27: -1507 | I27: -1151 | J27: -3020 | K27: -6293 | L27: -4429 | O27: Gross Block | P27: 164618 | Q27: 114109 | R27: 131302 | S27: 145444 | T27: 177037 | U27: 201047 | V27: 217939 | W27: 221752 | X27: 245395 | Y27: 259572 | AC27: Other fixed assets | AD27: 4935 | AE27: 6495 | AF27: 7315 | AG27: 5154 | AH27: 2919 | AI27: 3233 | AJ27: 3742 | AK27: 4424 | AL27: 5171 | AM27: 10953 | AN27: 20384 | AO27: 20546 | AT27: Interest paid fin | AU27: -3200 | AV27: -3676 | AW27: -5428 | AX27: -5483 | AY27: -4733 | AZ27: -5146 | BA27: -6901 | BB27: -7419 | BC27: -6804 | BD27: -4687 | BE27: -6120 | BF27: -8145
B28: Financial liabilities | C28: 0 | D28: -200 | E28: -208 | F28: -211 | G28: -276 | H28: -1029 | I28: -1284 | J28: -1310 | K28: -1114 | L28: -1140 | O28: Accumulated Depreciation | P28: 84913 | Q28: 36022 | R28: 35373 | S28: 46251 | T28: 49609 | U28: 61396 | V28: 71472 | W28: 77783 | X28: 88205 | Y28: 97940 | AC28: Gross Block | AD28: 147839 | AE28: 171891 | AF28: 164618 | AG28: 114109 | AH28: 131302 | AI28: 145444 | AJ28: 177037 | AK28: 201047 | AL28: 217939 | AM28: 221752 | AN28: 245395 | AO28: 259572 | AT28: Dividends paid | AU28: -1169 | AV28: -787 | AW28: -983 | AX28: -788 | AY28: -791 | AZ28: -982 | BA28: -1186 | BB28: -1507 | BC28: -1151 | BD28: -3020 | BE28: -6293 | BF28: -4429
B29: Other financing items | C29: 3781 | D29: 1743 | E29: 2501 | F29: 3892 | G29: -576 | H29: -564 | I29: -1714 | J29: -789 | K29: 2 | L29: 404 | O29: CWIP | P29: 28678 | Q29: 35996 | R29: 15784 | S29: 16614 | T29: 18641 | U29: 19497 | V29: 19007 | W29: 22046 | X29: 31213 | Y29: 34356 | Z29: 39051 | AC29: Accumulated Depreciation | AD29: 72716 | AE29: 88452 | AF29: 84913 | AG29: 36022 | AH29: 35373 | AI29: 46251 | AJ29: 49609 | AK29: 61396 | AL29: 71472 | AM29: 77783 | AN29: 88205 | AO29: 97940 | AT29: Financial liabilities | AU29: 0 | AV29: 0 | AW29: 0 | AX29: -200 | AY29: -208 | AZ29: -211 | BA29: -276 | BB29: -1029 | BC29: -1284 | BD29: -1310 | BE29: -1114 | BF29: -1140
B30: Net Cash Flow | C30: 241 | D30: -2068 | E30: -1245 | F30: 2933 | G30: -4513 | H30: 4462 | I30: -2200 | J30: 10075 | K30: -3477 | L30: -5049 | O30: Investments | P30: 3455 | Q30: 10714 | R30: 12457 | S30: 17899 | T30: 5738 | U30: 6285 | V30: 10682 | W30: 13140 | X30: 8410 | Y30: 6258 | Z30: 6471 | AC30: CWIP | AD30: 14277 | AE30: 26822 | AF30: 28678 | AG30: 35996 | AH30: 15784 | AI30: 16614 | AJ30: 18641 | AK30: 19497 | AL30: 19007 | AM30: 22046 | AN30: 31213 | AO30: 34356 | AP30: 39051 | AT30: Other financing items | AU30: 2589 | AV30: 5466 | AW30: 3781 | AX30: 1743 | AY30: 2501 | AZ30: 3892 | BA30: -576 | BB30: -564 | BC30: -1714 | BD30: -789 | BE30: 2 | BF30: 404
O31: Other Assets - | P31: 58876 | Q31: 57974 | R31: 52200 | S31: 78103 | T31: 83952 | U31: 88816 | V31: 78445 | W31: 113948 | X31: 99151 | Y31: 79885 | Z31: 85769 | AC31: Investments | AD31: 3258 | AE31: 5093 | AF31: 3455 | AG31: 10714 | AH31: 12457 | AI31: 17899 | AJ31: 5738 | AK31: 6285 | AL31: 10682 | AM31: 13140 | AN31: 8410 | AO31: 6258 | AP31: 6471 | AT31: Net Cash Flow | AU31: -844 | AV31: -1218 | AW31: 241 | AX31: -2068 | AY31: -1245 | AZ31: 2933 | BA31: -4513 | BB31: 4462 | BC31: -2200 | BD31: 10075 | BE31: -3477 | BF31: -5049
O32: Inventories | P32: 25150 | Q32: 20013 | R32: 24804 | S32: 28331 | T32: 31656 | U32: 31069 | V32: 33276 | W32: 48824 | X32: 54415 | Y32: 49158 | Z32: 51172 | AC32: Other Assets - | AD32: 61340 | AE32: 64781 | AF32: 58876 | AG32: 57974 | AH32: 52200 | AI32: 78103 | AJ32: 83952 | AK32: 88816 | AL32: 78445 | AM32: 113948 | AN32: 99151 | AO32: 79885 | AP32: 85769
O33: Trade receivables - | P33: 13310 | Q33: 12066 | R33: 11587 | S33: 12416 | T33: 11811 | U33: 7885 | V33: 9540 | W33: 12246 | X33: 8257 | Y33: 6264 | Z33: 6041 | AC33: Inventories | AD33: 24091 | AE33: 26880 | AF33: 25150 | AG33: 20013 | AH33: 24804 | AI33: 28331 | AJ33: 31656 | AK33: 31069 | AL33: 33276 | AM33: 48824 | AN33: 54415 | AO33: 49158 | AP33: 51172
O34: Receivables over 6m | P34: 443 | Q34: 0 | R34: 0 | S34: 0 | T34: 0 | U34: 0 | V34: 0 | W34: 563 | X34: 1051 | Y34: 608 | AC34: Trade receivables - | AD34: 13994 | AE34: 16006 | AF34: 13310 | AG34: 12066 | AH34: 11587 | AI34: 12416 | AJ34: 11811 | AK34: 7885 | AL34: 9540 | AM34: 12246 | AN34: 8257 | AO34: 6264 | AP34: 6041
O35: Receivables under 6m | P35: 13162 | Q35: 12386 | R35: 11814 | S35: 12666 | T35: 12204 | U35: 8194 | V35: 9899 | W35: 11948 | X35: 7961 | Y35: 5990 | AC35: Receivables over 6m | AD35: 615 | AE35: 440 | AF35: 443 | AG35: 0 | AH35: 0 | AI35: 0 | AJ35: 0 | AK35: 0 | AL35: 0 | AM35: 563 | AN35: 1051 | AO35: 608
O36: Prov for Doubtful | P36: -295 | Q36: -320 | R36: -227 | S36: -250 | T36: -393 | U36: -309 | V36: -360 | W36: -265 | X36: -755 | Y36: -335 | AC36: Receivables under 6m | AD36: 13747 | AE36: 15923 | AF36: 13162 | AG36: 12386 | AH36: 11814 | AI36: 12666 | AJ36: 12204 | AK36: 8194 | AL36: 9899 | AM36: 11948 | AN36: 7961 | AO36: 5990
O37: Cash Equivalents | P37: 8750 | Q37: 6186 | R37: 4921 | S37: 7938 | T37: 3341 | U37: 8055 | V37: 5782 | W37: 15899 | X37: 13357 | Y37: 8678 | Z37: 9934 | AC37: Prov for Doubtful | AD37: -368 | AE37: -357 | AF37: -295 | AG37: -320 | AH37: -227 | AI37: -250 | AJ37: -393 | AK37: -309 | AL37: -360 | AM37: -265 | AN37: -755 | AO37: -335
O38: Loans n Advances | P38: -182 | Q38: 107 | R38: 98 | S38: 219 | T38: -56 | U38: 195 | V38: 914 | W38: -158 | X38: -90 | Y38: -56 | Z38: 1779 | AC38: Cash Equivalents | AD38: 9834 | AE38: 8604 | AF38: 8750 | AG38: 6186 | AH38: 4921 | AI38: 7938 | AJ38: 3341 | AK38: 8055 | AL38: 5782 | AM38: 15899 | AN38: 13357 | AO38: 8678 | AP38: 9934
O39: Other asset items | P39: 11848 | Q39: 19602 | R39: 10790 | S39: 29200 | T39: 37200 | U39: 41613 | V39: 28932 | W39: 37137 | X39: 23211 | Y39: 15842 | Z39: 16843 | AC39: Loans n Advances | AD39: 487 | AE39: 171 | AF39: -182 | AG39: 107 | AH39: 98 | AI39: 219 | AJ39: -56 | AK39: 195 | AL39: 914 | AM39: -158 | AN39: -90 | AO39: -56 | AP39: 1779
O40: Total Assets | P40: 159109 | Q40: 176884 | R40: 172447 | S40: 208722 | T40: 232773 | U40: 249149 | V40: 243909 | W40: 282422 | X40: 285396 | Y40: 269312 | Z40: 2 | AC40: Other asset items | AD40: 12934 | AE40: 13119 | AF40: 11848 | AG40: 19602 | AH40: 10790 | AI40: 29200 | AJ40: 37200 | AK40: 41613 | AL40: 28932 | AM40: 37137 | AN40: 23211 | AO40: 15842 | AP40: 16843
AC41: Total Assets | AD41: 146876 | AE41: 171604 | AF41: 159109 | AG41: 176884 | AH41: 172447 | AI41: 208722 | AJ41: 232773 | AK41: 249149 | AL41: 243909 | AM41: 282422 | AN41: 285396 | AO41: 269312 | AP41: 280841

Sheet Beta
B2: Regressison Beta
B4: Tata Stell Monthly Return | F4: Nifty 50 Monthly Return | J4: Beta Drfting | O4: Beta 1 | P4: =SLOPE(D8:D66,H8:H66) -> 2.6354669
O5: Beta 2 | P5: =_xlfn.COVARIANCE.S(D8:D66,H8:H66)/_xlfn.VAR.S(H8:H66) -> 2.6354669
B6: Date | C6: Closing price | D6: Return | G6: Closing price | H6: Return | J6: Levered Raw beeta | L6: =P6 -> 2.6354669 | O6: Beta 3 | P6: =L31 -> 2.6354669
B7: 43952 | C7: 11.88 | G7: 9580.3 | J7: Raw Beeta Weight | L7: =75% -> 0.75
B8: 43983 | C8: 13.14 | D8: =C8/C7-1 -> 0.10606061 | G8: 10302.1 | H8: =G8/G7-1 -> 0.075342108
B9: 44013 | C9: 14.74 | D9: =C9/C8-1 -> 0.1217656 | G9: 11073.45 | H9: =G9/G8-1 -> 0.074873084 | J9: Market Beeta | L9: 1
B10: 44044 | C10: 16.61 | D10: =C10/C9-1 -> 0.12686567 | G10: 11387.5 | H10: =G10/G9-1 -> 0.028360628 | J10: Market Beeta Weight | L10: 0.25
B11: 44075 | C11: 14.85 | D11: =C11/C10-1 -> -0.10596026 | G11: 11247.55 | H11: =G11/G10-1 -> -0.012289791
B12: 44105 | C12: 16.94 | D12: =C12/C11-1 -> 0.14074074 | G12: 11642.4 | H12: =G12/G11-1 -> 0.035105423 | J12: Adjusted Beta | L12: =(L6*L7)+(L9*L10) -> 2.2266002
B13: 44136 | C13: 23.83 | D13: =C13/C12-1 -> 0.40672963 | G13: 12968.95 | H13: =G13/G12-1 -> 0.11394128
B14: 44166 | C14: 26.57 | D14: =C14/C13-1 -> 0.11498112 | G14: 13981.75 | H14: =G14/G13-1 -> 0.078094217 | K14: SUMMARY OUTPUT
B15: 44197 | C15: 24.8 | D15: =C15/C14-1 -> -0.066616485 | G15: 13634.6 | H15: =G15/G14-1 -> -0.024828795
B16: 44228 | C16: 29.52 | D16: =C16/C15-1 -> 0.19032258 | G16: 14529.15 | H16: =G16/G15-1 -> 0.065608819 | K16: Regression Statistics
B17: 44256 | C17: 33.51 | D17: =C17/C16-1 -> 0.1351626 | G17: 14690.7 | H17: =G17/G16-1 -> 0.011119026 | K17: Multiple R | L17: 0.42254286
B18: 44287 | C18: 42.68 | D18: =C18/C17-1 -> 0.27364966 | G18: 14631.1 | H18: =G18/G17-1 -> -0.0040569884 | K18: R Square | L18: 0.17854247
B19: 44317 | C19: 46.46 | D19: =C19/C18-1 -> 0.088566073 | G19: 15582.8 | H19: =G19/G18-1 -> 0.065046374 | K19: Adjusted R Square | L19: 0.16413093
B20: 44348 | C20: 48.15 | D20: =C20/C19-1 -> 0.036375377 | G20: 15721.5 | H20: =G20/G19-1 -> 0.0089008394 | K20: Standard Error | L20: 0.2323244
B21: 44378 | C21: 60.52 | D21: =C21/C20-1 -> 0.2569055 | G21: 15763.05 | H21: =G21/G20-1 -> 0.0026428776 | K21: Observations | L21: 59
B22: 44409 | C22: 61.2 | D22: =C22/C21-1 -> 0.011235955 | G22: 17132.2 | H22: =G22/G21-1 -> 0.086858191
B23: 44440 | C23: 54.39 | D23: =C23/C22-1 -> -0.11127451 | G23: 17618.15 | H23: =G23/G22-1 -> 0.028364717 | K23: ANOVA
B24: 44470 | C24: 55.53 | D24: =C24/C23-1 -> 0.020959735 | G24: 17671.65 | H24: =G24/G23-1 -> 0.0030366412 | L24: df | O24: SS | P24: MS | Q24: F | R24: Significance F
B25: 44501 | C25: 45.2 | D25: =C25/C24-1 -> -0.18602557 | G25: 16983.2 | H25: =G25/G24-1 -> -0.038957879 | K25: Regression | L25: 1 | O25: 0.66868397 | P25: 0.66868397 | Q25: 12.388858 | R25: 0.00085669941
B26: 44531 | C26: 46.9 | D26: =C26/C25-1 -> 0.037610619 | G26: 17354.05 | H26: =G26/G25-1 -> 0.021836285 | K26: Residual | L26: 57 | O26: 3.0765536 | P26: 0.053974625
B27: 44562 | C27: 45.81 | D27: =C27/C26-1 -> -0.023240938 | G27: 17339.85 | H27: =G27/G26-1 -> -0.0008182528 | K27: Total | L27: 58 | O27: 3.7452376
B28: 44593 | C28: 51.51 | D28: =C28/C27-1 -> 0.12442698 | G28: 16793.9 | H28: =G28/G27-1 -> -0.031485278
B29: 44621 | C29: 55.16 | D29: =C29/C28-1 -> 0.070860027 | G29: 17464.75 | H29: =G29/G28-1 -> 0.039946052 | L29: Coefficients | O29: Standard Error | P29: t Stat | Q29: P-value | R29: Lower 95% | S29: Upper 95% | T29: Lower 95.0% | U29: Upper 95.0%
B30: 44652 | C30: 53.63 | D30: =C30/C29-1 -> -0.027737491 | G30: 17102.55 | H30: =G30/G29-1 -> -0.020738917 | K30: Intercept | L30: 0.01866932 | O30: 0.032445422 | P30: 0.57540691 | Q30: 0.56728082 | R30: -0.046301517 | S30: 0.083640157 | T30: -0.046301517 | U30: 0.083640157
B31: 44682 | C31: 44.54 | D31: =C31/C30-1 -> -0.16949469 | G31: 16584.55 | H31: =G31/G30-1 -> -0.030287881 | K31: X Variable 1 | L31: 2.6354669 | O31: 0.74875879 | P31: 3.519781 | Q31: 0.00085669941 | R31: 1.1361033 | S31: 4.1348305 | T31: 1.1361033 | U31: 4.1348305
B32: 44713 | C32: 36.59 | D32: =C32/C31-1 -> -0.17849124 | G32: 15780.25 | H32: =G32/G31-1 -> -0.048496944
B33: 44743 | C33: 102.14 | D33: =C33/C32-1 -> 1.7914731 | G33: 17158.25 | H33: =G33/G32-1 -> 0.087324345
B34: 44774 | C34: 102.81 | D34: =C34/C33-1 -> 0.006559624 | G34: 17759.3 | H34: =G34/G33-1 -> 0.035029796
B35: 44805 | C35: 94.26 | D35: =C35/C34-1 -> -0.083163116 | G35: 17094.35 | H35: =G35/G34-1 -> -0.037442354
B36: 44835 | C36: 96.4 | D36: =C36/C35-1 -> 0.022703161 | G36: 18012.2 | H36: =G36/G35-1 -> 0.053693179
B37: 44866 | C37: 102.19 | D37: =C37/C36-1 -> 0.060062241 | G37: 18758.35 | H37: =G37/G36-1 -> 0.041424701
B38: 44896 | C38: 106.94 | D38: =C38/C37-1 -> 0.046482043 | G38: 18105.3 | H38: =G38/G37-1 -> -0.03481383
B39: 44927 | C39: 113.63 | D39: =C39/C38-1 -> 0.062558444 | G39: 17662.15 | H39: =G39/G38-1 -> -0.024476258
B40: 44958 | C40: 98.68 | D40: =C40/C39-1 -> -0.13156737 | G40: 17303.95 | H40: =G40/G39-1 -> -0.020280657
B41: 44986 | C41: 99.2 | D41: =C41/C40-1 -> 0.0052695582 | G41: 17359.75 | H41: =G41/G40-1 -> 0.0032246973
B42: 45017 | C42: 102.47 | D42: =C42/C41-1 -> 0.03296371 | G42: 18065 | H42: =G42/G41-1 -> 0.040625585
B43: 45047 | C43: 100.43 | D43: =C43/C42-1 -> -0.019908266 | G43: 18534.4 | H43: =G43/G42-1 -> 0.025983947
... B66: 45748 | C66: 134.62 | D66: =C66/C65-1 -> -0.018804665 | G66: 22904.45 | H66: =G66/G65-1 -> -0.02614443

Sheet RM
B2: Return On Market
B5: Year | C5: Annual
B6: 2000 | C6: -0.1465 | E6: Average Return | G6: =AVERAGE(C6:C30) -> 0.153348
B7: 2001 | C7: -0.1618 | E7: Divident Yield | G7: 0.0132
B8: 2002 | C8: 0.0325 | E8: Total Market Return | G8: =SUM(G6:G7) -> 0.166548
B9: 2003 | C9: 0.719
B10: 2004 | C10: 0.1068
B11: 2005 | C11: 0.3634
B12: 2006 | C12: 0.3983
B13: 2007 | C13: 0.5477
B14: 2008 | C14: -0.5179
B15: 2009 | C15: 0.7576
B16: 2010 | C16: 0.1795
B17: 2011 | C17: -0.2462
B18: 2012 | C18: 0.277
B19: 2013 | C19: 0.0676
B20: 2014 | C20: 0.3139
... B30: 2024 | C30: 0.0875

Sheet Rough Data Relative valuation
B2: S.No. | C2: Name | D2: CMP Rs. | E2: Debt Rs.Cr. | F2: Mar Cap Rs.Cr. | G2: Sales Rs.Cr. | H2: EV Rs.Cr. | I2: EV / EBITDA | J2: Ebitda | K2: Cash End Rs.Cr. | L2: Net Debt | M2: No. Eq. Shares Cr. | N2: PAT 12M Rs.Cr.
B3: 1 | C3: JSW Steel | D3: 956.2 | E3: 95258 | F3: 234035.56 | G3: 170274 | H3: 320004.56 | I3: 13.8 | J3: =H3/I3 -> 23188.736 | K3: 12348 | L3: =E3-K3 -> 82910 | M3: 244.55 | N3: 3498.48
B4: 2 | C4: Tata Steel | D4: 130.2 | E4: 99391.76 | F4: 162385.02 | G4: 221011.71 | H4: 251842.87 | I4: 9.42 | J4: =H4/I4 -> 26734.912 | K4: 8677.72 | L4: =E4-K4 -> 90714.04 | M4: 1248.35 | N4: 2831.41
B5: 3 | C5: Jindal Steel | D5: 801.35 | E5: 17266.45 | F5: 81703.45 | G5: 50068.78 | H5: 95446.77 | I5: 9.74 | J5: =H5/I5 -> 9799.463 | K5: 4024.13 | L5: =E5-K5 -> 13242.32 | M5: 102.01 | N5: 4082.33
A6: Positive hai | B6: 4 | C6: Tube Investments | D6: 2570 | E6: 698.92 | F6: 49705.77 | G6: 18804.8 | H6: 48868.6 | I6: 21.66 | J6: =H6/I6 -> 2256.1681 | K6: 1227.4 | L6: =E6-K6 -> -528.48 | M6: 19.35 | N6: 819.65
B7: 5 | C7: S A I L | D7: 104.8 | E7: 41265.03 | F7: 43300.32 | G7: 101121.44 | H7: 83810.93 | I7: 6.94 | J7: =H7/I7 -> 12076.503 | K7: 672.95 | L7: =E7-K7 -> 40592.08 | M7: 413.05 | N7: 2921.77
B8: 6 | C8: Jindal Stain. | D8: 524.1 | E8: 6473.08 | F8: 43177.95 | G8: 38567.91 | H8: 47533.45 | I8: 9.75 | J8: =H8/I8 -> 4875.2256 | K8: 1988.11 | L8: =E8-K8 -> 4484.97 | M8: 82.38 | N8: 2411.59
B9: 7 | C9: APL Apollo Tubes | D9: 1467.55 | E9: 1022.59 | F9: 40736.61 | G9: 19946.68 | H9: 41555.88 | I9: 36.28 | J9: =H9/I9 -> 1145.4212 | K9: 347.6 | L9: =E9-K9 -> 674.99 | M9: 27.75 | N9: 634.39
